Workbook

Sheet LEAME
A1: Ingeniería inversa – Metodología AM Best 'Life Settlement Securitization' (SPV USD 100 mm)
A2: Réplica independiente del proceso descrito públicamente por AM Best. NO es el modelo propietario ni una calificación de AM Best.
A4: Proceso replicado (en el orden que AM Best lo describe)
A5: 1. Filtros de elegibilidad: ~300 vidas, ≤3.33% del face por vida, ≥2 proveedores de LE, LE ≤12 meses, cartera adquirida antes de calificar.
A6: 2. Mortalidad: tabla base (2015 VBT en la revisión 2026) × calificación de mortalidad del underwriter, ajustada por
A7: Basic Adjustment Factor (nivel de la calificación y si la póliza fue premium-financed), Age-Based Adjustment Factor y Ratings Wear-Off.
A8: 3. Simulación Monte Carlo de muertes (con choque sistemático por error de estimación de LE), default de aseguradoras y caducidad por falta de liquidez.
A9: 4. Probabilidad de default de cada nota vs. su vencimiento esperado → Matriz Idealizada de Default (BILSM, Exhibit E.2) → calificación.
A10: 5. Escenarios de estrés y factores cualitativos → ajuste en notches para el comité.
A12: Cómo usarlo
A13: a) Pegue su cinta póliza por póliza en 'Cartera_Polizas' (columnas azules). Las columnas negras se calculan solas.
A14: b) Reemplace 'Tabla_Mortalidad' por la 2015 VBT real (q_x por edad) y 'Matriz_Default' por el Exhibit E.2 de BILSM.
... A19: Los valores de BAF, AAF, wear-off, sigma sistemática y la matriz de default son ESTIMACIONES: AM Best describe estos factores pero sus tablas no fueron accesibles.

Sheet Resultados_MC
A1: Resultados Monte Carlo y calificación indicada (réplica – no es una calificación de AM Best)
A2: Valores en columnas B–K los escribe el motor (python ambest_ls_model.py run). Columnas L–Q son fórmulas contra 'Matriz_Default'.
A3: Estado: | B3: Corrido: 5000 simulaciones, 300 pólizas, semilla 2026
A5: Escenario | B5: PD Senior | C5: Pérdida esperada Senior | D5: Vencim. esperado Senior (años) | E5: PD Mezz | F5: Pérdida esperada Mezz | G5: Vencim. esperado Mezz (años) | H5: P(caducidad con notas vigentes) | I5: LE realizada prom. (años) | J5: Muertes cobradas prom. (USD mm) | K5: Sims | L5: Senior – índice | M5: Senior – calificación MC | N5: Mezz – índice | O5: Mezz – calificación MC | P5: Senior – final (con notches) | Q5: Mezz – final (con notches)
A6: =Escenarios!A6 -> Base | B6: 0.0324 | C6: 0.018875285 | D6: 4.3893644 | E6: 0.0418 | F6: 0.036668659 | G6: 7.8933436 | H6: 0.0112 | I6: 7.6576057 | J6: 441.86747 | K6: 5000 | L6: =IF(B6="","",COUNTIF(INDEX(Matriz_Default!$C$5:$AF$20,0,MIN(30,MAX(1,ROUND(D6,0)))),"<"&B6)+1) -> 9 | M6: =IF(L6="","",INDEX(Matriz_Default!$A$5:$A$21,MIN(17,L6))) -> bbb | N6: =IF(E6="","",MAX(L6,COUNTIF(INDEX(Matriz_Default!$C$5:$AF$20,0,MIN(30,MAX(1,ROUND(G6,0)))),"<"&E6)+1)) -> 9 | O6: =IF(N6="","",INDEX(Matriz_Default!$A$5:$A$21,MIN(17,N6))) -> bbb | P6: =IF(L6="","",INDEX(Matriz_Default!$A$5:$A$21,MIN(17,L6-Ponderacion!$C$28))) -> bbb- | Q6: =IF(N6="","",INDEX(Matriz_Default!$A$5:$A$21,MIN(17,N6-Ponderacion!$C$28))) -> bbb-
A7: =Escenarios!A7 -> Extensión LE (q × 0.85) | B7: 0.1352 | C7: 0.087421669 | D7: 7.7271989 | E7: 0.1674 | F7: 0.15202808 | G7: 12.005471 | H7: 0.0488 | I7: 8.5347457 | J7: 435.37259 | K7: 5000 | L7: =IF(B7="","",COUNTIF(INDEX(Matriz_Default!$C$5:$AF$20,0,MIN(30,MAX(1,ROUND(D7,0)))),"<"&B7)+1) -> 11 | M7: =IF(L7="","",INDEX(Matriz_Default!$A$5:$A$21,MIN(17,L7))) -> bb+ | N7: =IF(E7="","",MAX(L7,COUNTIF(INDEX(Matriz_Default!$C$5:$AF$20,0,MIN(30,MAX(1,ROUND(G7,0)))),"<"&E7)+1)) -> 11 | O7: =IF(N7="","",INDEX(Matriz_Default!$A$5:$A$21,MIN(17,N7))) -> bb+ | P7: =IF(L7="","",INDEX(Matriz_Default!$A$5:$A$21,MIN(17,L7-Ponderacion!$C$28))) -> bb | Q7: =IF(N7="","",INDEX(Matriz_Default!$A$5:$A$21,MIN(17,N7-Ponderacion!$C$28))) -> bb
A8: =Escenarios!A8 -> Extensión severa (q × 0.75) | B8: 0.3056 | C8: 0.21627372 | D8: 11.816442 | E8: 0.3496 | F8: 0.32757599 | G8: 15.94245 | H8: 0.1354 | I8: 9.2435037 | J8: 423.82575 | K8: 5000 | L8: =IF(B8="","",COUNTIF(INDEX(Matriz_Default!$C$5:$AF$20,0,MIN(30,MAX(1,ROUND(D8,0)))),"<"&B8)+1) -> 13 | M8: =IF(L8="","",INDEX(Matriz_Default!$A$5:$A$21,MIN(17,L8))) -> bb- | N8: =IF(E8="","",MAX(L8,COUNTIF(INDEX(Matriz_Default!$C$5:$AF$20,0,MIN(30,MAX(1,ROUND(G8,0)))),"<"&E8)+1)) -> 13 | O8: =IF(N8="","",INDEX(Matriz_Default!$A$5:$A$21,MIN(17,N8))) -> bb- | P8: =IF(L8="","",INDEX(Matriz_Default!$A$5:$A$21,MIN(17,L8-Ponderacion!$C$28))) -> b+ | Q8: =IF(N8="","",INDEX(Matriz_Default!$A$5:$A$21,MIN(17,N8-Ponderacion!$C$28))) -> b+
A9: =Escenarios!A9 -> Primas +1.5% anual adicional | B9: 0.067 | C9: 0.04069154 | D9: 5.1278532 | E9: 0.0884 | F9: 0.076602736 | G9: 8.8358663 | H9: 0.0304 | I9: 7.6576057 | J9: 441.20079 | K9: 5000 | L9: =IF(B9="","",COUNTIF(INDEX(Matriz_Default!$C$5:$AF$20,0,MIN(30,MAX(1,ROUND(D9,0)))),"<"&B9)+1) -> 11 | M9: =IF(L9="","",INDEX(Matriz_Default!$A$5:$A$21,MIN(17,L9))) -> bb+ | N9: =IF(E9="","",MAX(L9,COUNTIF(INDEX(Matriz_Default!$C$5:$AF$20,0,MIN(30,MAX(1,ROUND(G9,0)))),"<"&E9)+1)) -> 11 | O9: =IF(N9="","",INDEX(Matriz_Default!$A$5:$A$21,MIN(17,N9))) -> bb+ | P9: =IF(L9="","",INDEX(Matriz_Default!$A$5:$A$21,MIN(17,L9-Ponderacion!$C$28))) -> bb | Q9: =IF(N9="","",INDEX(Matriz_Default!$A$5:$A$21,MIN(17,N9-Ponderacion!$C$28))) -> bb
A10: =Escenarios!A10 -> Default aseguradora mayor | B10: 0.1278 | C10: 0.077630238 | D10: 6.98016 | E10: 0.1596 | F10: 0.14455283 | G10: 11.149848 | H10: 0.0518 | I10: 7.6576057 | J10: 400.31921 | K10: 5000 | L10: =IF(B10="","",COUNTIF(INDEX(Matriz_Default!$C$5:$AF$20,0,MIN(30,MAX(1,ROUND(D10,0)))),"<"&B10)+1) -> 12 | M10: =IF(L10="","",INDEX(Matriz_Default!$A$5:$A$21,MIN(17,L10))) -> bb | N10: =IF(E10="","",MAX(L10,COUNTIF(INDEX(Matriz_Default!$C$5:$AF$20,0,MIN(30,MAX(1,ROUND(G10,0)))),"<"&E10)+1)) -> 12 | O10: =IF(N10="","",INDEX(Matriz_Default!$A$5:$A$21,MIN(17,N10))) -> bb | P10: =IF(L10="","",INDEX(Matriz_Default!$A$5:$A$21,MIN(17,L10-Ponderacion!$C$28))) -> bb- | Q10: =IF(N10="","",INDEX(Matriz_Default!$A$5:$A$21,MIN(17,N10-Ponderacion!$C$28))) -> bb-
A11: =Escenarios!A11 -> Liquidez −50% | B11: 0.0594 | C11: 0.033045875 | D11: 5.6204669 | E11: 0.0734 | F11: 0.06490962 | G11: 9.2008381 | H11: 0.021 | I11: 7.6576057 | J11: 441.35707 | K11: 5000 | L11: =IF(B11="","",COUNTIF(INDEX(Matriz_Default!$C$5:$AF$20,0,MIN(30,MAX(1,ROUND(D11,0)))),"<"&B11)+1) -> 10 | M11: =IF(L11="","",INDEX(Matriz_Default!$A$5:$A$21,MIN(17,L11))) -> bbb- | N11: =IF(E11="","",MAX(L11,COUNTIF(INDEX(Matriz_Default!$C$5:$AF$20,0,MIN(30,MAX(1,ROUND(G11,0)))),"<"&E11)+1)) -> 10 | O11: =IF(N11="","",INDEX(Matriz_Default!$A$5:$A$21,MIN(17,N11))) -> bbb- | P11: =IF(L11="","",INDEX(Matriz_Default!$A$5:$A$21,MIN(17,L11-Ponderacion!$C$28))) -> bb+ | Q11: =IF(N11="","",INDEX(Matriz_Default!$A$5:$A$21,MIN(17,N11-Ponderacion!$C$28))) -> bb+
A13: CALIFICACIÓN INDICADA (caso base MC − notches cualitativos y de elegibilidad)
A14: Senior | B14: =P6 -> bbb-
A15: Mezzanine | B15: =Q6 -> bbb-
A16: Notches aplicados | B16: =Ponderacion!C28 -> -1
A18: Conciliación: LE ponderada Excel vs. motor | B18: =Cartera_Polizas!I3 -> 7.5267385 | C18: 7.5267385 | D18: =IF(C18="","",IF(ABS(B18-C18)<0.05,"OK","REVISAR")) -> OK

Sheet Supuestos
A1: Supuestos
B3: Parámetro | C3: Valor | D3: Unidad | E3: Fuente / estatus
B5: Notas Senior | C5: 75 | D5: USD mm | E5: Estructura ilustrativa
B6: Cupón Senior | C6: 0.065 | D6: % anual | E6: Estructura ilustrativa
B7: Notas Mezzanine | C7: 25 | D7: USD mm | E7: Estructura ilustrativa
B8: Cupón Mezzanine | C8: 0.095 | D8: % anual | E8: Estructura ilustrativa
B9: Reserva de liquidez inicial (equity) | C9: 20 | D9: USD mm | E9: Estructura ilustrativa
B10: Reserva objetivo (meses de primas + gastos) | C10: 12 | D10: meses | E10: Práctica de mercado
B11: Tasa de reinversión de caja | C11: 0.03 | D11: % anual | E11: Supuesto
B12: Gastos fijos (servicer, trustee, tracking) | C12: 0.75 | D12: USD mm/año | E12: Supuesto
B13: Gasto variable sobre face en vigor | C13: 0.0005 | D13: % anual | E13: Supuesto
B14: Venta de cartera remanente al vencimiento legal | C14: 0.2 | D14: % face | E14: Supuesto (AM Best suele dar poco crédito)
B15: Vencimiento legal (años, máx. 40) | C15: 25 | D15: años | E15: Estructura ilustrativa
B16: Número de simulaciones Monte Carlo | C16: 5000 | D16: # | E16: Motor (AM Best: Monte Carlo)
... B27: Mínimo de proveedores de LE | C27: 2 | D27: # | E27: AM Best (publicado)

Sheet Factores
A1: Factores de ajuste de mortalidad y riesgo de aseguradoras
A2: Estructura descrita por AM Best; los valores son estimaciones a calibrar (factor < 1 reduce la mortalidad = extiende la LE).
A4: Basic Adjustment Factor (BAF) – por nivel de calificación de mortalidad y premium financing
A5: MR desde (≥) | B5: BAF no PF | C5: BAF premium-financed
A6: 0 | B6: 0.95 | C6: 0.9
A7: 1.5 | B7: 0.88 | C7: 0.82
A8: 3 | B8: 0.8 | C8: 0.74
A9: 5 | B9: 0.72 | C9: 0.66
A11: Age-Based Adjustment Factor (AAF)
A12: Edad desde (≥) | B12: AAF
A13: 0 | B13: 0.9
A14: 75 | B14: 0.95
A15: 85 | B15: 1
A16: 90 | B16: 1
A18: PD anual de aseguradoras por FSR
A19: FSR | B19: PD anual
A20: A++ | B20: 0.0001
A21: A+ | B21: 0.0003
A22: A | B22: 0.0006
A23: A- | B23: 0.001
A24: B++ | B24: 0.0025
A25: B+ | B25: 0.005
A27: Aseguradoras de la cartera
A28: ID | B28: Nombre | C28: FSR
A29: 1 | B29: Aseguradora 1 | C29: A+
A30: 2 | B30: Aseguradora 2 | C30: A+
A31: 3 | B31: Aseguradora 3 | C31: A
A32: 4 | B32: Aseguradora 4 | C32: A
A33: 5 | B33: Aseguradora 5 | C33: A-
A34: 6 | B34: Aseguradora 6 | C34: A
A35: 7 | B35: Aseguradora 7 | C35: A+
A36: 8 | B36: Aseguradora 8 | C36: B++

Sheet Tabla_Mortalidad
A1: Tabla base de mortalidad q_x (proxy Gompertz – REEMPLAZAR por 2015 VBT)
A2: Proxy: μ(x) = 0.07·e^{0.11(x−85)}, q = 1−e^{−μ}; q(120) = 1. La revisión 2026 de AM Best usa 2015 VBT.
A4: Edad | B4: q_x
A5: 50 | B5: 0.001488
A6: 51 | B6: 0.001661
A7: 52 | B7: 0.001854
A8: 53 | B8: 0.00207
A9: 54 | B9: 0.00231
A10: 55 | B10: 0.002578
A11: 56 | B11: 0.002878
A12: 57 | B12: 0.003212
A13: 58 | B13: 0.003585
A14: 59 | B14: 0.004001
A15: 60 | B15: 0.004465
A16: 61 | B16: 0.004983
... A75: 120 | B75: 1

Sheet Cartera_Polizas
A1: Cinta de datos póliza por póliza (ejemplo sintético de 300 vidas – reemplazar)
A2: Columnas A–L = input. M–R = fórmulas (ajustes de AM Best replicados). Deje filas vacías al final; el motor lee hasta la primera fila sin ID.
C3: Face total | D3: =SUM(D6:D405) -> 450.0005 | F3: Vidas | G3: =COUNT(A6:A405) -> 300 | H3: LE ponderada | I3: =SUMPRODUCT(Q6:Q305,D6:D305)/D3 -> 7.5267385 | J3: Mayor póliza % | K3: =MAX(R6:R305) -> 0.010170433 | L3: LE más antigua (m) | M3: =MAX(K6:K305) -> 11 | N3: MR ajust. prom. | O3: =SUMPRODUCT(P6:P305,D6:D305)/D3 -> 1.7910853
A5: ID | B5: Edad | C5: Sexo | D5: Face (USD mm) | E5: Aseguradora ID | F5: FSR | G5: Prima anual (% face) | H5: Premium financed (1/0) | I5: MR proveedor 1 | J5: MR proveedor 2 | K5: Antigüedad LE (meses) | L5: Enfermedad principal | M5: MR combinado | N5: BAF | O5: AAF | P5: MR ajustado | Q5: LE ajustada (años) | R5: % del face
A6: 1 | B6: 83 | C6: M | D6: 2.8855 | E6: 3 | F6: =INDEX(Factores!$C$29:$C$36,MATCH(E6,Factores!$A$29:$A$36,0)) -> A | G6: 0.047 | H6: 0 | I6: 1 | J6: 1.25 | K6: 11 | L6: Múltiple | M6: =IF(Supuestos!$C$23=1,AVERAGE(I6:J6),MIN(I6:J6)) -> 1.125 | N6: =INDEX(IF(H6=1,Factores!$C$6:$C$9,Factores!$B$6:$B$9),MATCH(M6,Factores!$A$6:$A$9,1)) -> 0.95 | O6: =INDEX(Factores!$B$13:$B$16,MATCH(B6,Factores!$A$13:$A$16,1)) -> 0.95 | P6: =M6*N6*O6 -> 1.0153125 | Q6: =LE!B4 -> 8.6870665 | R6: =D6/$D$3 -> 0.0064122151
A7: 2 | B7: 84 | C7: M | D7: 1.8765 | E7: 5 | F7: =INDEX(Factores!$C$29:$C$36,MATCH(E7,Factores!$A$29:$A$36,0)) -> A- | G7: 0.0558 | H7: 0 | I7: 2.5 | J7: 4 | K7: 7 | L7: Sin deterioro mayor | M7: =IF(Supuestos!$C$23=1,AVERAGE(I7:J7),MIN(I7:J7)) -> 3.25 | N7: =INDEX(IF(H7=1,Factores!$C$6:$C$9,Factores!$B$6:$B$9),MATCH(M7,Factores!$A$6:$A$9,1)) -> 0.8 | O7: =INDEX(Factores!$B$13:$B$16,MATCH(B7,Factores!$A$13:$A$16,1)) -> 0.95 | P7: =M7*N7*O7 -> 2.47 | Q7: =LE!B5 -> 4.8953688 | R7: =D7/$D$3 -> 0.0041699954
A8: 3 | B8: 82 | C8: F | D8: 1.4234 | E8: 6 | F8: =INDEX(Factores!$C$29:$C$36,MATCH(E8,Factores!$A$29:$A$36,0)) -> A | G8: 0.0479 | H8: 1 | I8: 2 | J8: 3 | K8: 4 | L8: Neurológica | M8: =IF(Supuestos!$C$23=1,AVERAGE(I8:J8),MIN(I8:J8)) -> 2.5 | N8: =INDEX(IF(H8=1,Factores!$C$6:$C$9,Factores!$B$6:$B$9),MATCH(M8,Factores!$A$6:$A$9,1)) -> 0.82 | O8: =INDEX(Factores!$B$13:$B$16,MATCH(B8,Factores!$A$13:$A$16,1)) -> 0.95 | P8: =M8*N8*O8 -> 1.9475 | Q8: =LE!B6 -> 6.8701522 | R8: =D8/$D$3 -> 0.0031631076
A9: 4 | B9: 79 | C9: M | D9: 1.126 | E9: 1 | F9: =INDEX(Factores!$C$29:$C$36,MATCH(E9,Factores!$A$29:$A$36,0)) -> A+ | G9: 0.041 | H9: 0 | I9: 2.25 | J9: 2.25 | K9: 10 | L9: Múltiple | M9: =IF(Supuestos!$C$23=1,AVERAGE(I9:J9),MIN(I9:J9)) -> 2.25 | N9: =INDEX(IF(H9=1,Factores!$C$6:$C$9,Factores!$B$6:$B$9),MATCH(M9,Factores!$A$6:$A$9,1)) -> 0.88 | O9: =INDEX(Factores!$B$13:$B$16,MATCH(B9,Factores!$A$13:$A$16,1)) -> 0.95 | P9: =M9*N9*O9 -> 1.881 | Q9: =LE!B7 -> 8.8634763 | R9: =D9/$D$3 -> 0.0025022194
A10: 5 | B10: 81 | C10: F | D10: 1.0981 | E10: 7 | F10: =INDEX(Factores!$C$29:$C$36,MATCH(E10,Factores!$A$29:$A$36,0)) -> A+ | G10: 0.0405 | H10: 0 | I10: 1 | J10: 1.25 | K10: 9 | L10: Neurológica | M10: =IF(Supuestos!$C$23=1,AVERAGE(I10:J10),MIN(I10:J10)) -> 1.125 | N10: =INDEX(IF(H10=1,Factores!$C$6:$C$9,Factores!$B$6:$B$9),MATCH(M10,Factores!$A$6:$A$9,1)) -> 0.95 | O10: =INDEX(Factores!$B$13:$B$16,MATCH(B10,Factores!$A$13:$A$16,1)) -> 0.95 | P10: =M10*N10*O10 -> 1.0153125 | Q10: =LE!B8 -> 9.8554715 | R10: =D10/$D$3 -> 0.0024402195
A11: 6 | B11: 78 | C11: M | D11: 3.0059 | E11: 2 | F11: =INDEX(Factores!$C$29:$C$36,MATCH(E11,Factores!$A$29:$A$36,0)) -> A+ | G11: 0.0364 | H11: 0 | I11: 1.75 | J11: 1.75 | K11: 7 | L11: Pulmonar | M11: =IF(Supuestos!$C$23=1,AVERAGE(I11:J11),MIN(I11:J11)) -> 1.75 | N11: =INDEX(IF(H11=1,Factores!$C$6:$C$9,Factores!$B$6:$B$9),MATCH(M11,Factores!$A$6:$A$9,1)) -> 0.88 | O11: =INDEX(Factores!$B$13:$B$16,MATCH(B11,Factores!$A$13:$A$16,1)) -> 0.95 | P11: =M11*N11*O11 -> 1.463 | Q11: =LE!B9 -> 10.543546 | R11: =D11/$D$3 -> 0.0066797704
A12: 7 | B12: 83 | C12: M | D12: 1.8356 | E12: 2 | F12: =INDEX(Factores!$C$29:$C$36,MATCH(E12,Factores!$A$29:$A$36,0)) -> A+ | G12: 0.0524 | H12: 0 | I12: 1.5 | J12: 1.5 | K12: 5 | L12: Cardiovascular | M12: =IF(Supuestos!$C$23=1,AVERAGE(I12:J12),MIN(I12:J12)) -> 1.5 | N12: =INDEX(IF(H12=1,Factores!$C$6:$C$9,Factores!$B$6:$B$9),MATCH(M12,Factores!$A$6:$A$9,1)) -> 0.88 | O12: =INDEX(Factores!$B$13:$B$16,MATCH(B12,Factores!$A$13:$A$16,1)) -> 0.95 | P12: =M12*N12*O12 -> 1.254 | Q12: =LE!B10 -> 7.97768 | R12: =D12/$D$3 -> 0.0040791066
A13: 8 | B13: 90 | C13: M | D13: 1.5065 | E13: 6 | F13: =INDEX(Factores!$C$29:$C$36,MATCH(E13,Factores!$A$29:$A$36,0)) -> A | G13: 0.0736 | H13: 1 | I13: 1.25 | J13: 1.75 | K13: 8 | L13: Múltiple | M13: =IF(Supuestos!$C$23=1,AVERAGE(I13:J13),MIN(I13:J13)) -> 1.5 | N13: =INDEX(IF(H13=1,Factores!$C$6:$C$9,Factores!$B$6:$B$9),MATCH(M13,Factores!$A$6:$A$9,1)) -> 0.82 | O13: =INDEX(Factores!$B$13:$B$16,MATCH(B13,Factores!$A$13:$A$16,1)) -> 1 | P13: =M13*N13*O13 -> 1.23 | Q13: =LE!B11 -> 4.7250665 | R13: =D13/$D$3 -> 0.0033477741
A14: 9 | B14: 81 | C14: F | D14: 1.2506 | E14: 7 | F14: =INDEX(Factores!$C$29:$C$36,MATCH(E14,Factores!$A$29:$A$36,0)) -> A+ | G14: 0.0515 | H14: 1 | I14: 1 | J14: 1 | K14: 10 | L14: Cardiovascular | M14: =IF(Supuestos!$C$23=1,AVERAGE(I14:J14),MIN(I14:J14)) -> 1 | N14: =INDEX(IF(H14=1,Factores!$C$6:$C$9,Factores!$B$6:$B$9),MATCH(M14,Factores!$A$6:$A$9,1)) -> 0.9 | O14: =INDEX(Factores!$B$13:$B$16,MATCH(B14,Factores!$A$13:$A$16,1)) -> 0.95 | P14: =M14*N14*O14 -> 0.855 | Q14: =LE!B12 -> 10.36828 | R14: =D14/$D$3 -> 0.002779108
A15: 10 | B15: 80 | C15: M | D15: 0.8872 | E15: 5 | F15: =INDEX(Factores!$C$29:$C$36,MATCH(E15,Factores!$A$29:$A$36,0)) -> A- | G15: 0.0447 | H15: 1 | I15: 1.75 | J15: 2.25 | K15: 6 | L15: Sin deterioro mayor | M15: =IF(Supuestos!$C$23=1,AVERAGE(I15:J15),MIN(I15:J15)) -> 2 | N15: =INDEX(IF(H15=1,Factores!$C$6:$C$9,Factores!$B$6:$B$9),MATCH(M15,Factores!$A$6:$A$9,1)) -> 0.82 | O15: =INDEX(Factores!$B$13:$B$16,MATCH(B15,Factores!$A$13:$A$16,1)) -> 0.95 | P15: =M15*N15*O15 -> 1.558 | Q15: =LE!B13 -> 8.9735149 | R15: =D15/$D$3 -> 0.0019715534
A16: 11 | B16: 85 | C16: M | D16: 1.418 | E16: 2 | F16: =INDEX(Factores!$C$29:$C$36,MATCH(E16,Factores!$A$29:$A$36,0)) -> A+ | G16: 0.0567 | H16: 1 | I16: 3 | J16: 3 | K16: 4 | L16: Cáncer | M16: =IF(Supuestos!$C$23=1,AVERAGE(I16:J16),MIN(I16:J16)) -> 3 | N16: =INDEX(IF(H16=1,Factores!$C$6:$C$9,Factores!$B$6:$B$9),MATCH(M16,Factores!$A$6:$A$9,1)) -> 0.74 | O16: =INDEX(Factores!$B$13:$B$16,MATCH(B16,Factores!$A$13:$A$16,1)) -> 1 | P16: =M16*N16*O16 -> 2.22 | Q16: =LE!B14 -> 4.8340514 | R16: =D16/$D$3 -> 0.0031511076
A17: 12 | B17: 85 | C17: F | D17: 2.1652 | E17: 3 | F17: =INDEX(Factores!$C$29:$C$36,MATCH(E17,Factores!$A$29:$A$36,0)) -> A | G17: 0.0542 | H17: 1 | I17: 2.25 | J17: 3 | K17: 4 | L17: Múltiple | M17: =IF(Supuestos!$C$23=1,AVERAGE(I17:J17),MIN(I17:J17)) -> 2.625 | N17: =INDEX(IF(H17=1,Factores!$C$6:$C$9,Factores!$B$6:$B$9),MATCH(M17,Factores!$A$6:$A$9,1)) -> 0.82 | O17: =INDEX(Factores!$B$13:$B$16,MATCH(B17,Factores!$A$13:$A$16,1)) -> 1 | P17: =M17*N17*O17 -> 2.1525 | Q17: =LE!B15 -> 4.946883 | R17: =D17/$D$3 -> 0.0048115502
... A305: 300 | B305: 83 | C305: M | D305: 0.9307 | E305: 1 | F305: =INDEX(Factores!$C$29:$C$36,MATCH(E305,Factores!$A$29:$A$36,0)) -> A+ | G305: 0.0517 | H305: 1 | I305: 1.25 | J305: 1.5 | K305: 3 | L305: Múltiple | M305: =IF(Supuestos!$C$23=1,AVERAGE(I305:J305),MIN(I305:J305)) -> 1.375 | N305: =INDEX(IF(H305=1,Factores!$C$6:$C$9,Factores!$B$6:$B$9),MATCH(M305,Factores!$A$6:$A$9,1)) -> 0.9 | O305: =INDEX(Factores!$B$13:$B$16,MATCH(B305,Factores!$A$13:$A$16,1)) -> 0.95 | P305: =M305*N305*O305 -> 1.175625 | Q305: =LE!B303 -> 8.201687 | R305: =D305/$D$3 -> 0.0020682199

Sheet LE
A1: Supervivencia ajustada por póliza: q_t = MIN(1, q_base(edad+t−1) × [1+(MRaj−1)·máx(0,1−(t−1)/W)] × (1−MI)^(t−1)); LE = Σ S_t + 0.5
A3: ID | B3: LE (años) | C3: 1 | D3: 2 | E3: 3 | F3: 4 | G3: 5 | H3: 6 | I3: 7 | J3: 8 | K3: 9 | L3: 10 | M3: 11 | N3: 12 | O3: 13 | P3: 14 | Q3: 15 | R3: 16 | S3: 17 | T3: 18 | U3: 19 | V3: 20 | W3: 21 | X3: 22 | Y3: 23 | Z3: 24 | AA3: 25 | AB3: 26 | AC3: 27 | AD3: 28 | AE3: 29 | AF3: 30 | AG3: 31 | AH3: 32 | AI3: 33 | AJ3: 34 | AK3: 35 | AL3: 36 | AM3: 37 | AN3: 38 | AO3: 39 | AP3: 40 | AQ3: 41 | AR3: 42 | AS3: 43 | AT3: 44 | AU3: 45
A4: =Cartera_Polizas!A6 -> 1 | B4: =SUM(C4:AU4)+0.5 -> 8.6870665 | C4: =1-MIN(1,INDEX(Tabla_Mortalidad!$B$5:$B$75,MIN(71,Cartera_Polizas!$B$6+0-49))*(1+(Cartera_Polizas!$P$6-1)*MAX(0,1-0/Supuestos!$C$20))*(1-Supuestos!$C$18)^0) -> 0.94453551 | D4: =C4*(1-MIN(1,INDEX(Tabla_Mortalidad!$B$5:$B$75,MIN(71,Cartera_Polizas!$B$6+1-49))*(1+(Cartera_Polizas!$P$6-1)*MAX(0,1-1/Supuestos!$C$20))*(1-Supuestos!$C$18)^1)) -> 0.88659446 | E4: =D4*(1-MIN(1,INDEX(Tabla_Mortalidad!$B$5:$B$75,MIN(71,Cartera_Polizas!$B$6+2-49))*(1+(Cartera_Polizas!$P$6-1)*MAX(0,1-2/Supuestos!$C$20))*(1-Supuestos!$C$18)^2)) -> 0.82646574 | F4: =E4*(1-MIN(1,INDEX(Tabla_Mortalidad!$B$5:$B$75,MIN(71,Cartera_Polizas!$B$6+3-49))*(1+(Cartera_Polizas!$P$6-1)*MAX(0,1-3/Supuestos!$C$20))*(1-Supuestos!$C$18)^3)) -> 0.76452198 | G4: =F4*(1-MIN(1,INDEX(Tabla_Mortalidad!$B$5:$B$75,MIN(71,Cartera_Polizas!$B$6+4-49))*(1+(Cartera_Polizas!$P$6-1)*MAX(0,1-4/Supuestos!$C$20))*(1-Supuestos!$C$18)^4)) -> 0.70122702 | H4: =G4*(1-MIN(1,INDEX(Tabla_Mortalidad!$B$5:$B$75,MIN(71,Cartera_Polizas!$B$6+5-49))*(1+(Cartera_Polizas!$P$6-1)*MAX(0,1-5/Supuestos!$C$20))*(1-Supuestos!$C$18)^5)) -> 0.63713115 | I4: =H4*(1-MIN(1,INDEX(Tabla_Mortalidad!$B$5:$B$75,MIN(71,Cartera_Polizas!$B$6+6-49))*(1+(Cartera_Polizas!$P$6-1)*MAX(0,1-6/Supuestos!$C$20))*(1-Supuestos!$C$18)^6)) -> 0.57287149 | J4: =I4*(1-MIN(1,INDEX(Tabla_Mortalidad!$B$5:$B$75,MIN(71,Cartera_Polizas!$B$6+7-49))*(1+(Cartera_Polizas!$P$6-1)*MAX(0,1-7/Supuestos!$C$20))*(1-Supuestos!$C$18)^7)) -> 0.50915818 | K4: =J4*(1-MIN(1,INDEX(Tabla_Mortalidad!$B$5:$B$75,MIN(71,Cartera_Polizas!$B$6+8-49))*(1+(Cartera_Polizas!$P$6-1)*MAX(0,1-8/Supuestos!$C$20))*(1-Supuestos!$C$18)^8)) -> 0.44675842 | L4: =K4*(1-MIN(1,INDEX(Tabla_Mortalidad!$B$5:$B$75,MIN(71,Cartera_Polizas!$B$6+9-49))*(1+(Cartera_Polizas!$P$6-1)*MAX(0,1-9/Supuestos!$C$20))*(1-Supuestos!$C$18)^9)) -> 0.38647179 | M4: =L4*(1-MIN(1,INDEX(Tabla_Mortalidad!$B$5:$B$75,MIN(71,Cartera_Polizas!$B$6+10-49))*(1+(Cartera_Polizas!$P$6-1)*MAX(0,1-10/Supuestos!$C$20))*(1-Supuestos!$C$18)^10)) -> 0.329099 | N4: =M4*(1-MIN(1,INDEX(Tabla_Mortalidad!$B$5:$B$75,MIN(71,Cartera_Polizas!$B$6+11-49))*(1+(Cartera_Polizas!$P$6-1)*MAX(0,1-11/Supuestos!$C$20))*(1-Supuestos!$C$18)^11)) -> 0.27540408 | O4: =N4*(1-MIN(1,INDEX(Tabla_Mortalidad!$B$5:$B$75,MIN(71,Cartera_Polizas!$B$6+12-49))*(1+(Cartera_Polizas!$P$6-1)*MAX(0,1-12/Supuestos!$C$20))*(1-Supuestos!$C$18)^12)) -> 0.22607163 | P4: =O4*(1-MIN(1,INDEX(Tabla_Mortalidad!$B$5:$B$75,MIN(71,Cartera_Polizas!$B$6+13-49))*(1+(Cartera_Polizas!$P$6-1)*MAX(0,1-13/Supuestos!$C$20))*(1-Supuestos!$C$18)^13)) -> 0.18166481 | Q4: =P4*(1-MIN(1,INDEX(Tabla_Mortalidad!$B$5:$B$75,MIN(71,Cartera_Polizas!$B$6+14-49))*(1+(Cartera_Polizas!$P$6-1)*MAX(0,1-14/Supuestos!$C$20))*(1-Supuestos!$C$18)^14)) -> 0.14258578 | R4: =Q4*(1-MIN(1,INDEX(Tabla_Mortalidad!$B$5:$B$75,MIN(71,Cartera_Polizas!$B$6+15-49))*(1+(Cartera_Polizas!$P$6-1)*MAX(0,1-15/Supuestos!$C$20))*(1-Supuestos!$C$18)^15)) -> 0.10904366 | S4: =R4*(1-MIN(1,INDEX(Tabla_Mortalidad!$B$5:$B$75,MIN(71,Cartera_Polizas!$B$6+16-49))*(1+(Cartera_Polizas!$P$6-1)*MAX(0,1-16/Supuestos!$C$20))*(1-Supuestos!$C$18)^16)) -> 0.081008334 | T4: =S4*(1-MIN(1,INDEX(Tabla_Mortalidad!$B$5:$B$75,MIN(71,Cartera_Polizas!$B$6+17-49))*(1+(Cartera_Polizas!$P$6-1)*MAX(0,1-17/Supuestos!$C$20))*(1-Supuestos!$C$18)^17)) -> 0.058285664 | U4: =T4*(1-MIN(1,INDEX(Tabla_Mortalidad!$B$5:$B$75,MIN(71,Cartera_Polizas!$B$6+18-49))*(1+(Cartera_Polizas!$P$6-1)*MAX(0,1-18/Supuestos!$C$20))*(1-Supuestos!$C$18)^18)) -> 0.040483426 | V4: =U4*(1-MIN(1,INDEX(Tabla_Mortalidad!$B$5:$B$75,MIN(71,Cartera_Polizas!$B$6+19-49))*(1+(Cartera_Polizas!$P$6-1)*MAX(0,1-19/Supuestos!$C$20))*(1-Supuestos!$C$18)^19)) -> 0.027048146 | W4: =V4*(1-MIN(1,INDEX(Tabla_Mortalidad!$B$5:$B$75,MIN(71,Cartera_Polizas!$B$6+20-49))*(1+(Cartera_Polizas!$P$6-1)*MAX(0,1-20/Supuestos!$C$20))*(1-Supuestos!$C$18)^20)) -> 0.01731733 | X4: =W4*(1-MIN(1,INDEX(Tabla_Mortalidad!$B$5:$B$75,MIN(71,Cartera_Polizas!$B$6+21-49))*(1+(Cartera_Polizas!$P$6-1)*MAX(0,1-21/Supuestos!$C$20))*(1-Supuestos!$C$18)^21)) -> 0.010580955 | Y4: =X4*(1-MIN(1,INDEX(Tabla_Mortalidad!$B$5:$B$75,MIN(71,Cartera_Polizas!$B$6+22-49))*(1+(Cartera_Polizas!$P$6-1)*MAX(0,1-22/Supuestos!$C$20))*(1-Supuestos!$C$18)^22)) -> 0.0061428874 | Z4: =Y4*(1-MIN(1,INDEX(Tabla_Mortalidad!$B$5:$B$75,MIN(71,Cartera_Polizas!$B$6+23-49))*(1+(Cartera_Polizas!$P$6-1)*MAX(0,1-23/Supuestos!$C$20))*(1-Supuestos!$C$18)^23)) -> 0.0033730796 | AA4: =Z4*(1-MIN(1,INDEX(Tabla_Mortalidad!$B$5:$B$75,MIN(71,Cartera_Polizas!$B$6+24-49))*(1+(Cartera_Polizas!$P$6-1)*MAX(0,1-24/Supuestos!$C$20))*(1-Supuestos!$C$18)^24)) -> 0.0017434572 | AB4: =AA4*(1-MIN(1,INDEX(Tabla_Mortalidad!$B$5:$B$75,MIN(71,Cartera_Polizas!$B$6+25-49))*(1+(Cartera_Polizas!$P$6-1)*MAX(0,1-25/Supuestos!$C$20))*(1-Supuestos!$C$18)^25)) -> 0.00084412856 | AC4: =AB4*(1-MIN(1,INDEX(Tabla_Mortalidad!$B$5:$B$75,MIN(71,Cartera_Polizas!$B$6+26-49))*(1+(Cartera_Polizas!$P$6-1)*MAX(0,1-26/Supuestos!$C$20))*(1-Supuestos!$C$18)^26)) -> 0.00038098703 | AD4: =AC4*(1-MIN(1,INDEX(Tabla_Mortalidad!$B$5:$B$75,MIN(71,Cartera_Polizas!$B$6+27-49))*(1+(Cartera_Polizas!$P$6-1)*MAX(0,1-27/Supuestos!$C$20))*(1-Supuestos!$C$18)^27)) -> 0.00015954907 | AE4: =AD4*(1-MIN(1,INDEX(Tabla_Mortalidad!$B$5:$B$75,MIN(71,Cartera_Polizas!$B$6+28-49))*(1+(Cartera_Polizas!$P$6-1)*MAX(0,1-28/Supuestos!$C$20))*(1-Supuestos!$C$18)^28)) -> 6.1733775e-05 | AF4: =AE4*(1-MIN(1,INDEX(Tabla_Mortalidad!$B$5:$B$75,MIN(71,Cartera_Polizas!$B$6+29-49))*(1+(Cartera_Polizas!$P$6-1)*MAX(0,1-29/Supuestos!$C$20))*(1-Supuestos!$C$18)^29)) -> 2.1992455e-05 | AG4: =AF4*(1-MIN(1,INDEX(Tabla_Mortalidad!$B$5:$B$75,MIN(71,Cartera_Polizas!$B$6+30-49))*(1+(Cartera_Polizas!$P$6-1)*MAX(0,1-30/Supuestos!$C$20))*(1-Supuestos!$C$18)^30)) -> 7.1962007e-06 | AH4: =AG4*(1-MIN(1,INDEX(Tabla_Mortalidad!$B$5:$B$75,MIN(71,Cartera_Polizas!$B$6+31-49))*(1+(Cartera_Polizas!$P$6-1)*MAX(0,1-31/Supuestos!$C$20))*(1-Supuestos!$C$18)^31)) -> 2.1608773e-06 | AI4: =AH4*(1-MIN(1,INDEX(Tabla_Mortalidad!$B$5:$B$75,MIN(71,Cartera_Polizas!$B$6+32-49))*(1+(Cartera_Polizas!$P$6-1)*MAX(0,1-32/Supuestos!$C$20))*(1-Supuestos!$C$18)^32)) -> 5.9612222e-07 | AJ4: =AI4*(1-MIN(1,INDEX(Tabla_Mortalidad!$B$5:$B$75,MIN(71,Cartera_Polizas!$B$6+33-49))*(1+(Cartera_Polizas!$P$6-1)*MAX(0,1-33/Supuestos!$C$20))*(1-Supuestos!$C$18)^33)) -> 1.5161486e-07 | AK4: =AJ4*(1-MIN(1,INDEX(Tabla_Mortalidad!$B$5:$B$75,MIN(71,Cartera_Polizas!$B$6+34-49))*(1+(Cartera_Polizas!$P$6-1)*MAX(0,1-34/Supuestos!$C$20))*(1-Supuestos!$C$18)^34)) -> 3.5770513e-08 | AL4: =AK4*(1-MIN(1,INDEX(Tabla_Mortalidad!$B$5:$B$75,MIN(71,Cartera_Polizas!$B$6+35-49))*(1+(Cartera_Polizas!$P$6-1)*MAX(0,1-35/Supuestos!$C$20))*(1-Supuestos!$C$18)^35)) -> 7.897997e-09 | AM4: =AL4*(1-MIN(1,INDEX(Tabla_Mortalidad!$B$5:$B$75,MIN(71,Cartera_Polizas!$B$6+36-49))*(1+(Cartera_Polizas!$P$6-1)*MAX(0,1-36/Supuestos!$C$20))*(1-Supuestos!$C$18)^36)) -> 1.6502238e-09 | AN4: =AM4*(1-MIN(1,INDEX(Tabla_Mortalidad!$B$5:$B$75,MIN(71,Cartera_Polizas!$B$6+37-49))*(1+(Cartera_Polizas!$P$6-1)*MAX(0,1-37/Supuestos!$C$20))*(1-Supuestos!$C$18)^37)) -> 2.7935203e-10 | AO4: =AN4*(1-MIN(1,INDEX(Tabla_Mortalidad!$B$5:$B$75,MIN(71,Cartera_Polizas!$B$6+38-49))*(1+(Cartera_Polizas!$P$6-1)*MAX(0,1-38/Supuestos!$C$20))*(1-Supuestos!$C$18)^38)) -> 4.8449389e-11 | AP4: =AO4*(1-MIN(1,INDEX(Tabla_Mortalidad!$B$5:$B$75,MIN(71,Cartera_Polizas!$B$6+39-49))*(1+(Cartera_Polizas!$P$6-1)*MAX(0,1-39/Supuestos!$C$20))*(1-Supuestos!$C$18)^39)) -> 8.6030474e-12 | AQ4: =AP4*(1-MIN(1,INDEX(Tabla_Mortalidad!$B$5:$B$75,MIN(71,Cartera_Polizas!$B$6+40-49))*(1+(Cartera_Polizas!$P$6-1)*MAX(0,1-40/Supuestos!$C$20))*(1-Supuestos!$C$18)^40)) -> 1.5630006e-12 | AR4: =AQ4*(1-MIN(1,INDEX(Tabla_Mortalidad!$B$5:$B$75,MIN(71,Cartera_Polizas!$B$6+41-49))*(1+(Cartera_Polizas!$P$6-1)*MAX(0,1-41/Supuestos!$C$20))*(1-Supuestos!$C$18)^41)) -> 2.9036094e-13 | AS4: =AR4*(1-MIN(1,INDEX(Tabla_Mortalidad!$B$5:$B$75,MIN(71,Cartera_Polizas!$B$6+42-49))*(1+(Cartera_Polizas!$P$6-1)*MAX(0,1-42/Supuestos!$C$20))*(1-Supuestos!$C$18)^42)) -> 5.5122881e-14 | AT4: =AS4*(1-MIN(1,INDEX(Tabla_Mortalidad!$B$5:$B$75,MIN(71,Cartera_Polizas!$B$6+43-49))*(1+(Cartera_Polizas!$P$6-1)*MAX(0,1-43/Supuestos!$C$20))*(1-Supuestos!$C$18)^43)) -> 1.0687963e-14 | AU4: =AT4*(1-MIN(1,INDEX(Tabla_Mortalidad!$B$5:$B$75,MIN(71,Cartera_Polizas!$B$6+44-49))*(1+(Cartera_Polizas!$P$6-1)*MAX(0,1-44/Supuestos!$C$20))*(1-Supuestos!$C$18)^44)) -> 2.1154038e-15
A5: =Cartera_Polizas!A7 -> 2 | B5: =SUM(C5:AU5)+0.5 -> 4.8953688 | C5: =1-MIN(1,INDEX(Tabla_Mortalidad!$B$5:$B$75,MIN(71,Cartera_Polizas!$B$7+0-49))*(1+(Cartera_Polizas!$P$7-1)*MAX(0,1-0/Supuestos!$C$20))*(1-Supuestos!$C$18)^0) -> 0.84986599 | D5: =C5*(1-MIN(1,INDEX(Tabla_Mortalidad!$B$5:$B$75,MIN(71,Cartera_Polizas!$B$7+1-49))*(1+(Cartera_Polizas!$P$7-1)*MAX(0,1-1/Supuestos!$C$20))*(1-Supuestos!$C$18)^1)) -> 0.71426169 | E5: =D5*(1-MIN(1,INDEX(Tabla_Mortalidad!$B$5:$B$75,MIN(71,Cartera_Polizas!$B$7+2-49))*(1+(Cartera_Polizas!$P$7-1)*MAX(0,1-2/Supuestos!$C$20))*(1-Supuestos!$C$18)^2)) -> 0.59339416 | F5: =E5*(1-MIN(1,INDEX(Tabla_Mortalidad!$B$5:$B$75,MIN(71,Cartera_Polizas!$B$7+3-49))*(1+(Cartera_Polizas!$P$7-1)*MAX(0,1-3/Supuestos!$C$20))*(1-Supuestos!$C$18)^3)) -> 0.48714912 | G5: =F5*(1-MIN(1,INDEX(Tabla_Mortalidad!$B$5:$B$75,MIN(71,Cartera_Polizas!$B$7+4-49))*(1+(Cartera_Polizas!$P$7-1)*MAX(0,1-4/Supuestos!$C$20))*(1-Supuestos!$C$18)^4)) -> 0.39509467 | H5: =G5*(1-MIN(1,INDEX(Tabla_Mortalidad!$B$5:$B$75,MIN(71,Cartera_Polizas!$B$7+5-49))*(1+(Cartera_Polizas!$P$7-1)*MAX(0,1-5/Supuestos!$C$20))*(1-Supuestos!$C$18)^5)) -> 0.31652027 | I5: =H5*(1-MIN(1,INDEX(Tabla_Mortalidad!$B$5:$B$75,MIN(71,Cartera_Polizas!$B$7+6-49))*(1+(Cartera_Polizas!$P$7-1)*MAX(0,1-6/Supuestos!$C$20))*(1-Supuestos!$C$18)^6)) -> 0.25047547 | J5: =I5*(1-MIN(1,INDEX(Tabla_Mortalidad!$B$5:$B$75,MIN(71,Cartera_Polizas!$B$7+7-49))*(1+(Cartera_Polizas!$P$7-1)*MAX(0,1-7/Supuestos!$C$20))*(1-Supuestos!$C$18)^7)) -> 0.1958274 | K5: =J5*(1-MIN(1,INDEX(Tabla_Mortalidad!$B$5:$B$75,MIN(71,Cartera_Polizas!$B$7+8-49))*(1+(Cartera_Polizas!$P$7-1)*MAX(0,1-8/Supuestos!$C$20))*(1-Supuestos!$C$18)^8)) -> 0.15132286 | L5: =K5*(1-MIN(1,INDEX(Tabla_Mortalidad!$B$5:$B$75,MIN(71,Cartera_Polizas!$B$7+9-49))*(1+(Cartera_Polizas!$P$7-1)*MAX(0,1-9/Supuestos!$C$20))*(1-Supuestos!$C$18)^9)) -> 0.11565237 | M5: =L5*(1-MIN(1,INDEX(Tabla_Mortalidad!$B$5:$B$75,MIN(71,Cartera_Polizas!$B$7+10-49))*(1+(Cartera_Polizas!$P$7-1)*MAX(0,1-10/Supuestos!$C$20))*(1-Supuestos!$C$18)^10)) -> 0.087510399 | N5: =M5*(1-MIN(1,INDEX(Tabla_Mortalidad!$B$5:$B$75,MIN(71,Cartera_Polizas!$B$7+11-49))*(1+(Cartera_Polizas!$P$7-1)*MAX(0,1-11/Supuestos!$C$20))*(1-Supuestos!$C$18)^11)) -> 0.065647376 | O5: =N5*(1-MIN(1,INDEX(Tabla_Mortalidad!$B$5:$B$75,MIN(71,Cartera_Polizas!$B$7+12-49))*(1+(Cartera_Polizas!$P$7-1)*MAX(0,1-12/Supuestos!$C$20))*(1-Supuestos!$C$18)^12)) -> 0.048911581 | P5: =O5*(1-MIN(1,INDEX(Tabla_Mortalidad!$B$5:$B$75,MIN(71,Cartera_Polizas!$B$7+13-49))*(1+(Cartera_Polizas!$P$7-1)*MAX(0,1-13/Supuestos!$C$20))*(1-Supuestos!$C$18)^13)) -> 0.036277326 | Q5: =P5*(1-MIN(1,INDEX(Tabla_Mortalidad!$B$5:$B$75,MIN(71,Cartera_Polizas!$B$7+14-49))*(1+(Cartera_Polizas!$P$7-1)*MAX(0,1-14/Supuestos!$C$20))*(1-Supuestos!$C$18)^14)) -> 0.026859973 | R5: =Q5*(1-MIN(1,INDEX(Tabla_Mortalidad!$B$5:$B$75,MIN(71,Cartera_Polizas!$B$7+15-49))*(1+(Cartera_Polizas!$P$7-1)*MAX(0,1-15/Supuestos!$C$20))*(1-Supuestos!$C$18)^15)) -> 0.019919522 | S5: =R5*(1-MIN(1,INDEX(Tabla_Mortalidad!$B$5:$B$75,MIN(71,Cartera_Polizas!$B$7+16-49))*(1+(Cartera_Polizas!$P$7-1)*MAX(0,1-16/Supuestos!$C$20))*(1-Supuestos!$C$18)^16)) -> 0.01430406 | T5: =S5*(1-MIN(1,INDEX(Tabla_Mortalidad!$B$5:$B$75,MIN(71,Cartera_Polizas!$B$7+17-49))*(1+(Cartera_Polizas!$P$7-1)*MAX(0,1-17/Supuestos!$C$20))*(1-Supuestos!$C$18)^17)) -> 0.0099132052 | U5: =T5*(1-MIN(1,INDEX(Tabla_Mortalidad!$B$5:$B$75,MIN(71,Cartera_Polizas!$B$7+18-49))*(1+(Cartera_Polizas!$P$7-1)*MAX(0,1-18/Supuestos!$C$20))*(1-Supuestos!$C$18)^18)) -> 0.0066067664 | V5: =U5*(1-MIN(1,INDEX(Tabla_Mortalidad!$B$5:$B$75,MIN(71,Cartera_Polizas!$B$7+19-49))*(1+(Cartera_Polizas!$P$7-1)*MAX(0,1-19/Supuestos!$C$20))*(1-Supuestos!$C$18)^19)) -> 0.0042179783 | W5: =V5*(1-MIN(1,INDEX(Tabla_Mortalidad!$B$5:$B$75,MIN(71,Cartera_Polizas!$B$7+20-49))*(1+(Cartera_Polizas!$P$7-1)*MAX(0,1-20/Supuestos!$C$20))*(1-Supuestos!$C$18)^20)) -> 0.0025689558 | X5: =W5*(1-MIN(1,INDEX(Tabla_Mortalidad!$B$5:$B$75,MIN(71,Cartera_Polizas!$B$7+21-49))*(1+(Cartera_Polizas!$P$7-1)*MAX(0,1-21/Supuestos!$C$20))*(1-Supuestos!$C$18)^21)) -> 0.0014860203 | Y5: =X5*(1-MIN(1,INDEX(Tabla_Mortalidad!$B$5:$B$75,MIN(71,Cartera_Polizas!$B$7+22-49))*(1+(Cartera_Polizas!$P$7-1)*MAX(0,1-22/Supuestos!$C$20))*(1-Supuestos!$C$18)^22)) -> 0.00081261157 | Z5: =Y5*(1-MIN(1,INDEX(Tabla_Mortalidad!$B$5:$B$75,MIN(71,Cartera_Polizas!$B$7+23-49))*(1+(Cartera_Polizas!$P$7-1)*MAX(0,1-23/Supuestos!$C$20))*(1-Supuestos!$C$18)^23)) -> 0.00041804498 | AA5: =Z5*(1-MIN(1,INDEX(Tabla_Mortalidad!$B$5:$B$75,MIN(71,Cartera_Polizas!$B$7+24-49))*(1+(Cartera_Polizas!$P$7-1)*MAX(0,1-24/Supuestos!$C$20))*(1-Supuestos!$C$18)^24)) -> 0.00020132095 | AB5: =AA5*(1-MIN(1,INDEX(Tabla_Mortalidad!$B$5:$B$75,MIN(71,Cartera_Polizas!$B$7+25-49))*(1+(Cartera_Polizas!$P$7-1)*MAX(0,1-25/Supuestos!$C$20))*(1-Supuestos!$C$18)^25)) -> 9.0308669e-05 | AC5: =AB5*(1-MIN(1,INDEX(Tabla_Mortalidad!$B$5:$B$75,MIN(71,Cartera_Polizas!$B$7+26-49))*(1+(Cartera_Polizas!$P$7-1)*MAX(0,1-26/Supuestos!$C$20))*(1-Supuestos!$C$18)^26)) -> 3.7555539e-05 | AD5: =AC5*(1-MIN(1,INDEX(Tabla_Mortalidad!$B$5:$B$75,MIN(71,Cartera_Polizas!$B$7+27-49))*(1+(Cartera_Polizas!$P$7-1)*MAX(0,1-27/Supuestos!$C$20))*(1-Supuestos!$C$18)^27)) -> 1.4415536e-05 | AE5: =AD5*(1-MIN(1,INDEX(Tabla_Mortalidad!$B$5:$B$75,MIN(71,Cartera_Polizas!$B$7+28-49))*(1+(Cartera_Polizas!$P$7-1)*MAX(0,1-28/Supuestos!$C$20))*(1-Supuestos!$C$18)^28)) -> 5.0888538e-06 | AF5: =AE5*(1-MIN(1,INDEX(Tabla_Mortalidad!$B$5:$B$75,MIN(71,Cartera_Polizas!$B$7+29-49))*(1+(Cartera_Polizas!$P$7-1)*MAX(0,1-29/Supuestos!$C$20))*(1-Supuestos!$C$18)^29)) -> 1.6479307e-06 | AG5: =AF5*(1-MIN(1,INDEX(Tabla_Mortalidad!$B$5:$B$75,MIN(71,Cartera_Polizas!$B$7+30-49))*(1+(Cartera_Polizas!$P$7-1)*MAX(0,1-30/Supuestos!$C$20))*(1-Supuestos!$C$18)^30)) -> 4.8904671e-07 | AH5: =AG5*(1-MIN(1,INDEX(Tabla_Mortalidad!$B$5:$B$75,MIN(71,Cartera_Polizas!$B$7+31-49))*(1+(Cartera_Polizas!$P$7-1)*MAX(0,1-31/Supuestos!$C$20))*(1-Supuestos!$C$18)^31)) -> 1.3313398e-07 | AI5: =AH5*(1-MIN(1,INDEX(Tabla_Mortalidad!$B$5:$B$75,MIN(71,Cartera_Polizas!$B$7+32-49))*(1+(Cartera_Polizas!$P$7-1)*MAX(0,1-32/Supuestos!$C$20))*(1-Supuestos!$C$18)^32)) -> 3.3361795e-08 | AJ5: =AI5*(1-MIN(1,INDEX(Tabla_Mortalidad!$B$5:$B$75,MIN(71,Cartera_Polizas!$B$7+33-49))*(1+(Cartera_Polizas!$P$7-1)*MAX(0,1-33/Supuestos!$C$20))*(1-Supuestos!$C$18)^33)) -> 7.7429583e-09 | AK5: =AJ5*(1-MIN(1,INDEX(Tabla_Mortalidad!$B$5:$B$75,MIN(71,Cartera_Polizas!$B$7+34-49))*(1+(Cartera_Polizas!$P$7-1)*MAX(0,1-34/Supuestos!$C$20))*(1-Supuestos!$C$18)^34)) -> 1.6792983e-09 | AL5: =AK5*(1-MIN(1,INDEX(Tabla_Mortalidad!$B$5:$B$75,MIN(71,Cartera_Polizas!$B$7+35-49))*(1+(Cartera_Polizas!$P$7-1)*MAX(0,1-35/Supuestos!$C$20))*(1-Supuestos!$C$18)^35)) -> 3.4420056e-10 | AM5: =AL5*(1-MIN(1,INDEX(Tabla_Mortalidad!$B$5:$B$75,MIN(71,Cartera_Polizas!$B$7+36-49))*(1+(Cartera_Polizas!$P$7-1)*MAX(0,1-36/Supuestos!$C$20))*(1-Supuestos!$C$18)^36)) -> 5.6829864e-11 | AN5: =AM5*(1-MIN(1,INDEX(Tabla_Mortalidad!$B$5:$B$75,MIN(71,Cartera_Polizas!$B$7+37-49))*(1+(Cartera_Polizas!$P$7-1)*MAX(0,1-37/Supuestos!$C$20))*(1-Supuestos!$C$18)^37)) -> 9.6202332e-12 | AO5: =AN5*(1-MIN(1,INDEX(Tabla_Mortalidad!$B$5:$B$75,MIN(71,Cartera_Polizas!$B$7+38-49))*(1+(Cartera_Polizas!$P$7-1)*MAX(0,1-38/Supuestos!$C$20))*(1-Supuestos!$C$18)^38)) -> 1.6684841e-12 | AP5: =AO5*(1-MIN(1,INDEX(Tabla_Mortalidad!$B$5:$B$75,MIN(71,Cartera_Polizas!$B$7+39-49))*(1+(Cartera_Polizas!$P$7-1)*MAX(0,1-39/Supuestos!$C$20))*(1-Supuestos!$C$18)^39)) -> 2.9626891e-13 | AQ5: =AP5*(1-MIN(1,INDEX(Tabla_Mortalidad!$B$5:$B$75,MIN(71,Cartera_Polizas!$B$7+40-49))*(1+(Cartera_Polizas!$P$7-1)*MAX(0,1-40/Supuestos!$C$20))*(1-Supuestos!$C$18)^40)) -> 5.3826101e-14 | AR5: =AQ5*(1-MIN(1,INDEX(Tabla_Mortalidad!$B$5:$B$75,MIN(71,Cartera_Polizas!$B$7+41-49))*(1+(Cartera_Polizas!$P$7-1)*MAX(0,1-41/Supuestos!$C$20))*(1-Supuestos!$C$18)^41)) -> 9.9993543e-15 | AS5: =AR5*(1-MIN(1,INDEX(Tabla_Mortalidad!$B$5:$B$75,MIN(71,Cartera_Polizas!$B$7+42-49))*(1+(Cartera_Polizas!$P$7-1)*MAX(0,1-42/Supuestos!$C$20))*(1-Supuestos!$C$18)^42)) -> 1.8983036e-15 | AT5: =AS5*(1-MIN(1,INDEX(Tabla_Mortalidad!$B$5:$B$75,MIN(71,Cartera_Polizas!$B$7+43-49))*(1+(Cartera_Polizas!$P$7-1)*MAX(0,1-43/Supuestos!$C$20))*(1-Supuestos!$C$18)^43)) -> 3.6806857e-16 | AU5: =AT5*(1-MIN(1,INDEX(Tabla_Mortalidad!$B$5:$B$75,MIN(71,Cartera_Polizas!$B$7+44-49))*(1+(Cartera_Polizas!$P$7-1)*MAX(0,1-44/Supuestos!$C$20))*(1-Supuestos!$C$18)^44)) -> 7.2849581e-17
A6: =Cartera_Polizas!A8 -> 3 | B6: =SUM(C6:AU6)+0.5 -> 6.8701522 | C6: =1-MIN(1,INDEX(Tabla_Mortalidad!$B$5:$B$75,MIN(71,Cartera_Polizas!$B$8+0-49))*(1+(Cartera_Polizas!$P$8-1)*MAX(0,1-0/Supuestos!$C$20))*(1-Supuestos!$C$18)^0) -> 0.90441865 | D6: =C6*(1-MIN(1,INDEX(Tabla_Mortalidad!$B$5:$B$75,MIN(71,Cartera_Polizas!$B$8+1-49))*(1+(Cartera_Polizas!$P$8-1)*MAX(0,1-1/Supuestos!$C$20))*(1-Supuestos!$C$18)^1)) -> 0.81178567 | E6: =D6*(1-MIN(1,INDEX(Tabla_Mortalidad!$B$5:$B$75,MIN(71,Cartera_Polizas!$B$8+2-49))*(1+(Cartera_Polizas!$P$8-1)*MAX(0,1-2/Supuestos!$C$20))*(1-Supuestos!$C$18)^2)) -> 0.72282063 | F6: =E6*(1-MIN(1,INDEX(Tabla_Mortalidad!$B$5:$B$75,MIN(71,Cartera_Polizas!$B$8+3-49))*(1+(Cartera_Polizas!$P$8-1)*MAX(0,1-3/Supuestos!$C$20))*(1-Supuestos!$C$18)^3)) -> 0.63819462 | G6: =F6*(1-MIN(1,INDEX(Tabla_Mortalidad!$B$5:$B$75,MIN(71,Cartera_Polizas!$B$8+4-49))*(1+(Cartera_Polizas!$P$8-1)*MAX(0,1-4/Supuestos!$C$20))*(1-Supuestos!$C$18)^4)) -> 0.5585075 | H6: =G6*(1-MIN(1,INDEX(Tabla_Mortalidad!$B$5:$B$75,MIN(71,Cartera_Polizas!$B$8+5-49))*(1+(Cartera_Polizas!$P$8-1)*MAX(0,1-5/Supuestos!$C$20))*(1-Supuestos!$C$18)^5)) -> 0.48427174 | I6: =H6*(1-MIN(1,INDEX(Tabla_Mortalidad!$B$5:$B$75,MIN(71,Cartera_Polizas!$B$8+6-49))*(1+(Cartera_Polizas!$P$8-1)*MAX(0,1-6/Supuestos!$C$20))*(1-Supuestos!$C$18)^6)) -> 0.41588733 | J6: =I6*(1-MIN(1,INDEX(Tabla_Mortalidad!$B$5:$B$75,MIN(71,Cartera_Polizas!$B$8+7-49))*(1+(Cartera_Polizas!$P$8-1)*MAX(0,1-7/Supuestos!$C$20))*(1-Supuestos!$C$18)^7)) -> 0.35363305 | K6: =J6*(1-MIN(1,INDEX(Tabla_Mortalidad!$B$5:$B$75,MIN(71,Cartera_Polizas!$B$8+8-49))*(1+(Cartera_Polizas!$P$8-1)*MAX(0,1-8/Supuestos!$C$20))*(1-Supuestos!$C$18)^8)) -> 0.29765317 | L6: =K6*(1-MIN(1,INDEX(Tabla_Mortalidad!$B$5:$B$75,MIN(71,Cartera_Polizas!$B$8+9-49))*(1+(Cartera_Polizas!$P$8-1)*MAX(0,1-9/Supuestos!$C$20))*(1-Supuestos!$C$18)^9)) -> 0.24795554 | M6: =L6*(1-MIN(1,INDEX(Tabla_Mortalidad!$B$5:$B$75,MIN(71,Cartera_Polizas!$B$8+10-49))*(1+(Cartera_Polizas!$P$8-1)*MAX(0,1-10/Supuestos!$C$20))*(1-Supuestos!$C$18)^10)) -> 0.20441496 | N6: =M6*(1-MIN(1,INDEX(Tabla_Mortalidad!$B$5:$B$75,MIN(71,Cartera_Polizas!$B$8+11-49))*(1+(Cartera_Polizas!$P$8-1)*MAX(0,1-11/Supuestos!$C$20))*(1-Supuestos!$C$18)^11)) -> 0.16678374 | O6: =N6*(1-MIN(1,INDEX(Tabla_Mortalidad!$B$5:$B$75,MIN(71,Cartera_Polizas!$B$8+12-49))*(1+(Cartera_Polizas!$P$8-1)*MAX(0,1-12/Supuestos!$C$20))*(1-Supuestos!$C$18)^12)) -> 0.1347079 | P6: =O6*(1-MIN(1,INDEX(Tabla_Mortalidad!$B$5:$B$75,MIN(71,Cartera_Polizas!$B$8+13-49))*(1+(Cartera_Polizas!$P$8-1)*MAX(0,1-13/Supuestos!$C$20))*(1-Supuestos!$C$18)^13)) -> 0.10774805 | Q6: =P6*(1-MIN(1,INDEX(Tabla_Mortalidad!$B$5:$B$75,MIN(71,Cartera_Polizas!$B$8+14-49))*(1+(Cartera_Polizas!$P$8-1)*MAX(0,1-14/Supuestos!$C$20))*(1-Supuestos!$C$18)^14)) -> 0.085404525 | R6: =Q6*(1-MIN(1,INDEX(Tabla_Mortalidad!$B$5:$B$75,MIN(71,Cartera_Polizas!$B$8+15-49))*(1+(Cartera_Polizas!$P$8-1)*MAX(0,1-15/Supuestos!$C$20))*(1-Supuestos!$C$18)^15)) -> 0.067143136 | S6: =R6*(1-MIN(1,INDEX(Tabla_Mortalidad!$B$5:$B$75,MIN(71,Cartera_Polizas!$B$8+16-49))*(1+(Cartera_Polizas!$P$8-1)*MAX(0,1-16/Supuestos!$C$20))*(1-Supuestos!$C$18)^16)) -> 0.051427245 | T6: =S6*(1-MIN(1,INDEX(Tabla_Mortalidad!$B$5:$B$75,MIN(71,Cartera_Polizas!$B$8+17-49))*(1+(Cartera_Polizas!$P$8-1)*MAX(0,1-17/Supuestos!$C$20))*(1-Supuestos!$C$18)^17)) -> 0.038271316 | U6: =T6*(1-MIN(1,INDEX(Tabla_Mortalidad!$B$5:$B$75,MIN(71,Cartera_Polizas!$B$8+18-49))*(1+(Cartera_Polizas!$P$8-1)*MAX(0,1-18/Supuestos!$C$20))*(1-Supuestos!$C$18)^18)) -> 0.027589966 | V6: =U6*(1-MIN(1,INDEX(Tabla_Mortalidad!$B$5:$B$75,MIN(71,Cartera_Polizas!$B$8+19-49))*(1+(Cartera_Polizas!$P$8-1)*MAX(0,1-19/Supuestos!$C$20))*(1-Supuestos!$C$18)^19)) -> 0.019205274 | W6: =V6*(1-MIN(1,INDEX(Tabla_Mortalidad!$B$5:$B$75,MIN(71,Cartera_Polizas!$B$8+20-49))*(1+(Cartera_Polizas!$P$8-1)*MAX(0,1-20/Supuestos!$C$20))*(1-Supuestos!$C$18)^20)) -> 0.012863467 | X6: =W6*(1-MIN(1,INDEX(Tabla_Mortalidad!$B$5:$B$75,MIN(71,Cartera_Polizas!$B$8+21-49))*(1+(Cartera_Polizas!$P$8-1)*MAX(0,1-21/Supuestos!$C$20))*(1-Supuestos!$C$18)^21)) -> 0.0082588566 | Y6: =X6*(1-MIN(1,INDEX(Tabla_Mortalidad!$B$5:$B$75,MIN(71,Cartera_Polizas!$B$8+22-49))*(1+(Cartera_Polizas!$P$8-1)*MAX(0,1-22/Supuestos!$C$20))*(1-Supuestos!$C$18)^22)) -> 0.0050622562 | Z6: =Y6*(1-MIN(1,INDEX(Tabla_Mortalidad!$B$5:$B$75,MIN(71,Cartera_Polizas!$B$8+23-49))*(1+(Cartera_Polizas!$P$8-1)*MAX(0,1-23/Supuestos!$C$20))*(1-Supuestos!$C$18)^23)) -> 0.002949564 | AA6: =Z6*(1-MIN(1,INDEX(Tabla_Mortalidad!$B$5:$B$75,MIN(71,Cartera_Polizas!$B$8+24-49))*(1+(Cartera_Polizas!$P$8-1)*MAX(0,1-24/Supuestos!$C$20))*(1-Supuestos!$C$18)^24)) -> 0.001626265 | AB6: =AA6*(1-MIN(1,INDEX(Tabla_Mortalidad!$B$5:$B$75,MIN(71,Cartera_Polizas!$B$8+25-49))*(1+(Cartera_Polizas!$P$8-1)*MAX(0,1-25/Supuestos!$C$20))*(1-Supuestos!$C$18)^25)) -> 0.00084450259 | AC6: =AB6*(1-MIN(1,INDEX(Tabla_Mortalidad!$B$5:$B$75,MIN(71,Cartera_Polizas!$B$8+26-49))*(1+(Cartera_Polizas!$P$8-1)*MAX(0,1-26/Supuestos!$C$20))*(1-Supuestos!$C$18)^26)) -> 0.00041106038 | AD6: =AC6*(1-MIN(1,INDEX(Tabla_Mortalidad!$B$5:$B$75,MIN(71,Cartera_Polizas!$B$8+27-49))*(1+(Cartera_Polizas!$P$8-1)*MAX(0,1-27/Supuestos!$C$20))*(1-Supuestos!$C$18)^27)) -> 0.00018665471 | AE6: =AD6*(1-MIN(1,INDEX(Tabla_Mortalidad!$B$5:$B$75,MIN(71,Cartera_Polizas!$B$8+28-49))*(1+(Cartera_Polizas!$P$8-1)*MAX(0,1-28/Supuestos!$C$20))*(1-Supuestos!$C$18)^28)) -> 7.8709366e-05 | AF6: =AE6*(1-MIN(1,INDEX(Tabla_Mortalidad!$B$5:$B$75,MIN(71,Cartera_Polizas!$B$8+29-49))*(1+(Cartera_Polizas!$P$8-1)*MAX(0,1-29/Supuestos!$C$20))*(1-Supuestos!$C$18)^29)) -> 3.0696018e-05 | AG6: =AF6*(1-MIN(1,INDEX(Tabla_Mortalidad!$B$5:$B$75,MIN(71,Cartera_Polizas!$B$8+30-49))*(1+(Cartera_Polizas!$P$8-1)*MAX(0,1-30/Supuestos!$C$20))*(1-Supuestos!$C$18)^30)) -> 1.1034159e-05 | AH6: =AG6*(1-MIN(1,INDEX(Tabla_Mortalidad!$B$5:$B$75,MIN(71,Cartera_Polizas!$B$8+31-49))*(1+(Cartera_Polizas!$P$8-1)*MAX(0,1-31/Supuestos!$C$20))*(1-Supuestos!$C$18)^31)) -> 3.6476302e-06 | AI6: =AH6*(1-MIN(1,INDEX(Tabla_Mortalidad!$B$5:$B$75,MIN(71,Cartera_Polizas!$B$8+32-49))*(1+(Cartera_Polizas!$P$8-1)*MAX(0,1-32/Supuestos!$C$20))*(1-Supuestos!$C$18)^32)) -> 1.1080731e-06 | AJ6: =AI6*(1-MIN(1,INDEX(Tabla_Mortalidad!$B$5:$B$75,MIN(71,Cartera_Polizas!$B$8+33-49))*(1+(Cartera_Polizas!$P$8-1)*MAX(0,1-33/Supuestos!$C$20))*(1-Supuestos!$C$18)^33)) -> 3.0969658e-07 | AK6: =AJ6*(1-MIN(1,INDEX(Tabla_Mortalidad!$B$5:$B$75,MIN(71,Cartera_Polizas!$B$8+34-49))*(1+(Cartera_Polizas!$P$8-1)*MAX(0,1-34/Supuestos!$C$20))*(1-Supuestos!$C$18)^34)) -> 7.9921387e-08 | AL6: =AK6*(1-MIN(1,INDEX(Tabla_Mortalidad!$B$5:$B$75,MIN(71,Cartera_Polizas!$B$8+35-49))*(1+(Cartera_Polizas!$P$8-1)*MAX(0,1-35/Supuestos!$C$20))*(1-Supuestos!$C$18)^35)) -> 1.9161191e-08 | AM6: =AL6*(1-MIN(1,INDEX(Tabla_Mortalidad!$B$5:$B$75,MIN(71,Cartera_Polizas!$B$8+36-49))*(1+(Cartera_Polizas!$P$8-1)*MAX(0,1-36/Supuestos!$C$20))*(1-Supuestos!$C$18)^36)) -> 4.3053724e-09 | AN6: =AM6*(1-MIN(1,INDEX(Tabla_Mortalidad!$B$5:$B$75,MIN(71,Cartera_Polizas!$B$8+37-49))*(1+(Cartera_Polizas!$P$8-1)*MAX(0,1-37/Supuestos!$C$20))*(1-Supuestos!$C$18)^37)) -> 9.166024e-10 | AO6: =AN6*(1-MIN(1,INDEX(Tabla_Mortalidad!$B$5:$B$75,MIN(71,Cartera_Polizas!$B$8+38-49))*(1+(Cartera_Polizas!$P$8-1)*MAX(0,1-38/Supuestos!$C$20))*(1-Supuestos!$C$18)^38)) -> 1.5897084e-10 | AP6: =AO6*(1-MIN(1,INDEX(Tabla_Mortalidad!$B$5:$B$75,MIN(71,Cartera_Polizas!$B$8+39-49))*(1+(Cartera_Polizas!$P$8-1)*MAX(0,1-39/Supuestos!$C$20))*(1-Supuestos!$C$18)^39)) -> 2.8228089e-11 | AQ6: =AP6*(1-MIN(1,INDEX(Tabla_Mortalidad!$B$5:$B$75,MIN(71,Cartera_Polizas!$B$8+40-49))*(1+(Cartera_Polizas!$P$8-1)*MAX(0,1-40/Supuestos!$C$20))*(1-Supuestos!$C$18)^40)) -> 5.1284758e-12 | AR6: =AQ6*(1-MIN(1,INDEX(Tabla_Mortalidad!$B$5:$B$75,MIN(71,Cartera_Polizas!$B$8+41-49))*(1+(Cartera_Polizas!$P$8-1)*MAX(0,1-41/Supuestos!$C$20))*(1-Supuestos!$C$18)^41)) -> 9.5272453e-13 | AS6: =AR6*(1-MIN(1,INDEX(Tabla_Mortalidad!$B$5:$B$75,MIN(71,Cartera_Polizas!$B$8+42-49))*(1+(Cartera_Polizas!$P$8-1)*MAX(0,1-42/Supuestos!$C$20))*(1-Supuestos!$C$18)^42)) -> 1.8086772e-13 | AT6: =AS6*(1-MIN(1,INDEX(Tabla_Mortalidad!$B$5:$B$75,MIN(71,Cartera_Polizas!$B$8+43-49))*(1+(Cartera_Polizas!$P$8-1)*MAX(0,1-43/Supuestos!$C$20))*(1-Supuestos!$C$18)^43)) -> 3.5069059e-14 | AU6: =AT6*(1-MIN(1,INDEX(Tabla_Mortalidad!$B$5:$B$75,MIN(71,Cartera_Polizas!$B$8+44-49))*(1+(Cartera_Polizas!$P$8-1)*MAX(0,1-44/Supuestos!$C$20))*(1-Supuestos!$C$18)^44)) -> 6.9410065e-15
A7: =Cartera_Polizas!A9 -> 4 | B7: =SUM(C7:AU7)+0.5 -> 8.8634763 | C7: =1-MIN(1,INDEX(Tabla_Mortalidad!$B$5:$B$75,MIN(71,Cartera_Polizas!$B$9+0-49))*(1+(Cartera_Polizas!$P$9-1)*MAX(0,1-0/Supuestos!$C$20))*(1-Supuestos!$C$18)^0) -> 0.93316243 | D7: =C7*(1-MIN(1,INDEX(Tabla_Mortalidad!$B$5:$B$75,MIN(71,Cartera_Polizas!$B$9+1-49))*(1+(Cartera_Polizas!$P$9-1)*MAX(0,1-1/Supuestos!$C$20))*(1-Supuestos!$C$18)^1)) -> 0.86619093 | E7: =D7*(1-MIN(1,INDEX(Tabla_Mortalidad!$B$5:$B$75,MIN(71,Cartera_Polizas!$B$9+2-49))*(1+(Cartera_Polizas!$P$9-1)*MAX(0,1-2/Supuestos!$C$20))*(1-Supuestos!$C$18)^2)) -> 0.79952639 | F7: =E7*(1-MIN(1,INDEX(Tabla_Mortalidad!$B$5:$B$75,MIN(71,Cartera_Polizas!$B$9+3-49))*(1+(Cartera_Polizas!$P$9-1)*MAX(0,1-3/Supuestos!$C$20))*(1-Supuestos!$C$18)^3)) -> 0.73362855 | G7: =F7*(1-MIN(1,INDEX(Tabla_Mortalidad!$B$5:$B$75,MIN(71,Cartera_Polizas!$B$9+4-49))*(1+(Cartera_Polizas!$P$9-1)*MAX(0,1-4/Supuestos!$C$20))*(1-Supuestos!$C$18)^4)) -> 0.66896921 | H7: =G7*(1-MIN(1,INDEX(Tabla_Mortalidad!$B$5:$B$75,MIN(71,Cartera_Polizas!$B$9+5-49))*(1+(Cartera_Polizas!$P$9-1)*MAX(0,1-5/Supuestos!$C$20))*(1-Supuestos!$C$18)^5)) -> 0.60602268 | I7: =H7*(1-MIN(1,INDEX(Tabla_Mortalidad!$B$5:$B$75,MIN(71,Cartera_Polizas!$B$9+6-49))*(1+(Cartera_Polizas!$P$9-1)*MAX(0,1-6/Supuestos!$C$20))*(1-Supuestos!$C$18)^6)) -> 0.54525027 | J7: =I7*(1-MIN(1,INDEX(Tabla_Mortalidad!$B$5:$B$75,MIN(71,Cartera_Polizas!$B$9+7-49))*(1+(Cartera_Polizas!$P$9-1)*MAX(0,1-7/Supuestos!$C$20))*(1-Supuestos!$C$18)^7)) -> 0.4870867 | K7: =J7*(1-MIN(1,INDEX(Tabla_Mortalidad!$B$5:$B$75,MIN(71,Cartera_Polizas!$B$9+8-49))*(1+(Cartera_Polizas!$P$9-1)*MAX(0,1-8/Supuestos!$C$20))*(1-Supuestos!$C$18)^8)) -> 0.43193026 | L7: =K7*(1-MIN(1,INDEX(Tabla_Mortalidad!$B$5:$B$75,MIN(71,Cartera_Polizas!$B$9+9-49))*(1+(Cartera_Polizas!$P$9-1)*MAX(0,1-9/Supuestos!$C$20))*(1-Supuestos!$C$18)^9)) -> 0.38012527 | M7: =L7*(1-MIN(1,INDEX(Tabla_Mortalidad!$B$5:$B$75,MIN(71,Cartera_Polizas!$B$9+10-49))*(1+(Cartera_Polizas!$P$9-1)*MAX(0,1-10/Supuestos!$C$20))*(1-Supuestos!$C$18)^10)) -> 0.33195499 | N7: =M7*(1-MIN(1,INDEX(Tabla_Mortalidad!$B$5:$B$75,MIN(71,Cartera_Polizas!$B$9+11-49))*(1+(Cartera_Polizas!$P$9-1)*MAX(0,1-11/Supuestos!$C$20))*(1-Supuestos!$C$18)^11)) -> 0.28762929 | O7: =N7*(1-MIN(1,INDEX(Tabla_Mortalidad!$B$5:$B$75,MIN(71,Cartera_Polizas!$B$9+12-49))*(1+(Cartera_Polizas!$P$9-1)*MAX(0,1-12/Supuestos!$C$20))*(1-Supuestos!$C$18)^12)) -> 0.2472792 | P7: =O7*(1-MIN(1,INDEX(Tabla_Mortalidad!$B$5:$B$75,MIN(71,Cartera_Polizas!$B$9+13-49))*(1+(Cartera_Polizas!$P$9-1)*MAX(0,1-13/Supuestos!$C$20))*(1-Supuestos!$C$18)^13)) -> 0.21095377 | Q7: =P7*(1-MIN(1,INDEX(Tabla_Mortalidad!$B$5:$B$75,MIN(71,Cartera_Polizas!$B$9+14-49))*(1+(Cartera_Polizas!$P$9-1)*MAX(0,1-14/Supuestos!$C$20))*(1-Supuestos!$C$18)^14)) -> 0.17862097 | R7: =Q7*(1-MIN(1,INDEX(Tabla_Mortalidad!$B$5:$B$75,MIN(71,Cartera_Polizas!$B$9+15-49))*(1+(Cartera_Polizas!$P$9-1)*MAX(0,1-15/Supuestos!$C$20))*(1-Supuestos!$C$18)^15)) -> 0.15017232 | S7: =R7*(1-MIN(1,INDEX(Tabla_Mortalidad!$B$5:$B$75,MIN(71,Cartera_Polizas!$B$9+16-49))*(1+(Cartera_Polizas!$P$9-1)*MAX(0,1-16/Supuestos!$C$20))*(1-Supuestos!$C$18)^16)) -> 0.1238868 | T7: =S7*(1-MIN(1,INDEX(Tabla_Mortalidad!$B$5:$B$75,MIN(71,Cartera_Polizas!$B$9+17-49))*(1+(Cartera_Polizas!$P$9-1)*MAX(0,1-17/Supuestos!$C$20))*(1-Supuestos!$C$18)^17)) -> 0.10008361 | U7: =T7*(1-MIN(1,INDEX(Tabla_Mortalidad!$B$5:$B$75,MIN(71,Cartera_Polizas!$B$9+18-49))*(1+(Cartera_Polizas!$P$9-1)*MAX(0,1-18/Supuestos!$C$20))*(1-Supuestos!$C$18)^18)) -> 0.079002906 | V7: =U7*(1-MIN(1,INDEX(Tabla_Mortalidad!$B$5:$B$75,MIN(71,Cartera_Polizas!$B$9+19-49))*(1+(Cartera_Polizas!$P$9-1)*MAX(0,1-19/Supuestos!$C$20))*(1-Supuestos!$C$18)^19)) -> 0.060787046 | W7: =V7*(1-MIN(1,INDEX(Tabla_Mortalidad!$B$5:$B$75,MIN(71,Cartera_Polizas!$B$9+20-49))*(1+(Cartera_Polizas!$P$9-1)*MAX(0,1-20/Supuestos!$C$20))*(1-Supuestos!$C$18)^20)) -> 0.045468817 | X7: =W7*(1-MIN(1,INDEX(Tabla_Mortalidad!$B$5:$B$75,MIN(71,Cartera_Polizas!$B$9+21-49))*(1+(Cartera_Polizas!$P$9-1)*MAX(0,1-21/Supuestos!$C$20))*(1-Supuestos!$C$18)^21)) -> 0.032968079 | Y7: =X7*(1-MIN(1,INDEX(Tabla_Mortalidad!$B$5:$B$75,MIN(71,Cartera_Polizas!$B$9+22-49))*(1+(Cartera_Polizas!$P$9-1)*MAX(0,1-22/Supuestos!$C$20))*(1-Supuestos!$C$18)^22)) -> 0.023098496 | Z7: =Y7*(1-MIN(1,INDEX(Tabla_Mortalidad!$B$5:$B$75,MIN(71,Cartera_Polizas!$B$9+23-49))*(1+(Cartera_Polizas!$P$9-1)*MAX(0,1-23/Supuestos!$C$20))*(1-Supuestos!$C$18)^23)) -> 0.01558494 | AA7: =Z7*(1-MIN(1,INDEX(Tabla_Mortalidad!$B$5:$B$75,MIN(71,Cartera_Polizas!$B$9+24-49))*(1+(Cartera_Polizas!$P$9-1)*MAX(0,1-24/Supuestos!$C$20))*(1-Supuestos!$C$18)^24)) -> 0.010089415 | AB7: =AA7*(1-MIN(1,INDEX(Tabla_Mortalidad!$B$5:$B$75,MIN(71,Cartera_Polizas!$B$9+25-49))*(1+(Cartera_Polizas!$P$9-1)*MAX(0,1-25/Supuestos!$C$20))*(1-Supuestos!$C$18)^25)) -> 0.0062425792 | AC7: =AB7*(1-MIN(1,INDEX(Tabla_Mortalidad!$B$5:$B$75,MIN(71,Cartera_Polizas!$B$9+26-49))*(1+(Cartera_Polizas!$P$9-1)*MAX(0,1-26/Supuestos!$C$20))*(1-Supuestos!$C$18)^26)) -> 0.0036761729 | AD7: =AC7*(1-MIN(1,INDEX(Tabla_Mortalidad!$B$5:$B$75,MIN(71,Cartera_Polizas!$B$9+27-49))*(1+(Cartera_Polizas!$P$9-1)*MAX(0,1-27/Supuestos!$C$20))*(1-Supuestos!$C$18)^27)) -> 0.0020515023 | AE7: =AD7*(1-MIN(1,INDEX(Tabla_Mortalidad!$B$5:$B$75,MIN(71,Cartera_Polizas!$B$9+28-49))*(1+(Cartera_Polizas!$P$9-1)*MAX(0,1-28/Supuestos!$C$20))*(1-Supuestos!$C$18)^28)) -> 0.0010800427 | AF7: =AE7*(1-MIN(1,INDEX(Tabla_Mortalidad!$B$5:$B$75,MIN(71,Cartera_Polizas!$B$9+29-49))*(1+(Cartera_Polizas!$P$9-1)*MAX(0,1-29/Supuestos!$C$20))*(1-Supuestos!$C$18)^29)) -> 0.00053398269 | AG7: =AF7*(1-MIN(1,INDEX(Tabla_Mortalidad!$B$5:$B$75,MIN(71,Cartera_Polizas!$B$9+30-49))*(1+(Cartera_Polizas!$P$9-1)*MAX(0,1-30/Supuestos!$C$20))*(1-Supuestos!$C$18)^30)) -> 0.00024682223 | AH7: =AG7*(1-MIN(1,INDEX(Tabla_Mortalidad!$B$5:$B$75,MIN(71,Cartera_Polizas!$B$9+31-49))*(1+(Cartera_Polizas!$P$9-1)*MAX(0,1-31/Supuestos!$C$20))*(1-Supuestos!$C$18)^31)) -> 0.0001062115 | AI7: =AH7*(1-MIN(1,INDEX(Tabla_Mortalidad!$B$5:$B$75,MIN(71,Cartera_Polizas!$B$9+32-49))*(1+(Cartera_Polizas!$P$9-1)*MAX(0,1-32/Supuestos!$C$20))*(1-Supuestos!$C$18)^32)) -> 4.2388625e-05 | AJ7: =AI7*(1-MIN(1,INDEX(Tabla_Mortalidad!$B$5:$B$75,MIN(71,Cartera_Polizas!$B$9+33-49))*(1+(Cartera_Polizas!$P$9-1)*MAX(0,1-33/Supuestos!$C$20))*(1-Supuestos!$C$18)^33)) -> 1.5642485e-05 | AK7: =AJ7*(1-MIN(1,INDEX(Tabla_Mortalidad!$B$5:$B$75,MIN(71,Cartera_Polizas!$B$9+34-49))*(1+(Cartera_Polizas!$P$9-1)*MAX(0,1-34/Supuestos!$C$20))*(1-Supuestos!$C$18)^34)) -> 5.3273209e-06 | AL7: =AK7*(1-MIN(1,INDEX(Tabla_Mortalidad!$B$5:$B$75,MIN(71,Cartera_Polizas!$B$9+35-49))*(1+(Cartera_Polizas!$P$9-1)*MAX(0,1-35/Supuestos!$C$20))*(1-Supuestos!$C$18)^35)) -> 1.6736849e-06 | AM7: =AL7*(1-MIN(1,INDEX(Tabla_Mortalidad!$B$5:$B$75,MIN(71,Cartera_Polizas!$B$9+36-49))*(1+(Cartera_Polizas!$P$9-1)*MAX(0,1-36/Supuestos!$C$20))*(1-Supuestos!$C$18)^36)) -> 4.8577832e-07 | AN7: =AM7*(1-MIN(1,INDEX(Tabla_Mortalidad!$B$5:$B$75,MIN(71,Cartera_Polizas!$B$9+37-49))*(1+(Cartera_Polizas!$P$9-1)*MAX(0,1-37/Supuestos!$C$20))*(1-Supuestos!$C$18)^37)) -> 1.3074093e-07 | AO7: =AN7*(1-MIN(1,INDEX(Tabla_Mortalidad!$B$5:$B$75,MIN(71,Cartera_Polizas!$B$9+38-49))*(1+(Cartera_Polizas!$P$9-1)*MAX(0,1-38/Supuestos!$C$20))*(1-Supuestos!$C$18)^38)) -> 3.2828693e-08 | AP7: =AO7*(1-MIN(1,INDEX(Tabla_Mortalidad!$B$5:$B$75,MIN(71,Cartera_Polizas!$B$9+39-49))*(1+(Cartera_Polizas!$P$9-1)*MAX(0,1-39/Supuestos!$C$20))*(1-Supuestos!$C$18)^39)) -> 7.7562346e-09 | AQ7: =AP7*(1-MIN(1,INDEX(Tabla_Mortalidad!$B$5:$B$75,MIN(71,Cartera_Polizas!$B$9+40-49))*(1+(Cartera_Polizas!$P$9-1)*MAX(0,1-40/Supuestos!$C$20))*(1-Supuestos!$C$18)^40)) -> 1.742399e-09 | AR7: =AQ7*(1-MIN(1,INDEX(Tabla_Mortalidad!$B$5:$B$75,MIN(71,Cartera_Polizas!$B$9+41-49))*(1+(Cartera_Polizas!$P$9-1)*MAX(0,1-41/Supuestos!$C$20))*(1-Supuestos!$C$18)^41)) -> 3.2368804e-10 | AS7: =AR7*(1-MIN(1,INDEX(Tabla_Mortalidad!$B$5:$B$75,MIN(71,Cartera_Polizas!$B$9+42-49))*(1+(Cartera_Polizas!$P$9-1)*MAX(0,1-42/Supuestos!$C$20))*(1-Supuestos!$C$18)^42)) -> 6.1449786e-11 | AT7: =AS7*(1-MIN(1,INDEX(Tabla_Mortalidad!$B$5:$B$75,MIN(71,Cartera_Polizas!$B$9+43-49))*(1+(Cartera_Polizas!$P$9-1)*MAX(0,1-43/Supuestos!$C$20))*(1-Supuestos!$C$18)^43)) -> 1.1914709e-11 | AU7: =AT7*(1-MIN(1,INDEX(Tabla_Mortalidad!$B$5:$B$75,MIN(71,Cartera_Polizas!$B$9+44-49))*(1+(Cartera_Polizas!$P$9-1)*MAX(0,1-44/Supuestos!$C$20))*(1-Supuestos!$C$18)^44)) -> 2.3582061e-12
A8: =Cartera_Polizas!A10 -> 5 | B8: =SUM(C8:AU8)+0.5 -> 9.8554715 | C8: =1-MIN(1,INDEX(Tabla_Mortalidad!$B$5:$B$75,MIN(71,Cartera_Polizas!$B$10+0-49))*(1+(Cartera_Polizas!$P$10-1)*MAX(0,1-0/Supuestos!$C$20))*(1-Supuestos!$C$18)^0) -> 0.95524401 | D8: =C8*(1-MIN(1,INDEX(Tabla_Mortalidad!$B$5:$B$75,MIN(71,Cartera_Polizas!$B$10+1-49))*(1+(Cartera_Polizas!$P$10-1)*MAX(0,1-1/Supuestos!$C$20))*(1-Supuestos!$C$18)^1)) -> 0.90792932 | E8: =D8*(1-MIN(1,INDEX(Tabla_Mortalidad!$B$5:$B$75,MIN(71,Cartera_Polizas!$B$10+2-49))*(1+(Cartera_Polizas!$P$10-1)*MAX(0,1-2/Supuestos!$C$20))*(1-Supuestos!$C$18)^2)) -> 0.85817406 | F8: =E8*(1-MIN(1,INDEX(Tabla_Mortalidad!$B$5:$B$75,MIN(71,Cartera_Polizas!$B$10+3-49))*(1+(Cartera_Polizas!$P$10-1)*MAX(0,1-3/Supuestos!$C$20))*(1-Supuestos!$C$18)^3)) -> 0.80616074 | G8: =F8*(1-MIN(1,INDEX(Tabla_Mortalidad!$B$5:$B$75,MIN(71,Cartera_Polizas!$B$10+4-49))*(1+(Cartera_Polizas!$P$10-1)*MAX(0,1-4/Supuestos!$C$20))*(1-Supuestos!$C$18)^4)) -> 0.75214146 | H8: =G8*(1-MIN(1,INDEX(Tabla_Mortalidad!$B$5:$B$75,MIN(71,Cartera_Polizas!$B$10+5-49))*(1+(Cartera_Polizas!$P$10-1)*MAX(0,1-5/Supuestos!$C$20))*(1-Supuestos!$C$18)^5)) -> 0.69644321 | I8: =H8*(1-MIN(1,INDEX(Tabla_Mortalidad!$B$5:$B$75,MIN(71,Cartera_Polizas!$B$10+6-49))*(1+(Cartera_Polizas!$P$10-1)*MAX(0,1-6/Supuestos!$C$20))*(1-Supuestos!$C$18)^6)) -> 0.6394749 | J8: =I8*(1-MIN(1,INDEX(Tabla_Mortalidad!$B$5:$B$75,MIN(71,Cartera_Polizas!$B$10+7-49))*(1+(Cartera_Polizas!$P$10-1)*MAX(0,1-7/Supuestos!$C$20))*(1-Supuestos!$C$18)^7)) -> 0.58172352 | K8: =J8*(1-MIN(1,INDEX(Tabla_Mortalidad!$B$5:$B$75,MIN(71,Cartera_Polizas!$B$10+8-49))*(1+(Cartera_Polizas!$P$10-1)*MAX(0,1-8/Supuestos!$C$20))*(1-Supuestos!$C$18)^8)) -> 0.5237549 | L8: =K8*(1-MIN(1,INDEX(Tabla_Mortalidad!$B$5:$B$75,MIN(71,Cartera_Polizas!$B$10+9-49))*(1+(Cartera_Polizas!$P$10-1)*MAX(0,1-9/Supuestos!$C$20))*(1-Supuestos!$C$18)^9)) -> 0.46620206 | M8: =L8*(1-MIN(1,INDEX(Tabla_Mortalidad!$B$5:$B$75,MIN(71,Cartera_Polizas!$B$10+10-49))*(1+(Cartera_Polizas!$P$10-1)*MAX(0,1-10/Supuestos!$C$20))*(1-Supuestos!$C$18)^10)) -> 0.40975137 | N8: =M8*(1-MIN(1,INDEX(Tabla_Mortalidad!$B$5:$B$75,MIN(71,Cartera_Polizas!$B$10+11-49))*(1+(Cartera_Polizas!$P$10-1)*MAX(0,1-11/Supuestos!$C$20))*(1-Supuestos!$C$18)^11)) -> 0.35512118 | O8: =N8*(1-MIN(1,INDEX(Tabla_Mortalidad!$B$5:$B$75,MIN(71,Cartera_Polizas!$B$10+12-49))*(1+(Cartera_Polizas!$P$10-1)*MAX(0,1-12/Supuestos!$C$20))*(1-Supuestos!$C$18)^12)) -> 0.30303436 | P8: =O8*(1-MIN(1,INDEX(Tabla_Mortalidad!$B$5:$B$75,MIN(71,Cartera_Polizas!$B$10+13-49))*(1+(Cartera_Polizas!$P$10-1)*MAX(0,1-13/Supuestos!$C$20))*(1-Supuestos!$C$18)^13)) -> 0.2541848 | Q8: =P8*(1-MIN(1,INDEX(Tabla_Mortalidad!$B$5:$B$75,MIN(71,Cartera_Polizas!$B$10+14-49))*(1+(Cartera_Polizas!$P$10-1)*MAX(0,1-14/Supuestos!$C$20))*(1-Supuestos!$C$18)^14)) -> 0.20919923 | R8: =Q8*(1-MIN(1,INDEX(Tabla_Mortalidad!$B$5:$B$75,MIN(71,Cartera_Polizas!$B$10+15-49))*(1+(Cartera_Polizas!$P$10-1)*MAX(0,1-15/Supuestos!$C$20))*(1-Supuestos!$C$18)^15)) -> 0.16859942 | S8: =R8*(1-MIN(1,INDEX(Tabla_Mortalidad!$B$5:$B$75,MIN(71,Cartera_Polizas!$B$10+16-49))*(1+(Cartera_Polizas!$P$10-1)*MAX(0,1-16/Supuestos!$C$20))*(1-Supuestos!$C$18)^16)) -> 0.13272936 | T8: =S8*(1-MIN(1,INDEX(Tabla_Mortalidad!$B$5:$B$75,MIN(71,Cartera_Polizas!$B$10+17-49))*(1+(Cartera_Polizas!$P$10-1)*MAX(0,1-17/Supuestos!$C$20))*(1-Supuestos!$C$18)^17)) -> 0.10181733 | U8: =T8*(1-MIN(1,INDEX(Tabla_Mortalidad!$B$5:$B$75,MIN(71,Cartera_Polizas!$B$10+18-49))*(1+(Cartera_Polizas!$P$10-1)*MAX(0,1-18/Supuestos!$C$20))*(1-Supuestos!$C$18)^18)) -> 0.07590103 | V8: =U8*(1-MIN(1,INDEX(Tabla_Mortalidad!$B$5:$B$75,MIN(71,Cartera_Polizas!$B$10+19-49))*(1+(Cartera_Polizas!$P$10-1)*MAX(0,1-19/Supuestos!$C$20))*(1-Supuestos!$C$18)^19)) -> 0.054823317 | W8: =V8*(1-MIN(1,INDEX(Tabla_Mortalidad!$B$5:$B$75,MIN(71,Cartera_Polizas!$B$10+20-49))*(1+(Cartera_Polizas!$P$10-1)*MAX(0,1-20/Supuestos!$C$20))*(1-Supuestos!$C$18)^20)) -> 0.038245615 | X8: =W8*(1-MIN(1,INDEX(Tabla_Mortalidad!$B$5:$B$75,MIN(71,Cartera_Polizas!$B$10+21-49))*(1+(Cartera_Polizas!$P$10-1)*MAX(0,1-21/Supuestos!$C$20))*(1-Supuestos!$C$18)^21)) -> 0.025679608 | Y8: =X8*(1-MIN(1,INDEX(Tabla_Mortalidad!$B$5:$B$75,MIN(71,Cartera_Polizas!$B$10+22-49))*(1+(Cartera_Polizas!$P$10-1)*MAX(0,1-22/Supuestos!$C$20))*(1-Supuestos!$C$18)^22)) -> 0.01653329 | Z8: =Y8*(1-MIN(1,INDEX(Tabla_Mortalidad!$B$5:$B$75,MIN(71,Cartera_Polizas!$B$10+23-49))*(1+(Cartera_Polizas!$P$10-1)*MAX(0,1-23/Supuestos!$C$20))*(1-Supuestos!$C$18)^23)) -> 0.010166057 | AA8: =Z8*(1-MIN(1,INDEX(Tabla_Mortalidad!$B$5:$B$75,MIN(71,Cartera_Polizas!$B$10+24-49))*(1+(Cartera_Polizas!$P$10-1)*MAX(0,1-24/Supuestos!$C$20))*(1-Supuestos!$C$18)^24)) -> 0.0059445476 | AB8: =AA8*(1-MIN(1,INDEX(Tabla_Mortalidad!$B$5:$B$75,MIN(71,Cartera_Polizas!$B$10+25-49))*(1+(Cartera_Polizas!$P$10-1)*MAX(0,1-25/Supuestos!$C$20))*(1-Supuestos!$C$18)^25)) -> 0.0032909073 | AC8: =AB8*(1-MIN(1,INDEX(Tabla_Mortalidad!$B$5:$B$75,MIN(71,Cartera_Polizas!$B$10+26-49))*(1+(Cartera_Polizas!$P$10-1)*MAX(0,1-26/Supuestos!$C$20))*(1-Supuestos!$C$18)^26)) -> 0.001716844 | AD8: =AC8*(1-MIN(1,INDEX(Tabla_Mortalidad!$B$5:$B$75,MIN(71,Cartera_Polizas!$B$10+27-49))*(1+(Cartera_Polizas!$P$10-1)*MAX(0,1-27/Supuestos!$C$20))*(1-Supuestos!$C$18)^27)) -> 0.00084007712 | AE8: =AD8*(1-MIN(1,INDEX(Tabla_Mortalidad!$B$5:$B$75,MIN(71,Cartera_Polizas!$B$10+28-49))*(1+(Cartera_Polizas!$P$10-1)*MAX(0,1-28/Supuestos!$C$20))*(1-Supuestos!$C$18)^28)) -> 0.00038375613 | AF8: =AE8*(1-MIN(1,INDEX(Tabla_Mortalidad!$B$5:$B$75,MIN(71,Cartera_Polizas!$B$10+29-49))*(1+(Cartera_Polizas!$P$10-1)*MAX(0,1-29/Supuestos!$C$20))*(1-Supuestos!$C$18)^29)) -> 0.00016293361 | AG8: =AF8*(1-MIN(1,INDEX(Tabla_Mortalidad!$B$5:$B$75,MIN(71,Cartera_Polizas!$B$10+30-49))*(1+(Cartera_Polizas!$P$10-1)*MAX(0,1-30/Supuestos!$C$20))*(1-Supuestos!$C$18)^30)) -> 6.4039747e-05 | AH8: =AG8*(1-MIN(1,INDEX(Tabla_Mortalidad!$B$5:$B$75,MIN(71,Cartera_Polizas!$B$10+31-49))*(1+(Cartera_Polizas!$P$10-1)*MAX(0,1-31/Supuestos!$C$20))*(1-Supuestos!$C$18)^31)) -> 2.3225177e-05 | AI8: =AH8*(1-MIN(1,INDEX(Tabla_Mortalidad!$B$5:$B$75,MIN(71,Cartera_Polizas!$B$10+32-49))*(1+(Cartera_Polizas!$P$10-1)*MAX(0,1-32/Supuestos!$C$20))*(1-Supuestos!$C$18)^32)) -> 7.755428e-06 | AJ8: =AI8*(1-MIN(1,INDEX(Tabla_Mortalidad!$B$5:$B$75,MIN(71,Cartera_Polizas!$B$10+33-49))*(1+(Cartera_Polizas!$P$10-1)*MAX(0,1-33/Supuestos!$C$20))*(1-Supuestos!$C$18)^33)) -> 2.3829328e-06 | AK8: =AJ8*(1-MIN(1,INDEX(Tabla_Mortalidad!$B$5:$B$75,MIN(71,Cartera_Polizas!$B$10+34-49))*(1+(Cartera_Polizas!$P$10-1)*MAX(0,1-34/Supuestos!$C$20))*(1-Supuestos!$C$18)^34)) -> 6.7459316e-07 | AL8: =AK8*(1-MIN(1,INDEX(Tabla_Mortalidad!$B$5:$B$75,MIN(71,Cartera_Polizas!$B$10+35-49))*(1+(Cartera_Polizas!$P$10-1)*MAX(0,1-35/Supuestos!$C$20))*(1-Supuestos!$C$18)^35)) -> 1.7659041e-07 | AM8: =AL8*(1-MIN(1,INDEX(Tabla_Mortalidad!$B$5:$B$75,MIN(71,Cartera_Polizas!$B$10+36-49))*(1+(Cartera_Polizas!$P$10-1)*MAX(0,1-36/Supuestos!$C$20))*(1-Supuestos!$C$18)^36)) -> 4.3008899e-08 | AN8: =AM8*(1-MIN(1,INDEX(Tabla_Mortalidad!$B$5:$B$75,MIN(71,Cartera_Polizas!$B$10+37-49))*(1+(Cartera_Polizas!$P$10-1)*MAX(0,1-37/Supuestos!$C$20))*(1-Supuestos!$C$18)^37)) -> 9.830495e-09 | AO8: =AN8*(1-MIN(1,INDEX(Tabla_Mortalidad!$B$5:$B$75,MIN(71,Cartera_Polizas!$B$10+38-49))*(1+(Cartera_Polizas!$P$10-1)*MAX(0,1-38/Supuestos!$C$20))*(1-Supuestos!$C$18)^38)) -> 2.1315744e-09 | AP8: =AO8*(1-MIN(1,INDEX(Tabla_Mortalidad!$B$5:$B$75,MIN(71,Cartera_Polizas!$B$10+39-49))*(1+(Cartera_Polizas!$P$10-1)*MAX(0,1-39/Supuestos!$C$20))*(1-Supuestos!$C$18)^39)) -> 3.784988e-10 | AQ8: =AP8*(1-MIN(1,INDEX(Tabla_Mortalidad!$B$5:$B$75,MIN(71,Cartera_Polizas!$B$10+40-49))*(1+(Cartera_Polizas!$P$10-1)*MAX(0,1-40/Supuestos!$C$20))*(1-Supuestos!$C$18)^40)) -> 6.8765616e-11 | AR8: =AQ8*(1-MIN(1,INDEX(Tabla_Mortalidad!$B$5:$B$75,MIN(71,Cartera_Polizas!$B$10+41-49))*(1+(Cartera_Polizas!$P$10-1)*MAX(0,1-41/Supuestos!$C$20))*(1-Supuestos!$C$18)^41)) -> 1.277469e-11 | AS8: =AR8*(1-MIN(1,INDEX(Tabla_Mortalidad!$B$5:$B$75,MIN(71,Cartera_Polizas!$B$10+42-49))*(1+(Cartera_Polizas!$P$10-1)*MAX(0,1-42/Supuestos!$C$20))*(1-Supuestos!$C$18)^42)) -> 2.4251807e-12 | AT8: =AS8*(1-MIN(1,INDEX(Tabla_Mortalidad!$B$5:$B$75,MIN(71,Cartera_Polizas!$B$10+43-49))*(1+(Cartera_Polizas!$P$10-1)*MAX(0,1-43/Supuestos!$C$20))*(1-Supuestos!$C$18)^43)) -> 4.7022656e-13 | AU8: =AT8*(1-MIN(1,INDEX(Tabla_Mortalidad!$B$5:$B$75,MIN(71,Cartera_Polizas!$B$10+44-49))*(1+(Cartera_Polizas!$P$10-1)*MAX(0,1-44/Supuestos!$C$20))*(1-Supuestos!$C$18)^44)) -> 9.3069093e-14
A9: =Cartera_Polizas!A11 -> 6 | B9: =SUM(C9:AU9)+0.5 -> 10.543546 | C9: =1-MIN(1,INDEX(Tabla_Mortalidad!$B$5:$B$75,MIN(71,Cartera_Polizas!$B$11+0-49))*(1+(Cartera_Polizas!$P$11-1)*MAX(0,1-0/Supuestos!$C$20))*(1-Supuestos!$C$18)^0) -> 0.95334347 | D9: =C9*(1-MIN(1,INDEX(Tabla_Mortalidad!$B$5:$B$75,MIN(71,Cartera_Polizas!$B$11+1-49))*(1+(Cartera_Polizas!$P$11-1)*MAX(0,1-1/Supuestos!$C$20))*(1-Supuestos!$C$18)^1)) -> 0.9050723 | E9: =D9*(1-MIN(1,INDEX(Tabla_Mortalidad!$B$5:$B$75,MIN(71,Cartera_Polizas!$B$11+2-49))*(1+(Cartera_Polizas!$P$11-1)*MAX(0,1-2/Supuestos!$C$20))*(1-Supuestos!$C$18)^2)) -> 0.85537326 | F9: =E9*(1-MIN(1,INDEX(Tabla_Mortalidad!$B$5:$B$75,MIN(71,Cartera_Polizas!$B$11+3-49))*(1+(Cartera_Polizas!$P$11-1)*MAX(0,1-3/Supuestos!$C$20))*(1-Supuestos!$C$18)^3)) -> 0.80447257 | G9: =F9*(1-MIN(1,INDEX(Tabla_Mortalidad!$B$5:$B$75,MIN(71,Cartera_Polizas!$B$11+4-49))*(1+(Cartera_Polizas!$P$11-1)*MAX(0,1-4/Supuestos!$C$20))*(1-Supuestos!$C$18)^4)) -> 0.75263403 | H9: =G9*(1-MIN(1,INDEX(Tabla_Mortalidad!$B$5:$B$75,MIN(71,Cartera_Polizas!$B$11+5-49))*(1+(Cartera_Polizas!$P$11-1)*MAX(0,1-5/Supuestos!$C$20))*(1-Supuestos!$C$18)^5)) -> 0.7001601 | I9: =H9*(1-MIN(1,INDEX(Tabla_Mortalidad!$B$5:$B$75,MIN(71,Cartera_Polizas!$B$11+6-49))*(1+(Cartera_Polizas!$P$11-1)*MAX(0,1-6/Supuestos!$C$20))*(1-Supuestos!$C$18)^6)) -> 0.64739085 | J9: =I9*(1-MIN(1,INDEX(Tabla_Mortalidad!$B$5:$B$75,MIN(71,Cartera_Polizas!$B$11+7-49))*(1+(Cartera_Polizas!$P$11-1)*MAX(0,1-7/Supuestos!$C$20))*(1-Supuestos!$C$18)^7)) -> 0.59469741 | K9: =J9*(1-MIN(1,INDEX(Tabla_Mortalidad!$B$5:$B$75,MIN(71,Cartera_Polizas!$B$11+8-49))*(1+(Cartera_Polizas!$P$11-1)*MAX(0,1-8/Supuestos!$C$20))*(1-Supuestos!$C$18)^8)) -> 0.54247538 | L9: =K9*(1-MIN(1,INDEX(Tabla_Mortalidad!$B$5:$B$75,MIN(71,Cartera_Polizas!$B$11+9-49))*(1+(Cartera_Polizas!$P$11-1)*MAX(0,1-9/Supuestos!$C$20))*(1-Supuestos!$C$18)^9)) -> 0.49114001 | M9: =L9*(1-MIN(1,INDEX(Tabla_Mortalidad!$B$5:$B$75,MIN(71,Cartera_Polizas!$B$11+10-49))*(1+(Cartera_Polizas!$P$11-1)*MAX(0,1-10/Supuestos!$C$20))*(1-Supuestos!$C$18)^10)) -> 0.4411121 | N9: =M9*(1-MIN(1,INDEX(Tabla_Mortalidad!$B$5:$B$75,MIN(71,Cartera_Polizas!$B$11+11-49))*(1+(Cartera_Polizas!$P$11-1)*MAX(0,1-11/Supuestos!$C$20))*(1-Supuestos!$C$18)^11)) -> 0.39281041 | O9: =N9*(1-MIN(1,INDEX(Tabla_Mortalidad!$B$5:$B$75,MIN(71,Cartera_Polizas!$B$11+12-49))*(1+(Cartera_Polizas!$P$11-1)*MAX(0,1-12/Supuestos!$C$20))*(1-Supuestos!$C$18)^12)) -> 0.34663613 | P9: =O9*(1-MIN(1,INDEX(Tabla_Mortalidad!$B$5:$B$75,MIN(71,Cartera_Polizas!$B$11+13-49))*(1+(Cartera_Polizas!$P$11-1)*MAX(0,1-13/Supuestos!$C$20))*(1-Supuestos!$C$18)^13)) -> 0.30296016 | Q9: =P9*(1-MIN(1,INDEX(Tabla_Mortalidad!$B$5:$B$75,MIN(71,Cartera_Polizas!$B$11+14-49))*(1+(Cartera_Polizas!$P$11-1)*MAX(0,1-14/Supuestos!$C$20))*(1-Supuestos!$C$18)^14)) -> 0.26210943 | R9: =Q9*(1-MIN(1,INDEX(Tabla_Mortalidad!$B$5:$B$75,MIN(71,Cartera_Polizas!$B$11+15-49))*(1+(Cartera_Polizas!$P$11-1)*MAX(0,1-15/Supuestos!$C$20))*(1-Supuestos!$C$18)^15)) -> 0.22435438 | S9: =R9*(1-MIN(1,INDEX(Tabla_Mortalidad!$B$5:$B$75,MIN(71,Cartera_Polizas!$B$11+16-49))*(1+(Cartera_Polizas!$P$11-1)*MAX(0,1-16/Supuestos!$C$20))*(1-Supuestos!$C$18)^16)) -> 0.18880051 | T9: =S9*(1-MIN(1,INDEX(Tabla_Mortalidad!$B$5:$B$75,MIN(71,Cartera_Polizas!$B$11+17-49))*(1+(Cartera_Polizas!$P$11-1)*MAX(0,1-17/Supuestos!$C$20))*(1-Supuestos!$C$18)^17)) -> 0.15591891 | U9: =T9*(1-MIN(1,INDEX(Tabla_Mortalidad!$B$5:$B$75,MIN(71,Cartera_Polizas!$B$11+18-49))*(1+(Cartera_Polizas!$P$11-1)*MAX(0,1-18/Supuestos!$C$20))*(1-Supuestos!$C$18)^18)) -> 0.12611097 | V9: =U9*(1-MIN(1,INDEX(Tabla_Mortalidad!$B$5:$B$75,MIN(71,Cartera_Polizas!$B$11+19-49))*(1+(Cartera_Polizas!$P$11-1)*MAX(0,1-19/Supuestos!$C$20))*(1-Supuestos!$C$18)^19)) -> 0.099680912 | W9: =V9*(1-MIN(1,INDEX(Tabla_Mortalidad!$B$5:$B$75,MIN(71,Cartera_Polizas!$B$11+20-49))*(1+(Cartera_Polizas!$P$11-1)*MAX(0,1-20/Supuestos!$C$20))*(1-Supuestos!$C$18)^20)) -> 0.0768122 | X9: =W9*(1-MIN(1,INDEX(Tabla_Mortalidad!$B$5:$B$75,MIN(71,Cartera_Polizas!$B$11+21-49))*(1+(Cartera_Polizas!$P$11-1)*MAX(0,1-21/Supuestos!$C$20))*(1-Supuestos!$C$18)^21)) -> 0.057552443 | Y9: =X9*(1-MIN(1,INDEX(Tabla_Mortalidad!$B$5:$B$75,MIN(71,Cartera_Polizas!$B$11+22-49))*(1+(Cartera_Polizas!$P$11-1)*MAX(0,1-22/Supuestos!$C$20))*(1-Supuestos!$C$18)^22)) -> 0.04180867 | Z9: =Y9*(1-MIN(1,INDEX(Tabla_Mortalidad!$B$5:$B$75,MIN(71,Cartera_Polizas!$B$11+23-49))*(1+(Cartera_Polizas!$P$11-1)*MAX(0,1-23/Supuestos!$C$20))*(1-Supuestos!$C$18)^23)) -> 0.029355079 | AA9: =Z9*(1-MIN(1,INDEX(Tabla_Mortalidad!$B$5:$B$75,MIN(71,Cartera_Polizas!$B$11+24-49))*(1+(Cartera_Polizas!$P$11-1)*MAX(0,1-24/Supuestos!$C$20))*(1-Supuestos!$C$18)^24)) -> 0.019854105 | AB9: =AA9*(1-MIN(1,INDEX(Tabla_Mortalidad!$B$5:$B$75,MIN(71,Cartera_Polizas!$B$11+25-49))*(1+(Cartera_Polizas!$P$11-1)*MAX(0,1-25/Supuestos!$C$20))*(1-Supuestos!$C$18)^25)) -> 0.012888201 | AC9: =AB9*(1-MIN(1,INDEX(Tabla_Mortalidad!$B$5:$B$75,MIN(71,Cartera_Polizas!$B$11+26-49))*(1+(Cartera_Polizas!$P$11-1)*MAX(0,1-26/Supuestos!$C$20))*(1-Supuestos!$C$18)^26)) -> 0.0079988295 | AD9: =AC9*(1-MIN(1,INDEX(Tabla_Mortalidad!$B$5:$B$75,MIN(71,Cartera_Polizas!$B$11+27-49))*(1+(Cartera_Polizas!$P$11-1)*MAX(0,1-27/Supuestos!$C$20))*(1-Supuestos!$C$18)^27)) -> 0.0047268477 | AE9: =AD9*(1-MIN(1,INDEX(Tabla_Mortalidad!$B$5:$B$75,MIN(71,Cartera_Polizas!$B$11+28-49))*(1+(Cartera_Polizas!$P$11-1)*MAX(0,1-28/Supuestos!$C$20))*(1-Supuestos!$C$18)^28)) -> 0.0026482804 | AF9: =AE9*(1-MIN(1,INDEX(Tabla_Mortalidad!$B$5:$B$75,MIN(71,Cartera_Polizas!$B$11+29-49))*(1+(Cartera_Polizas!$P$11-1)*MAX(0,1-29/Supuestos!$C$20))*(1-Supuestos!$C$18)^29)) -> 0.0014004954 | AG9: =AF9*(1-MIN(1,INDEX(Tabla_Mortalidad!$B$5:$B$75,MIN(71,Cartera_Polizas!$B$11+30-49))*(1+(Cartera_Polizas!$P$11-1)*MAX(0,1-30/Supuestos!$C$20))*(1-Supuestos!$C$18)^30)) -> 0.00069595772 | AH9: =AG9*(1-MIN(1,INDEX(Tabla_Mortalidad!$B$5:$B$75,MIN(71,Cartera_Polizas!$B$11+31-49))*(1+(Cartera_Polizas!$P$11-1)*MAX(0,1-31/Supuestos!$C$20))*(1-Supuestos!$C$18)^31)) -> 0.0003235631 | AI9: =AH9*(1-MIN(1,INDEX(Tabla_Mortalidad!$B$5:$B$75,MIN(71,Cartera_Polizas!$B$11+32-49))*(1+(Cartera_Polizas!$P$11-1)*MAX(0,1-32/Supuestos!$C$20))*(1-Supuestos!$C$18)^32)) -> 0.00014015595 | AJ9: =AI9*(1-MIN(1,INDEX(Tabla_Mortalidad!$B$5:$B$75,MIN(71,Cartera_Polizas!$B$11+33-49))*(1+(Cartera_Polizas!$P$11-1)*MAX(0,1-33/Supuestos!$C$20))*(1-Supuestos!$C$18)^33)) -> 5.6356834e-05 | AK9: =AJ9*(1-MIN(1,INDEX(Tabla_Mortalidad!$B$5:$B$75,MIN(71,Cartera_Polizas!$B$11+34-49))*(1+(Cartera_Polizas!$P$11-1)*MAX(0,1-34/Supuestos!$C$20))*(1-Supuestos!$C$18)^34)) -> 2.0974909e-05 | AL9: =AK9*(1-MIN(1,INDEX(Tabla_Mortalidad!$B$5:$B$75,MIN(71,Cartera_Polizas!$B$11+35-49))*(1+(Cartera_Polizas!$P$11-1)*MAX(0,1-35/Supuestos!$C$20))*(1-Supuestos!$C$18)^35)) -> 7.2125287e-06 | AM9: =AL9*(1-MIN(1,INDEX(Tabla_Mortalidad!$B$5:$B$75,MIN(71,Cartera_Polizas!$B$11+36-49))*(1+(Cartera_Polizas!$P$11-1)*MAX(0,1-36/Supuestos!$C$20))*(1-Supuestos!$C$18)^36)) -> 2.2906936e-06 | AN9: =AM9*(1-MIN(1,INDEX(Tabla_Mortalidad!$B$5:$B$75,MIN(71,Cartera_Polizas!$B$11+37-49))*(1+(Cartera_Polizas!$P$11-1)*MAX(0,1-37/Supuestos!$C$20))*(1-Supuestos!$C$18)^37)) -> 6.7299105e-07 | AO9: =AN9*(1-MIN(1,INDEX(Tabla_Mortalidad!$B$5:$B$75,MIN(71,Cartera_Polizas!$B$11+38-49))*(1+(Cartera_Polizas!$P$11-1)*MAX(0,1-38/Supuestos!$C$20))*(1-Supuestos!$C$18)^38)) -> 1.8358612e-07 | AP9: =AO9*(1-MIN(1,INDEX(Tabla_Mortalidad!$B$5:$B$75,MIN(71,Cartera_Polizas!$B$11+39-49))*(1+(Cartera_Polizas!$P$11-1)*MAX(0,1-39/Supuestos!$C$20))*(1-Supuestos!$C$18)^39)) -> 4.6785419e-08 | AQ9: =AP9*(1-MIN(1,INDEX(Tabla_Mortalidad!$B$5:$B$75,MIN(71,Cartera_Polizas!$B$11+40-49))*(1+(Cartera_Polizas!$P$11-1)*MAX(0,1-40/Supuestos!$C$20))*(1-Supuestos!$C$18)^40)) -> 1.1232363e-08 | AR9: =AQ9*(1-MIN(1,INDEX(Tabla_Mortalidad!$B$5:$B$75,MIN(71,Cartera_Polizas!$B$11+41-49))*(1+(Cartera_Polizas!$P$11-1)*MAX(0,1-41/Supuestos!$C$20))*(1-Supuestos!$C$18)^41)) -> 2.5668392e-09 | AS9: =AR9*(1-MIN(1,INDEX(Tabla_Mortalidad!$B$5:$B$75,MIN(71,Cartera_Polizas!$B$11+42-49))*(1+(Cartera_Polizas!$P$11-1)*MAX(0,1-42/Supuestos!$C$20))*(1-Supuestos!$C$18)^42)) -> 4.8729548e-10 | AT9: =AS9*(1-MIN(1,INDEX(Tabla_Mortalidad!$B$5:$B$75,MIN(71,Cartera_Polizas!$B$11+43-49))*(1+(Cartera_Polizas!$P$11-1)*MAX(0,1-43/Supuestos!$C$20))*(1-Supuestos!$C$18)^43)) -> 9.4483382e-11 | AU9: =AT9*(1-MIN(1,INDEX(Tabla_Mortalidad!$B$5:$B$75,MIN(71,Cartera_Polizas!$B$11+44-49))*(1+(Cartera_Polizas!$P$11-1)*MAX(0,1-44/Supuestos!$C$20))*(1-Supuestos!$C$18)^44)) -> 1.8700523e-11
A10: =Cartera_Polizas!A12 -> 7 | B10: =SUM(C10:AU10)+0.5 -> 7.97768 | C10: =1-MIN(1,INDEX(Tabla_Mortalidad!$B$5:$B$75,MIN(71,Cartera_Polizas!$B$12+0-49))*(1+(Cartera_Polizas!$P$12-1)*MAX(0,1-0/Supuestos!$C$20))*(1-Supuestos!$C$18)^0) -> 0.93149649 | D10: =C10*(1-MIN(1,INDEX(Tabla_Mortalidad!$B$5:$B$75,MIN(71,Cartera_Polizas!$B$12+1-49))*(1+(Cartera_Polizas!$P$12-1)*MAX(0,1-1/Supuestos!$C$20))*(1-Supuestos!$C$18)^1)) -> 0.86180503 | E10: =D10*(1-MIN(1,INDEX(Tabla_Mortalidad!$B$5:$B$75,MIN(71,Cartera_Polizas!$B$12+2-49))*(1+(Cartera_Polizas!$P$12-1)*MAX(0,1-2/Supuestos!$C$20))*(1-Supuestos!$C$18)^2)) -> 0.79142528 | F10: =E10*(1-MIN(1,INDEX(Tabla_Mortalidad!$B$5:$B$75,MIN(71,Cartera_Polizas!$B$12+3-49))*(1+(Cartera_Polizas!$P$12-1)*MAX(0,1-3/Supuestos!$C$20))*(1-Supuestos!$C$18)^3)) -> 0.72091822 | G10: =F10*(1-MIN(1,INDEX(Tabla_Mortalidad!$B$5:$B$75,MIN(71,Cartera_Polizas!$B$12+4-49))*(1+(Cartera_Polizas!$P$12-1)*MAX(0,1-4/Supuestos!$C$20))*(1-Supuestos!$C$18)^4)) -> 0.65090211 | H10: =G10*(1-MIN(1,INDEX(Tabla_Mortalidad!$B$5:$B$75,MIN(71,Cartera_Polizas!$B$12+5-49))*(1+(Cartera_Polizas!$P$12-1)*MAX(0,1-5/Supuestos!$C$20))*(1-Supuestos!$C$18)^5)) -> 0.5820346 | I10: =H10*(1-MIN(1,INDEX(Tabla_Mortalidad!$B$5:$B$75,MIN(71,Cartera_Polizas!$B$12+6-49))*(1+(Cartera_Polizas!$P$12-1)*MAX(0,1-6/Supuestos!$C$20))*(1-Supuestos!$C$18)^6)) -> 0.51500142 | J10: =I10*(1-MIN(1,INDEX(Tabla_Mortalidad!$B$5:$B$75,MIN(71,Cartera_Polizas!$B$12+7-49))*(1+(Cartera_Polizas!$P$12-1)*MAX(0,1-7/Supuestos!$C$20))*(1-Supuestos!$C$18)^7)) -> 0.45049196 | K10: =J10*(1-MIN(1,INDEX(Tabla_Mortalidad!$B$5:$B$75,MIN(71,Cartera_Polizas!$B$12+8-49))*(1+(Cartera_Polizas!$P$12-1)*MAX(0,1-8/Supuestos!$C$20))*(1-Supuestos!$C$18)^8)) -> 0.38917596 | L10: =K10*(1-MIN(1,INDEX(Tabla_Mortalidad!$B$5:$B$75,MIN(71,Cartera_Polizas!$B$12+9-49))*(1+(Cartera_Polizas!$P$12-1)*MAX(0,1-9/Supuestos!$C$20))*(1-Supuestos!$C$18)^9)) -> 0.33167617 | M10: =L10*(1-MIN(1,INDEX(Tabla_Mortalidad!$B$5:$B$75,MIN(71,Cartera_Polizas!$B$12+10-49))*(1+(Cartera_Polizas!$P$12-1)*MAX(0,1-10/Supuestos!$C$20))*(1-Supuestos!$C$18)^10)) -> 0.27854031 | N10: =M10*(1-MIN(1,INDEX(Tabla_Mortalidad!$B$5:$B$75,MIN(71,Cartera_Polizas!$B$12+11-49))*(1+(Cartera_Polizas!$P$12-1)*MAX(0,1-11/Supuestos!$C$20))*(1-Supuestos!$C$18)^11)) -> 0.23021355 | O10: =N10*(1-MIN(1,INDEX(Tabla_Mortalidad!$B$5:$B$75,MIN(71,Cartera_Polizas!$B$12+12-49))*(1+(Cartera_Polizas!$P$12-1)*MAX(0,1-12/Supuestos!$C$20))*(1-Supuestos!$C$18)^12)) -> 0.18701339 | P10: =O10*(1-MIN(1,INDEX(Tabla_Mortalidad!$B$5:$B$75,MIN(71,Cartera_Polizas!$B$12+13-49))*(1+(Cartera_Polizas!$P$12-1)*MAX(0,1-13/Supuestos!$C$20))*(1-Supuestos!$C$18)^13)) -> 0.14911201 | Q10: =P10*(1-MIN(1,INDEX(Tabla_Mortalidad!$B$5:$B$75,MIN(71,Cartera_Polizas!$B$12+14-49))*(1+(Cartera_Polizas!$P$12-1)*MAX(0,1-14/Supuestos!$C$20))*(1-Supuestos!$C$18)^14)) -> 0.11652572 | R10: =Q10*(1-MIN(1,INDEX(Tabla_Mortalidad!$B$5:$B$75,MIN(71,Cartera_Polizas!$B$12+15-49))*(1+(Cartera_Polizas!$P$12-1)*MAX(0,1-15/Supuestos!$C$20))*(1-Supuestos!$C$18)^15)) -> 0.089114012 | S10: =R10*(1-MIN(1,INDEX(Tabla_Mortalidad!$B$5:$B$75,MIN(71,Cartera_Polizas!$B$12+16-49))*(1+(Cartera_Polizas!$P$12-1)*MAX(0,1-16/Supuestos!$C$20))*(1-Supuestos!$C$18)^16)) -> 0.066202635 | T10: =S10*(1-MIN(1,INDEX(Tabla_Mortalidad!$B$5:$B$75,MIN(71,Cartera_Polizas!$B$12+17-49))*(1+(Cartera_Polizas!$P$12-1)*MAX(0,1-17/Supuestos!$C$20))*(1-Supuestos!$C$18)^17)) -> 0.047632933 | U10: =T10*(1-MIN(1,INDEX(Tabla_Mortalidad!$B$5:$B$75,MIN(71,Cartera_Polizas!$B$12+18-49))*(1+(Cartera_Polizas!$P$12-1)*MAX(0,1-18/Supuestos!$C$20))*(1-Supuestos!$C$18)^18)) -> 0.033084367 | V10: =U10*(1-MIN(1,INDEX(Tabla_Mortalidad!$B$5:$B$75,MIN(71,Cartera_Polizas!$B$12+19-49))*(1+(Cartera_Polizas!$P$12-1)*MAX(0,1-19/Supuestos!$C$20))*(1-Supuestos!$C$18)^19)) -> 0.022104621 | W10: =V10*(1-MIN(1,INDEX(Tabla_Mortalidad!$B$5:$B$75,MIN(71,Cartera_Polizas!$B$12+20-49))*(1+(Cartera_Polizas!$P$12-1)*MAX(0,1-20/Supuestos!$C$20))*(1-Supuestos!$C$18)^20)) -> 0.014152283 | X10: =W10*(1-MIN(1,INDEX(Tabla_Mortalidad!$B$5:$B$75,MIN(71,Cartera_Polizas!$B$12+21-49))*(1+(Cartera_Polizas!$P$12-1)*MAX(0,1-21/Supuestos!$C$20))*(1-Supuestos!$C$18)^21)) -> 0.008647099 | Y10: =X10*(1-MIN(1,INDEX(Tabla_Mortalidad!$B$5:$B$75,MIN(71,Cartera_Polizas!$B$12+22-49))*(1+(Cartera_Polizas!$P$12-1)*MAX(0,1-22/Supuestos!$C$20))*(1-Supuestos!$C$18)^22)) -> 0.0050201666 | Z10: =Y10*(1-MIN(1,INDEX(Tabla_Mortalidad!$B$5:$B$75,MIN(71,Cartera_Polizas!$B$12+23-49))*(1+(Cartera_Polizas!$P$12-1)*MAX(0,1-23/Supuestos!$C$20))*(1-Supuestos!$C$18)^23)) -> 0.0027565899 | AA10: =Z10*(1-MIN(1,INDEX(Tabla_Mortalidad!$B$5:$B$75,MIN(71,Cartera_Polizas!$B$12+24-49))*(1+(Cartera_Polizas!$P$12-1)*MAX(0,1-24/Supuestos!$C$20))*(1-Supuestos!$C$18)^24)) -> 0.0014248097 | AB10: =AA10*(1-MIN(1,INDEX(Tabla_Mortalidad!$B$5:$B$75,MIN(71,Cartera_Polizas!$B$12+25-49))*(1+(Cartera_Polizas!$P$12-1)*MAX(0,1-25/Supuestos!$C$20))*(1-Supuestos!$C$18)^25)) -> 0.00068984921 | AC10: =AB10*(1-MIN(1,INDEX(Tabla_Mortalidad!$B$5:$B$75,MIN(71,Cartera_Polizas!$B$12+26-49))*(1+(Cartera_Polizas!$P$12-1)*MAX(0,1-26/Supuestos!$C$20))*(1-Supuestos!$C$18)^26)) -> 0.00031135495 | AD10: =AC10*(1-MIN(1,INDEX(Tabla_Mortalidad!$B$5:$B$75,MIN(71,Cartera_Polizas!$B$12+27-49))*(1+(Cartera_Polizas!$P$12-1)*MAX(0,1-27/Supuestos!$C$20))*(1-Supuestos!$C$18)^27)) -> 0.00013038867 | AE10: =AD10*(1-MIN(1,INDEX(Tabla_Mortalidad!$B$5:$B$75,MIN(71,Cartera_Polizas!$B$12+28-49))*(1+(Cartera_Polizas!$P$12-1)*MAX(0,1-28/Supuestos!$C$20))*(1-Supuestos!$C$18)^28)) -> 5.0450841e-05 | AF10: =AE10*(1-MIN(1,INDEX(Tabla_Mortalidad!$B$5:$B$75,MIN(71,Cartera_Polizas!$B$12+29-49))*(1+(Cartera_Polizas!$P$12-1)*MAX(0,1-29/Supuestos!$C$20))*(1-Supuestos!$C$18)^29)) -> 1.7972946e-05 | AG10: =AF10*(1-MIN(1,INDEX(Tabla_Mortalidad!$B$5:$B$75,MIN(71,Cartera_Polizas!$B$12+30-49))*(1+(Cartera_Polizas!$P$12-1)*MAX(0,1-30/Supuestos!$C$20))*(1-Supuestos!$C$18)^30)) -> 5.8809683e-06 | AH10: =AG10*(1-MIN(1,INDEX(Tabla_Mortalidad!$B$5:$B$75,MIN(71,Cartera_Polizas!$B$12+31-49))*(1+(Cartera_Polizas!$P$12-1)*MAX(0,1-31/Supuestos!$C$20))*(1-Supuestos!$C$18)^31)) -> 1.7659389e-06 | AI10: =AH10*(1-MIN(1,INDEX(Tabla_Mortalidad!$B$5:$B$75,MIN(71,Cartera_Polizas!$B$12+32-49))*(1+(Cartera_Polizas!$P$12-1)*MAX(0,1-32/Supuestos!$C$20))*(1-Supuestos!$C$18)^32)) -> 4.8717039e-07 | AJ10: =AI10*(1-MIN(1,INDEX(Tabla_Mortalidad!$B$5:$B$75,MIN(71,Cartera_Polizas!$B$12+33-49))*(1+(Cartera_Polizas!$P$12-1)*MAX(0,1-33/Supuestos!$C$20))*(1-Supuestos!$C$18)^33)) -> 1.2390457e-07 | AK10: =AJ10*(1-MIN(1,INDEX(Tabla_Mortalidad!$B$5:$B$75,MIN(71,Cartera_Polizas!$B$12+34-49))*(1+(Cartera_Polizas!$P$12-1)*MAX(0,1-34/Supuestos!$C$20))*(1-Supuestos!$C$18)^34)) -> 2.9232822e-08 | AL10: =AK10*(1-MIN(1,INDEX(Tabla_Mortalidad!$B$5:$B$75,MIN(71,Cartera_Polizas!$B$12+35-49))*(1+(Cartera_Polizas!$P$12-1)*MAX(0,1-35/Supuestos!$C$20))*(1-Supuestos!$C$18)^35)) -> 6.4544991e-09 | AM10: =AL10*(1-MIN(1,INDEX(Tabla_Mortalidad!$B$5:$B$75,MIN(71,Cartera_Polizas!$B$12+36-49))*(1+(Cartera_Polizas!$P$12-1)*MAX(0,1-36/Supuestos!$C$20))*(1-Supuestos!$C$18)^36)) -> 1.3486164e-09 | AN10: =AM10*(1-MIN(1,INDEX(Tabla_Mortalidad!$B$5:$B$75,MIN(71,Cartera_Polizas!$B$12+37-49))*(1+(Cartera_Polizas!$P$12-1)*MAX(0,1-37/Supuestos!$C$20))*(1-Supuestos!$C$18)^37)) -> 2.2829553e-10 | AO10: =AN10*(1-MIN(1,INDEX(Tabla_Mortalidad!$B$5:$B$75,MIN(71,Cartera_Polizas!$B$12+38-49))*(1+(Cartera_Polizas!$P$12-1)*MAX(0,1-38/Supuestos!$C$20))*(1-Supuestos!$C$18)^38)) -> 3.959441e-11 | AP10: =AO10*(1-MIN(1,INDEX(Tabla_Mortalidad!$B$5:$B$75,MIN(71,Cartera_Polizas!$B$12+39-49))*(1+(Cartera_Polizas!$P$12-1)*MAX(0,1-39/Supuestos!$C$20))*(1-Supuestos!$C$18)^39)) -> 7.030689e-12 | AQ10: =AP10*(1-MIN(1,INDEX(Tabla_Mortalidad!$B$5:$B$75,MIN(71,Cartera_Polizas!$B$12+40-49))*(1+(Cartera_Polizas!$P$12-1)*MAX(0,1-40/Supuestos!$C$20))*(1-Supuestos!$C$18)^40)) -> 1.2773347e-12 | AR10: =AQ10*(1-MIN(1,INDEX(Tabla_Mortalidad!$B$5:$B$75,MIN(71,Cartera_Polizas!$B$12+41-49))*(1+(Cartera_Polizas!$P$12-1)*MAX(0,1-41/Supuestos!$C$20))*(1-Supuestos!$C$18)^41)) -> 2.3729236e-13 | AS10: =AR10*(1-MIN(1,INDEX(Tabla_Mortalidad!$B$5:$B$75,MIN(71,Cartera_Polizas!$B$12+42-49))*(1+(Cartera_Polizas!$P$12-1)*MAX(0,1-42/Supuestos!$C$20))*(1-Supuestos!$C$18)^42)) -> 4.5048204e-14 | AT10: =AS10*(1-MIN(1,INDEX(Tabla_Mortalidad!$B$5:$B$75,MIN(71,Cartera_Polizas!$B$12+43-49))*(1+(Cartera_Polizas!$P$12-1)*MAX(0,1-43/Supuestos!$C$20))*(1-Supuestos!$C$18)^43)) -> 8.7345499e-15 | AU10: =AT10*(1-MIN(1,INDEX(Tabla_Mortalidad!$B$5:$B$75,MIN(71,Cartera_Polizas!$B$12+44-49))*(1+(Cartera_Polizas!$P$12-1)*MAX(0,1-44/Supuestos!$C$20))*(1-Supuestos!$C$18)^44)) -> 1.7287766e-15
A11: =Cartera_Polizas!A13 -> 8 | B11: =SUM(C11:AU11)+0.5 -> 4.7250665 | C11: =1-MIN(1,INDEX(Tabla_Mortalidad!$B$5:$B$75,MIN(71,Cartera_Polizas!$B$13+0-49))*(1+(Cartera_Polizas!$P$13-1)*MAX(0,1-0/Supuestos!$C$20))*(1-Supuestos!$C$18)^0) -> 0.85946512 | D11: =C11*(1-MIN(1,INDEX(Tabla_Mortalidad!$B$5:$B$75,MIN(71,Cartera_Polizas!$B$13+1-49))*(1+(Cartera_Polizas!$P$13-1)*MAX(0,1-1/Supuestos!$C$20))*(1-Supuestos!$C$18)^1)) -> 0.72789367 | E11: =D11*(1-MIN(1,INDEX(Tabla_Mortalidad!$B$5:$B$75,MIN(71,Cartera_Polizas!$B$13+2-49))*(1+(Cartera_Polizas!$P$13-1)*MAX(0,1-2/Supuestos!$C$20))*(1-Supuestos!$C$18)^2)) -> 0.60662667 | F11: =E11*(1-MIN(1,INDEX(Tabla_Mortalidad!$B$5:$B$75,MIN(71,Cartera_Polizas!$B$13+3-49))*(1+(Cartera_Polizas!$P$13-1)*MAX(0,1-3/Supuestos!$C$20))*(1-Supuestos!$C$18)^3)) -> 0.49675424 | G11: =F11*(1-MIN(1,INDEX(Tabla_Mortalidad!$B$5:$B$75,MIN(71,Cartera_Polizas!$B$13+4-49))*(1+(Cartera_Polizas!$P$13-1)*MAX(0,1-4/Supuestos!$C$20))*(1-Supuestos!$C$18)^4)) -> 0.39905133 | H11: =G11*(1-MIN(1,INDEX(Tabla_Mortalidad!$B$5:$B$75,MIN(71,Cartera_Polizas!$B$13+5-49))*(1+(Cartera_Polizas!$P$13-1)*MAX(0,1-5/Supuestos!$C$20))*(1-Supuestos!$C$18)^5)) -> 0.31392647 | I11: =H11*(1-MIN(1,INDEX(Tabla_Mortalidad!$B$5:$B$75,MIN(71,Cartera_Polizas!$B$13+6-49))*(1+(Cartera_Polizas!$P$13-1)*MAX(0,1-6/Supuestos!$C$20))*(1-Supuestos!$C$18)^6)) -> 0.24139501 | J11: =I11*(1-MIN(1,INDEX(Tabla_Mortalidad!$B$5:$B$75,MIN(71,Cartera_Polizas!$B$13+7-49))*(1+(Cartera_Polizas!$P$13-1)*MAX(0,1-7/Supuestos!$C$20))*(1-Supuestos!$C$18)^7)) -> 0.18107694 | K11: =J11*(1-MIN(1,INDEX(Tabla_Mortalidad!$B$5:$B$75,MIN(71,Cartera_Polizas!$B$13+8-49))*(1+(Cartera_Polizas!$P$13-1)*MAX(0,1-8/Supuestos!$C$20))*(1-Supuestos!$C$18)^8)) -> 0.1322236 | L11: =K11*(1-MIN(1,INDEX(Tabla_Mortalidad!$B$5:$B$75,MIN(71,Cartera_Polizas!$B$13+9-49))*(1+(Cartera_Polizas!$P$13-1)*MAX(0,1-9/Supuestos!$C$20))*(1-Supuestos!$C$18)^9)) -> 0.09377547 | M11: =L11*(1-MIN(1,INDEX(Tabla_Mortalidad!$B$5:$B$75,MIN(71,Cartera_Polizas!$B$13+10-49))*(1+(Cartera_Polizas!$P$13-1)*MAX(0,1-10/Supuestos!$C$20))*(1-Supuestos!$C$18)^10)) -> 0.064443677 | N11: =M11*(1-MIN(1,INDEX(Tabla_Mortalidad!$B$5:$B$75,MIN(71,Cartera_Polizas!$B$13+11-49))*(1+(Cartera_Polizas!$P$13-1)*MAX(0,1-11/Supuestos!$C$20))*(1-Supuestos!$C$18)^11)) -> 0.042807356 | O11: =N11*(1-MIN(1,INDEX(Tabla_Mortalidad!$B$5:$B$75,MIN(71,Cartera_Polizas!$B$13+12-49))*(1+(Cartera_Polizas!$P$13-1)*MAX(0,1-12/Supuestos!$C$20))*(1-Supuestos!$C$18)^12)) -> 0.02741667 | P11: =O11*(1-MIN(1,INDEX(Tabla_Mortalidad!$B$5:$B$75,MIN(71,Cartera_Polizas!$B$13+13-49))*(1+(Cartera_Polizas!$P$13-1)*MAX(0,1-13/Supuestos!$C$20))*(1-Supuestos!$C$18)^13)) -> 0.016887767 | Q11: =P11*(1-MIN(1,INDEX(Tabla_Mortalidad!$B$5:$B$75,MIN(71,Cartera_Polizas!$B$13+14-49))*(1+(Cartera_Polizas!$P$13-1)*MAX(0,1-14/Supuestos!$C$20))*(1-Supuestos!$C$18)^14)) -> 0.009979571 | R11: =Q11*(1-MIN(1,INDEX(Tabla_Mortalidad!$B$5:$B$75,MIN(71,Cartera_Polizas!$B$13+15-49))*(1+(Cartera_Polizas!$P$13-1)*MAX(0,1-15/Supuestos!$C$20))*(1-Supuestos!$C$18)^15)) -> 0.0056442692 | S11: =R11*(1-MIN(1,INDEX(Tabla_Mortalidad!$B$5:$B$75,MIN(71,Cartera_Polizas!$B$13+16-49))*(1+(Cartera_Polizas!$P$13-1)*MAX(0,1-16/Supuestos!$C$20))*(1-Supuestos!$C$18)^16)) -> 0.0030084038 | T11: =S11*(1-MIN(1,INDEX(Tabla_Mortalidad!$B$5:$B$75,MIN(71,Cartera_Polizas!$B$13+17-49))*(1+(Cartera_Polizas!$P$13-1)*MAX(0,1-17/Supuestos!$C$20))*(1-Supuestos!$C$18)^17)) -> 0.0015030626 | U11: =T11*(1-MIN(1,INDEX(Tabla_Mortalidad!$B$5:$B$75,MIN(71,Cartera_Polizas!$B$13+18-49))*(1+(Cartera_Polizas!$P$13-1)*MAX(0,1-18/Supuestos!$C$20))*(1-Supuestos!$C$18)^18)) -> 0.00070004947 | V11: =U11*(1-MIN(1,INDEX(Tabla_Mortalidad!$B$5:$B$75,MIN(71,Cartera_Polizas!$B$13+19-49))*(1+(Cartera_Polizas!$P$13-1)*MAX(0,1-19/Supuestos!$C$20))*(1-Supuestos!$C$18)^19)) -> 0.00030224258 | W11: =V11*(1-MIN(1,INDEX(Tabla_Mortalidad!$B$5:$B$75,MIN(71,Cartera_Polizas!$B$13+20-49))*(1+(Cartera_Polizas!$P$13-1)*MAX(0,1-20/Supuestos!$C$20))*(1-Supuestos!$C$18)^20)) -> 0.00012029933 | X11: =W11*(1-MIN(1,INDEX(Tabla_Mortalidad!$B$5:$B$75,MIN(71,Cartera_Polizas!$B$13+21-49))*(1+(Cartera_Polizas!$P$13-1)*MAX(0,1-21/Supuestos!$C$20))*(1-Supuestos!$C$18)^21)) -> 4.3913263e-05 | Y11: =X11*(1-MIN(1,INDEX(Tabla_Mortalidad!$B$5:$B$75,MIN(71,Cartera_Polizas!$B$13+22-49))*(1+(Cartera_Polizas!$P$13-1)*MAX(0,1-22/Supuestos!$C$20))*(1-Supuestos!$C$18)^22)) -> 1.4634441e-05 | Z11: =Y11*(1-MIN(1,INDEX(Tabla_Mortalidad!$B$5:$B$75,MIN(71,Cartera_Polizas!$B$13+23-49))*(1+(Cartera_Polizas!$P$13-1)*MAX(0,1-23/Supuestos!$C$20))*(1-Supuestos!$C$18)^23)) -> 4.4369661e-06 | AA11: =Z11*(1-MIN(1,INDEX(Tabla_Mortalidad!$B$5:$B$75,MIN(71,Cartera_Polizas!$B$13+24-49))*(1+(Cartera_Polizas!$P$13-1)*MAX(0,1-24/Supuestos!$C$20))*(1-Supuestos!$C$18)^24)) -> 1.2214651e-06 | AB11: =AA11*(1-MIN(1,INDEX(Tabla_Mortalidad!$B$5:$B$75,MIN(71,Cartera_Polizas!$B$13+25-49))*(1+(Cartera_Polizas!$P$13-1)*MAX(0,1-25/Supuestos!$C$20))*(1-Supuestos!$C$18)^25)) -> 3.0538013e-07 | AC11: =AB11*(1-MIN(1,INDEX(Tabla_Mortalidad!$B$5:$B$75,MIN(71,Cartera_Polizas!$B$13+26-49))*(1+(Cartera_Polizas!$P$13-1)*MAX(0,1-26/Supuestos!$C$20))*(1-Supuestos!$C$18)^26)) -> 6.9537201e-08 | AD11: =AC11*(1-MIN(1,INDEX(Tabla_Mortalidad!$B$5:$B$75,MIN(71,Cartera_Polizas!$B$13+27-49))*(1+(Cartera_Polizas!$P$13-1)*MAX(0,1-27/Supuestos!$C$20))*(1-Supuestos!$C$18)^27)) -> 1.4508569e-08 | AE11: =AD11*(1-MIN(1,INDEX(Tabla_Mortalidad!$B$5:$B$75,MIN(71,Cartera_Polizas!$B$13+28-49))*(1+(Cartera_Polizas!$P$13-1)*MAX(0,1-28/Supuestos!$C$20))*(1-Supuestos!$C$18)^28)) -> 2.7997251e-09 | AF11: =AE11*(1-MIN(1,INDEX(Tabla_Mortalidad!$B$5:$B$75,MIN(71,Cartera_Polizas!$B$13+29-49))*(1+(Cartera_Polizas!$P$13-1)*MAX(0,1-29/Supuestos!$C$20))*(1-Supuestos!$C$18)^29)) -> 5.058904e-10 | AG11: =AF11*(1-MIN(1,INDEX(Tabla_Mortalidad!$B$5:$B$75,MIN(71,Cartera_Polizas!$B$13+30-49))*(1+(Cartera_Polizas!$P$13-1)*MAX(0,1-30/Supuestos!$C$20))*(1-Supuestos!$C$18)^30)) -> 7.0630297e-11 | AH11: =AG11*(1-MIN(1,INDEX(Tabla_Mortalidad!$B$5:$B$75,MIN(71,Cartera_Polizas!$B$13+31-49))*(1+(Cartera_Polizas!$P$13-1)*MAX(0,1-31/Supuestos!$C$20))*(1-Supuestos!$C$18)^31)) -> 1.0164952e-11 | AI11: =AH11*(1-MIN(1,INDEX(Tabla_Mortalidad!$B$5:$B$75,MIN(71,Cartera_Polizas!$B$13+32-49))*(1+(Cartera_Polizas!$P$13-1)*MAX(0,1-32/Supuestos!$C$20))*(1-Supuestos!$C$18)^32)) -> 1.506427e-12 | AJ11: =AI11*(1-MIN(1,INDEX(Tabla_Mortalidad!$B$5:$B$75,MIN(71,Cartera_Polizas!$B$13+33-49))*(1+(Cartera_Polizas!$P$13-1)*MAX(0,1-33/Supuestos!$C$20))*(1-Supuestos!$C$18)^33)) -> 2.2966556e-13 | AK11: =AJ11*(1-MIN(1,INDEX(Tabla_Mortalidad!$B$5:$B$75,MIN(71,Cartera_Polizas!$B$13+34-49))*(1+(Cartera_Polizas!$P$13-1)*MAX(0,1-34/Supuestos!$C$20))*(1-Supuestos!$C$18)^34)) -> 3.5987414e-14 | AL11: =AK11*(1-MIN(1,INDEX(Tabla_Mortalidad!$B$5:$B$75,MIN(71,Cartera_Polizas!$B$13+35-49))*(1+(Cartera_Polizas!$P$13-1)*MAX(0,1-35/Supuestos!$C$20))*(1-Supuestos!$C$18)^35)) -> 5.7907848e-15 | AM11: =AL11*(1-MIN(1,INDEX(Tabla_Mortalidad!$B$5:$B$75,MIN(71,Cartera_Polizas!$B$13+36-49))*(1+(Cartera_Polizas!$P$13-1)*MAX(0,1-36/Supuestos!$C$20))*(1-Supuestos!$C$18)^36)) -> 9.5609814e-16 | AN11: =AM11*(1-MIN(1,INDEX(Tabla_Mortalidad!$B$5:$B$75,MIN(71,Cartera_Polizas!$B$13+37-49))*(1+(Cartera_Polizas!$P$13-1)*MAX(0,1-37/Supuestos!$C$20))*(1-Supuestos!$C$18)^37)) -> 1.6184953e-16 | AO11: =AN11*(1-MIN(1,INDEX(Tabla_Mortalidad!$B$5:$B$75,MIN(71,Cartera_Polizas!$B$13+38-49))*(1+(Cartera_Polizas!$P$13-1)*MAX(0,1-38/Supuestos!$C$20))*(1-Supuestos!$C$18)^38)) -> 2.8070357e-17 | AP11: =AO11*(1-MIN(1,INDEX(Tabla_Mortalidad!$B$5:$B$75,MIN(71,Cartera_Polizas!$B$13+39-49))*(1+(Cartera_Polizas!$P$13-1)*MAX(0,1-39/Supuestos!$C$20))*(1-Supuestos!$C$18)^39)) -> 4.9843892e-18 | AQ11: =AP11*(1-MIN(1,INDEX(Tabla_Mortalidad!$B$5:$B$75,MIN(71,Cartera_Polizas!$B$13+40-49))*(1+(Cartera_Polizas!$P$13-1)*MAX(0,1-40/Supuestos!$C$20))*(1-Supuestos!$C$18)^40)) -> 9.0556322e-19 | AR11: =AQ11*(1-MIN(1,INDEX(Tabla_Mortalidad!$B$5:$B$75,MIN(71,Cartera_Polizas!$B$13+41-49))*(1+(Cartera_Polizas!$P$13-1)*MAX(0,1-41/Supuestos!$C$20))*(1-Supuestos!$C$18)^41)) -> 1.6822782e-19 | AS11: =AR11*(1-MIN(1,INDEX(Tabla_Mortalidad!$B$5:$B$75,MIN(71,Cartera_Polizas!$B$13+42-49))*(1+(Cartera_Polizas!$P$13-1)*MAX(0,1-42/Supuestos!$C$20))*(1-Supuestos!$C$18)^42)) -> 3.193681e-20 | AT11: =AS11*(1-MIN(1,INDEX(Tabla_Mortalidad!$B$5:$B$75,MIN(71,Cartera_Polizas!$B$13+43-49))*(1+(Cartera_Polizas!$P$13-1)*MAX(0,1-43/Supuestos!$C$20))*(1-Supuestos!$C$18)^43)) -> 6.192337e-21 | AU11: =AT11*(1-MIN(1,INDEX(Tabla_Mortalidad!$B$5:$B$75,MIN(71,Cartera_Polizas!$B$13+44-49))*(1+(Cartera_Polizas!$P$13-1)*MAX(0,1-44/Supuestos!$C$20))*(1-Supuestos!$C$18)^44)) -> 1.2256118e-21
A12: =Cartera_Polizas!A14 -> 9 | B12: =SUM(C12:AU12)+0.5 -> 10.36828 | C12: =1-MIN(1,INDEX(Tabla_Mortalidad!$B$5:$B$75,MIN(71,Cartera_Polizas!$B$14+0-49))*(1+(Cartera_Polizas!$P$14-1)*MAX(0,1-0/Supuestos!$C$20))*(1-Supuestos!$C$18)^0) -> 0.96231075 | D12: =C12*(1-MIN(1,INDEX(Tabla_Mortalidad!$B$5:$B$75,MIN(71,Cartera_Polizas!$B$14+1-49))*(1+(Cartera_Polizas!$P$14-1)*MAX(0,1-1/Supuestos!$C$20))*(1-Supuestos!$C$18)^1)) -> 0.92167738 | E12: =D12*(1-MIN(1,INDEX(Tabla_Mortalidad!$B$5:$B$75,MIN(71,Cartera_Polizas!$B$14+2-49))*(1+(Cartera_Polizas!$P$14-1)*MAX(0,1-2/Supuestos!$C$20))*(1-Supuestos!$C$18)^2)) -> 0.87809434 | F12: =E12*(1-MIN(1,INDEX(Tabla_Mortalidad!$B$5:$B$75,MIN(71,Cartera_Polizas!$B$14+3-49))*(1+(Cartera_Polizas!$P$14-1)*MAX(0,1-3/Supuestos!$C$20))*(1-Supuestos!$C$18)^3)) -> 0.83161662 | G12: =F12*(1-MIN(1,INDEX(Tabla_Mortalidad!$B$5:$B$75,MIN(71,Cartera_Polizas!$B$14+4-49))*(1+(Cartera_Polizas!$P$14-1)*MAX(0,1-4/Supuestos!$C$20))*(1-Supuestos!$C$18)^4)) -> 0.78237002 | H12: =G12*(1-MIN(1,INDEX(Tabla_Mortalidad!$B$5:$B$75,MIN(71,Cartera_Polizas!$B$14+5-49))*(1+(Cartera_Polizas!$P$14-1)*MAX(0,1-5/Supuestos!$C$20))*(1-Supuestos!$C$18)^5)) -> 0.73056268 | I12: =H12*(1-MIN(1,INDEX(Tabla_Mortalidad!$B$5:$B$75,MIN(71,Cartera_Polizas!$B$14+6-49))*(1+(Cartera_Polizas!$P$14-1)*MAX(0,1-6/Supuestos!$C$20))*(1-Supuestos!$C$18)^6)) -> 0.6764992 | J12: =I12*(1-MIN(1,INDEX(Tabla_Mortalidad!$B$5:$B$75,MIN(71,Cartera_Polizas!$B$14+7-49))*(1+(Cartera_Polizas!$P$14-1)*MAX(0,1-7/Supuestos!$C$20))*(1-Supuestos!$C$18)^7)) -> 0.62058544 | K12: =J12*(1-MIN(1,INDEX(Tabla_Mortalidad!$B$5:$B$75,MIN(71,Cartera_Polizas!$B$14+8-49))*(1+(Cartera_Polizas!$P$14-1)*MAX(0,1-8/Supuestos!$C$20))*(1-Supuestos!$C$18)^8)) -> 0.56333791 | L12: =K12*(1-MIN(1,INDEX(Tabla_Mortalidad!$B$5:$B$75,MIN(71,Cartera_Polizas!$B$14+9-49))*(1+(Cartera_Polizas!$P$14-1)*MAX(0,1-9/Supuestos!$C$20))*(1-Supuestos!$C$18)^9)) -> 0.50538082 | M12: =L12*(1-MIN(1,INDEX(Tabla_Mortalidad!$B$5:$B$75,MIN(71,Cartera_Polizas!$B$14+10-49))*(1+(Cartera_Polizas!$P$14-1)*MAX(0,1-10/Supuestos!$C$20))*(1-Supuestos!$C$18)^10)) -> 0.4474396 | N12: =M12*(1-MIN(1,INDEX(Tabla_Mortalidad!$B$5:$B$75,MIN(71,Cartera_Polizas!$B$14+11-49))*(1+(Cartera_Polizas!$P$14-1)*MAX(0,1-11/Supuestos!$C$20))*(1-Supuestos!$C$18)^11)) -> 0.3903245 | O12: =N12*(1-MIN(1,INDEX(Tabla_Mortalidad!$B$5:$B$75,MIN(71,Cartera_Polizas!$B$14+12-49))*(1+(Cartera_Polizas!$P$14-1)*MAX(0,1-12/Supuestos!$C$20))*(1-Supuestos!$C$18)^12)) -> 0.33490427 | P12: =O12*(1-MIN(1,INDEX(Tabla_Mortalidad!$B$5:$B$75,MIN(71,Cartera_Polizas!$B$14+13-49))*(1+(Cartera_Polizas!$P$14-1)*MAX(0,1-13/Supuestos!$C$20))*(1-Supuestos!$C$18)^13)) -> 0.28206886 | Q12: =P12*(1-MIN(1,INDEX(Tabla_Mortalidad!$B$5:$B$75,MIN(71,Cartera_Polizas!$B$14+14-49))*(1+(Cartera_Polizas!$P$14-1)*MAX(0,1-14/Supuestos!$C$20))*(1-Supuestos!$C$18)^14)) -> 0.23268136 | R12: =Q12*(1-MIN(1,INDEX(Tabla_Mortalidad!$B$5:$B$75,MIN(71,Cartera_Polizas!$B$14+15-49))*(1+(Cartera_Polizas!$P$14-1)*MAX(0,1-15/Supuestos!$C$20))*(1-Supuestos!$C$18)^15)) -> 0.18752431 | S12: =R12*(1-MIN(1,INDEX(Tabla_Mortalidad!$B$5:$B$75,MIN(71,Cartera_Polizas!$B$14+16-49))*(1+(Cartera_Polizas!$P$14-1)*MAX(0,1-16/Supuestos!$C$20))*(1-Supuestos!$C$18)^16)) -> 0.14762792 | T12: =S12*(1-MIN(1,INDEX(Tabla_Mortalidad!$B$5:$B$75,MIN(71,Cartera_Polizas!$B$14+17-49))*(1+(Cartera_Polizas!$P$14-1)*MAX(0,1-17/Supuestos!$C$20))*(1-Supuestos!$C$18)^17)) -> 0.11324609 | U12: =T12*(1-MIN(1,INDEX(Tabla_Mortalidad!$B$5:$B$75,MIN(71,Cartera_Polizas!$B$14+18-49))*(1+(Cartera_Polizas!$P$14-1)*MAX(0,1-18/Supuestos!$C$20))*(1-Supuestos!$C$18)^18)) -> 0.084420743 | V12: =U12*(1-MIN(1,INDEX(Tabla_Mortalidad!$B$5:$B$75,MIN(71,Cartera_Polizas!$B$14+19-49))*(1+(Cartera_Polizas!$P$14-1)*MAX(0,1-19/Supuestos!$C$20))*(1-Supuestos!$C$18)^19)) -> 0.060977106 | W12: =V12*(1-MIN(1,INDEX(Tabla_Mortalidad!$B$5:$B$75,MIN(71,Cartera_Polizas!$B$14+20-49))*(1+(Cartera_Polizas!$P$14-1)*MAX(0,1-20/Supuestos!$C$20))*(1-Supuestos!$C$18)^20)) -> 0.042538596 | X12: =W12*(1-MIN(1,INDEX(Tabla_Mortalidad!$B$5:$B$75,MIN(71,Cartera_Polizas!$B$14+21-49))*(1+(Cartera_Polizas!$P$14-1)*MAX(0,1-21/Supuestos!$C$20))*(1-Supuestos!$C$18)^21)) -> 0.028562084 | Y12: =X12*(1-MIN(1,INDEX(Tabla_Mortalidad!$B$5:$B$75,MIN(71,Cartera_Polizas!$B$14+22-49))*(1+(Cartera_Polizas!$P$14-1)*MAX(0,1-22/Supuestos!$C$20))*(1-Supuestos!$C$18)^22)) -> 0.018389113 | Z12: =Y12*(1-MIN(1,INDEX(Tabla_Mortalidad!$B$5:$B$75,MIN(71,Cartera_Polizas!$B$14+23-49))*(1+(Cartera_Polizas!$P$14-1)*MAX(0,1-23/Supuestos!$C$20))*(1-Supuestos!$C$18)^23)) -> 0.011307173 | AA12: =Z12*(1-MIN(1,INDEX(Tabla_Mortalidad!$B$5:$B$75,MIN(71,Cartera_Polizas!$B$14+24-49))*(1+(Cartera_Polizas!$P$14-1)*MAX(0,1-24/Supuestos!$C$20))*(1-Supuestos!$C$18)^24)) -> 0.0066118092 | AB12: =AA12*(1-MIN(1,INDEX(Tabla_Mortalidad!$B$5:$B$75,MIN(71,Cartera_Polizas!$B$14+25-49))*(1+(Cartera_Polizas!$P$14-1)*MAX(0,1-25/Supuestos!$C$20))*(1-Supuestos!$C$18)^25)) -> 0.003660304 | AC12: =AB12*(1-MIN(1,INDEX(Tabla_Mortalidad!$B$5:$B$75,MIN(71,Cartera_Polizas!$B$14+26-49))*(1+(Cartera_Polizas!$P$14-1)*MAX(0,1-26/Supuestos!$C$20))*(1-Supuestos!$C$18)^26)) -> 0.0019095557 | AD12: =AC12*(1-MIN(1,INDEX(Tabla_Mortalidad!$B$5:$B$75,MIN(71,Cartera_Polizas!$B$14+27-49))*(1+(Cartera_Polizas!$P$14-1)*MAX(0,1-27/Supuestos!$C$20))*(1-Supuestos!$C$18)^27)) -> 0.00093437381 | AE12: =AD12*(1-MIN(1,INDEX(Tabla_Mortalidad!$B$5:$B$75,MIN(71,Cartera_Polizas!$B$14+28-49))*(1+(Cartera_Polizas!$P$14-1)*MAX(0,1-28/Supuestos!$C$20))*(1-Supuestos!$C$18)^28)) -> 0.00042683185 | AF12: =AE12*(1-MIN(1,INDEX(Tabla_Mortalidad!$B$5:$B$75,MIN(71,Cartera_Polizas!$B$14+29-49))*(1+(Cartera_Polizas!$P$14-1)*MAX(0,1-29/Supuestos!$C$20))*(1-Supuestos!$C$18)^29)) -> 0.00018122252 | AG12: =AF12*(1-MIN(1,INDEX(Tabla_Mortalidad!$B$5:$B$75,MIN(71,Cartera_Polizas!$B$14+30-49))*(1+(Cartera_Polizas!$P$14-1)*MAX(0,1-30/Supuestos!$C$20))*(1-Supuestos!$C$18)^30)) -> 7.1228058e-05 | AH12: =AG12*(1-MIN(1,INDEX(Tabla_Mortalidad!$B$5:$B$75,MIN(71,Cartera_Polizas!$B$14+31-49))*(1+(Cartera_Polizas!$P$14-1)*MAX(0,1-31/Supuestos!$C$20))*(1-Supuestos!$C$18)^31)) -> 2.5832148e-05 | AI12: =AH12*(1-MIN(1,INDEX(Tabla_Mortalidad!$B$5:$B$75,MIN(71,Cartera_Polizas!$B$14+32-49))*(1+(Cartera_Polizas!$P$14-1)*MAX(0,1-32/Supuestos!$C$20))*(1-Supuestos!$C$18)^32)) -> 8.6259566e-06 | AJ12: =AI12*(1-MIN(1,INDEX(Tabla_Mortalidad!$B$5:$B$75,MIN(71,Cartera_Polizas!$B$14+33-49))*(1+(Cartera_Polizas!$P$14-1)*MAX(0,1-33/Supuestos!$C$20))*(1-Supuestos!$C$18)^33)) -> 2.6504114e-06 | AK12: =AJ12*(1-MIN(1,INDEX(Tabla_Mortalidad!$B$5:$B$75,MIN(71,Cartera_Polizas!$B$14+34-49))*(1+(Cartera_Polizas!$P$14-1)*MAX(0,1-34/Supuestos!$C$20))*(1-Supuestos!$C$18)^34)) -> 7.5031466e-07 | AL12: =AK12*(1-MIN(1,INDEX(Tabla_Mortalidad!$B$5:$B$75,MIN(71,Cartera_Polizas!$B$14+35-49))*(1+(Cartera_Polizas!$P$14-1)*MAX(0,1-35/Supuestos!$C$20))*(1-Supuestos!$C$18)^35)) -> 1.9641227e-07 | AM12: =AL12*(1-MIN(1,INDEX(Tabla_Mortalidad!$B$5:$B$75,MIN(71,Cartera_Polizas!$B$14+36-49))*(1+(Cartera_Polizas!$P$14-1)*MAX(0,1-36/Supuestos!$C$20))*(1-Supuestos!$C$18)^36)) -> 4.7836547e-08 | AN12: =AM12*(1-MIN(1,INDEX(Tabla_Mortalidad!$B$5:$B$75,MIN(71,Cartera_Polizas!$B$14+37-49))*(1+(Cartera_Polizas!$P$14-1)*MAX(0,1-37/Supuestos!$C$20))*(1-Supuestos!$C$18)^37)) -> 1.0933945e-08 | AO12: =AN12*(1-MIN(1,INDEX(Tabla_Mortalidad!$B$5:$B$75,MIN(71,Cartera_Polizas!$B$14+38-49))*(1+(Cartera_Polizas!$P$14-1)*MAX(0,1-38/Supuestos!$C$20))*(1-Supuestos!$C$18)^38)) -> 2.3708386e-09 | AP12: =AO12*(1-MIN(1,INDEX(Tabla_Mortalidad!$B$5:$B$75,MIN(71,Cartera_Polizas!$B$14+39-49))*(1+(Cartera_Polizas!$P$14-1)*MAX(0,1-39/Supuestos!$C$20))*(1-Supuestos!$C$18)^39)) -> 4.2098441e-10 | AQ12: =AP12*(1-MIN(1,INDEX(Tabla_Mortalidad!$B$5:$B$75,MIN(71,Cartera_Polizas!$B$14+40-49))*(1+(Cartera_Polizas!$P$14-1)*MAX(0,1-40/Supuestos!$C$20))*(1-Supuestos!$C$18)^40)) -> 7.6484396e-11 | AR12: =AQ12*(1-MIN(1,INDEX(Tabla_Mortalidad!$B$5:$B$75,MIN(71,Cartera_Polizas!$B$14+41-49))*(1+(Cartera_Polizas!$P$14-1)*MAX(0,1-41/Supuestos!$C$20))*(1-Supuestos!$C$18)^41)) -> 1.4208619e-11 | AS12: =AR12*(1-MIN(1,INDEX(Tabla_Mortalidad!$B$5:$B$75,MIN(71,Cartera_Polizas!$B$14+42-49))*(1+(Cartera_Polizas!$P$14-1)*MAX(0,1-42/Supuestos!$C$20))*(1-Supuestos!$C$18)^42)) -> 2.6974016e-12 | AT12: =AS12*(1-MIN(1,INDEX(Tabla_Mortalidad!$B$5:$B$75,MIN(71,Cartera_Polizas!$B$14+43-49))*(1+(Cartera_Polizas!$P$14-1)*MAX(0,1-43/Supuestos!$C$20))*(1-Supuestos!$C$18)^43)) -> 5.2300838e-13 | AU12: =AT12*(1-MIN(1,INDEX(Tabla_Mortalidad!$B$5:$B$75,MIN(71,Cartera_Polizas!$B$14+44-49))*(1+(Cartera_Polizas!$P$14-1)*MAX(0,1-44/Supuestos!$C$20))*(1-Supuestos!$C$18)^44)) -> 1.0351588e-13
A13: =Cartera_Polizas!A15 -> 10 | B13: =SUM(C13:AU13)+0.5 -> 8.9735149 | C13: =1-MIN(1,INDEX(Tabla_Mortalidad!$B$5:$B$75,MIN(71,Cartera_Polizas!$B$15+0-49))*(1+(Cartera_Polizas!$P$15-1)*MAX(0,1-0/Supuestos!$C$20))*(1-Supuestos!$C$18)^0) -> 0.93833124 | D13: =C13*(1-MIN(1,INDEX(Tabla_Mortalidad!$B$5:$B$75,MIN(71,Cartera_Polizas!$B$15+1-49))*(1+(Cartera_Polizas!$P$15-1)*MAX(0,1-1/Supuestos!$C$20))*(1-Supuestos!$C$18)^1)) -> 0.87574155 | E13: =D13*(1-MIN(1,INDEX(Tabla_Mortalidad!$B$5:$B$75,MIN(71,Cartera_Polizas!$B$15+2-49))*(1+(Cartera_Polizas!$P$15-1)*MAX(0,1-2/Supuestos!$C$20))*(1-Supuestos!$C$18)^2)) -> 0.81261172 | F13: =E13*(1-MIN(1,INDEX(Tabla_Mortalidad!$B$5:$B$75,MIN(71,Cartera_Polizas!$B$15+3-49))*(1+(Cartera_Polizas!$P$15-1)*MAX(0,1-3/Supuestos!$C$20))*(1-Supuestos!$C$18)^3)) -> 0.74936237 | G13: =F13*(1-MIN(1,INDEX(Tabla_Mortalidad!$B$5:$B$75,MIN(71,Cartera_Polizas!$B$15+4-49))*(1+(Cartera_Polizas!$P$15-1)*MAX(0,1-4/Supuestos!$C$20))*(1-Supuestos!$C$18)^4)) -> 0.68644958 | H13: =G13*(1-MIN(1,INDEX(Tabla_Mortalidad!$B$5:$B$75,MIN(71,Cartera_Polizas!$B$15+5-49))*(1+(Cartera_Polizas!$P$15-1)*MAX(0,1-5/Supuestos!$C$20))*(1-Supuestos!$C$18)^5)) -> 0.62435361 | I13: =H13*(1-MIN(1,INDEX(Tabla_Mortalidad!$B$5:$B$75,MIN(71,Cartera_Polizas!$B$15+6-49))*(1+(Cartera_Polizas!$P$15-1)*MAX(0,1-6/Supuestos!$C$20))*(1-Supuestos!$C$18)^6)) -> 0.56356798 | J13: =I13*(1-MIN(1,INDEX(Tabla_Mortalidad!$B$5:$B$75,MIN(71,Cartera_Polizas!$B$15+7-49))*(1+(Cartera_Polizas!$P$15-1)*MAX(0,1-7/Supuestos!$C$20))*(1-Supuestos!$C$18)^7)) -> 0.50459053 | K13: =J13*(1-MIN(1,INDEX(Tabla_Mortalidad!$B$5:$B$75,MIN(71,Cartera_Polizas!$B$15+8-49))*(1+(Cartera_Polizas!$P$15-1)*MAX(0,1-8/Supuestos!$C$20))*(1-Supuestos!$C$18)^8)) -> 0.44790435 | L13: =K13*(1-MIN(1,INDEX(Tabla_Mortalidad!$B$5:$B$75,MIN(71,Cartera_Polizas!$B$15+9-49))*(1+(Cartera_Polizas!$P$15-1)*MAX(0,1-9/Supuestos!$C$20))*(1-Supuestos!$C$18)^9)) -> 0.39396698 | M13: =L13*(1-MIN(1,INDEX(Tabla_Mortalidad!$B$5:$B$75,MIN(71,Cartera_Polizas!$B$15+10-49))*(1+(Cartera_Polizas!$P$15-1)*MAX(0,1-10/Supuestos!$C$20))*(1-Supuestos!$C$18)^10)) -> 0.34319147 | N13: =M13*(1-MIN(1,INDEX(Tabla_Mortalidad!$B$5:$B$75,MIN(71,Cartera_Polizas!$B$15+11-49))*(1+(Cartera_Polizas!$P$15-1)*MAX(0,1-11/Supuestos!$C$20))*(1-Supuestos!$C$18)^11)) -> 0.29593209 | O13: =N13*(1-MIN(1,INDEX(Tabla_Mortalidad!$B$5:$B$75,MIN(71,Cartera_Polizas!$B$15+12-49))*(1+(Cartera_Polizas!$P$15-1)*MAX(0,1-12/Supuestos!$C$20))*(1-Supuestos!$C$18)^12)) -> 0.25247044 | P13: =O13*(1-MIN(1,INDEX(Tabla_Mortalidad!$B$5:$B$75,MIN(71,Cartera_Polizas!$B$15+13-49))*(1+(Cartera_Polizas!$P$15-1)*MAX(0,1-13/Supuestos!$C$20))*(1-Supuestos!$C$18)^13)) -> 0.21300446 | Q13: =P13*(1-MIN(1,INDEX(Tabla_Mortalidad!$B$5:$B$75,MIN(71,Cartera_Polizas!$B$15+14-49))*(1+(Cartera_Polizas!$P$15-1)*MAX(0,1-14/Supuestos!$C$20))*(1-Supuestos!$C$18)^14)) -> 0.1776408 | R13: =Q13*(1-MIN(1,INDEX(Tabla_Mortalidad!$B$5:$B$75,MIN(71,Cartera_Polizas!$B$15+15-49))*(1+(Cartera_Polizas!$P$15-1)*MAX(0,1-15/Supuestos!$C$20))*(1-Supuestos!$C$18)^15)) -> 0.14639106 | S13: =R13*(1-MIN(1,INDEX(Tabla_Mortalidad!$B$5:$B$75,MIN(71,Cartera_Polizas!$B$15+16-49))*(1+(Cartera_Polizas!$P$15-1)*MAX(0,1-16/Supuestos!$C$20))*(1-Supuestos!$C$18)^16)) -> 0.11812264 | T13: =S13*(1-MIN(1,INDEX(Tabla_Mortalidad!$B$5:$B$75,MIN(71,Cartera_Polizas!$B$15+17-49))*(1+(Cartera_Polizas!$P$15-1)*MAX(0,1-17/Supuestos!$C$20))*(1-Supuestos!$C$18)^17)) -> 0.093117329 | U13: =T13*(1-MIN(1,INDEX(Tabla_Mortalidad!$B$5:$B$75,MIN(71,Cartera_Polizas!$B$15+18-49))*(1+(Cartera_Polizas!$P$15-1)*MAX(0,1-18/Supuestos!$C$20))*(1-Supuestos!$C$18)^18)) -> 0.071539187 | V13: =U13*(1-MIN(1,INDEX(Tabla_Mortalidad!$B$5:$B$75,MIN(71,Cartera_Polizas!$B$15+19-49))*(1+(Cartera_Polizas!$P$15-1)*MAX(0,1-19/Supuestos!$C$20))*(1-Supuestos!$C$18)^19)) -> 0.053420845 | W13: =V13*(1-MIN(1,INDEX(Tabla_Mortalidad!$B$5:$B$75,MIN(71,Cartera_Polizas!$B$15+20-49))*(1+(Cartera_Polizas!$P$15-1)*MAX(0,1-20/Supuestos!$C$20))*(1-Supuestos!$C$18)^20)) -> 0.038660053 | X13: =W13*(1-MIN(1,INDEX(Tabla_Mortalidad!$B$5:$B$75,MIN(71,Cartera_Polizas!$B$15+21-49))*(1+(Cartera_Polizas!$P$15-1)*MAX(0,1-21/Supuestos!$C$20))*(1-Supuestos!$C$18)^21)) -> 0.027028317 | Y13: =X13*(1-MIN(1,INDEX(Tabla_Mortalidad!$B$5:$B$75,MIN(71,Cartera_Polizas!$B$15+22-49))*(1+(Cartera_Polizas!$P$15-1)*MAX(0,1-22/Supuestos!$C$20))*(1-Supuestos!$C$18)^22)) -> 0.018192276 | Z13: =Y13*(1-MIN(1,INDEX(Tabla_Mortalidad!$B$5:$B$75,MIN(71,Cartera_Polizas!$B$15+23-49))*(1+(Cartera_Polizas!$P$15-1)*MAX(0,1-23/Supuestos!$C$20))*(1-Supuestos!$C$18)^23)) -> 0.011745122 | AA13: =Z13*(1-MIN(1,INDEX(Tabla_Mortalidad!$B$5:$B$75,MIN(71,Cartera_Polizas!$B$15+24-49))*(1+(Cartera_Polizas!$P$15-1)*MAX(0,1-24/Supuestos!$C$20))*(1-Supuestos!$C$18)^24)) -> 0.0072445047 | AB13: =AA13*(1-MIN(1,INDEX(Tabla_Mortalidad!$B$5:$B$75,MIN(71,Cartera_Polizas!$B$15+25-49))*(1+(Cartera_Polizas!$P$15-1)*MAX(0,1-25/Supuestos!$C$20))*(1-Supuestos!$C$18)^25)) -> 0.0042512273 | AC13: =AB13*(1-MIN(1,INDEX(Tabla_Mortalidad!$B$5:$B$75,MIN(71,Cartera_Polizas!$B$15+26-49))*(1+(Cartera_Polizas!$P$15-1)*MAX(0,1-26/Supuestos!$C$20))*(1-Supuestos!$C$18)^26)) -> 0.0023629722 | AD13: =AC13*(1-MIN(1,INDEX(Tabla_Mortalidad!$B$5:$B$75,MIN(71,Cartera_Polizas!$B$15+27-49))*(1+(Cartera_Polizas!$P$15-1)*MAX(0,1-27/Supuestos!$C$20))*(1-Supuestos!$C$18)^27)) -> 0.0012383977 | AE13: =AD13*(1-MIN(1,INDEX(Tabla_Mortalidad!$B$5:$B$75,MIN(71,Cartera_Polizas!$B$15+28-49))*(1+(Cartera_Polizas!$P$15-1)*MAX(0,1-28/Supuestos!$C$20))*(1-Supuestos!$C$18)^28)) -> 0.00060912844 | AF13: =AE13*(1-MIN(1,INDEX(Tabla_Mortalidad!$B$5:$B$75,MIN(71,Cartera_Polizas!$B$15+29-49))*(1+(Cartera_Polizas!$P$15-1)*MAX(0,1-29/Supuestos!$C$20))*(1-Supuestos!$C$18)^29)) -> 0.00027991068 | AG13: =AF13*(1-MIN(1,INDEX(Tabla_Mortalidad!$B$5:$B$75,MIN(71,Cartera_Polizas!$B$15+30-49))*(1+(Cartera_Polizas!$P$15-1)*MAX(0,1-30/Supuestos!$C$20))*(1-Supuestos!$C$18)^30)) -> 0.00011964867 | AH13: =AG13*(1-MIN(1,INDEX(Tabla_Mortalidad!$B$5:$B$75,MIN(71,Cartera_Polizas!$B$15+31-49))*(1+(Cartera_Polizas!$P$15-1)*MAX(0,1-31/Supuestos!$C$20))*(1-Supuestos!$C$18)^31)) -> 4.7390058e-05 | AI13: =AH13*(1-MIN(1,INDEX(Tabla_Mortalidad!$B$5:$B$75,MIN(71,Cartera_Polizas!$B$15+32-49))*(1+(Cartera_Polizas!$P$15-1)*MAX(0,1-32/Supuestos!$C$20))*(1-Supuestos!$C$18)^32)) -> 1.7337881e-05 | AJ13: =AI13*(1-MIN(1,INDEX(Tabla_Mortalidad!$B$5:$B$75,MIN(71,Cartera_Polizas!$B$15+33-49))*(1+(Cartera_Polizas!$P$15-1)*MAX(0,1-33/Supuestos!$C$20))*(1-Supuestos!$C$18)^33)) -> 5.8472644e-06 | AK13: =AJ13*(1-MIN(1,INDEX(Tabla_Mortalidad!$B$5:$B$75,MIN(71,Cartera_Polizas!$B$15+34-49))*(1+(Cartera_Polizas!$P$15-1)*MAX(0,1-34/Supuestos!$C$20))*(1-Supuestos!$C$18)^34)) -> 1.8168837e-06 | AL13: =AK13*(1-MIN(1,INDEX(Tabla_Mortalidad!$B$5:$B$75,MIN(71,Cartera_Polizas!$B$15+35-49))*(1+(Cartera_Polizas!$P$15-1)*MAX(0,1-35/Supuestos!$C$20))*(1-Supuestos!$C$18)^35)) -> 5.2086091e-07 | AM13: =AL13*(1-MIN(1,INDEX(Tabla_Mortalidad!$B$5:$B$75,MIN(71,Cartera_Polizas!$B$15+36-49))*(1+(Cartera_Polizas!$P$15-1)*MAX(0,1-36/Supuestos!$C$20))*(1-Supuestos!$C$18)^36)) -> 1.3826999e-07 | AN13: =AM13*(1-MIN(1,INDEX(Tabla_Mortalidad!$B$5:$B$75,MIN(71,Cartera_Polizas!$B$15+37-49))*(1+(Cartera_Polizas!$P$15-1)*MAX(0,1-37/Supuestos!$C$20))*(1-Supuestos!$C$18)^37)) -> 3.4198866e-08 | AO13: =AN13*(1-MIN(1,INDEX(Tabla_Mortalidad!$B$5:$B$75,MIN(71,Cartera_Polizas!$B$15+38-49))*(1+(Cartera_Polizas!$P$15-1)*MAX(0,1-38/Supuestos!$C$20))*(1-Supuestos!$C$18)^38)) -> 7.9487062e-09 | AP13: =AO13*(1-MIN(1,INDEX(Tabla_Mortalidad!$B$5:$B$75,MIN(71,Cartera_Polizas!$B$15+39-49))*(1+(Cartera_Polizas!$P$15-1)*MAX(0,1-39/Supuestos!$C$20))*(1-Supuestos!$C$18)^39)) -> 1.7546666e-09 | AQ13: =AP13*(1-MIN(1,INDEX(Tabla_Mortalidad!$B$5:$B$75,MIN(71,Cartera_Polizas!$B$15+40-49))*(1+(Cartera_Polizas!$P$15-1)*MAX(0,1-40/Supuestos!$C$20))*(1-Supuestos!$C$18)^40)) -> 3.1878761e-10 | AR13: =AQ13*(1-MIN(1,INDEX(Tabla_Mortalidad!$B$5:$B$75,MIN(71,Cartera_Polizas!$B$15+41-49))*(1+(Cartera_Polizas!$P$15-1)*MAX(0,1-41/Supuestos!$C$20))*(1-Supuestos!$C$18)^41)) -> 5.9221646e-11 | AS13: =AR13*(1-MIN(1,INDEX(Tabla_Mortalidad!$B$5:$B$75,MIN(71,Cartera_Polizas!$B$15+42-49))*(1+(Cartera_Polizas!$P$15-1)*MAX(0,1-42/Supuestos!$C$20))*(1-Supuestos!$C$18)^42)) -> 1.1242793e-11 | AT13: =AS13*(1-MIN(1,INDEX(Tabla_Mortalidad!$B$5:$B$75,MIN(71,Cartera_Polizas!$B$15+43-49))*(1+(Cartera_Polizas!$P$15-1)*MAX(0,1-43/Supuestos!$C$20))*(1-Supuestos!$C$18)^43)) -> 2.1799034e-12 | AU13: =AT13*(1-MIN(1,INDEX(Tabla_Mortalidad!$B$5:$B$75,MIN(71,Cartera_Polizas!$B$15+44-49))*(1+(Cartera_Polizas!$P$15-1)*MAX(0,1-44/Supuestos!$C$20))*(1-Supuestos!$C$18)^44)) -> 4.3145507e-13
A14: =Cartera_Polizas!A16 -> 11 | B14: =SUM(C14:AU14)+0.5 -> 4.8340514 | C14: =1-MIN(1,INDEX(Tabla_Mortalidad!$B$5:$B$75,MIN(71,Cartera_Polizas!$B$16+0-49))*(1+(Cartera_Polizas!$P$16-1)*MAX(0,1-0/Supuestos!$C$20))*(1-Supuestos!$C$18)^0) -> 0.84991468 | D14: =C14*(1-MIN(1,INDEX(Tabla_Mortalidad!$B$5:$B$75,MIN(71,Cartera_Polizas!$B$16+1-49))*(1+(Cartera_Polizas!$P$16-1)*MAX(0,1-1/Supuestos!$C$20))*(1-Supuestos!$C$18)^1)) -> 0.71397158 | E14: =D14*(1-MIN(1,INDEX(Tabla_Mortalidad!$B$5:$B$75,MIN(71,Cartera_Polizas!$B$16+2-49))*(1+(Cartera_Polizas!$P$16-1)*MAX(0,1-2/Supuestos!$C$20))*(1-Supuestos!$C$18)^2)) -> 0.59250158 | F14: =E14*(1-MIN(1,INDEX(Tabla_Mortalidad!$B$5:$B$75,MIN(71,Cartera_Polizas!$B$16+3-49))*(1+(Cartera_Polizas!$P$16-1)*MAX(0,1-3/Supuestos!$C$20))*(1-Supuestos!$C$18)^3)) -> 0.48549987 | G14: =F14*(1-MIN(1,INDEX(Tabla_Mortalidad!$B$5:$B$75,MIN(71,Cartera_Polizas!$B$16+4-49))*(1+(Cartera_Polizas!$P$16-1)*MAX(0,1-4/Supuestos!$C$20))*(1-Supuestos!$C$18)^4)) -> 0.39264311 | H14: =G14*(1-MIN(1,INDEX(Tabla_Mortalidad!$B$5:$B$75,MIN(71,Cartera_Polizas!$B$16+5-49))*(1+(Cartera_Polizas!$P$16-1)*MAX(0,1-5/Supuestos!$C$20))*(1-Supuestos!$C$18)^5)) -> 0.31330716 | I14: =H14*(1-MIN(1,INDEX(Tabla_Mortalidad!$B$5:$B$75,MIN(71,Cartera_Polizas!$B$16+6-49))*(1+(Cartera_Polizas!$P$16-1)*MAX(0,1-6/Supuestos!$C$20))*(1-Supuestos!$C$18)^6)) -> 0.24660961 | J14: =I14*(1-MIN(1,INDEX(Tabla_Mortalidad!$B$5:$B$75,MIN(71,Cartera_Polizas!$B$16+7-49))*(1+(Cartera_Polizas!$P$16-1)*MAX(0,1-7/Supuestos!$C$20))*(1-Supuestos!$C$18)^7)) -> 0.1914629 | K14: =J14*(1-MIN(1,INDEX(Tabla_Mortalidad!$B$5:$B$75,MIN(71,Cartera_Polizas!$B$16+8-49))*(1+(Cartera_Polizas!$P$16-1)*MAX(0,1-8/Supuestos!$C$20))*(1-Supuestos!$C$18)^8)) -> 0.14663682 | L14: =K14*(1-MIN(1,INDEX(Tabla_Mortalidad!$B$5:$B$75,MIN(71,Cartera_Polizas!$B$16+9-49))*(1+(Cartera_Polizas!$P$16-1)*MAX(0,1-9/Supuestos!$C$20))*(1-Supuestos!$C$18)^9)) -> 0.11082416 | M14: =L14*(1-MIN(1,INDEX(Tabla_Mortalidad!$B$5:$B$75,MIN(71,Cartera_Polizas!$B$16+10-49))*(1+(Cartera_Polizas!$P$16-1)*MAX(0,1-10/Supuestos!$C$20))*(1-Supuestos!$C$18)^10)) -> 0.082704251 | N14: =M14*(1-MIN(1,INDEX(Tabla_Mortalidad!$B$5:$B$75,MIN(71,Cartera_Polizas!$B$16+11-49))*(1+(Cartera_Polizas!$P$16-1)*MAX(0,1-11/Supuestos!$C$20))*(1-Supuestos!$C$18)^11)) -> 0.061001011 | O14: =N14*(1-MIN(1,INDEX(Tabla_Mortalidad!$B$5:$B$75,MIN(71,Cartera_Polizas!$B$16+12-49))*(1+(Cartera_Polizas!$P$16-1)*MAX(0,1-12/Supuestos!$C$20))*(1-Supuestos!$C$18)^12)) -> 0.044529209 | P14: =O14*(1-MIN(1,INDEX(Tabla_Mortalidad!$B$5:$B$75,MIN(71,Cartera_Polizas!$B$16+13-49))*(1+(Cartera_Polizas!$P$16-1)*MAX(0,1-13/Supuestos!$C$20))*(1-Supuestos!$C$18)^13)) -> 0.032227418 | Q14: =P14*(1-MIN(1,INDEX(Tabla_Mortalidad!$B$5:$B$75,MIN(71,Cartera_Polizas!$B$16+14-49))*(1+(Cartera_Polizas!$P$16-1)*MAX(0,1-14/Supuestos!$C$20))*(1-Supuestos!$C$18)^14)) -> 0.023177511 | R14: =Q14*(1-MIN(1,INDEX(Tabla_Mortalidad!$B$5:$B$75,MIN(71,Cartera_Polizas!$B$16+15-49))*(1+(Cartera_Polizas!$P$16-1)*MAX(0,1-15/Supuestos!$C$20))*(1-Supuestos!$C$18)^15)) -> 0.016610764 | S14: =R14*(1-MIN(1,INDEX(Tabla_Mortalidad!$B$5:$B$75,MIN(71,Cartera_Polizas!$B$16+16-49))*(1+(Cartera_Polizas!$P$16-1)*MAX(0,1-16/Supuestos!$C$20))*(1-Supuestos!$C$18)^16)) -> 0.011486207 | T14: =S14*(1-MIN(1,INDEX(Tabla_Mortalidad!$B$5:$B$75,MIN(71,Cartera_Polizas!$B$16+17-49))*(1+(Cartera_Polizas!$P$16-1)*MAX(0,1-17/Supuestos!$C$20))*(1-Supuestos!$C$18)^17)) -> 0.0076358594 | U14: =T14*(1-MIN(1,INDEX(Tabla_Mortalidad!$B$5:$B$75,MIN(71,Cartera_Polizas!$B$16+18-49))*(1+(Cartera_Polizas!$P$16-1)*MAX(0,1-18/Supuestos!$C$20))*(1-Supuestos!$C$18)^18)) -> 0.0048611116 | V14: =U14*(1-MIN(1,INDEX(Tabla_Mortalidad!$B$5:$B$75,MIN(71,Cartera_Polizas!$B$16+19-49))*(1+(Cartera_Polizas!$P$16-1)*MAX(0,1-19/Supuestos!$C$20))*(1-Supuestos!$C$18)^19)) -> 0.0029511054 | W14: =V14*(1-MIN(1,INDEX(Tabla_Mortalidad!$B$5:$B$75,MIN(71,Cartera_Polizas!$B$16+20-49))*(1+(Cartera_Polizas!$P$16-1)*MAX(0,1-20/Supuestos!$C$20))*(1-Supuestos!$C$18)^20)) -> 0.0017008246 | X14: =W14*(1-MIN(1,INDEX(Tabla_Mortalidad!$B$5:$B$75,MIN(71,Cartera_Polizas!$B$16+21-49))*(1+(Cartera_Polizas!$P$16-1)*MAX(0,1-21/Supuestos!$C$20))*(1-Supuestos!$C$18)^21)) -> 0.00092620147 | Y14: =X14*(1-MIN(1,INDEX(Tabla_Mortalidad!$B$5:$B$75,MIN(71,Cartera_Polizas!$B$16+22-49))*(1+(Cartera_Polizas!$P$16-1)*MAX(0,1-22/Supuestos!$C$20))*(1-Supuestos!$C$18)^22)) -> 0.00047422098 | Z14: =Y14*(1-MIN(1,INDEX(Tabla_Mortalidad!$B$5:$B$75,MIN(71,Cartera_Polizas!$B$16+23-49))*(1+(Cartera_Polizas!$P$16-1)*MAX(0,1-23/Supuestos!$C$20))*(1-Supuestos!$C$18)^23)) -> 0.00022713862 | AA14: =Z14*(1-MIN(1,INDEX(Tabla_Mortalidad!$B$5:$B$75,MIN(71,Cartera_Polizas!$B$16+24-49))*(1+(Cartera_Polizas!$P$16-1)*MAX(0,1-24/Supuestos!$C$20))*(1-Supuestos!$C$18)^24)) -> 0.00010126058 | AB14: =AA14*(1-MIN(1,INDEX(Tabla_Mortalidad!$B$5:$B$75,MIN(71,Cartera_Polizas!$B$16+25-49))*(1+(Cartera_Polizas!$P$16-1)*MAX(0,1-25/Supuestos!$C$20))*(1-Supuestos!$C$18)^25)) -> 4.1812736e-05 | AC14: =AB14*(1-MIN(1,INDEX(Tabla_Mortalidad!$B$5:$B$75,MIN(71,Cartera_Polizas!$B$16+26-49))*(1+(Cartera_Polizas!$P$16-1)*MAX(0,1-26/Supuestos!$C$20))*(1-Supuestos!$C$18)^26)) -> 1.592018e-05 | AD14: =AC14*(1-MIN(1,INDEX(Tabla_Mortalidad!$B$5:$B$75,MIN(71,Cartera_Polizas!$B$16+27-49))*(1+(Cartera_Polizas!$P$16-1)*MAX(0,1-27/Supuestos!$C$20))*(1-Supuestos!$C$18)^27)) -> 5.5682513e-06 | AE14: =AD14*(1-MIN(1,INDEX(Tabla_Mortalidad!$B$5:$B$75,MIN(71,Cartera_Polizas!$B$16+28-49))*(1+(Cartera_Polizas!$P$16-1)*MAX(0,1-28/Supuestos!$C$20))*(1-Supuestos!$C$18)^28)) -> 1.7842547e-06 | AF14: =AE14*(1-MIN(1,INDEX(Tabla_Mortalidad!$B$5:$B$75,MIN(71,Cartera_Polizas!$B$16+29-49))*(1+(Cartera_Polizas!$P$16-1)*MAX(0,1-29/Supuestos!$C$20))*(1-Supuestos!$C$18)^29)) -> 5.2319749e-07 | AG14: =AF14*(1-MIN(1,INDEX(Tabla_Mortalidad!$B$5:$B$75,MIN(71,Cartera_Polizas!$B$16+30-49))*(1+(Cartera_Polizas!$P$16-1)*MAX(0,1-30/Supuestos!$C$20))*(1-Supuestos!$C$18)^30)) -> 1.405175e-07 | AH14: =AG14*(1-MIN(1,INDEX(Tabla_Mortalidad!$B$5:$B$75,MIN(71,Cartera_Polizas!$B$16+31-49))*(1+(Cartera_Polizas!$P$16-1)*MAX(0,1-31/Supuestos!$C$20))*(1-Supuestos!$C$18)^31)) -> 3.4682845e-08 | AI14: =AH14*(1-MIN(1,INDEX(Tabla_Mortalidad!$B$5:$B$75,MIN(71,Cartera_Polizas!$B$16+32-49))*(1+(Cartera_Polizas!$P$16-1)*MAX(0,1-32/Supuestos!$C$20))*(1-Supuestos!$C$18)^32)) -> 7.915726e-09 | AJ14: =AI14*(1-MIN(1,INDEX(Tabla_Mortalidad!$B$5:$B$75,MIN(71,Cartera_Polizas!$B$16+33-49))*(1+(Cartera_Polizas!$P$16-1)*MAX(0,1-33/Supuestos!$C$20))*(1-Supuestos!$C$18)^33)) -> 1.6856177e-09 | AK14: =AJ14*(1-MIN(1,INDEX(Tabla_Mortalidad!$B$5:$B$75,MIN(71,Cartera_Polizas!$B$16+34-49))*(1+(Cartera_Polizas!$P$16-1)*MAX(0,1-34/Supuestos!$C$20))*(1-Supuestos!$C$18)^34)) -> 3.3876155e-10 | AL14: =AK14*(1-MIN(1,INDEX(Tabla_Mortalidad!$B$5:$B$75,MIN(71,Cartera_Polizas!$B$16+35-49))*(1+(Cartera_Polizas!$P$16-1)*MAX(0,1-35/Supuestos!$C$20))*(1-Supuestos!$C$18)^35)) -> 5.4510592e-11 | AM14: =AL14*(1-MIN(1,INDEX(Tabla_Mortalidad!$B$5:$B$75,MIN(71,Cartera_Polizas!$B$16+36-49))*(1+(Cartera_Polizas!$P$16-1)*MAX(0,1-36/Supuestos!$C$20))*(1-Supuestos!$C$18)^36)) -> 9.0000713e-12 | AN14: =AM14*(1-MIN(1,INDEX(Tabla_Mortalidad!$B$5:$B$75,MIN(71,Cartera_Polizas!$B$16+37-49))*(1+(Cartera_Polizas!$P$16-1)*MAX(0,1-37/Supuestos!$C$20))*(1-Supuestos!$C$18)^37)) -> 1.5235437e-12 | AO14: =AN14*(1-MIN(1,INDEX(Tabla_Mortalidad!$B$5:$B$75,MIN(71,Cartera_Polizas!$B$16+38-49))*(1+(Cartera_Polizas!$P$16-1)*MAX(0,1-38/Supuestos!$C$20))*(1-Supuestos!$C$18)^38)) -> 2.6423565e-13 | AP14: =AO14*(1-MIN(1,INDEX(Tabla_Mortalidad!$B$5:$B$75,MIN(71,Cartera_Polizas!$B$16+39-49))*(1+(Cartera_Polizas!$P$16-1)*MAX(0,1-39/Supuestos!$C$20))*(1-Supuestos!$C$18)^39)) -> 4.691972e-14 | AQ14: =AP14*(1-MIN(1,INDEX(Tabla_Mortalidad!$B$5:$B$75,MIN(71,Cartera_Polizas!$B$16+40-49))*(1+(Cartera_Polizas!$P$16-1)*MAX(0,1-40/Supuestos!$C$20))*(1-Supuestos!$C$18)^40)) -> 8.5243691e-15 | AR14: =AQ14*(1-MIN(1,INDEX(Tabla_Mortalidad!$B$5:$B$75,MIN(71,Cartera_Polizas!$B$16+41-49))*(1+(Cartera_Polizas!$P$16-1)*MAX(0,1-41/Supuestos!$C$20))*(1-Supuestos!$C$18)^41)) -> 1.5835847e-15 | AS14: =AR14*(1-MIN(1,INDEX(Tabla_Mortalidad!$B$5:$B$75,MIN(71,Cartera_Polizas!$B$16+42-49))*(1+(Cartera_Polizas!$P$16-1)*MAX(0,1-42/Supuestos!$C$20))*(1-Supuestos!$C$18)^42)) -> 3.0063187e-16 | AT14: =AS14*(1-MIN(1,INDEX(Tabla_Mortalidad!$B$5:$B$75,MIN(71,Cartera_Polizas!$B$16+43-49))*(1+(Cartera_Polizas!$P$16-1)*MAX(0,1-43/Supuestos!$C$20))*(1-Supuestos!$C$18)^43)) -> 5.8290537e-17 | AU14: =AT14*(1-MIN(1,INDEX(Tabla_Mortalidad!$B$5:$B$75,MIN(71,Cartera_Polizas!$B$16+44-49))*(1+(Cartera_Polizas!$P$16-1)*MAX(0,1-44/Supuestos!$C$20))*(1-Supuestos!$C$18)^44)) -> 1.1537093e-17
A15: =Cartera_Polizas!A17 -> 12 | B15: =SUM(C15:AU15)+0.5 -> 4.946883 | C15: =1-MIN(1,INDEX(Tabla_Mortalidad!$B$5:$B$75,MIN(71,Cartera_Polizas!$B$17+0-49))*(1+(Cartera_Polizas!$P$17-1)*MAX(0,1-0/Supuestos!$C$20))*(1-Supuestos!$C$18)^0) -> 0.85447808 | D15: =C15*(1-MIN(1,INDEX(Tabla_Mortalidad!$B$5:$B$75,MIN(71,Cartera_Polizas!$B$17+1-49))*(1+(Cartera_Polizas!$P$17-1)*MAX(0,1-1/Supuestos!$C$20))*(1-Supuestos!$C$18)^1)) -> 0.72183113 | E15: =D15*(1-MIN(1,INDEX(Tabla_Mortalidad!$B$5:$B$75,MIN(71,Cartera_Polizas!$B$17+2-49))*(1+(Cartera_Polizas!$P$17-1)*MAX(0,1-2/Supuestos!$C$20))*(1-Supuestos!$C$18)^2)) -> 0.60251597 | F15: =E15*(1-MIN(1,INDEX(Tabla_Mortalidad!$B$5:$B$75,MIN(71,Cartera_Polizas!$B$17+3-49))*(1+(Cartera_Polizas!$P$17-1)*MAX(0,1-3/Supuestos!$C$20))*(1-Supuestos!$C$18)^3)) -> 0.49667929 | G15: =F15*(1-MIN(1,INDEX(Tabla_Mortalidad!$B$5:$B$75,MIN(71,Cartera_Polizas!$B$17+4-49))*(1+(Cartera_Polizas!$P$17-1)*MAX(0,1-4/Supuestos!$C$20))*(1-Supuestos!$C$18)^4)) -> 0.40416619 | H15: =G15*(1-MIN(1,INDEX(Tabla_Mortalidad!$B$5:$B$75,MIN(71,Cartera_Polizas!$B$17+5-49))*(1+(Cartera_Polizas!$P$17-1)*MAX(0,1-5/Supuestos!$C$20))*(1-Supuestos!$C$18)^5)) -> 0.32452852 | I15: =H15*(1-MIN(1,INDEX(Tabla_Mortalidad!$B$5:$B$75,MIN(71,Cartera_Polizas!$B$17+6-49))*(1+(Cartera_Polizas!$P$17-1)*MAX(0,1-6/Supuestos!$C$20))*(1-Supuestos!$C$18)^6)) -> 0.25705761 | J15: =I15*(1-MIN(1,INDEX(Tabla_Mortalidad!$B$5:$B$75,MIN(71,Cartera_Polizas!$B$17+7-49))*(1+(Cartera_Polizas!$P$17-1)*MAX(0,1-7/Supuestos!$C$20))*(1-Supuestos!$C$18)^7)) -> 0.2008282 | K15: =J15*(1-MIN(1,INDEX(Tabla_Mortalidad!$B$5:$B$75,MIN(71,Cartera_Polizas!$B$17+8-49))*(1+(Cartera_Polizas!$P$17-1)*MAX(0,1-8/Supuestos!$C$20))*(1-Supuestos!$C$18)^8)) -> 0.15475325 | L15: =K15*(1-MIN(1,INDEX(Tabla_Mortalidad!$B$5:$B$75,MIN(71,Cartera_Polizas!$B$17+9-49))*(1+(Cartera_Polizas!$P$17-1)*MAX(0,1-9/Supuestos!$C$20))*(1-Supuestos!$C$18)^9)) -> 0.11764413 | M15: =L15*(1-MIN(1,INDEX(Tabla_Mortalidad!$B$5:$B$75,MIN(71,Cartera_Polizas!$B$17+10-49))*(1+(Cartera_Polizas!$P$17-1)*MAX(0,1-10/Supuestos!$C$20))*(1-Supuestos!$C$18)^10)) -> 0.088271225 | N15: =M15*(1-MIN(1,INDEX(Tabla_Mortalidad!$B$5:$B$75,MIN(71,Cartera_Polizas!$B$17+11-49))*(1+(Cartera_Polizas!$P$17-1)*MAX(0,1-11/Supuestos!$C$20))*(1-Supuestos!$C$18)^11)) -> 0.065421704 | O15: =N15*(1-MIN(1,INDEX(Tabla_Mortalidad!$B$5:$B$75,MIN(71,Cartera_Polizas!$B$17+12-49))*(1+(Cartera_Polizas!$P$17-1)*MAX(0,1-12/Supuestos!$C$20))*(1-Supuestos!$C$18)^12)) -> 0.047947911 | P15: =O15*(1-MIN(1,INDEX(Tabla_Mortalidad!$B$5:$B$75,MIN(71,Cartera_Polizas!$B$17+13-49))*(1+(Cartera_Polizas!$P$17-1)*MAX(0,1-13/Supuestos!$C$20))*(1-Supuestos!$C$18)^13)) -> 0.034804195 | Q15: =P15*(1-MIN(1,INDEX(Tabla_Mortalidad!$B$5:$B$75,MIN(71,Cartera_Polizas!$B$17+14-49))*(1+(Cartera_Polizas!$P$17-1)*MAX(0,1-14/Supuestos!$C$20))*(1-Supuestos!$C$18)^14)) -> 0.025071366 | R15: =Q15*(1-MIN(1,INDEX(Tabla_Mortalidad!$B$5:$B$75,MIN(71,Cartera_Polizas!$B$17+15-49))*(1+(Cartera_Polizas!$P$17-1)*MAX(0,1-15/Supuestos!$C$20))*(1-Supuestos!$C$18)^15)) -> 0.017968044 | S15: =R15*(1-MIN(1,INDEX(Tabla_Mortalidad!$B$5:$B$75,MIN(71,Cartera_Polizas!$B$17+16-49))*(1+(Cartera_Polizas!$P$17-1)*MAX(0,1-16/Supuestos!$C$20))*(1-Supuestos!$C$18)^16)) -> 0.012424755 | T15: =S15*(1-MIN(1,INDEX(Tabla_Mortalidad!$B$5:$B$75,MIN(71,Cartera_Polizas!$B$17+17-49))*(1+(Cartera_Polizas!$P$17-1)*MAX(0,1-17/Supuestos!$C$20))*(1-Supuestos!$C$18)^17)) -> 0.0082597922 | U15: =T15*(1-MIN(1,INDEX(Tabla_Mortalidad!$B$5:$B$75,MIN(71,Cartera_Polizas!$B$17+18-49))*(1+(Cartera_Polizas!$P$17-1)*MAX(0,1-18/Supuestos!$C$20))*(1-Supuestos!$C$18)^18)) -> 0.0052583174 | V15: =U15*(1-MIN(1,INDEX(Tabla_Mortalidad!$B$5:$B$75,MIN(71,Cartera_Polizas!$B$17+19-49))*(1+(Cartera_Polizas!$P$17-1)*MAX(0,1-19/Supuestos!$C$20))*(1-Supuestos!$C$18)^19)) -> 0.0031922429 | W15: =V15*(1-MIN(1,INDEX(Tabla_Mortalidad!$B$5:$B$75,MIN(71,Cartera_Polizas!$B$17+20-49))*(1+(Cartera_Polizas!$P$17-1)*MAX(0,1-20/Supuestos!$C$20))*(1-Supuestos!$C$18)^20)) -> 0.0018398004 | X15: =W15*(1-MIN(1,INDEX(Tabla_Mortalidad!$B$5:$B$75,MIN(71,Cartera_Polizas!$B$17+21-49))*(1+(Cartera_Polizas!$P$17-1)*MAX(0,1-21/Supuestos!$C$20))*(1-Supuestos!$C$18)^21)) -> 0.0010018822 | Y15: =X15*(1-MIN(1,INDEX(Tabla_Mortalidad!$B$5:$B$75,MIN(71,Cartera_Polizas!$B$17+22-49))*(1+(Cartera_Polizas!$P$17-1)*MAX(0,1-22/Supuestos!$C$20))*(1-Supuestos!$C$18)^22)) -> 0.00051296999 | Z15: =Y15*(1-MIN(1,INDEX(Tabla_Mortalidad!$B$5:$B$75,MIN(71,Cartera_Polizas!$B$17+23-49))*(1+(Cartera_Polizas!$P$17-1)*MAX(0,1-23/Supuestos!$C$20))*(1-Supuestos!$C$18)^23)) -> 0.00024569831 | AA15: =Z15*(1-MIN(1,INDEX(Tabla_Mortalidad!$B$5:$B$75,MIN(71,Cartera_Polizas!$B$17+24-49))*(1+(Cartera_Polizas!$P$17-1)*MAX(0,1-24/Supuestos!$C$20))*(1-Supuestos!$C$18)^24)) -> 0.00010953468 | AB15: =AA15*(1-MIN(1,INDEX(Tabla_Mortalidad!$B$5:$B$75,MIN(71,Cartera_Polizas!$B$17+25-49))*(1+(Cartera_Polizas!$P$17-1)*MAX(0,1-25/Supuestos!$C$20))*(1-Supuestos!$C$18)^25)) -> 4.5229291e-05 | AC15: =AB15*(1-MIN(1,INDEX(Tabla_Mortalidad!$B$5:$B$75,MIN(71,Cartera_Polizas!$B$17+26-49))*(1+(Cartera_Polizas!$P$17-1)*MAX(0,1-26/Supuestos!$C$20))*(1-Supuestos!$C$18)^26)) -> 1.7221032e-05 | AD15: =AC15*(1-MIN(1,INDEX(Tabla_Mortalidad!$B$5:$B$75,MIN(71,Cartera_Polizas!$B$17+27-49))*(1+(Cartera_Polizas!$P$17-1)*MAX(0,1-27/Supuestos!$C$20))*(1-Supuestos!$C$18)^27)) -> 6.023238e-06 | AE15: =AD15*(1-MIN(1,INDEX(Tabla_Mortalidad!$B$5:$B$75,MIN(71,Cartera_Polizas!$B$17+28-49))*(1+(Cartera_Polizas!$P$17-1)*MAX(0,1-28/Supuestos!$C$20))*(1-Supuestos!$C$18)^28)) -> 1.9300477e-06 | AF15: =AE15*(1-MIN(1,INDEX(Tabla_Mortalidad!$B$5:$B$75,MIN(71,Cartera_Polizas!$B$17+29-49))*(1+(Cartera_Polizas!$P$17-1)*MAX(0,1-29/Supuestos!$C$20))*(1-Supuestos!$C$18)^29)) -> 5.6594842e-07 | AG15: =AF15*(1-MIN(1,INDEX(Tabla_Mortalidad!$B$5:$B$75,MIN(71,Cartera_Polizas!$B$17+30-49))*(1+(Cartera_Polizas!$P$17-1)*MAX(0,1-30/Supuestos!$C$20))*(1-Supuestos!$C$18)^30)) -> 1.5199931e-07 | AH15: =AG15*(1-MIN(1,INDEX(Tabla_Mortalidad!$B$5:$B$75,MIN(71,Cartera_Polizas!$B$17+31-49))*(1+(Cartera_Polizas!$P$17-1)*MAX(0,1-31/Supuestos!$C$20))*(1-Supuestos!$C$18)^31)) -> 3.7516811e-08 | AI15: =AH15*(1-MIN(1,INDEX(Tabla_Mortalidad!$B$5:$B$75,MIN(71,Cartera_Polizas!$B$17+32-49))*(1+(Cartera_Polizas!$P$17-1)*MAX(0,1-32/Supuestos!$C$20))*(1-Supuestos!$C$18)^32)) -> 8.5625269e-09 | AJ15: =AI15*(1-MIN(1,INDEX(Tabla_Mortalidad!$B$5:$B$75,MIN(71,Cartera_Polizas!$B$17+33-49))*(1+(Cartera_Polizas!$P$17-1)*MAX(0,1-33/Supuestos!$C$20))*(1-Supuestos!$C$18)^33)) -> 1.823351e-09 | AK15: =AJ15*(1-MIN(1,INDEX(Tabla_Mortalidad!$B$5:$B$75,MIN(71,Cartera_Polizas!$B$17+34-49))*(1+(Cartera_Polizas!$P$17-1)*MAX(0,1-34/Supuestos!$C$20))*(1-Supuestos!$C$18)^34)) -> 3.6644206e-10 | AL15: =AK15*(1-MIN(1,INDEX(Tabla_Mortalidad!$B$5:$B$75,MIN(71,Cartera_Polizas!$B$17+35-49))*(1+(Cartera_Polizas!$P$17-1)*MAX(0,1-35/Supuestos!$C$20))*(1-Supuestos!$C$18)^35)) -> 5.8964701e-11 | AM15: =AL15*(1-MIN(1,INDEX(Tabla_Mortalidad!$B$5:$B$75,MIN(71,Cartera_Polizas!$B$17+36-49))*(1+(Cartera_Polizas!$P$17-1)*MAX(0,1-36/Supuestos!$C$20))*(1-Supuestos!$C$18)^36)) -> 9.735475e-12 | AN15: =AM15*(1-MIN(1,INDEX(Tabla_Mortalidad!$B$5:$B$75,MIN(71,Cartera_Polizas!$B$17+37-49))*(1+(Cartera_Polizas!$P$17-1)*MAX(0,1-37/Supuestos!$C$20))*(1-Supuestos!$C$18)^37)) -> 1.6480339e-12 | AO15: =AN15*(1-MIN(1,INDEX(Tabla_Mortalidad!$B$5:$B$75,MIN(71,Cartera_Polizas!$B$17+38-49))*(1+(Cartera_Polizas!$P$17-1)*MAX(0,1-38/Supuestos!$C$20))*(1-Supuestos!$C$18)^38)) -> 2.8582657e-13 | AP15: =AO15*(1-MIN(1,INDEX(Tabla_Mortalidad!$B$5:$B$75,MIN(71,Cartera_Polizas!$B$17+39-49))*(1+(Cartera_Polizas!$P$17-1)*MAX(0,1-39/Supuestos!$C$20))*(1-Supuestos!$C$18)^39)) -> 5.0753572e-14 | AQ15: =AP15*(1-MIN(1,INDEX(Tabla_Mortalidad!$B$5:$B$75,MIN(71,Cartera_Polizas!$B$17+40-49))*(1+(Cartera_Polizas!$P$17-1)*MAX(0,1-40/Supuestos!$C$20))*(1-Supuestos!$C$18)^40)) -> 9.2209029e-15 | AR15: =AQ15*(1-MIN(1,INDEX(Tabla_Mortalidad!$B$5:$B$75,MIN(71,Cartera_Polizas!$B$17+41-49))*(1+(Cartera_Polizas!$P$17-1)*MAX(0,1-41/Supuestos!$C$20))*(1-Supuestos!$C$18)^41)) -> 1.7129808e-15 | AS15: =AR15*(1-MIN(1,INDEX(Tabla_Mortalidad!$B$5:$B$75,MIN(71,Cartera_Polizas!$B$17+42-49))*(1+(Cartera_Polizas!$P$17-1)*MAX(0,1-42/Supuestos!$C$20))*(1-Supuestos!$C$18)^42)) -> 3.2519676e-16 | AT15: =AS15*(1-MIN(1,INDEX(Tabla_Mortalidad!$B$5:$B$75,MIN(71,Cartera_Polizas!$B$17+43-49))*(1+(Cartera_Polizas!$P$17-1)*MAX(0,1-43/Supuestos!$C$20))*(1-Supuestos!$C$18)^43)) -> 6.3053509e-17 | AU15: =AT15*(1-MIN(1,INDEX(Tabla_Mortalidad!$B$5:$B$75,MIN(71,Cartera_Polizas!$B$17+44-49))*(1+(Cartera_Polizas!$P$17-1)*MAX(0,1-44/Supuestos!$C$20))*(1-Supuestos!$C$18)^44)) -> 1.2479799e-17
A16: =Cartera_Polizas!A18 -> 13 | B16: =SUM(C16:AU16)+0.5 -> 7.428413 | C16: =1-MIN(1,INDEX(Tabla_Mortalidad!$B$5:$B$75,MIN(71,Cartera_Polizas!$B$18+0-49))*(1+(Cartera_Polizas!$P$18-1)*MAX(0,1-0/Supuestos!$C$20))*(1-Supuestos!$C$18)^0) -> 0.92377812 | D16: =C16*(1-MIN(1,INDEX(Tabla_Mortalidad!$B$5:$B$75,MIN(71,Cartera_Polizas!$B$18+1-49))*(1+(Cartera_Polizas!$P$18-1)*MAX(0,1-1/Supuestos!$C$20))*(1-Supuestos!$C$18)^1)) -> 0.84690596 | E16: =D16*(1-MIN(1,INDEX(Tabla_Mortalidad!$B$5:$B$75,MIN(71,Cartera_Polizas!$B$18+2-49))*(1+(Cartera_Polizas!$P$18-1)*MAX(0,1-2/Supuestos!$C$20))*(1-Supuestos!$C$18)^2)) -> 0.77000986 | F16: =E16*(1-MIN(1,INDEX(Tabla_Mortalidad!$B$5:$B$75,MIN(71,Cartera_Polizas!$B$18+3-49))*(1+(Cartera_Polizas!$P$18-1)*MAX(0,1-3/Supuestos!$C$20))*(1-Supuestos!$C$18)^3)) -> 0.69377728 | G16: =F16*(1-MIN(1,INDEX(Tabla_Mortalidad!$B$5:$B$75,MIN(71,Cartera_Polizas!$B$18+4-49))*(1+(Cartera_Polizas!$P$18-1)*MAX(0,1-4/Supuestos!$C$20))*(1-Supuestos!$C$18)^4)) -> 0.61893625 | H16: =G16*(1-MIN(1,INDEX(Tabla_Mortalidad!$B$5:$B$75,MIN(71,Cartera_Polizas!$B$18+5-49))*(1+(Cartera_Polizas!$P$18-1)*MAX(0,1-5/Supuestos!$C$20))*(1-Supuestos!$C$18)^5)) -> 0.54624219 | I16: =H16*(1-MIN(1,INDEX(Tabla_Mortalidad!$B$5:$B$75,MIN(71,Cartera_Polizas!$B$18+6-49))*(1+(Cartera_Polizas!$P$18-1)*MAX(0,1-6/Supuestos!$C$20))*(1-Supuestos!$C$18)^6)) -> 0.47645013 | J16: =I16*(1-MIN(1,INDEX(Tabla_Mortalidad!$B$5:$B$75,MIN(71,Cartera_Polizas!$B$18+7-49))*(1+(Cartera_Polizas!$P$18-1)*MAX(0,1-7/Supuestos!$C$20))*(1-Supuestos!$C$18)^7)) -> 0.41028844 | K16: =J16*(1-MIN(1,INDEX(Tabla_Mortalidad!$B$5:$B$75,MIN(71,Cartera_Polizas!$B$18+8-49))*(1+(Cartera_Polizas!$P$18-1)*MAX(0,1-8/Supuestos!$C$20))*(1-Supuestos!$C$18)^8)) -> 0.34842822 | L16: =K16*(1-MIN(1,INDEX(Tabla_Mortalidad!$B$5:$B$75,MIN(71,Cartera_Polizas!$B$18+9-49))*(1+(Cartera_Polizas!$P$18-1)*MAX(0,1-9/Supuestos!$C$20))*(1-Supuestos!$C$18)^9)) -> 0.29145231 | M16: =L16*(1-MIN(1,INDEX(Tabla_Mortalidad!$B$5:$B$75,MIN(71,Cartera_Polizas!$B$18+10-49))*(1+(Cartera_Polizas!$P$18-1)*MAX(0,1-10/Supuestos!$C$20))*(1-Supuestos!$C$18)^10)) -> 0.23982523 | N16: =M16*(1-MIN(1,INDEX(Tabla_Mortalidad!$B$5:$B$75,MIN(71,Cartera_Polizas!$B$18+11-49))*(1+(Cartera_Polizas!$P$18-1)*MAX(0,1-11/Supuestos!$C$20))*(1-Supuestos!$C$18)^11)) -> 0.1938664 | O16: =N16*(1-MIN(1,INDEX(Tabla_Mortalidad!$B$5:$B$75,MIN(71,Cartera_Polizas!$B$18+12-49))*(1+(Cartera_Polizas!$P$18-1)*MAX(0,1-12/Supuestos!$C$20))*(1-Supuestos!$C$18)^12)) -> 0.15373195 | P16: =O16*(1-MIN(1,INDEX(Tabla_Mortalidad!$B$5:$B$75,MIN(71,Cartera_Polizas!$B$18+13-49))*(1+(Cartera_Polizas!$P$18-1)*MAX(0,1-13/Supuestos!$C$20))*(1-Supuestos!$C$18)^13)) -> 0.11940498 | Q16: =P16*(1-MIN(1,INDEX(Tabla_Mortalidad!$B$5:$B$75,MIN(71,Cartera_Polizas!$B$18+14-49))*(1+(Cartera_Polizas!$P$18-1)*MAX(0,1-14/Supuestos!$C$20))*(1-Supuestos!$C$18)^14)) -> 0.09069677 | R16: =Q16*(1-MIN(1,INDEX(Tabla_Mortalidad!$B$5:$B$75,MIN(71,Cartera_Polizas!$B$18+15-49))*(1+(Cartera_Polizas!$P$18-1)*MAX(0,1-15/Supuestos!$C$20))*(1-Supuestos!$C$18)^15)) -> 0.067261285 | S16: =R16*(1-MIN(1,INDEX(Tabla_Mortalidad!$B$5:$B$75,MIN(71,Cartera_Polizas!$B$18+16-49))*(1+(Cartera_Polizas!$P$18-1)*MAX(0,1-16/Supuestos!$C$20))*(1-Supuestos!$C$18)^16)) -> 0.048299827 | T16: =S16*(1-MIN(1,INDEX(Tabla_Mortalidad!$B$5:$B$75,MIN(71,Cartera_Polizas!$B$18+17-49))*(1+(Cartera_Polizas!$P$18-1)*MAX(0,1-17/Supuestos!$C$20))*(1-Supuestos!$C$18)^17)) -> 0.033473439 | U16: =T16*(1-MIN(1,INDEX(Tabla_Mortalidad!$B$5:$B$75,MIN(71,Cartera_Polizas!$B$18+18-49))*(1+(Cartera_Polizas!$P$18-1)*MAX(0,1-18/Supuestos!$C$20))*(1-Supuestos!$C$18)^18)) -> 0.022308748 | V16: =U16*(1-MIN(1,INDEX(Tabla_Mortalidad!$B$5:$B$75,MIN(71,Cartera_Polizas!$B$18+19-49))*(1+(Cartera_Polizas!$P$18-1)*MAX(0,1-19/Supuestos!$C$20))*(1-Supuestos!$C$18)^19)) -> 0.014242643 | W16: =V16*(1-MIN(1,INDEX(Tabla_Mortalidad!$B$5:$B$75,MIN(71,Cartera_Polizas!$B$18+20-49))*(1+(Cartera_Polizas!$P$18-1)*MAX(0,1-20/Supuestos!$C$20))*(1-Supuestos!$C$18)^20)) -> 0.0086744684 | X16: =W16*(1-MIN(1,INDEX(Tabla_Mortalidad!$B$5:$B$75,MIN(71,Cartera_Polizas!$B$18+21-49))*(1+(Cartera_Polizas!$P$18-1)*MAX(0,1-21/Supuestos!$C$20))*(1-Supuestos!$C$18)^21)) -> 0.0050177727 | Y16: =X16*(1-MIN(1,INDEX(Tabla_Mortalidad!$B$5:$B$75,MIN(71,Cartera_Polizas!$B$18+22-49))*(1+(Cartera_Polizas!$P$18-1)*MAX(0,1-22/Supuestos!$C$20))*(1-Supuestos!$C$18)^22)) -> 0.0027439061 | Z16: =Y16*(1-MIN(1,INDEX(Tabla_Mortalidad!$B$5:$B$75,MIN(71,Cartera_Polizas!$B$18+23-49))*(1+(Cartera_Polizas!$P$18-1)*MAX(0,1-23/Supuestos!$C$20))*(1-Supuestos!$C$18)^23)) -> 0.0014115922 | AA16: =Z16*(1-MIN(1,INDEX(Tabla_Mortalidad!$B$5:$B$75,MIN(71,Cartera_Polizas!$B$18+24-49))*(1+(Cartera_Polizas!$P$18-1)*MAX(0,1-24/Supuestos!$C$20))*(1-Supuestos!$C$18)^24)) -> 0.00067979069 | AB16: =AA16*(1-MIN(1,INDEX(Tabla_Mortalidad!$B$5:$B$75,MIN(71,Cartera_Polizas!$B$18+25-49))*(1+(Cartera_Polizas!$P$18-1)*MAX(0,1-25/Supuestos!$C$20))*(1-Supuestos!$C$18)^25)) -> 0.00030494091 | AC16: =AB16*(1-MIN(1,INDEX(Tabla_Mortalidad!$B$5:$B$75,MIN(71,Cartera_Polizas!$B$18+26-49))*(1+(Cartera_Polizas!$P$18-1)*MAX(0,1-26/Supuestos!$C$20))*(1-Supuestos!$C$18)^26)) -> 0.00012681197 | AD16: =AC16*(1-MIN(1,INDEX(Tabla_Mortalidad!$B$5:$B$75,MIN(71,Cartera_Polizas!$B$18+27-49))*(1+(Cartera_Polizas!$P$18-1)*MAX(0,1-27/Supuestos!$C$20))*(1-Supuestos!$C$18)^27)) -> 4.8676241e-05 | AE16: =AD16*(1-MIN(1,INDEX(Tabla_Mortalidad!$B$5:$B$75,MIN(71,Cartera_Polizas!$B$18+28-49))*(1+(Cartera_Polizas!$P$18-1)*MAX(0,1-28/Supuestos!$C$20))*(1-Supuestos!$C$18)^28)) -> 1.7183286e-05 | AF16: =AE16*(1-MIN(1,INDEX(Tabla_Mortalidad!$B$5:$B$75,MIN(71,Cartera_Polizas!$B$18+29-49))*(1+(Cartera_Polizas!$P$18-1)*MAX(0,1-29/Supuestos!$C$20))*(1-Supuestos!$C$18)^29)) -> 5.5644878e-06 | AG16: =AF16*(1-MIN(1,INDEX(Tabla_Mortalidad!$B$5:$B$75,MIN(71,Cartera_Polizas!$B$18+30-49))*(1+(Cartera_Polizas!$P$18-1)*MAX(0,1-30/Supuestos!$C$20))*(1-Supuestos!$C$18)^30)) -> 1.6513403e-06 | AH16: =AG16*(1-MIN(1,INDEX(Tabla_Mortalidad!$B$5:$B$75,MIN(71,Cartera_Polizas!$B$18+31-49))*(1+(Cartera_Polizas!$P$18-1)*MAX(0,1-31/Supuestos!$C$20))*(1-Supuestos!$C$18)^31)) -> 4.4954705e-07 | AI16: =AH16*(1-MIN(1,INDEX(Tabla_Mortalidad!$B$5:$B$75,MIN(71,Cartera_Polizas!$B$18+32-49))*(1+(Cartera_Polizas!$P$18-1)*MAX(0,1-32/Supuestos!$C$20))*(1-Supuestos!$C$18)^32)) -> 1.1265115e-07 | AJ16: =AI16*(1-MIN(1,INDEX(Tabla_Mortalidad!$B$5:$B$75,MIN(71,Cartera_Polizas!$B$18+33-49))*(1+(Cartera_Polizas!$P$18-1)*MAX(0,1-33/Supuestos!$C$20))*(1-Supuestos!$C$18)^33)) -> 2.6145272e-08 | AK16: =AJ16*(1-MIN(1,INDEX(Tabla_Mortalidad!$B$5:$B$75,MIN(71,Cartera_Polizas!$B$18+34-49))*(1+(Cartera_Polizas!$P$18-1)*MAX(0,1-34/Supuestos!$C$20))*(1-Supuestos!$C$18)^34)) -> 5.6704051e-09 | AL16: =AK16*(1-MIN(1,INDEX(Tabla_Mortalidad!$B$5:$B$75,MIN(71,Cartera_Polizas!$B$18+35-49))*(1+(Cartera_Polizas!$P$18-1)*MAX(0,1-35/Supuestos!$C$20))*(1-Supuestos!$C$18)^35)) -> 1.1622453e-09 | AM16: =AL16*(1-MIN(1,INDEX(Tabla_Mortalidad!$B$5:$B$75,MIN(71,Cartera_Polizas!$B$18+36-49))*(1+(Cartera_Polizas!$P$18-1)*MAX(0,1-36/Supuestos!$C$20))*(1-Supuestos!$C$18)^36)) -> 1.9189465e-10 | AN16: =AM16*(1-MIN(1,INDEX(Tabla_Mortalidad!$B$5:$B$75,MIN(71,Cartera_Polizas!$B$18+37-49))*(1+(Cartera_Polizas!$P$18-1)*MAX(0,1-37/Supuestos!$C$20))*(1-Supuestos!$C$18)^37)) -> 3.2484175e-11 | AO16: =AN16*(1-MIN(1,INDEX(Tabla_Mortalidad!$B$5:$B$75,MIN(71,Cartera_Polizas!$B$18+38-49))*(1+(Cartera_Polizas!$P$18-1)*MAX(0,1-38/Supuestos!$C$20))*(1-Supuestos!$C$18)^38)) -> 5.6338894e-12 | AP16: =AO16*(1-MIN(1,INDEX(Tabla_Mortalidad!$B$5:$B$75,MIN(71,Cartera_Polizas!$B$18+39-49))*(1+(Cartera_Polizas!$P$18-1)*MAX(0,1-39/Supuestos!$C$20))*(1-Supuestos!$C$18)^39)) -> 1.0003969e-12 | AQ16: =AP16*(1-MIN(1,INDEX(Tabla_Mortalidad!$B$5:$B$75,MIN(71,Cartera_Polizas!$B$18+40-49))*(1+(Cartera_Polizas!$P$18-1)*MAX(0,1-40/Supuestos!$C$20))*(1-Supuestos!$C$18)^40)) -> 1.8175198e-13 | AR16: =AQ16*(1-MIN(1,INDEX(Tabla_Mortalidad!$B$5:$B$75,MIN(71,Cartera_Polizas!$B$18+41-49))*(1+(Cartera_Polizas!$P$18-1)*MAX(0,1-41/Supuestos!$C$20))*(1-Supuestos!$C$18)^41)) -> 3.3764335e-14 | AS16: =AR16*(1-MIN(1,INDEX(Tabla_Mortalidad!$B$5:$B$75,MIN(71,Cartera_Polizas!$B$18+42-49))*(1+(Cartera_Polizas!$P$18-1)*MAX(0,1-42/Supuestos!$C$20))*(1-Supuestos!$C$18)^42)) -> 6.4099099e-15 | AT16: =AS16*(1-MIN(1,INDEX(Tabla_Mortalidad!$B$5:$B$75,MIN(71,Cartera_Polizas!$B$18+43-49))*(1+(Cartera_Polizas!$P$18-1)*MAX(0,1-43/Supuestos!$C$20))*(1-Supuestos!$C$18)^43)) -> 1.2428393e-15 | AU16: =AT16*(1-MIN(1,INDEX(Tabla_Mortalidad!$B$5:$B$75,MIN(71,Cartera_Polizas!$B$18+44-49))*(1+(Cartera_Polizas!$P$18-1)*MAX(0,1-44/Supuestos!$C$20))*(1-Supuestos!$C$18)^44)) -> 2.4598765e-16
A17: =Cartera_Polizas!A19 -> 14 | B17: =SUM(C17:AU17)+0.5 -> 10.281028 | C17: =1-MIN(1,INDEX(Tabla_Mortalidad!$B$5:$B$75,MIN(71,Cartera_Polizas!$B$19+0-49))*(1+(Cartera_Polizas!$P$19-1)*MAX(0,1-0/Supuestos!$C$20))*(1-Supuestos!$C$18)^0) -> 0.95001086 | D17: =C17*(1-MIN(1,INDEX(Tabla_Mortalidad!$B$5:$B$75,MIN(71,Cartera_Polizas!$B$19+1-49))*(1+(Cartera_Polizas!$P$19-1)*MAX(0,1-1/Supuestos!$C$20))*(1-Supuestos!$C$18)^1)) -> 0.89863249 | E17: =D17*(1-MIN(1,INDEX(Tabla_Mortalidad!$B$5:$B$75,MIN(71,Cartera_Polizas!$B$19+2-49))*(1+(Cartera_Polizas!$P$19-1)*MAX(0,1-2/Supuestos!$C$20))*(1-Supuestos!$C$18)^2)) -> 0.84609778 | F17: =E17*(1-MIN(1,INDEX(Tabla_Mortalidad!$B$5:$B$75,MIN(71,Cartera_Polizas!$B$19+3-49))*(1+(Cartera_Polizas!$P$19-1)*MAX(0,1-3/Supuestos!$C$20))*(1-Supuestos!$C$18)^3)) -> 0.79267756 | G17: =F17*(1-MIN(1,INDEX(Tabla_Mortalidad!$B$5:$B$75,MIN(71,Cartera_Polizas!$B$19+4-49))*(1+(Cartera_Polizas!$P$19-1)*MAX(0,1-4/Supuestos!$C$20))*(1-Supuestos!$C$18)^4)) -> 0.73867692 | H17: =G17*(1-MIN(1,INDEX(Tabla_Mortalidad!$B$5:$B$75,MIN(71,Cartera_Polizas!$B$19+5-49))*(1+(Cartera_Polizas!$P$19-1)*MAX(0,1-5/Supuestos!$C$20))*(1-Supuestos!$C$18)^5)) -> 0.68443444 | I17: =H17*(1-MIN(1,INDEX(Tabla_Mortalidad!$B$5:$B$75,MIN(71,Cartera_Polizas!$B$19+6-49))*(1+(Cartera_Polizas!$P$19-1)*MAX(0,1-6/Supuestos!$C$20))*(1-Supuestos!$C$18)^6)) -> 0.63031924 | J17: =I17*(1-MIN(1,INDEX(Tabla_Mortalidad!$B$5:$B$75,MIN(71,Cartera_Polizas!$B$19+7-49))*(1+(Cartera_Polizas!$P$19-1)*MAX(0,1-7/Supuestos!$C$20))*(1-Supuestos!$C$18)^7)) -> 0.57672222 | K17: =J17*(1-MIN(1,INDEX(Tabla_Mortalidad!$B$5:$B$75,MIN(71,Cartera_Polizas!$B$19+8-49))*(1+(Cartera_Polizas!$P$19-1)*MAX(0,1-8/Supuestos!$C$20))*(1-Supuestos!$C$18)^8)) -> 0.52404773 | L17: =K17*(1-MIN(1,INDEX(Tabla_Mortalidad!$B$5:$B$75,MIN(71,Cartera_Polizas!$B$19+9-49))*(1+(Cartera_Polizas!$P$19-1)*MAX(0,1-9/Supuestos!$C$20))*(1-Supuestos!$C$18)^9)) -> 0.47270719 | M17: =L17*(1-MIN(1,INDEX(Tabla_Mortalidad!$B$5:$B$75,MIN(71,Cartera_Polizas!$B$19+10-49))*(1+(Cartera_Polizas!$P$19-1)*MAX(0,1-10/Supuestos!$C$20))*(1-Supuestos!$C$18)^10)) -> 0.42310387 | N17: =M17*(1-MIN(1,INDEX(Tabla_Mortalidad!$B$5:$B$75,MIN(71,Cartera_Polizas!$B$19+11-49))*(1+(Cartera_Polizas!$P$19-1)*MAX(0,1-11/Supuestos!$C$20))*(1-Supuestos!$C$18)^11)) -> 0.37562491 | O17: =N17*(1-MIN(1,INDEX(Tabla_Mortalidad!$B$5:$B$75,MIN(71,Cartera_Polizas!$B$19+12-49))*(1+(Cartera_Polizas!$P$19-1)*MAX(0,1-12/Supuestos!$C$20))*(1-Supuestos!$C$18)^12)) -> 0.33062614 | P17: =O17*(1-MIN(1,INDEX(Tabla_Mortalidad!$B$5:$B$75,MIN(71,Cartera_Polizas!$B$19+13-49))*(1+(Cartera_Polizas!$P$19-1)*MAX(0,1-13/Supuestos!$C$20))*(1-Supuestos!$C$18)^13)) -> 0.28842073 | Q17: =P17*(1-MIN(1,INDEX(Tabla_Mortalidad!$B$5:$B$75,MIN(71,Cartera_Polizas!$B$19+14-49))*(1+(Cartera_Polizas!$P$19-1)*MAX(0,1-14/Supuestos!$C$20))*(1-Supuestos!$C$18)^14)) -> 0.24926766 | R17: =Q17*(1-MIN(1,INDEX(Tabla_Mortalidad!$B$5:$B$75,MIN(71,Cartera_Polizas!$B$19+15-49))*(1+(Cartera_Polizas!$P$19-1)*MAX(0,1-15/Supuestos!$C$20))*(1-Supuestos!$C$18)^15)) -> 0.21336237 | S17: =R17*(1-MIN(1,INDEX(Tabla_Mortalidad!$B$5:$B$75,MIN(71,Cartera_Polizas!$B$19+16-49))*(1+(Cartera_Polizas!$P$19-1)*MAX(0,1-16/Supuestos!$C$20))*(1-Supuestos!$C$18)^16)) -> 0.17955043 | T17: =S17*(1-MIN(1,INDEX(Tabla_Mortalidad!$B$5:$B$75,MIN(71,Cartera_Polizas!$B$19+17-49))*(1+(Cartera_Polizas!$P$19-1)*MAX(0,1-17/Supuestos!$C$20))*(1-Supuestos!$C$18)^17)) -> 0.14827983 | U17: =T17*(1-MIN(1,INDEX(Tabla_Mortalidad!$B$5:$B$75,MIN(71,Cartera_Polizas!$B$19+18-49))*(1+(Cartera_Polizas!$P$19-1)*MAX(0,1-18/Supuestos!$C$20))*(1-Supuestos!$C$18)^18)) -> 0.1199323 | V17: =U17*(1-MIN(1,INDEX(Tabla_Mortalidad!$B$5:$B$75,MIN(71,Cartera_Polizas!$B$19+19-49))*(1+(Cartera_Polizas!$P$19-1)*MAX(0,1-19/Supuestos!$C$20))*(1-Supuestos!$C$18)^19)) -> 0.094797151 | W17: =V17*(1-MIN(1,INDEX(Tabla_Mortalidad!$B$5:$B$75,MIN(71,Cartera_Polizas!$B$19+20-49))*(1+(Cartera_Polizas!$P$19-1)*MAX(0,1-20/Supuestos!$C$20))*(1-Supuestos!$C$18)^20)) -> 0.073048867 | X17: =W17*(1-MIN(1,INDEX(Tabla_Mortalidad!$B$5:$B$75,MIN(71,Cartera_Polizas!$B$19+21-49))*(1+(Cartera_Polizas!$P$19-1)*MAX(0,1-21/Supuestos!$C$20))*(1-Supuestos!$C$18)^21)) -> 0.054732722 | Y17: =X17*(1-MIN(1,INDEX(Tabla_Mortalidad!$B$5:$B$75,MIN(71,Cartera_Polizas!$B$19+22-49))*(1+(Cartera_Polizas!$P$19-1)*MAX(0,1-22/Supuestos!$C$20))*(1-Supuestos!$C$18)^22)) -> 0.039760298 | Z17: =Y17*(1-MIN(1,INDEX(Tabla_Mortalidad!$B$5:$B$75,MIN(71,Cartera_Polizas!$B$19+23-49))*(1+(Cartera_Polizas!$P$19-1)*MAX(0,1-23/Supuestos!$C$20))*(1-Supuestos!$C$18)^23)) -> 0.027916857 | AA17: =Z17*(1-MIN(1,INDEX(Tabla_Mortalidad!$B$5:$B$75,MIN(71,Cartera_Polizas!$B$19+24-49))*(1+(Cartera_Polizas!$P$19-1)*MAX(0,1-24/Supuestos!$C$20))*(1-Supuestos!$C$18)^24)) -> 0.018881374 | AB17: =AA17*(1-MIN(1,INDEX(Tabla_Mortalidad!$B$5:$B$75,MIN(71,Cartera_Polizas!$B$19+25-49))*(1+(Cartera_Polizas!$P$19-1)*MAX(0,1-25/Supuestos!$C$20))*(1-Supuestos!$C$18)^25)) -> 0.012256757 | AC17: =AB17*(1-MIN(1,INDEX(Tabla_Mortalidad!$B$5:$B$75,MIN(71,Cartera_Polizas!$B$19+26-49))*(1+(Cartera_Polizas!$P$19-1)*MAX(0,1-26/Supuestos!$C$20))*(1-Supuestos!$C$18)^26)) -> 0.0076069353 | AD17: =AC17*(1-MIN(1,INDEX(Tabla_Mortalidad!$B$5:$B$75,MIN(71,Cartera_Polizas!$B$19+27-49))*(1+(Cartera_Polizas!$P$19-1)*MAX(0,1-27/Supuestos!$C$20))*(1-Supuestos!$C$18)^27)) -> 0.0044952608 | AE17: =AD17*(1-MIN(1,INDEX(Tabla_Mortalidad!$B$5:$B$75,MIN(71,Cartera_Polizas!$B$19+28-49))*(1+(Cartera_Polizas!$P$19-1)*MAX(0,1-28/Supuestos!$C$20))*(1-Supuestos!$C$18)^28)) -> 0.0025185307 | AF17: =AE17*(1-MIN(1,INDEX(Tabla_Mortalidad!$B$5:$B$75,MIN(71,Cartera_Polizas!$B$19+29-49))*(1+(Cartera_Polizas!$P$19-1)*MAX(0,1-29/Supuestos!$C$20))*(1-Supuestos!$C$18)^29)) -> 0.0013318796 | AG17: =AF17*(1-MIN(1,INDEX(Tabla_Mortalidad!$B$5:$B$75,MIN(71,Cartera_Polizas!$B$19+30-49))*(1+(Cartera_Polizas!$P$19-1)*MAX(0,1-30/Supuestos!$C$20))*(1-Supuestos!$C$18)^30)) -> 0.00066186 | AH17: =AG17*(1-MIN(1,INDEX(Tabla_Mortalidad!$B$5:$B$75,MIN(71,Cartera_Polizas!$B$19+31-49))*(1+(Cartera_Polizas!$P$19-1)*MAX(0,1-31/Supuestos!$C$20))*(1-Supuestos!$C$18)^31)) -> 0.00030771047 | AI17: =AH17*(1-MIN(1,INDEX(Tabla_Mortalidad!$B$5:$B$75,MIN(71,Cartera_Polizas!$B$19+32-49))*(1+(Cartera_Polizas!$P$19-1)*MAX(0,1-32/Supuestos!$C$20))*(1-Supuestos!$C$18)^32)) -> 0.00013328916 | AJ17: =AI17*(1-MIN(1,INDEX(Tabla_Mortalidad!$B$5:$B$75,MIN(71,Cartera_Polizas!$B$19+33-49))*(1+(Cartera_Polizas!$P$19-1)*MAX(0,1-33/Supuestos!$C$20))*(1-Supuestos!$C$18)^33)) -> 5.359569e-05 | AK17: =AJ17*(1-MIN(1,INDEX(Tabla_Mortalidad!$B$5:$B$75,MIN(71,Cartera_Polizas!$B$19+34-49))*(1+(Cartera_Polizas!$P$19-1)*MAX(0,1-34/Supuestos!$C$20))*(1-Supuestos!$C$18)^34)) -> 1.9947266e-05 | AL17: =AK17*(1-MIN(1,INDEX(Tabla_Mortalidad!$B$5:$B$75,MIN(71,Cartera_Polizas!$B$19+35-49))*(1+(Cartera_Polizas!$P$19-1)*MAX(0,1-35/Supuestos!$C$20))*(1-Supuestos!$C$18)^35)) -> 6.8591584e-06 | AM17: =AL17*(1-MIN(1,INDEX(Tabla_Mortalidad!$B$5:$B$75,MIN(71,Cartera_Polizas!$B$19+36-49))*(1+(Cartera_Polizas!$P$19-1)*MAX(0,1-36/Supuestos!$C$20))*(1-Supuestos!$C$18)^36)) -> 2.1784635e-06 | AN17: =AM17*(1-MIN(1,INDEX(Tabla_Mortalidad!$B$5:$B$75,MIN(71,Cartera_Polizas!$B$19+37-49))*(1+(Cartera_Polizas!$P$19-1)*MAX(0,1-37/Supuestos!$C$20))*(1-Supuestos!$C$18)^37)) -> 6.4001856e-07 | AO17: =AN17*(1-MIN(1,INDEX(Tabla_Mortalidad!$B$5:$B$75,MIN(71,Cartera_Polizas!$B$19+38-49))*(1+(Cartera_Polizas!$P$19-1)*MAX(0,1-38/Supuestos!$C$20))*(1-Supuestos!$C$18)^38)) -> 1.7459151e-07 | AP17: =AO17*(1-MIN(1,INDEX(Tabla_Mortalidad!$B$5:$B$75,MIN(71,Cartera_Polizas!$B$19+39-49))*(1+(Cartera_Polizas!$P$19-1)*MAX(0,1-39/Supuestos!$C$20))*(1-Supuestos!$C$18)^39)) -> 4.4493217e-08 | AQ17: =AP17*(1-MIN(1,INDEX(Tabla_Mortalidad!$B$5:$B$75,MIN(71,Cartera_Polizas!$B$19+40-49))*(1+(Cartera_Polizas!$P$19-1)*MAX(0,1-40/Supuestos!$C$20))*(1-Supuestos!$C$18)^40)) -> 1.0682046e-08 | AR17: =AQ17*(1-MIN(1,INDEX(Tabla_Mortalidad!$B$5:$B$75,MIN(71,Cartera_Polizas!$B$19+41-49))*(1+(Cartera_Polizas!$P$19-1)*MAX(0,1-41/Supuestos!$C$20))*(1-Supuestos!$C$18)^41)) -> 2.4410796e-09 | AS17: =AR17*(1-MIN(1,INDEX(Tabla_Mortalidad!$B$5:$B$75,MIN(71,Cartera_Polizas!$B$19+42-49))*(1+(Cartera_Polizas!$P$19-1)*MAX(0,1-42/Supuestos!$C$20))*(1-Supuestos!$C$18)^42)) -> 4.6342095e-10 | AT17: =AS17*(1-MIN(1,INDEX(Tabla_Mortalidad!$B$5:$B$75,MIN(71,Cartera_Polizas!$B$19+43-49))*(1+(Cartera_Polizas!$P$19-1)*MAX(0,1-43/Supuestos!$C$20))*(1-Supuestos!$C$18)^43)) -> 8.9854268e-11 | AU17: =AT17*(1-MIN(1,INDEX(Tabla_Mortalidad!$B$5:$B$75,MIN(71,Cartera_Polizas!$B$19+44-49))*(1+(Cartera_Polizas!$P$19-1)*MAX(0,1-44/Supuestos!$C$20))*(1-Supuestos!$C$18)^44)) -> 1.7784311e-11
A18: =Cartera_Polizas!A20 -> 15 | B18: =SUM(C18:AU18)+0.5 -> 5.4852667 | C18: =1-MIN(1,INDEX(Tabla_Mortalidad!$B$5:$B$75,MIN(71,Cartera_Polizas!$B$20+0-49))*(1+(Cartera_Polizas!$P$20-1)*MAX(0,1-0/Supuestos!$C$20))*(1-Supuestos!$C$18)^0) -> 0.8687016 | D18: =C18*(1-MIN(1,INDEX(Tabla_Mortalidad!$B$5:$B$75,MIN(71,Cartera_Polizas!$B$20+1-49))*(1+(Cartera_Polizas!$P$20-1)*MAX(0,1-1/Supuestos!$C$20))*(1-Supuestos!$C$18)^1)) -> 0.74734168 | E18: =D18*(1-MIN(1,INDEX(Tabla_Mortalidad!$B$5:$B$75,MIN(71,Cartera_Polizas!$B$20+2-49))*(1+(Cartera_Polizas!$P$20-1)*MAX(0,1-2/Supuestos!$C$20))*(1-Supuestos!$C$18)^2)) -> 0.63647726 | F18: =E18*(1-MIN(1,INDEX(Tabla_Mortalidad!$B$5:$B$75,MIN(71,Cartera_Polizas!$B$20+3-49))*(1+(Cartera_Polizas!$P$20-1)*MAX(0,1-3/Supuestos!$C$20))*(1-Supuestos!$C$18)^3)) -> 0.53643652 | G18: =F18*(1-MIN(1,INDEX(Tabla_Mortalidad!$B$5:$B$75,MIN(71,Cartera_Polizas!$B$20+4-49))*(1+(Cartera_Polizas!$P$20-1)*MAX(0,1-4/Supuestos!$C$20))*(1-Supuestos!$C$18)^4)) -> 0.44731555 | H18: =G18*(1-MIN(1,INDEX(Tabla_Mortalidad!$B$5:$B$75,MIN(71,Cartera_Polizas!$B$20+5-49))*(1+(Cartera_Polizas!$P$20-1)*MAX(0,1-5/Supuestos!$C$20))*(1-Supuestos!$C$18)^5)) -> 0.36897168 | I18: =H18*(1-MIN(1,INDEX(Tabla_Mortalidad!$B$5:$B$75,MIN(71,Cartera_Polizas!$B$20+6-49))*(1+(Cartera_Polizas!$P$20-1)*MAX(0,1-6/Supuestos!$C$20))*(1-Supuestos!$C$18)^6)) -> 0.30104444 | J18: =I18*(1-MIN(1,INDEX(Tabla_Mortalidad!$B$5:$B$75,MIN(71,Cartera_Polizas!$B$20+7-49))*(1+(Cartera_Polizas!$P$20-1)*MAX(0,1-7/Supuestos!$C$20))*(1-Supuestos!$C$18)^7)) -> 0.24297534 | K18: =J18*(1-MIN(1,INDEX(Tabla_Mortalidad!$B$5:$B$75,MIN(71,Cartera_Polizas!$B$20+8-49))*(1+(Cartera_Polizas!$P$20-1)*MAX(0,1-8/Supuestos!$C$20))*(1-Supuestos!$C$18)^8)) -> 0.19404375 | L18: =K18*(1-MIN(1,INDEX(Tabla_Mortalidad!$B$5:$B$75,MIN(71,Cartera_Polizas!$B$20+9-49))*(1+(Cartera_Polizas!$P$20-1)*MAX(0,1-9/Supuestos!$C$20))*(1-Supuestos!$C$18)^9)) -> 0.15340782 | M18: =L18*(1-MIN(1,INDEX(Tabla_Mortalidad!$B$5:$B$75,MIN(71,Cartera_Polizas!$B$20+10-49))*(1+(Cartera_Polizas!$P$20-1)*MAX(0,1-10/Supuestos!$C$20))*(1-Supuestos!$C$18)^10)) -> 0.12014942 | N18: =M18*(1-MIN(1,INDEX(Tabla_Mortalidad!$B$5:$B$75,MIN(71,Cartera_Polizas!$B$20+11-49))*(1+(Cartera_Polizas!$P$20-1)*MAX(0,1-11/Supuestos!$C$20))*(1-Supuestos!$C$18)^11)) -> 0.093318876 | O18: =N18*(1-MIN(1,INDEX(Tabla_Mortalidad!$B$5:$B$75,MIN(71,Cartera_Polizas!$B$20+12-49))*(1+(Cartera_Polizas!$P$20-1)*MAX(0,1-12/Supuestos!$C$20))*(1-Supuestos!$C$18)^12)) -> 0.071976081 | P18: =O18*(1-MIN(1,INDEX(Tabla_Mortalidad!$B$5:$B$75,MIN(71,Cartera_Polizas!$B$20+13-49))*(1+(Cartera_Polizas!$P$20-1)*MAX(0,1-13/Supuestos!$C$20))*(1-Supuestos!$C$18)^13)) -> 0.055226441 | Q18: =P18*(1-MIN(1,INDEX(Tabla_Mortalidad!$B$5:$B$75,MIN(71,Cartera_Polizas!$B$20+14-49))*(1+(Cartera_Polizas!$P$20-1)*MAX(0,1-14/Supuestos!$C$20))*(1-Supuestos!$C$18)^14)) -> 0.04224801 | R18: =Q18*(1-MIN(1,INDEX(Tabla_Mortalidad!$B$5:$B$75,MIN(71,Cartera_Polizas!$B$20+15-49))*(1+(Cartera_Polizas!$P$20-1)*MAX(0,1-15/Supuestos!$C$20))*(1-Supuestos!$C$18)^15)) -> 0.032309517 | S18: =R18*(1-MIN(1,INDEX(Tabla_Mortalidad!$B$5:$B$75,MIN(71,Cartera_Polizas!$B$20+16-49))*(1+(Cartera_Polizas!$P$20-1)*MAX(0,1-16/Supuestos!$C$20))*(1-Supuestos!$C$18)^16)) -> 0.02400268 | T18: =S18*(1-MIN(1,INDEX(Tabla_Mortalidad!$B$5:$B$75,MIN(71,Cartera_Polizas!$B$20+17-49))*(1+(Cartera_Polizas!$P$20-1)*MAX(0,1-17/Supuestos!$C$20))*(1-Supuestos!$C$18)^17)) -> 0.017269978 | U18: =T18*(1-MIN(1,INDEX(Tabla_Mortalidad!$B$5:$B$75,MIN(71,Cartera_Polizas!$B$20+18-49))*(1+(Cartera_Polizas!$P$20-1)*MAX(0,1-18/Supuestos!$C$20))*(1-Supuestos!$C$18)^18)) -> 0.011995195 | V18: =U18*(1-MIN(1,INDEX(Tabla_Mortalidad!$B$5:$B$75,MIN(71,Cartera_Polizas!$B$20+19-49))*(1+(Cartera_Polizas!$P$20-1)*MAX(0,1-19/Supuestos!$C$20))*(1-Supuestos!$C$18)^19)) -> 0.0080143359 | W18: =V18*(1-MIN(1,INDEX(Tabla_Mortalidad!$B$5:$B$75,MIN(71,Cartera_Polizas!$B$20+20-49))*(1+(Cartera_Polizas!$P$20-1)*MAX(0,1-20/Supuestos!$C$20))*(1-Supuestos!$C$18)^20)) -> 0.0051311059 | X18: =W18*(1-MIN(1,INDEX(Tabla_Mortalidad!$B$5:$B$75,MIN(71,Cartera_Polizas!$B$20+21-49))*(1+(Cartera_Polizas!$P$20-1)*MAX(0,1-21/Supuestos!$C$20))*(1-Supuestos!$C$18)^21)) -> 0.0031351253 | Y18: =X18*(1-MIN(1,INDEX(Tabla_Mortalidad!$B$5:$B$75,MIN(71,Cartera_Polizas!$B$20+22-49))*(1+(Cartera_Polizas!$P$20-1)*MAX(0,1-22/Supuestos!$C$20))*(1-Supuestos!$C$18)^22)) -> 0.0018201308 | Z18: =Y18*(1-MIN(1,INDEX(Tabla_Mortalidad!$B$5:$B$75,MIN(71,Cartera_Polizas!$B$20+23-49))*(1+(Cartera_Polizas!$P$20-1)*MAX(0,1-23/Supuestos!$C$20))*(1-Supuestos!$C$18)^23)) -> 0.00099943978 | AA18: =Z18*(1-MIN(1,INDEX(Tabla_Mortalidad!$B$5:$B$75,MIN(71,Cartera_Polizas!$B$20+24-49))*(1+(Cartera_Polizas!$P$20-1)*MAX(0,1-24/Supuestos!$C$20))*(1-Supuestos!$C$18)^24)) -> 0.00051658447 | AB18: =AA18*(1-MIN(1,INDEX(Tabla_Mortalidad!$B$5:$B$75,MIN(71,Cartera_Polizas!$B$20+25-49))*(1+(Cartera_Polizas!$P$20-1)*MAX(0,1-25/Supuestos!$C$20))*(1-Supuestos!$C$18)^25)) -> 0.00025011437 | AC18: =AB18*(1-MIN(1,INDEX(Tabla_Mortalidad!$B$5:$B$75,MIN(71,Cartera_Polizas!$B$20+26-49))*(1+(Cartera_Polizas!$P$20-1)*MAX(0,1-26/Supuestos!$C$20))*(1-Supuestos!$C$18)^26)) -> 0.00011288604 | AD18: =AC18*(1-MIN(1,INDEX(Tabla_Mortalidad!$B$5:$B$75,MIN(71,Cartera_Polizas!$B$20+27-49))*(1+(Cartera_Polizas!$P$20-1)*MAX(0,1-27/Supuestos!$C$20))*(1-Supuestos!$C$18)^27)) -> 4.7274216e-05 | AE18: =AD18*(1-MIN(1,INDEX(Tabla_Mortalidad!$B$5:$B$75,MIN(71,Cartera_Polizas!$B$20+28-49))*(1+(Cartera_Polizas!$P$20-1)*MAX(0,1-28/Supuestos!$C$20))*(1-Supuestos!$C$18)^28)) -> 1.829165e-05 | AF18: =AE18*(1-MIN(1,INDEX(Tabla_Mortalidad!$B$5:$B$75,MIN(71,Cartera_Polizas!$B$20+29-49))*(1+(Cartera_Polizas!$P$20-1)*MAX(0,1-29/Supuestos!$C$20))*(1-Supuestos!$C$18)^29)) -> 6.5163401e-06 | AG18: =AF18*(1-MIN(1,INDEX(Tabla_Mortalidad!$B$5:$B$75,MIN(71,Cartera_Polizas!$B$20+30-49))*(1+(Cartera_Polizas!$P$20-1)*MAX(0,1-30/Supuestos!$C$20))*(1-Supuestos!$C$18)^30)) -> 2.1322264e-06 | AH18: =AG18*(1-MIN(1,INDEX(Tabla_Mortalidad!$B$5:$B$75,MIN(71,Cartera_Polizas!$B$20+31-49))*(1+(Cartera_Polizas!$P$20-1)*MAX(0,1-31/Supuestos!$C$20))*(1-Supuestos!$C$18)^31)) -> 6.4026557e-07 | AI18: =AH18*(1-MIN(1,INDEX(Tabla_Mortalidad!$B$5:$B$75,MIN(71,Cartera_Polizas!$B$20+32-49))*(1+(Cartera_Polizas!$P$20-1)*MAX(0,1-32/Supuestos!$C$20))*(1-Supuestos!$C$18)^32)) -> 1.7663036e-07 | AJ18: =AI18*(1-MIN(1,INDEX(Tabla_Mortalidad!$B$5:$B$75,MIN(71,Cartera_Polizas!$B$20+33-49))*(1+(Cartera_Polizas!$P$20-1)*MAX(0,1-33/Supuestos!$C$20))*(1-Supuestos!$C$18)^33)) -> 4.4923316e-08 | AK18: =AJ18*(1-MIN(1,INDEX(Tabla_Mortalidad!$B$5:$B$75,MIN(71,Cartera_Polizas!$B$20+34-49))*(1+(Cartera_Polizas!$P$20-1)*MAX(0,1-34/Supuestos!$C$20))*(1-Supuestos!$C$18)^34)) -> 1.0598764e-08 | AL18: =AK18*(1-MIN(1,INDEX(Tabla_Mortalidad!$B$5:$B$75,MIN(71,Cartera_Polizas!$B$20+35-49))*(1+(Cartera_Polizas!$P$20-1)*MAX(0,1-35/Supuestos!$C$20))*(1-Supuestos!$C$18)^35)) -> 2.3401679e-09 | AM18: =AL18*(1-MIN(1,INDEX(Tabla_Mortalidad!$B$5:$B$75,MIN(71,Cartera_Polizas!$B$20+36-49))*(1+(Cartera_Polizas!$P$20-1)*MAX(0,1-36/Supuestos!$C$20))*(1-Supuestos!$C$18)^36)) -> 4.889595e-10 | AN18: =AM18*(1-MIN(1,INDEX(Tabla_Mortalidad!$B$5:$B$75,MIN(71,Cartera_Polizas!$B$20+37-49))*(1+(Cartera_Polizas!$P$20-1)*MAX(0,1-37/Supuestos!$C$20))*(1-Supuestos!$C$18)^37)) -> 8.2771699e-11 | AO18: =AN18*(1-MIN(1,INDEX(Tabla_Mortalidad!$B$5:$B$75,MIN(71,Cartera_Polizas!$B$20+38-49))*(1+(Cartera_Polizas!$P$20-1)*MAX(0,1-38/Supuestos!$C$20))*(1-Supuestos!$C$18)^38)) -> 1.4355501e-11 | AP18: =AO18*(1-MIN(1,INDEX(Tabla_Mortalidad!$B$5:$B$75,MIN(71,Cartera_Polizas!$B$20+39-49))*(1+(Cartera_Polizas!$P$20-1)*MAX(0,1-39/Supuestos!$C$20))*(1-Supuestos!$C$18)^39)) -> 2.5490735e-12 | AQ18: =AP18*(1-MIN(1,INDEX(Tabla_Mortalidad!$B$5:$B$75,MIN(71,Cartera_Polizas!$B$20+40-49))*(1+(Cartera_Polizas!$P$20-1)*MAX(0,1-40/Supuestos!$C$20))*(1-Supuestos!$C$18)^40)) -> 4.6311536e-13 | AR18: =AQ18*(1-MIN(1,INDEX(Tabla_Mortalidad!$B$5:$B$75,MIN(71,Cartera_Polizas!$B$20+41-49))*(1+(Cartera_Polizas!$P$20-1)*MAX(0,1-41/Supuestos!$C$20))*(1-Supuestos!$C$18)^41)) -> 8.6033627e-14 | AS18: =AR18*(1-MIN(1,INDEX(Tabla_Mortalidad!$B$5:$B$75,MIN(71,Cartera_Polizas!$B$20+42-49))*(1+(Cartera_Polizas!$P$20-1)*MAX(0,1-42/Supuestos!$C$20))*(1-Supuestos!$C$18)^42)) -> 1.6332849e-14 | AT18: =AS18*(1-MIN(1,INDEX(Tabla_Mortalidad!$B$5:$B$75,MIN(71,Cartera_Polizas!$B$20+43-49))*(1+(Cartera_Polizas!$P$20-1)*MAX(0,1-43/Supuestos!$C$20))*(1-Supuestos!$C$18)^43)) -> 3.1668318e-15 | AU18: =AT18*(1-MIN(1,INDEX(Tabla_Mortalidad!$B$5:$B$75,MIN(71,Cartera_Polizas!$B$20+44-49))*(1+(Cartera_Polizas!$P$20-1)*MAX(0,1-44/Supuestos!$C$20))*(1-Supuestos!$C$18)^44)) -> 6.2679184e-16
A19: =Cartera_Polizas!A21 -> 16 | B19: =SUM(C19:AU19)+0.5 -> 6.9382365 | C19: =1-MIN(1,INDEX(Tabla_Mortalidad!$B$5:$B$75,MIN(71,Cartera_Polizas!$B$21+0-49))*(1+(Cartera_Polizas!$P$21-1)*MAX(0,1-0/Supuestos!$C$20))*(1-Supuestos!$C$18)^0) -> 0.91966741 | D19: =C19*(1-MIN(1,INDEX(Tabla_Mortalidad!$B$5:$B$75,MIN(71,Cartera_Polizas!$B$21+1-49))*(1+(Cartera_Polizas!$P$21-1)*MAX(0,1-1/Supuestos!$C$20))*(1-Supuestos!$C$18)^1)) -> 0.83832804 | E19: =D19*(1-MIN(1,INDEX(Tabla_Mortalidad!$B$5:$B$75,MIN(71,Cartera_Polizas!$B$21+2-49))*(1+(Cartera_Polizas!$P$21-1)*MAX(0,1-2/Supuestos!$C$20))*(1-Supuestos!$C$18)^2)) -> 0.75673741 | F19: =E19*(1-MIN(1,INDEX(Tabla_Mortalidad!$B$5:$B$75,MIN(71,Cartera_Polizas!$B$21+3-49))*(1+(Cartera_Polizas!$P$21-1)*MAX(0,1-3/Supuestos!$C$20))*(1-Supuestos!$C$18)^3)) -> 0.67574092 | G19: =F19*(1-MIN(1,INDEX(Tabla_Mortalidad!$B$5:$B$75,MIN(71,Cartera_Polizas!$B$21+4-49))*(1+(Cartera_Polizas!$P$21-1)*MAX(0,1-4/Supuestos!$C$20))*(1-Supuestos!$C$18)^4)) -> 0.5962508 | H19: =G19*(1-MIN(1,INDEX(Tabla_Mortalidad!$B$5:$B$75,MIN(71,Cartera_Polizas!$B$21+5-49))*(1+(Cartera_Polizas!$P$21-1)*MAX(0,1-5/Supuestos!$C$20))*(1-Supuestos!$C$18)^5)) -> 0.51922077 | I19: =H19*(1-MIN(1,INDEX(Tabla_Mortalidad!$B$5:$B$75,MIN(71,Cartera_Polizas!$B$21+6-49))*(1+(Cartera_Polizas!$P$21-1)*MAX(0,1-6/Supuestos!$C$20))*(1-Supuestos!$C$18)^6)) -> 0.44561122 | J19: =I19*(1-MIN(1,INDEX(Tabla_Mortalidad!$B$5:$B$75,MIN(71,Cartera_Polizas!$B$21+7-49))*(1+(Cartera_Polizas!$P$21-1)*MAX(0,1-7/Supuestos!$C$20))*(1-Supuestos!$C$18)^7)) -> 0.37634793 | K19: =J19*(1-MIN(1,INDEX(Tabla_Mortalidad!$B$5:$B$75,MIN(71,Cartera_Polizas!$B$21+8-49))*(1+(Cartera_Polizas!$P$21-1)*MAX(0,1-8/Supuestos!$C$20))*(1-Supuestos!$C$18)^8)) -> 0.3122754 | L19: =K19*(1-MIN(1,INDEX(Tabla_Mortalidad!$B$5:$B$75,MIN(71,Cartera_Polizas!$B$21+9-49))*(1+(Cartera_Polizas!$P$21-1)*MAX(0,1-9/Supuestos!$C$20))*(1-Supuestos!$C$18)^9)) -> 0.25410732 | M19: =L19*(1-MIN(1,INDEX(Tabla_Mortalidad!$B$5:$B$75,MIN(71,Cartera_Polizas!$B$21+10-49))*(1+(Cartera_Polizas!$P$21-1)*MAX(0,1-10/Supuestos!$C$20))*(1-Supuestos!$C$18)^10)) -> 0.20238166 | N19: =M19*(1-MIN(1,INDEX(Tabla_Mortalidad!$B$5:$B$75,MIN(71,Cartera_Polizas!$B$21+11-49))*(1+(Cartera_Polizas!$P$21-1)*MAX(0,1-11/Supuestos!$C$20))*(1-Supuestos!$C$18)^11)) -> 0.15742214 | O19: =N19*(1-MIN(1,INDEX(Tabla_Mortalidad!$B$5:$B$75,MIN(71,Cartera_Polizas!$B$21+12-49))*(1+(Cartera_Polizas!$P$21-1)*MAX(0,1-12/Supuestos!$C$20))*(1-Supuestos!$C$18)^12)) -> 0.11931189 | P19: =O19*(1-MIN(1,INDEX(Tabla_Mortalidad!$B$5:$B$75,MIN(71,Cartera_Polizas!$B$21+13-49))*(1+(Cartera_Polizas!$P$21-1)*MAX(0,1-13/Supuestos!$C$20))*(1-Supuestos!$C$18)^13)) -> 0.087886365 | Q19: =P19*(1-MIN(1,INDEX(Tabla_Mortalidad!$B$5:$B$75,MIN(71,Cartera_Polizas!$B$21+14-49))*(1+(Cartera_Polizas!$P$21-1)*MAX(0,1-14/Supuestos!$C$20))*(1-Supuestos!$C$18)^14)) -> 0.062746214 | R19: =Q19*(1-MIN(1,INDEX(Tabla_Mortalidad!$B$5:$B$75,MIN(71,Cartera_Polizas!$B$21+15-49))*(1+(Cartera_Polizas!$P$21-1)*MAX(0,1-15/Supuestos!$C$20))*(1-Supuestos!$C$18)^15)) -> 0.043291218 | S19: =R19*(1-MIN(1,INDEX(Tabla_Mortalidad!$B$5:$B$75,MIN(71,Cartera_Polizas!$B$21+16-49))*(1+(Cartera_Polizas!$P$21-1)*MAX(0,1-16/Supuestos!$C$20))*(1-Supuestos!$C$18)^16)) -> 0.028706433 | T19: =S19*(1-MIN(1,INDEX(Tabla_Mortalidad!$B$5:$B$75,MIN(71,Cartera_Polizas!$B$21+17-49))*(1+(Cartera_Polizas!$P$21-1)*MAX(0,1-17/Supuestos!$C$20))*(1-Supuestos!$C$18)^17)) -> 0.01822256 | U19: =T19*(1-MIN(1,INDEX(Tabla_Mortalidad!$B$5:$B$75,MIN(71,Cartera_Polizas!$B$21+18-49))*(1+(Cartera_Polizas!$P$21-1)*MAX(0,1-18/Supuestos!$C$20))*(1-Supuestos!$C$18)^18)) -> 0.011026654 | V19: =U19*(1-MIN(1,INDEX(Tabla_Mortalidad!$B$5:$B$75,MIN(71,Cartera_Polizas!$B$21+19-49))*(1+(Cartera_Polizas!$P$21-1)*MAX(0,1-19/Supuestos!$C$20))*(1-Supuestos!$C$18)^19)) -> 0.0063315683 | W19: =V19*(1-MIN(1,INDEX(Tabla_Mortalidad!$B$5:$B$75,MIN(71,Cartera_Polizas!$B$21+20-49))*(1+(Cartera_Polizas!$P$21-1)*MAX(0,1-20/Supuestos!$C$20))*(1-Supuestos!$C$18)^20)) -> 0.0034334298 | X19: =W19*(1-MIN(1,INDEX(Tabla_Mortalidad!$B$5:$B$75,MIN(71,Cartera_Polizas!$B$21+21-49))*(1+(Cartera_Polizas!$P$21-1)*MAX(0,1-21/Supuestos!$C$20))*(1-Supuestos!$C$18)^21)) -> 0.0017495181 | Y19: =X19*(1-MIN(1,INDEX(Tabla_Mortalidad!$B$5:$B$75,MIN(71,Cartera_Polizas!$B$21+22-49))*(1+(Cartera_Polizas!$P$21-1)*MAX(0,1-22/Supuestos!$C$20))*(1-Supuestos!$C$18)^22)) -> 0.00083338971 | Z19: =Y19*(1-MIN(1,INDEX(Tabla_Mortalidad!$B$5:$B$75,MIN(71,Cartera_Polizas!$B$21+23-49))*(1+(Cartera_Polizas!$P$21-1)*MAX(0,1-23/Supuestos!$C$20))*(1-Supuestos!$C$18)^23)) -> 0.00036921228 | AA19: =Z19*(1-MIN(1,INDEX(Tabla_Mortalidad!$B$5:$B$75,MIN(71,Cartera_Polizas!$B$21+24-49))*(1+(Cartera_Polizas!$P$21-1)*MAX(0,1-24/Supuestos!$C$20))*(1-Supuestos!$C$18)^24)) -> 0.00015136669 | AB19: =AA19*(1-MIN(1,INDEX(Tabla_Mortalidad!$B$5:$B$75,MIN(71,Cartera_Polizas!$B$21+25-49))*(1+(Cartera_Polizas!$P$21-1)*MAX(0,1-25/Supuestos!$C$20))*(1-Supuestos!$C$18)^25)) -> 5.7161774e-05 | AC19: =AB19*(1-MIN(1,INDEX(Tabla_Mortalidad!$B$5:$B$75,MIN(71,Cartera_Polizas!$B$21+26-49))*(1+(Cartera_Polizas!$P$21-1)*MAX(0,1-26/Supuestos!$C$20))*(1-Supuestos!$C$18)^26)) -> 1.9806157e-05 | AD19: =AC19*(1-MIN(1,INDEX(Tabla_Mortalidad!$B$5:$B$75,MIN(71,Cartera_Polizas!$B$21+27-49))*(1+(Cartera_Polizas!$P$21-1)*MAX(0,1-27/Supuestos!$C$20))*(1-Supuestos!$C$18)^27)) -> 6.2789216e-06 | AE19: =AD19*(1-MIN(1,INDEX(Tabla_Mortalidad!$B$5:$B$75,MIN(71,Cartera_Polizas!$B$21+28-49))*(1+(Cartera_Polizas!$P$21-1)*MAX(0,1-28/Supuestos!$C$20))*(1-Supuestos!$C$18)^28)) -> 1.8188696e-06 | AF19: =AE19*(1-MIN(1,INDEX(Tabla_Mortalidad!$B$5:$B$75,MIN(71,Cartera_Polizas!$B$21+29-49))*(1+(Cartera_Polizas!$P$21-1)*MAX(0,1-29/Supuestos!$C$20))*(1-Supuestos!$C$18)^29)) -> 4.8181672e-07 | AG19: =AF19*(1-MIN(1,INDEX(Tabla_Mortalidad!$B$5:$B$75,MIN(71,Cartera_Polizas!$B$21+30-49))*(1+(Cartera_Polizas!$P$21-1)*MAX(0,1-30/Supuestos!$C$20))*(1-Supuestos!$C$18)^30)) -> 1.170995e-07 | AH19: =AG19*(1-MIN(1,INDEX(Tabla_Mortalidad!$B$5:$B$75,MIN(71,Cartera_Polizas!$B$21+31-49))*(1+(Cartera_Polizas!$P$21-1)*MAX(0,1-31/Supuestos!$C$20))*(1-Supuestos!$C$18)^31)) -> 2.6271683e-08 | AI19: =AH19*(1-MIN(1,INDEX(Tabla_Mortalidad!$B$5:$B$75,MIN(71,Cartera_Polizas!$B$21+32-49))*(1+(Cartera_Polizas!$P$21-1)*MAX(0,1-32/Supuestos!$C$20))*(1-Supuestos!$C$18)^32)) -> 5.4905292e-09 | AJ19: =AI19*(1-MIN(1,INDEX(Tabla_Mortalidad!$B$5:$B$75,MIN(71,Cartera_Polizas!$B$21+33-49))*(1+(Cartera_Polizas!$P$21-1)*MAX(0,1-33/Supuestos!$C$20))*(1-Supuestos!$C$18)^33)) -> 1.0813956e-09 | AK19: =AJ19*(1-MIN(1,INDEX(Tabla_Mortalidad!$B$5:$B$75,MIN(71,Cartera_Polizas!$B$21+34-49))*(1+(Cartera_Polizas!$P$21-1)*MAX(0,1-34/Supuestos!$C$20))*(1-Supuestos!$C$18)^34)) -> 1.6944914e-10 | AL19: =AK19*(1-MIN(1,INDEX(Tabla_Mortalidad!$B$5:$B$75,MIN(71,Cartera_Polizas!$B$21+35-49))*(1+(Cartera_Polizas!$P$21-1)*MAX(0,1-35/Supuestos!$C$20))*(1-Supuestos!$C$18)^35)) -> 2.7266297e-11 | AM19: =AL19*(1-MIN(1,INDEX(Tabla_Mortalidad!$B$5:$B$75,MIN(71,Cartera_Polizas!$B$21+36-49))*(1+(Cartera_Polizas!$P$21-1)*MAX(0,1-36/Supuestos!$C$20))*(1-Supuestos!$C$18)^36)) -> 4.5018519e-12 | AN19: =AM19*(1-MIN(1,INDEX(Tabla_Mortalidad!$B$5:$B$75,MIN(71,Cartera_Polizas!$B$21+37-49))*(1+(Cartera_Polizas!$P$21-1)*MAX(0,1-37/Supuestos!$C$20))*(1-Supuestos!$C$18)^37)) -> 7.6207933e-13 | AO19: =AN19*(1-MIN(1,INDEX(Tabla_Mortalidad!$B$5:$B$75,MIN(71,Cartera_Polizas!$B$21+38-49))*(1+(Cartera_Polizas!$P$21-1)*MAX(0,1-38/Supuestos!$C$20))*(1-Supuestos!$C$18)^38)) -> 1.3217115e-13 | AP19: =AO19*(1-MIN(1,INDEX(Tabla_Mortalidad!$B$5:$B$75,MIN(71,Cartera_Polizas!$B$21+39-49))*(1+(Cartera_Polizas!$P$21-1)*MAX(0,1-39/Supuestos!$C$20))*(1-Supuestos!$C$18)^39)) -> 2.3469329e-14 | AQ19: =AP19*(1-MIN(1,INDEX(Tabla_Mortalidad!$B$5:$B$75,MIN(71,Cartera_Polizas!$B$21+40-49))*(1+(Cartera_Polizas!$P$21-1)*MAX(0,1-40/Supuestos!$C$20))*(1-Supuestos!$C$18)^40)) -> 4.2639048e-15 | AR19: =AQ19*(1-MIN(1,INDEX(Tabla_Mortalidad!$B$5:$B$75,MIN(71,Cartera_Polizas!$B$21+41-49))*(1+(Cartera_Polizas!$P$21-1)*MAX(0,1-41/Supuestos!$C$20))*(1-Supuestos!$C$18)^41)) -> 7.9211191e-16 | AS19: =AR19*(1-MIN(1,INDEX(Tabla_Mortalidad!$B$5:$B$75,MIN(71,Cartera_Polizas!$B$21+42-49))*(1+(Cartera_Polizas!$P$21-1)*MAX(0,1-42/Supuestos!$C$20))*(1-Supuestos!$C$18)^42)) -> 1.503766e-16 | AT19: =AS19*(1-MIN(1,INDEX(Tabla_Mortalidad!$B$5:$B$75,MIN(71,Cartera_Polizas!$B$21+43-49))*(1+(Cartera_Polizas!$P$21-1)*MAX(0,1-43/Supuestos!$C$20))*(1-Supuestos!$C$18)^43)) -> 2.9157032e-17 | AU19: =AT19*(1-MIN(1,INDEX(Tabla_Mortalidad!$B$5:$B$75,MIN(71,Cartera_Polizas!$B$21+44-49))*(1+(Cartera_Polizas!$P$21-1)*MAX(0,1-44/Supuestos!$C$20))*(1-Supuestos!$C$18)^44)) -> 5.7708747e-18
A20: =Cartera_Polizas!A22 -> 17 | B20: =SUM(C20:AU20)+0.5 -> 11.738626 | C20: =1-MIN(1,INDEX(Tabla_Mortalidad!$B$5:$B$75,MIN(71,Cartera_Polizas!$B$22+0-49))*(1+(Cartera_Polizas!$P$22-1)*MAX(0,1-0/Supuestos!$C$20))*(1-Supuestos!$C$18)^0) -> 0.95999835 | D20: =C20*(1-MIN(1,INDEX(Tabla_Mortalidad!$B$5:$B$75,MIN(71,Cartera_Polizas!$B$22+1-49))*(1+(Cartera_Polizas!$P$22-1)*MAX(0,1-1/Supuestos!$C$20))*(1-Supuestos!$C$18)^1)) -> 0.91842742 | E20: =D20*(1-MIN(1,INDEX(Tabla_Mortalidad!$B$5:$B$75,MIN(71,Cartera_Polizas!$B$22+2-49))*(1+(Cartera_Polizas!$P$22-1)*MAX(0,1-2/Supuestos!$C$20))*(1-Supuestos!$C$18)^2)) -> 0.87540687 | F20: =E20*(1-MIN(1,INDEX(Tabla_Mortalidad!$B$5:$B$75,MIN(71,Cartera_Polizas!$B$22+3-49))*(1+(Cartera_Polizas!$P$22-1)*MAX(0,1-3/Supuestos!$C$20))*(1-Supuestos!$C$18)^3)) -> 0.83108689 | G20: =F20*(1-MIN(1,INDEX(Tabla_Mortalidad!$B$5:$B$75,MIN(71,Cartera_Polizas!$B$22+4-49))*(1+(Cartera_Polizas!$P$22-1)*MAX(0,1-4/Supuestos!$C$20))*(1-Supuestos!$C$18)^4)) -> 0.78564995 | H20: =G20*(1-MIN(1,INDEX(Tabla_Mortalidad!$B$5:$B$75,MIN(71,Cartera_Polizas!$B$22+5-49))*(1+(Cartera_Polizas!$P$22-1)*MAX(0,1-5/Supuestos!$C$20))*(1-Supuestos!$C$18)^5)) -> 0.73931059 | I20: =H20*(1-MIN(1,INDEX(Tabla_Mortalidad!$B$5:$B$75,MIN(71,Cartera_Polizas!$B$22+6-49))*(1+(Cartera_Polizas!$P$22-1)*MAX(0,1-6/Supuestos!$C$20))*(1-Supuestos!$C$18)^6)) -> 0.69231281 | J20: =I20*(1-MIN(1,INDEX(Tabla_Mortalidad!$B$5:$B$75,MIN(71,Cartera_Polizas!$B$22+7-49))*(1+(Cartera_Polizas!$P$22-1)*MAX(0,1-7/Supuestos!$C$20))*(1-Supuestos!$C$18)^7)) -> 0.64493008 | K20: =J20*(1-MIN(1,INDEX(Tabla_Mortalidad!$B$5:$B$75,MIN(71,Cartera_Polizas!$B$22+8-49))*(1+(Cartera_Polizas!$P$22-1)*MAX(0,1-8/Supuestos!$C$20))*(1-Supuestos!$C$18)^8)) -> 0.59746352 | L20: =K20*(1-MIN(1,INDEX(Tabla_Mortalidad!$B$5:$B$75,MIN(71,Cartera_Polizas!$B$22+9-49))*(1+(Cartera_Polizas!$P$22-1)*MAX(0,1-9/Supuestos!$C$20))*(1-Supuestos!$C$18)^9)) -> 0.55023527 | M20: =L20*(1-MIN(1,INDEX(Tabla_Mortalidad!$B$5:$B$75,MIN(71,Cartera_Polizas!$B$22+10-49))*(1+(Cartera_Polizas!$P$22-1)*MAX(0,1-10/Supuestos!$C$20))*(1-Supuestos!$C$18)^10)) -> 0.50358227 | N20: =M20*(1-MIN(1,INDEX(Tabla_Mortalidad!$B$5:$B$75,MIN(71,Cartera_Polizas!$B$22+11-49))*(1+(Cartera_Polizas!$P$22-1)*MAX(0,1-11/Supuestos!$C$20))*(1-Supuestos!$C$18)^11)) -> 0.45785176 | O20: =N20*(1-MIN(1,INDEX(Tabla_Mortalidad!$B$5:$B$75,MIN(71,Cartera_Polizas!$B$22+12-49))*(1+(Cartera_Polizas!$P$22-1)*MAX(0,1-12/Supuestos!$C$20))*(1-Supuestos!$C$18)^12)) -> 0.4133891 | P20: =O20*(1-MIN(1,INDEX(Tabla_Mortalidad!$B$5:$B$75,MIN(71,Cartera_Polizas!$B$22+13-49))*(1+(Cartera_Polizas!$P$22-1)*MAX(0,1-13/Supuestos!$C$20))*(1-Supuestos!$C$18)^13)) -> 0.37053185 | Q20: =P20*(1-MIN(1,INDEX(Tabla_Mortalidad!$B$5:$B$75,MIN(71,Cartera_Polizas!$B$22+14-49))*(1+(Cartera_Polizas!$P$22-1)*MAX(0,1-14/Supuestos!$C$20))*(1-Supuestos!$C$18)^14)) -> 0.32959728 | R20: =Q20*(1-MIN(1,INDEX(Tabla_Mortalidad!$B$5:$B$75,MIN(71,Cartera_Polizas!$B$22+15-49))*(1+(Cartera_Polizas!$P$22-1)*MAX(0,1-15/Supuestos!$C$20))*(1-Supuestos!$C$18)^15)) -> 0.29087303 | S20: =R20*(1-MIN(1,INDEX(Tabla_Mortalidad!$B$5:$B$75,MIN(71,Cartera_Polizas!$B$22+16-49))*(1+(Cartera_Polizas!$P$22-1)*MAX(0,1-16/Supuestos!$C$20))*(1-Supuestos!$C$18)^16)) -> 0.253206 | T20: =S20*(1-MIN(1,INDEX(Tabla_Mortalidad!$B$5:$B$75,MIN(71,Cartera_Polizas!$B$22+17-49))*(1+(Cartera_Polizas!$P$22-1)*MAX(0,1-17/Supuestos!$C$20))*(1-Supuestos!$C$18)^17)) -> 0.21709723 | U20: =T20*(1-MIN(1,INDEX(Tabla_Mortalidad!$B$5:$B$75,MIN(71,Cartera_Polizas!$B$22+18-49))*(1+(Cartera_Polizas!$P$22-1)*MAX(0,1-18/Supuestos!$C$20))*(1-Supuestos!$C$18)^18)) -> 0.1830366 | V20: =U20*(1-MIN(1,INDEX(Tabla_Mortalidad!$B$5:$B$75,MIN(71,Cartera_Polizas!$B$22+19-49))*(1+(Cartera_Polizas!$P$22-1)*MAX(0,1-19/Supuestos!$C$20))*(1-Supuestos!$C$18)^19)) -> 0.15147683 | W20: =V20*(1-MIN(1,INDEX(Tabla_Mortalidad!$B$5:$B$75,MIN(71,Cartera_Polizas!$B$22+20-49))*(1+(Cartera_Polizas!$P$22-1)*MAX(0,1-20/Supuestos!$C$20))*(1-Supuestos!$C$18)^20)) -> 0.12280697 | X20: =W20*(1-MIN(1,INDEX(Tabla_Mortalidad!$B$5:$B$75,MIN(71,Cartera_Polizas!$B$22+21-49))*(1+(Cartera_Polizas!$P$22-1)*MAX(0,1-21/Supuestos!$C$20))*(1-Supuestos!$C$18)^21)) -> 0.097326089 | Y20: =X20*(1-MIN(1,INDEX(Tabla_Mortalidad!$B$5:$B$75,MIN(71,Cartera_Polizas!$B$22+22-49))*(1+(Cartera_Polizas!$P$22-1)*MAX(0,1-22/Supuestos!$C$20))*(1-Supuestos!$C$18)^22)) -> 0.075220345 | Z20: =Y20*(1-MIN(1,INDEX(Tabla_Mortalidad!$B$5:$B$75,MIN(71,Cartera_Polizas!$B$22+23-49))*(1+(Cartera_Polizas!$P$22-1)*MAX(0,1-23/Supuestos!$C$20))*(1-Supuestos!$C$18)^23)) -> 0.056547862 | AA20: =Z20*(1-MIN(1,INDEX(Tabla_Mortalidad!$B$5:$B$75,MIN(71,Cartera_Polizas!$B$22+24-49))*(1+(Cartera_Polizas!$P$22-1)*MAX(0,1-24/Supuestos!$C$20))*(1-Supuestos!$C$18)^24)) -> 0.0412332 | AB20: =AA20*(1-MIN(1,INDEX(Tabla_Mortalidad!$B$5:$B$75,MIN(71,Cartera_Polizas!$B$22+25-49))*(1+(Cartera_Polizas!$P$22-1)*MAX(0,1-25/Supuestos!$C$20))*(1-Supuestos!$C$18)^25)) -> 0.029073539 | AC20: =AB20*(1-MIN(1,INDEX(Tabla_Mortalidad!$B$5:$B$75,MIN(71,Cartera_Polizas!$B$22+26-49))*(1+(Cartera_Polizas!$P$22-1)*MAX(0,1-26/Supuestos!$C$20))*(1-Supuestos!$C$18)^26)) -> 0.019757551 | AD20: =AC20*(1-MIN(1,INDEX(Tabla_Mortalidad!$B$5:$B$75,MIN(71,Cartera_Polizas!$B$22+27-49))*(1+(Cartera_Polizas!$P$22-1)*MAX(0,1-27/Supuestos!$C$20))*(1-Supuestos!$C$18)^27)) -> 0.012894671 | AE20: =AD20*(1-MIN(1,INDEX(Tabla_Mortalidad!$B$5:$B$75,MIN(71,Cartera_Polizas!$B$22+28-49))*(1+(Cartera_Polizas!$P$22-1)*MAX(0,1-28/Supuestos!$C$20))*(1-Supuestos!$C$18)^28)) -> 0.0080516406 | AF20: =AE20*(1-MIN(1,INDEX(Tabla_Mortalidad!$B$5:$B$75,MIN(71,Cartera_Polizas!$B$22+29-49))*(1+(Cartera_Polizas!$P$22-1)*MAX(0,1-29/Supuestos!$C$20))*(1-Supuestos!$C$18)^29)) -> 0.0047909096 | AG20: =AF20*(1-MIN(1,INDEX(Tabla_Mortalidad!$B$5:$B$75,MIN(71,Cartera_Polizas!$B$22+30-49))*(1+(Cartera_Polizas!$P$22-1)*MAX(0,1-30/Supuestos!$C$20))*(1-Supuestos!$C$18)^30)) -> 0.0027051866 | AH20: =AG20*(1-MIN(1,INDEX(Tabla_Mortalidad!$B$5:$B$75,MIN(71,Cartera_Polizas!$B$22+31-49))*(1+(Cartera_Polizas!$P$22-1)*MAX(0,1-31/Supuestos!$C$20))*(1-Supuestos!$C$18)^31)) -> 0.0014433034 | AI20: =AH20*(1-MIN(1,INDEX(Tabla_Mortalidad!$B$5:$B$75,MIN(71,Cartera_Polizas!$B$22+32-49))*(1+(Cartera_Polizas!$P$22-1)*MAX(0,1-32/Supuestos!$C$20))*(1-Supuestos!$C$18)^32)) -> 0.00072447313 | AJ20: =AI20*(1-MIN(1,INDEX(Tabla_Mortalidad!$B$5:$B$75,MIN(71,Cartera_Polizas!$B$22+33-49))*(1+(Cartera_Polizas!$P$22-1)*MAX(0,1-33/Supuestos!$C$20))*(1-Supuestos!$C$18)^33)) -> 0.00034068726 | AK20: =AJ20*(1-MIN(1,INDEX(Tabla_Mortalidad!$B$5:$B$75,MIN(71,Cartera_Polizas!$B$22+34-49))*(1+(Cartera_Polizas!$P$22-1)*MAX(0,1-34/Supuestos!$C$20))*(1-Supuestos!$C$18)^34)) -> 0.00014949983 | AL20: =AK20*(1-MIN(1,INDEX(Tabla_Mortalidad!$B$5:$B$75,MIN(71,Cartera_Polizas!$B$22+35-49))*(1+(Cartera_Polizas!$P$22-1)*MAX(0,1-35/Supuestos!$C$20))*(1-Supuestos!$C$18)^35)) -> 6.100564e-05 | AM20: =AL20*(1-MIN(1,INDEX(Tabla_Mortalidad!$B$5:$B$75,MIN(71,Cartera_Polizas!$B$22+36-49))*(1+(Cartera_Polizas!$P$22-1)*MAX(0,1-36/Supuestos!$C$20))*(1-Supuestos!$C$18)^36)) -> 2.3087152e-05 | AN20: =AM20*(1-MIN(1,INDEX(Tabla_Mortalidad!$B$5:$B$75,MIN(71,Cartera_Polizas!$B$22+37-49))*(1+(Cartera_Polizas!$P$22-1)*MAX(0,1-37/Supuestos!$C$20))*(1-Supuestos!$C$18)^37)) -> 8.0899584e-06 | AO20: =AN20*(1-MIN(1,INDEX(Tabla_Mortalidad!$B$5:$B$75,MIN(71,Cartera_Polizas!$B$22+38-49))*(1+(Cartera_Polizas!$P$22-1)*MAX(0,1-38/Supuestos!$C$20))*(1-Supuestos!$C$18)^38)) -> 2.6244325e-06 | AP20: =AO20*(1-MIN(1,INDEX(Tabla_Mortalidad!$B$5:$B$75,MIN(71,Cartera_Polizas!$B$22+39-49))*(1+(Cartera_Polizas!$P$22-1)*MAX(0,1-39/Supuestos!$C$20))*(1-Supuestos!$C$18)^39)) -> 7.8952898e-07 | AQ20: =AP20*(1-MIN(1,INDEX(Tabla_Mortalidad!$B$5:$B$75,MIN(71,Cartera_Polizas!$B$22+40-49))*(1+(Cartera_Polizas!$P$22-1)*MAX(0,1-40/Supuestos!$C$20))*(1-Supuestos!$C$18)^40)) -> 2.2110382e-07 | AR20: =AQ20*(1-MIN(1,INDEX(Tabla_Mortalidad!$B$5:$B$75,MIN(71,Cartera_Polizas!$B$22+41-49))*(1+(Cartera_Polizas!$P$22-1)*MAX(0,1-41/Supuestos!$C$20))*(1-Supuestos!$C$18)^41)) -> 5.7989953e-08 | AS20: =AR20*(1-MIN(1,INDEX(Tabla_Mortalidad!$B$5:$B$75,MIN(71,Cartera_Polizas!$B$22+42-49))*(1+(Cartera_Polizas!$P$22-1)*MAX(0,1-42/Supuestos!$C$20))*(1-Supuestos!$C$18)^42)) -> 1.4361951e-08 | AT20: =AS20*(1-MIN(1,INDEX(Tabla_Mortalidad!$B$5:$B$75,MIN(71,Cartera_Polizas!$B$22+43-49))*(1+(Cartera_Polizas!$P$22-1)*MAX(0,1-43/Supuestos!$C$20))*(1-Supuestos!$C$18)^43)) -> 3.3925403e-09 | AU20: =AT20*(1-MIN(1,INDEX(Tabla_Mortalidad!$B$5:$B$75,MIN(71,Cartera_Polizas!$B$22+44-49))*(1+(Cartera_Polizas!$P$22-1)*MAX(0,1-44/Supuestos!$C$20))*(1-Supuestos!$C$18)^44)) -> 6.7146494e-10
A21: =Cartera_Polizas!A23 -> 18 | B21: =SUM(C21:AU21)+0.5 -> 7.2505006 | C21: =1-MIN(1,INDEX(Tabla_Mortalidad!$B$5:$B$75,MIN(71,Cartera_Polizas!$B$23+0-49))*(1+(Cartera_Polizas!$P$23-1)*MAX(0,1-0/Supuestos!$C$20))*(1-Supuestos!$C$18)^0) -> 0.90985987 | D21: =C21*(1-MIN(1,INDEX(Tabla_Mortalidad!$B$5:$B$75,MIN(71,Cartera_Polizas!$B$23+1-49))*(1+(Cartera_Polizas!$P$23-1)*MAX(0,1-1/Supuestos!$C$20))*(1-Supuestos!$C$18)^1)) -> 0.82209756 | E21: =D21*(1-MIN(1,INDEX(Tabla_Mortalidad!$B$5:$B$75,MIN(71,Cartera_Polizas!$B$23+2-49))*(1+(Cartera_Polizas!$P$23-1)*MAX(0,1-2/Supuestos!$C$20))*(1-Supuestos!$C$18)^2)) -> 0.73737344 | F21: =E21*(1-MIN(1,INDEX(Tabla_Mortalidad!$B$5:$B$75,MIN(71,Cartera_Polizas!$B$23+3-49))*(1+(Cartera_Polizas!$P$23-1)*MAX(0,1-3/Supuestos!$C$20))*(1-Supuestos!$C$18)^3)) -> 0.65631693 | G21: =F21*(1-MIN(1,INDEX(Tabla_Mortalidad!$B$5:$B$75,MIN(71,Cartera_Polizas!$B$23+4-49))*(1+(Cartera_Polizas!$P$23-1)*MAX(0,1-4/Supuestos!$C$20))*(1-Supuestos!$C$18)^4)) -> 0.57950277 | H21: =G21*(1-MIN(1,INDEX(Tabla_Mortalidad!$B$5:$B$75,MIN(71,Cartera_Polizas!$B$23+5-49))*(1+(Cartera_Polizas!$P$23-1)*MAX(0,1-5/Supuestos!$C$20))*(1-Supuestos!$C$18)^5)) -> 0.50743156 | I21: =H21*(1-MIN(1,INDEX(Tabla_Mortalidad!$B$5:$B$75,MIN(71,Cartera_Polizas!$B$23+6-49))*(1+(Cartera_Polizas!$P$23-1)*MAX(0,1-6/Supuestos!$C$20))*(1-Supuestos!$C$18)^6)) -> 0.44051698 | J21: =I21*(1-MIN(1,INDEX(Tabla_Mortalidad!$B$5:$B$75,MIN(71,Cartera_Polizas!$B$23+7-49))*(1+(Cartera_Polizas!$P$23-1)*MAX(0,1-7/Supuestos!$C$20))*(1-Supuestos!$C$18)^7)) -> 0.37906552 | K21: =J21*(1-MIN(1,INDEX(Tabla_Mortalidad!$B$5:$B$75,MIN(71,Cartera_Polizas!$B$23+8-49))*(1+(Cartera_Polizas!$P$23-1)*MAX(0,1-8/Supuestos!$C$20))*(1-Supuestos!$C$18)^8)) -> 0.32327161 | L21: =K21*(1-MIN(1,INDEX(Tabla_Mortalidad!$B$5:$B$75,MIN(71,Cartera_Polizas!$B$23+9-49))*(1+(Cartera_Polizas!$P$23-1)*MAX(0,1-9/Supuestos!$C$20))*(1-Supuestos!$C$18)^9)) -> 0.2732088 | M21: =L21*(1-MIN(1,INDEX(Tabla_Mortalidad!$B$5:$B$75,MIN(71,Cartera_Polizas!$B$23+10-49))*(1+(Cartera_Polizas!$P$23-1)*MAX(0,1-10/Supuestos!$C$20))*(1-Supuestos!$C$18)^10)) -> 0.22883133 | N21: =M21*(1-MIN(1,INDEX(Tabla_Mortalidad!$B$5:$B$75,MIN(71,Cartera_Polizas!$B$23+11-49))*(1+(Cartera_Polizas!$P$23-1)*MAX(0,1-11/Supuestos!$C$20))*(1-Supuestos!$C$18)^11)) -> 0.18998017 | O21: =N21*(1-MIN(1,INDEX(Tabla_Mortalidad!$B$5:$B$75,MIN(71,Cartera_Polizas!$B$23+12-49))*(1+(Cartera_Polizas!$P$23-1)*MAX(0,1-12/Supuestos!$C$20))*(1-Supuestos!$C$18)^12)) -> 0.1563949 | P21: =O21*(1-MIN(1,INDEX(Tabla_Mortalidad!$B$5:$B$75,MIN(71,Cartera_Polizas!$B$23+13-49))*(1+(Cartera_Polizas!$P$23-1)*MAX(0,1-13/Supuestos!$C$20))*(1-Supuestos!$C$18)^13)) -> 0.12773002 | Q21: =P21*(1-MIN(1,INDEX(Tabla_Mortalidad!$B$5:$B$75,MIN(71,Cartera_Polizas!$B$23+14-49))*(1+(Cartera_Polizas!$P$23-1)*MAX(0,1-14/Supuestos!$C$20))*(1-Supuestos!$C$18)^14)) -> 0.10357438 | R21: =Q21*(1-MIN(1,INDEX(Tabla_Mortalidad!$B$5:$B$75,MIN(71,Cartera_Polizas!$B$23+15-49))*(1+(Cartera_Polizas!$P$23-1)*MAX(0,1-15/Supuestos!$C$20))*(1-Supuestos!$C$18)^15)) -> 0.083473443 | S21: =R21*(1-MIN(1,INDEX(Tabla_Mortalidad!$B$5:$B$75,MIN(71,Cartera_Polizas!$B$23+16-49))*(1+(Cartera_Polizas!$P$23-1)*MAX(0,1-16/Supuestos!$C$20))*(1-Supuestos!$C$18)^16)) -> 0.065714205 | T21: =S21*(1-MIN(1,INDEX(Tabla_Mortalidad!$B$5:$B$75,MIN(71,Cartera_Polizas!$B$23+17-49))*(1+(Cartera_Polizas!$P$23-1)*MAX(0,1-17/Supuestos!$C$20))*(1-Supuestos!$C$18)^17)) -> 0.050409685 | U21: =T21*(1-MIN(1,INDEX(Tabla_Mortalidad!$B$5:$B$75,MIN(71,Cartera_Polizas!$B$23+18-49))*(1+(Cartera_Polizas!$P$23-1)*MAX(0,1-18/Supuestos!$C$20))*(1-Supuestos!$C$18)^18)) -> 0.037578542 | V21: =U21*(1-MIN(1,INDEX(Tabla_Mortalidad!$B$5:$B$75,MIN(71,Cartera_Polizas!$B$23+19-49))*(1+(Cartera_Polizas!$P$23-1)*MAX(0,1-19/Supuestos!$C$20))*(1-Supuestos!$C$18)^19)) -> 0.027142982 | W21: =V21*(1-MIN(1,INDEX(Tabla_Mortalidad!$B$5:$B$75,MIN(71,Cartera_Polizas!$B$23+20-49))*(1+(Cartera_Polizas!$P$23-1)*MAX(0,1-20/Supuestos!$C$20))*(1-Supuestos!$C$18)^20)) -> 0.018935375 | X21: =W21*(1-MIN(1,INDEX(Tabla_Mortalidad!$B$5:$B$75,MIN(71,Cartera_Polizas!$B$23+21-49))*(1+(Cartera_Polizas!$P$23-1)*MAX(0,1-21/Supuestos!$C$20))*(1-Supuestos!$C$18)^21)) -> 0.012713954 | Y21: =X21*(1-MIN(1,INDEX(Tabla_Mortalidad!$B$5:$B$75,MIN(71,Cartera_Polizas!$B$23+22-49))*(1+(Cartera_Polizas!$P$23-1)*MAX(0,1-22/Supuestos!$C$20))*(1-Supuestos!$C$18)^22)) -> 0.0081856194 | Z21: =Y21*(1-MIN(1,INDEX(Tabla_Mortalidad!$B$5:$B$75,MIN(71,Cartera_Polizas!$B$23+23-49))*(1+(Cartera_Polizas!$P$23-1)*MAX(0,1-23/Supuestos!$C$20))*(1-Supuestos!$C$18)^23)) -> 0.0050332068 | AA21: =Z21*(1-MIN(1,INDEX(Tabla_Mortalidad!$B$5:$B$75,MIN(71,Cartera_Polizas!$B$23+24-49))*(1+(Cartera_Polizas!$P$23-1)*MAX(0,1-24/Supuestos!$C$20))*(1-Supuestos!$C$18)^24)) -> 0.002943141 | AB21: =AA21*(1-MIN(1,INDEX(Tabla_Mortalidad!$B$5:$B$75,MIN(71,Cartera_Polizas!$B$23+25-49))*(1+(Cartera_Polizas!$P$23-1)*MAX(0,1-25/Supuestos!$C$20))*(1-Supuestos!$C$18)^25)) -> 0.0016293257 | AC21: =AB21*(1-MIN(1,INDEX(Tabla_Mortalidad!$B$5:$B$75,MIN(71,Cartera_Polizas!$B$23+26-49))*(1+(Cartera_Polizas!$P$23-1)*MAX(0,1-26/Supuestos!$C$20))*(1-Supuestos!$C$18)^26)) -> 0.00085000815 | AD21: =AC21*(1-MIN(1,INDEX(Tabla_Mortalidad!$B$5:$B$75,MIN(71,Cartera_Polizas!$B$23+27-49))*(1+(Cartera_Polizas!$P$23-1)*MAX(0,1-27/Supuestos!$C$20))*(1-Supuestos!$C$18)^27)) -> 0.00041592154 | AE21: =AD21*(1-MIN(1,INDEX(Tabla_Mortalidad!$B$5:$B$75,MIN(71,Cartera_Polizas!$B$23+28-49))*(1+(Cartera_Polizas!$P$23-1)*MAX(0,1-28/Supuestos!$C$20))*(1-Supuestos!$C$18)^28)) -> 0.00018999736 | AF21: =AE21*(1-MIN(1,INDEX(Tabla_Mortalidad!$B$5:$B$75,MIN(71,Cartera_Polizas!$B$23+29-49))*(1+(Cartera_Polizas!$P$23-1)*MAX(0,1-29/Supuestos!$C$20))*(1-Supuestos!$C$18)^29)) -> 8.0668305e-05 | AG21: =AF21*(1-MIN(1,INDEX(Tabla_Mortalidad!$B$5:$B$75,MIN(71,Cartera_Polizas!$B$23+30-49))*(1+(Cartera_Polizas!$P$23-1)*MAX(0,1-30/Supuestos!$C$20))*(1-Supuestos!$C$18)^30)) -> 3.170603e-05 | AH21: =AG21*(1-MIN(1,INDEX(Tabla_Mortalidad!$B$5:$B$75,MIN(71,Cartera_Polizas!$B$23+31-49))*(1+(Cartera_Polizas!$P$23-1)*MAX(0,1-31/Supuestos!$C$20))*(1-Supuestos!$C$18)^31)) -> 1.1498767e-05 | AI21: =AH21*(1-MIN(1,INDEX(Tabla_Mortalidad!$B$5:$B$75,MIN(71,Cartera_Polizas!$B$23+32-49))*(1+(Cartera_Polizas!$P$23-1)*MAX(0,1-32/Supuestos!$C$20))*(1-Supuestos!$C$18)^32)) -> 3.8397064e-06 | AJ21: =AI21*(1-MIN(1,INDEX(Tabla_Mortalidad!$B$5:$B$75,MIN(71,Cartera_Polizas!$B$23+33-49))*(1+(Cartera_Polizas!$P$23-1)*MAX(0,1-33/Supuestos!$C$20))*(1-Supuestos!$C$18)^33)) -> 1.1797882e-06 | AK21: =AJ21*(1-MIN(1,INDEX(Tabla_Mortalidad!$B$5:$B$75,MIN(71,Cartera_Polizas!$B$23+34-49))*(1+(Cartera_Polizas!$P$23-1)*MAX(0,1-34/Supuestos!$C$20))*(1-Supuestos!$C$18)^34)) -> 3.3399056e-07 | AL21: =AK21*(1-MIN(1,INDEX(Tabla_Mortalidad!$B$5:$B$75,MIN(71,Cartera_Polizas!$B$23+35-49))*(1+(Cartera_Polizas!$P$23-1)*MAX(0,1-35/Supuestos!$C$20))*(1-Supuestos!$C$18)^35)) -> 8.7429776e-08 | AM21: =AL21*(1-MIN(1,INDEX(Tabla_Mortalidad!$B$5:$B$75,MIN(71,Cartera_Polizas!$B$23+36-49))*(1+(Cartera_Polizas!$P$23-1)*MAX(0,1-36/Supuestos!$C$20))*(1-Supuestos!$C$18)^36)) -> 2.1293673e-08 | AN21: =AM21*(1-MIN(1,INDEX(Tabla_Mortalidad!$B$5:$B$75,MIN(71,Cartera_Polizas!$B$23+37-49))*(1+(Cartera_Polizas!$P$23-1)*MAX(0,1-37/Supuestos!$C$20))*(1-Supuestos!$C$18)^37)) -> 4.8670705e-09 | AO21: =AN21*(1-MIN(1,INDEX(Tabla_Mortalidad!$B$5:$B$75,MIN(71,Cartera_Polizas!$B$23+38-49))*(1+(Cartera_Polizas!$P$23-1)*MAX(0,1-38/Supuestos!$C$20))*(1-Supuestos!$C$18)^38)) -> 1.0553409e-09 | AP21: =AO21*(1-MIN(1,INDEX(Tabla_Mortalidad!$B$5:$B$75,MIN(71,Cartera_Polizas!$B$23+39-49))*(1+(Cartera_Polizas!$P$23-1)*MAX(0,1-39/Supuestos!$C$20))*(1-Supuestos!$C$18)^39)) -> 1.8739447e-10 | AQ21: =AP21*(1-MIN(1,INDEX(Tabla_Mortalidad!$B$5:$B$75,MIN(71,Cartera_Polizas!$B$23+40-49))*(1+(Cartera_Polizas!$P$23-1)*MAX(0,1-40/Supuestos!$C$20))*(1-Supuestos!$C$18)^40)) -> 3.4045804e-11 | AR21: =AQ21*(1-MIN(1,INDEX(Tabla_Mortalidad!$B$5:$B$75,MIN(71,Cartera_Polizas!$B$23+41-49))*(1+(Cartera_Polizas!$P$23-1)*MAX(0,1-41/Supuestos!$C$20))*(1-Supuestos!$C$18)^41)) -> 6.3247394e-12 | AS21: =AR21*(1-MIN(1,INDEX(Tabla_Mortalidad!$B$5:$B$75,MIN(71,Cartera_Polizas!$B$23+42-49))*(1+(Cartera_Polizas!$P$23-1)*MAX(0,1-42/Supuestos!$C$20))*(1-Supuestos!$C$18)^42)) -> 1.2007051e-12 | AT21: =AS21*(1-MIN(1,INDEX(Tabla_Mortalidad!$B$5:$B$75,MIN(71,Cartera_Polizas!$B$23+43-49))*(1+(Cartera_Polizas!$P$23-1)*MAX(0,1-43/Supuestos!$C$20))*(1-Supuestos!$C$18)^43)) -> 2.3280881e-13 | AU21: =AT21*(1-MIN(1,INDEX(Tabla_Mortalidad!$B$5:$B$75,MIN(71,Cartera_Polizas!$B$23+44-49))*(1+(Cartera_Polizas!$P$23-1)*MAX(0,1-44/Supuestos!$C$20))*(1-Supuestos!$C$18)^44)) -> 4.6078437e-14
A22: =Cartera_Polizas!A24 -> 19 | B22: =SUM(C22:AU22)+0.5 -> 12.940999 | C22: =1-MIN(1,INDEX(Tabla_Mortalidad!$B$5:$B$75,MIN(71,Cartera_Polizas!$B$24+0-49))*(1+(Cartera_Polizas!$P$24-1)*MAX(0,1-0/Supuestos!$C$20))*(1-Supuestos!$C$18)^0) -> 0.96148445 | D22: =C22*(1-MIN(1,INDEX(Tabla_Mortalidad!$B$5:$B$75,MIN(71,Cartera_Polizas!$B$24+1-49))*(1+(Cartera_Polizas!$P$24-1)*MAX(0,1-1/Supuestos!$C$20))*(1-Supuestos!$C$18)^1)) -> 0.92182064 | E22: =D22*(1-MIN(1,INDEX(Tabla_Mortalidad!$B$5:$B$75,MIN(71,Cartera_Polizas!$B$24+2-49))*(1+(Cartera_Polizas!$P$24-1)*MAX(0,1-2/Supuestos!$C$20))*(1-Supuestos!$C$18)^2)) -> 0.88114493 | F22: =E22*(1-MIN(1,INDEX(Tabla_Mortalidad!$B$5:$B$75,MIN(71,Cartera_Polizas!$B$24+3-49))*(1+(Cartera_Polizas!$P$24-1)*MAX(0,1-3/Supuestos!$C$20))*(1-Supuestos!$C$18)^3)) -> 0.83962214 | G22: =F22*(1-MIN(1,INDEX(Tabla_Mortalidad!$B$5:$B$75,MIN(71,Cartera_Polizas!$B$24+4-49))*(1+(Cartera_Polizas!$P$24-1)*MAX(0,1-4/Supuestos!$C$20))*(1-Supuestos!$C$18)^4)) -> 0.7974369 | H22: =G22*(1-MIN(1,INDEX(Tabla_Mortalidad!$B$5:$B$75,MIN(71,Cartera_Polizas!$B$24+5-49))*(1+(Cartera_Polizas!$P$24-1)*MAX(0,1-5/Supuestos!$C$20))*(1-Supuestos!$C$18)^5)) -> 0.75479466 | I22: =H22*(1-MIN(1,INDEX(Tabla_Mortalidad!$B$5:$B$75,MIN(71,Cartera_Polizas!$B$24+6-49))*(1+(Cartera_Polizas!$P$24-1)*MAX(0,1-6/Supuestos!$C$20))*(1-Supuestos!$C$18)^6)) -> 0.71192025 | J22: =I22*(1-MIN(1,INDEX(Tabla_Mortalidad!$B$5:$B$75,MIN(71,Cartera_Polizas!$B$24+7-49))*(1+(Cartera_Polizas!$P$24-1)*MAX(0,1-7/Supuestos!$C$20))*(1-Supuestos!$C$18)^7)) -> 0.66905554 | K22: =J22*(1-MIN(1,INDEX(Tabla_Mortalidad!$B$5:$B$75,MIN(71,Cartera_Polizas!$B$24+8-49))*(1+(Cartera_Polizas!$P$24-1)*MAX(0,1-8/Supuestos!$C$20))*(1-Supuestos!$C$18)^8)) -> 0.62645537 | L22: =K22*(1-MIN(1,INDEX(Tabla_Mortalidad!$B$5:$B$75,MIN(71,Cartera_Polizas!$B$24+9-49))*(1+(Cartera_Polizas!$P$24-1)*MAX(0,1-9/Supuestos!$C$20))*(1-Supuestos!$C$18)^9)) -> 0.58438123 | M22: =L22*(1-MIN(1,INDEX(Tabla_Mortalidad!$B$5:$B$75,MIN(71,Cartera_Polizas!$B$24+10-49))*(1+(Cartera_Polizas!$P$24-1)*MAX(0,1-10/Supuestos!$C$20))*(1-Supuestos!$C$18)^10)) -> 0.54309789 | N22: =M22*(1-MIN(1,INDEX(Tabla_Mortalidad!$B$5:$B$75,MIN(71,Cartera_Polizas!$B$24+11-49))*(1+(Cartera_Polizas!$P$24-1)*MAX(0,1-11/Supuestos!$C$20))*(1-Supuestos!$C$18)^11)) -> 0.50286881 | O22: =N22*(1-MIN(1,INDEX(Tabla_Mortalidad!$B$5:$B$75,MIN(71,Cartera_Polizas!$B$24+12-49))*(1+(Cartera_Polizas!$P$24-1)*MAX(0,1-12/Supuestos!$C$20))*(1-Supuestos!$C$18)^12)) -> 0.46394826 | P22: =O22*(1-MIN(1,INDEX(Tabla_Mortalidad!$B$5:$B$75,MIN(71,Cartera_Polizas!$B$24+13-49))*(1+(Cartera_Polizas!$P$24-1)*MAX(0,1-13/Supuestos!$C$20))*(1-Supuestos!$C$18)^13)) -> 0.42657502 | Q22: =P22*(1-MIN(1,INDEX(Tabla_Mortalidad!$B$5:$B$75,MIN(71,Cartera_Polizas!$B$24+14-49))*(1+(Cartera_Polizas!$P$24-1)*MAX(0,1-14/Supuestos!$C$20))*(1-Supuestos!$C$18)^14)) -> 0.39096899 | R22: =Q22*(1-MIN(1,INDEX(Tabla_Mortalidad!$B$5:$B$75,MIN(71,Cartera_Polizas!$B$24+15-49))*(1+(Cartera_Polizas!$P$24-1)*MAX(0,1-15/Supuestos!$C$20))*(1-Supuestos!$C$18)^15)) -> 0.35732298 | S22: =R22*(1-MIN(1,INDEX(Tabla_Mortalidad!$B$5:$B$75,MIN(71,Cartera_Polizas!$B$24+16-49))*(1+(Cartera_Polizas!$P$24-1)*MAX(0,1-16/Supuestos!$C$20))*(1-Supuestos!$C$18)^16)) -> 0.32335815 | T22: =S22*(1-MIN(1,INDEX(Tabla_Mortalidad!$B$5:$B$75,MIN(71,Cartera_Polizas!$B$24+17-49))*(1+(Cartera_Polizas!$P$24-1)*MAX(0,1-17/Supuestos!$C$20))*(1-Supuestos!$C$18)^17)) -> 0.28943039 | U22: =T22*(1-MIN(1,INDEX(Tabla_Mortalidad!$B$5:$B$75,MIN(71,Cartera_Polizas!$B$24+18-49))*(1+(Cartera_Polizas!$P$24-1)*MAX(0,1-18/Supuestos!$C$20))*(1-Supuestos!$C$18)^18)) -> 0.25593286 | V22: =U22*(1-MIN(1,INDEX(Tabla_Mortalidad!$B$5:$B$75,MIN(71,Cartera_Polizas!$B$24+19-49))*(1+(Cartera_Polizas!$P$24-1)*MAX(0,1-19/Supuestos!$C$20))*(1-Supuestos!$C$18)^19)) -> 0.22328511 | W22: =V22*(1-MIN(1,INDEX(Tabla_Mortalidad!$B$5:$B$75,MIN(71,Cartera_Polizas!$B$24+20-49))*(1+(Cartera_Polizas!$P$24-1)*MAX(0,1-20/Supuestos!$C$20))*(1-Supuestos!$C$18)^20)) -> 0.19191849 | X22: =W22*(1-MIN(1,INDEX(Tabla_Mortalidad!$B$5:$B$75,MIN(71,Cartera_Polizas!$B$24+21-49))*(1+(Cartera_Polizas!$P$24-1)*MAX(0,1-21/Supuestos!$C$20))*(1-Supuestos!$C$18)^21)) -> 0.16225758 | Y22: =X22*(1-MIN(1,INDEX(Tabla_Mortalidad!$B$5:$B$75,MIN(71,Cartera_Polizas!$B$24+22-49))*(1+(Cartera_Polizas!$P$24-1)*MAX(0,1-22/Supuestos!$C$20))*(1-Supuestos!$C$18)^22)) -> 0.13469816 | Z22: =Y22*(1-MIN(1,INDEX(Tabla_Mortalidad!$B$5:$B$75,MIN(71,Cartera_Polizas!$B$24+23-49))*(1+(Cartera_Polizas!$P$24-1)*MAX(0,1-23/Supuestos!$C$20))*(1-Supuestos!$C$18)^23)) -> 0.10958448 | AA22: =Z22*(1-MIN(1,INDEX(Tabla_Mortalidad!$B$5:$B$75,MIN(71,Cartera_Polizas!$B$24+24-49))*(1+(Cartera_Polizas!$P$24-1)*MAX(0,1-24/Supuestos!$C$20))*(1-Supuestos!$C$18)^24)) -> 0.087186458 | AB22: =AA22*(1-MIN(1,INDEX(Tabla_Mortalidad!$B$5:$B$75,MIN(71,Cartera_Polizas!$B$24+25-49))*(1+(Cartera_Polizas!$P$24-1)*MAX(0,1-25/Supuestos!$C$20))*(1-Supuestos!$C$18)^25)) -> 0.067679294 | AC22: =AB22*(1-MIN(1,INDEX(Tabla_Mortalidad!$B$5:$B$75,MIN(71,Cartera_Polizas!$B$24+26-49))*(1+(Cartera_Polizas!$P$24-1)*MAX(0,1-26/Supuestos!$C$20))*(1-Supuestos!$C$18)^26)) -> 0.051129529 | AD22: =AC22*(1-MIN(1,INDEX(Tabla_Mortalidad!$B$5:$B$75,MIN(71,Cartera_Polizas!$B$24+27-49))*(1+(Cartera_Polizas!$P$24-1)*MAX(0,1-27/Supuestos!$C$20))*(1-Supuestos!$C$18)^27)) -> 0.037488967 | AE22: =AD22*(1-MIN(1,INDEX(Tabla_Mortalidad!$B$5:$B$75,MIN(71,Cartera_Polizas!$B$24+28-49))*(1+(Cartera_Polizas!$P$24-1)*MAX(0,1-28/Supuestos!$C$20))*(1-Supuestos!$C$18)^28)) -> 0.026598484 | AF22: =AE22*(1-MIN(1,INDEX(Tabla_Mortalidad!$B$5:$B$75,MIN(71,Cartera_Polizas!$B$24+29-49))*(1+(Cartera_Polizas!$P$24-1)*MAX(0,1-29/Supuestos!$C$20))*(1-Supuestos!$C$18)^29)) -> 0.018202779 | AG22: =AF22*(1-MIN(1,INDEX(Tabla_Mortalidad!$B$5:$B$75,MIN(71,Cartera_Polizas!$B$24+30-49))*(1+(Cartera_Polizas!$P$24-1)*MAX(0,1-30/Supuestos!$C$20))*(1-Supuestos!$C$18)^30)) -> 0.011974325 | AH22: =AG22*(1-MIN(1,INDEX(Tabla_Mortalidad!$B$5:$B$75,MIN(71,Cartera_Polizas!$B$24+31-49))*(1+(Cartera_Polizas!$P$24-1)*MAX(0,1-31/Supuestos!$C$20))*(1-Supuestos!$C$18)^31)) -> 0.0075440859 | AI22: =AH22*(1-MIN(1,INDEX(Tabla_Mortalidad!$B$5:$B$75,MIN(71,Cartera_Polizas!$B$24+32-49))*(1+(Cartera_Polizas!$P$24-1)*MAX(0,1-32/Supuestos!$C$20))*(1-Supuestos!$C$18)^32)) -> 0.004534502 | AJ22: =AI22*(1-MIN(1,INDEX(Tabla_Mortalidad!$B$5:$B$75,MIN(71,Cartera_Polizas!$B$24+33-49))*(1+(Cartera_Polizas!$P$24-1)*MAX(0,1-33/Supuestos!$C$20))*(1-Supuestos!$C$18)^33)) -> 0.0025898697 | AK22: =AJ22*(1-MIN(1,INDEX(Tabla_Mortalidad!$B$5:$B$75,MIN(71,Cartera_Polizas!$B$24+34-49))*(1+(Cartera_Polizas!$P$24-1)*MAX(0,1-34/Supuestos!$C$20))*(1-Supuestos!$C$18)^34)) -> 0.001399809 | AL22: =AK22*(1-MIN(1,INDEX(Tabla_Mortalidad!$B$5:$B$75,MIN(71,Cartera_Polizas!$B$24+35-49))*(1+(Cartera_Polizas!$P$24-1)*MAX(0,1-35/Supuestos!$C$20))*(1-Supuestos!$C$18)^35)) -> 0.00071304626 | AM22: =AL22*(1-MIN(1,INDEX(Tabla_Mortalidad!$B$5:$B$75,MIN(71,Cartera_Polizas!$B$24+36-49))*(1+(Cartera_Polizas!$P$24-1)*MAX(0,1-36/Supuestos!$C$20))*(1-Supuestos!$C$18)^36)) -> 0.00034095142 | AN22: =AM22*(1-MIN(1,INDEX(Tabla_Mortalidad!$B$5:$B$75,MIN(71,Cartera_Polizas!$B$24+37-49))*(1+(Cartera_Polizas!$P$24-1)*MAX(0,1-37/Supuestos!$C$20))*(1-Supuestos!$C$18)^37)) -> 0.00015247146 | AO22: =AN22*(1-MIN(1,INDEX(Tabla_Mortalidad!$B$5:$B$75,MIN(71,Cartera_Polizas!$B$24+38-49))*(1+(Cartera_Polizas!$P$24-1)*MAX(0,1-38/Supuestos!$C$20))*(1-Supuestos!$C$18)^38)) -> 6.3565298e-05 | AP22: =AO22*(1-MIN(1,INDEX(Tabla_Mortalidad!$B$5:$B$75,MIN(71,Cartera_Polizas!$B$24+39-49))*(1+(Cartera_Polizas!$P$24-1)*MAX(0,1-39/Supuestos!$C$20))*(1-Supuestos!$C$18)^39)) -> 2.464552e-05 | AQ22: =AP22*(1-MIN(1,INDEX(Tabla_Mortalidad!$B$5:$B$75,MIN(71,Cartera_Polizas!$B$24+40-49))*(1+(Cartera_Polizas!$P$24-1)*MAX(0,1-40/Supuestos!$C$20))*(1-Supuestos!$C$18)^40)) -> 8.874969e-06 | AR22: =AQ22*(1-MIN(1,INDEX(Tabla_Mortalidad!$B$5:$B$75,MIN(71,Cartera_Polizas!$B$24+41-49))*(1+(Cartera_Polizas!$P$24-1)*MAX(0,1-41/Supuestos!$C$20))*(1-Supuestos!$C$18)^41)) -> 2.968584e-06 | AS22: =AR22*(1-MIN(1,INDEX(Tabla_Mortalidad!$B$5:$B$75,MIN(71,Cartera_Polizas!$B$24+42-49))*(1+(Cartera_Polizas!$P$24-1)*MAX(0,1-42/Supuestos!$C$20))*(1-Supuestos!$C$18)^42)) -> 9.2404023e-07 | AT22: =AS22*(1-MIN(1,INDEX(Tabla_Mortalidad!$B$5:$B$75,MIN(71,Cartera_Polizas!$B$24+43-49))*(1+(Cartera_Polizas!$P$24-1)*MAX(0,1-43/Supuestos!$C$20))*(1-Supuestos!$C$18)^43)) -> 2.6870225e-07 | AU22: =AT22*(1-MIN(1,INDEX(Tabla_Mortalidad!$B$5:$B$75,MIN(71,Cartera_Polizas!$B$24+44-49))*(1+(Cartera_Polizas!$P$24-1)*MAX(0,1-44/Supuestos!$C$20))*(1-Supuestos!$C$18)^44)) -> 7.3432404e-08
A23: =Cartera_Polizas!A25 -> 20 | B23: =SUM(C23:AU23)+0.5 -> 8.6846746 | C23: =1-MIN(1,INDEX(Tabla_Mortalidad!$B$5:$B$75,MIN(71,Cartera_Polizas!$B$25+0-49))*(1+(Cartera_Polizas!$P$25-1)*MAX(0,1-0/Supuestos!$C$20))*(1-Supuestos!$C$18)^0) -> 0.92387878 | D23: =C23*(1-MIN(1,INDEX(Tabla_Mortalidad!$B$5:$B$75,MIN(71,Cartera_Polizas!$B$25+1-49))*(1+(Cartera_Polizas!$P$25-1)*MAX(0,1-1/Supuestos!$C$20))*(1-Supuestos!$C$18)^1)) -> 0.84914227 | E23: =D23*(1-MIN(1,INDEX(Tabla_Mortalidad!$B$5:$B$75,MIN(71,Cartera_Polizas!$B$25+2-49))*(1+(Cartera_Polizas!$P$25-1)*MAX(0,1-2/Supuestos!$C$20))*(1-Supuestos!$C$18)^2)) -> 0.77629539 | F23: =E23*(1-MIN(1,INDEX(Tabla_Mortalidad!$B$5:$B$75,MIN(71,Cartera_Polizas!$B$25+3-49))*(1+(Cartera_Polizas!$P$25-1)*MAX(0,1-3/Supuestos!$C$20))*(1-Supuestos!$C$18)^3)) -> 0.70582982 | G23: =F23*(1-MIN(1,INDEX(Tabla_Mortalidad!$B$5:$B$75,MIN(71,Cartera_Polizas!$B$25+4-49))*(1+(Cartera_Polizas!$P$25-1)*MAX(0,1-4/Supuestos!$C$20))*(1-Supuestos!$C$18)^4)) -> 0.63820989 | H23: =G23*(1-MIN(1,INDEX(Tabla_Mortalidad!$B$5:$B$75,MIN(71,Cartera_Polizas!$B$25+5-49))*(1+(Cartera_Polizas!$P$25-1)*MAX(0,1-5/Supuestos!$C$20))*(1-Supuestos!$C$18)^5)) -> 0.57385664 | I23: =H23*(1-MIN(1,INDEX(Tabla_Mortalidad!$B$5:$B$75,MIN(71,Cartera_Polizas!$B$25+6-49))*(1+(Cartera_Polizas!$P$25-1)*MAX(0,1-6/Supuestos!$C$20))*(1-Supuestos!$C$18)^6)) -> 0.5131386 | J23: =I23*(1-MIN(1,INDEX(Tabla_Mortalidad!$B$5:$B$75,MIN(71,Cartera_Polizas!$B$25+7-49))*(1+(Cartera_Polizas!$P$25-1)*MAX(0,1-7/Supuestos!$C$20))*(1-Supuestos!$C$18)^7)) -> 0.45636237 | K23: =J23*(1-MIN(1,INDEX(Tabla_Mortalidad!$B$5:$B$75,MIN(71,Cartera_Polizas!$B$25+8-49))*(1+(Cartera_Polizas!$P$25-1)*MAX(0,1-8/Supuestos!$C$20))*(1-Supuestos!$C$18)^8)) -> 0.40376107 | L23: =K23*(1-MIN(1,INDEX(Tabla_Mortalidad!$B$5:$B$75,MIN(71,Cartera_Polizas!$B$25+9-49))*(1+(Cartera_Polizas!$P$25-1)*MAX(0,1-9/Supuestos!$C$20))*(1-Supuestos!$C$18)^9)) -> 0.35548842 | M23: =L23*(1-MIN(1,INDEX(Tabla_Mortalidad!$B$5:$B$75,MIN(71,Cartera_Polizas!$B$25+10-49))*(1+(Cartera_Polizas!$P$25-1)*MAX(0,1-10/Supuestos!$C$20))*(1-Supuestos!$C$18)^10)) -> 0.31161937 | N23: =M23*(1-MIN(1,INDEX(Tabla_Mortalidad!$B$5:$B$75,MIN(71,Cartera_Polizas!$B$25+11-49))*(1+(Cartera_Polizas!$P$25-1)*MAX(0,1-11/Supuestos!$C$20))*(1-Supuestos!$C$18)^11)) -> 0.27214735 | O23: =N23*(1-MIN(1,INDEX(Tabla_Mortalidad!$B$5:$B$75,MIN(71,Cartera_Polizas!$B$25+12-49))*(1+(Cartera_Polizas!$P$25-1)*MAX(0,1-12/Supuestos!$C$20))*(1-Supuestos!$C$18)^12)) -> 0.23699256 | P23: =O23*(1-MIN(1,INDEX(Tabla_Mortalidad!$B$5:$B$75,MIN(71,Cartera_Polizas!$B$25+13-49))*(1+(Cartera_Polizas!$P$25-1)*MAX(0,1-13/Supuestos!$C$20))*(1-Supuestos!$C$18)^13)) -> 0.20600781 | Q23: =P23*(1-MIN(1,INDEX(Tabla_Mortalidad!$B$5:$B$75,MIN(71,Cartera_Polizas!$B$25+14-49))*(1+(Cartera_Polizas!$P$25-1)*MAX(0,1-14/Supuestos!$C$20))*(1-Supuestos!$C$18)^14)) -> 0.1789904 | R23: =Q23*(1-MIN(1,INDEX(Tabla_Mortalidad!$B$5:$B$75,MIN(71,Cartera_Polizas!$B$25+15-49))*(1+(Cartera_Polizas!$P$25-1)*MAX(0,1-15/Supuestos!$C$20))*(1-Supuestos!$C$18)^15)) -> 0.1556953 | S23: =R23*(1-MIN(1,INDEX(Tabla_Mortalidad!$B$5:$B$75,MIN(71,Cartera_Polizas!$B$25+16-49))*(1+(Cartera_Polizas!$P$25-1)*MAX(0,1-16/Supuestos!$C$20))*(1-Supuestos!$C$18)^16)) -> 0.1333806 | T23: =S23*(1-MIN(1,INDEX(Tabla_Mortalidad!$B$5:$B$75,MIN(71,Cartera_Polizas!$B$25+17-49))*(1+(Cartera_Polizas!$P$25-1)*MAX(0,1-17/Supuestos!$C$20))*(1-Supuestos!$C$18)^17)) -> 0.11234921 | U23: =T23*(1-MIN(1,INDEX(Tabla_Mortalidad!$B$5:$B$75,MIN(71,Cartera_Polizas!$B$25+18-49))*(1+(Cartera_Polizas!$P$25-1)*MAX(0,1-18/Supuestos!$C$20))*(1-Supuestos!$C$18)^18)) -> 0.09288024 | V23: =U23*(1-MIN(1,INDEX(Tabla_Mortalidad!$B$5:$B$75,MIN(71,Cartera_Polizas!$B$25+19-49))*(1+(Cartera_Polizas!$P$25-1)*MAX(0,1-19/Supuestos!$C$20))*(1-Supuestos!$C$18)^19)) -> 0.075212557 | W23: =V23*(1-MIN(1,INDEX(Tabla_Mortalidad!$B$5:$B$75,MIN(71,Cartera_Polizas!$B$25+20-49))*(1+(Cartera_Polizas!$P$25-1)*MAX(0,1-20/Supuestos!$C$20))*(1-Supuestos!$C$18)^20)) -> 0.05952849 | X23: =W23*(1-MIN(1,INDEX(Tabla_Mortalidad!$B$5:$B$75,MIN(71,Cartera_Polizas!$B$25+21-49))*(1+(Cartera_Polizas!$P$25-1)*MAX(0,1-21/Supuestos!$C$20))*(1-Supuestos!$C$18)^21)) -> 0.045939798 | Y23: =X23*(1-MIN(1,INDEX(Tabla_Mortalidad!$B$5:$B$75,MIN(71,Cartera_Polizas!$B$25+22-49))*(1+(Cartera_Polizas!$P$25-1)*MAX(0,1-22/Supuestos!$C$20))*(1-Supuestos!$C$18)^22)) -> 0.034478528 | Z23: =Y23*(1-MIN(1,INDEX(Tabla_Mortalidad!$B$5:$B$75,MIN(71,Cartera_Polizas!$B$25+23-49))*(1+(Cartera_Polizas!$P$25-1)*MAX(0,1-23/Supuestos!$C$20))*(1-Supuestos!$C$18)^23)) -> 0.025093904 | AA23: =Z23*(1-MIN(1,INDEX(Tabla_Mortalidad!$B$5:$B$75,MIN(71,Cartera_Polizas!$B$25+24-49))*(1+(Cartera_Polizas!$P$25-1)*MAX(0,1-24/Supuestos!$C$20))*(1-Supuestos!$C$18)^24)) -> 0.017656531 | AB23: =AA23*(1-MIN(1,INDEX(Tabla_Mortalidad!$B$5:$B$75,MIN(71,Cartera_Polizas!$B$25+25-49))*(1+(Cartera_Polizas!$P$25-1)*MAX(0,1-25/Supuestos!$C$20))*(1-Supuestos!$C$18)^25)) -> 0.011970446 | AC23: =AB23*(1-MIN(1,INDEX(Tabla_Mortalidad!$B$5:$B$75,MIN(71,Cartera_Polizas!$B$25+26-49))*(1+(Cartera_Polizas!$P$25-1)*MAX(0,1-26/Supuestos!$C$20))*(1-Supuestos!$C$18)^26)) -> 0.0077915597 | AD23: =AC23*(1-MIN(1,INDEX(Tabla_Mortalidad!$B$5:$B$75,MIN(71,Cartera_Polizas!$B$25+27-49))*(1+(Cartera_Polizas!$P$25-1)*MAX(0,1-27/Supuestos!$C$20))*(1-Supuestos!$C$18)^27)) -> 0.0048504703 | AE23: =AD23*(1-MIN(1,INDEX(Tabla_Mortalidad!$B$5:$B$75,MIN(71,Cartera_Polizas!$B$25+28-49))*(1+(Cartera_Polizas!$P$25-1)*MAX(0,1-28/Supuestos!$C$20))*(1-Supuestos!$C$18)^28)) -> 0.0028762693 | AF23: =AE23*(1-MIN(1,INDEX(Tabla_Mortalidad!$B$5:$B$75,MIN(71,Cartera_Polizas!$B$25+29-49))*(1+(Cartera_Polizas!$P$25-1)*MAX(0,1-29/Supuestos!$C$20))*(1-Supuestos!$C$18)^29)) -> 0.0016177928 | AG23: =AF23*(1-MIN(1,INDEX(Tabla_Mortalidad!$B$5:$B$75,MIN(71,Cartera_Polizas!$B$25+30-49))*(1+(Cartera_Polizas!$P$25-1)*MAX(0,1-30/Supuestos!$C$20))*(1-Supuestos!$C$18)^30)) -> 0.00085935186 | AH23: =AG23*(1-MIN(1,INDEX(Tabla_Mortalidad!$B$5:$B$75,MIN(71,Cartera_Polizas!$B$25+31-49))*(1+(Cartera_Polizas!$P$25-1)*MAX(0,1-31/Supuestos!$C$20))*(1-Supuestos!$C$18)^31)) -> 0.00042920511 | AI23: =AH23*(1-MIN(1,INDEX(Tabla_Mortalidad!$B$5:$B$75,MIN(71,Cartera_Polizas!$B$25+32-49))*(1+(Cartera_Polizas!$P$25-1)*MAX(0,1-32/Supuestos!$C$20))*(1-Supuestos!$C$18)^32)) -> 0.00020069338 | AJ23: =AI23*(1-MIN(1,INDEX(Tabla_Mortalidad!$B$5:$B$75,MIN(71,Cartera_Polizas!$B$25+33-49))*(1+(Cartera_Polizas!$P$25-1)*MAX(0,1-33/Supuestos!$C$20))*(1-Supuestos!$C$18)^33)) -> 8.7501986e-05 | AK23: =AJ23*(1-MIN(1,INDEX(Tabla_Mortalidad!$B$5:$B$75,MIN(71,Cartera_Polizas!$B$25+34-49))*(1+(Cartera_Polizas!$P$25-1)*MAX(0,1-34/Supuestos!$C$20))*(1-Supuestos!$C$18)^34)) -> 3.5446214e-05 | AL23: =AK23*(1-MIN(1,INDEX(Tabla_Mortalidad!$B$5:$B$75,MIN(71,Cartera_Polizas!$B$25+35-49))*(1+(Cartera_Polizas!$P$25-1)*MAX(0,1-35/Supuestos!$C$20))*(1-Supuestos!$C$18)^35)) -> 1.3303656e-05 | AM23: =AL23*(1-MIN(1,INDEX(Tabla_Mortalidad!$B$5:$B$75,MIN(71,Cartera_Polizas!$B$25+36-49))*(1+(Cartera_Polizas!$P$25-1)*MAX(0,1-36/Supuestos!$C$20))*(1-Supuestos!$C$18)^36)) -> 4.6183011e-06 | AN23: =AM23*(1-MIN(1,INDEX(Tabla_Mortalidad!$B$5:$B$75,MIN(71,Cartera_Polizas!$B$25+37-49))*(1+(Cartera_Polizas!$P$25-1)*MAX(0,1-37/Supuestos!$C$20))*(1-Supuestos!$C$18)^37)) -> 1.4825265e-06 | AO23: =AN23*(1-MIN(1,INDEX(Tabla_Mortalidad!$B$5:$B$75,MIN(71,Cartera_Polizas!$B$25+38-49))*(1+(Cartera_Polizas!$P$25-1)*MAX(0,1-38/Supuestos!$C$20))*(1-Supuestos!$C$18)^38)) -> 4.4079162e-07 | AP23: =AO23*(1-MIN(1,INDEX(Tabla_Mortalidad!$B$5:$B$75,MIN(71,Cartera_Polizas!$B$25+39-49))*(1+(Cartera_Polizas!$P$25-1)*MAX(0,1-39/Supuestos!$C$20))*(1-Supuestos!$C$18)^39)) -> 1.2184687e-07 | AQ23: =AP23*(1-MIN(1,INDEX(Tabla_Mortalidad!$B$5:$B$75,MIN(71,Cartera_Polizas!$B$25+40-49))*(1+(Cartera_Polizas!$P$25-1)*MAX(0,1-40/Supuestos!$C$20))*(1-Supuestos!$C$18)^40)) -> 3.1505652e-08 | AR23: =AQ23*(1-MIN(1,INDEX(Tabla_Mortalidad!$B$5:$B$75,MIN(71,Cartera_Polizas!$B$25+41-49))*(1+(Cartera_Polizas!$P$25-1)*MAX(0,1-41/Supuestos!$C$20))*(1-Supuestos!$C$18)^41)) -> 7.6836663e-09 | AS23: =AR23*(1-MIN(1,INDEX(Tabla_Mortalidad!$B$5:$B$75,MIN(71,Cartera_Polizas!$B$25+42-49))*(1+(Cartera_Polizas!$P$25-1)*MAX(0,1-42/Supuestos!$C$20))*(1-Supuestos!$C$18)^42)) -> 1.7855237e-09 | AT23: =AS23*(1-MIN(1,INDEX(Tabla_Mortalidad!$B$5:$B$75,MIN(71,Cartera_Polizas!$B$25+43-49))*(1+(Cartera_Polizas!$P$25-1)*MAX(0,1-43/Supuestos!$C$20))*(1-Supuestos!$C$18)^43)) -> 3.4620127e-10 | AU23: =AT23*(1-MIN(1,INDEX(Tabla_Mortalidad!$B$5:$B$75,MIN(71,Cartera_Polizas!$B$25+44-49))*(1+(Cartera_Polizas!$P$25-1)*MAX(0,1-44/Supuestos!$C$20))*(1-Supuestos!$C$18)^44)) -> 6.852152e-11
A24: =Cartera_Polizas!A26 -> 21 | B24: =SUM(C24:AU24)+0.5 -> 11.076233 | C24: =1-MIN(1,INDEX(Tabla_Mortalidad!$B$5:$B$75,MIN(71,Cartera_Polizas!$B$26+0-49))*(1+(Cartera_Polizas!$P$26-1)*MAX(0,1-0/Supuestos!$C$20))*(1-Supuestos!$C$18)^0) -> 0.94608523 | D24: =C24*(1-MIN(1,INDEX(Tabla_Mortalidad!$B$5:$B$75,MIN(71,Cartera_Polizas!$B$26+1-49))*(1+(Cartera_Polizas!$P$26-1)*MAX(0,1-1/Supuestos!$C$20))*(1-Supuestos!$C$18)^1)) -> 0.8918242 | E24: =D24*(1-MIN(1,INDEX(Tabla_Mortalidad!$B$5:$B$75,MIN(71,Cartera_Polizas!$B$26+2-49))*(1+(Cartera_Polizas!$P$26-1)*MAX(0,1-2/Supuestos!$C$20))*(1-Supuestos!$C$18)^2)) -> 0.83752395 | F24: =E24*(1-MIN(1,INDEX(Tabla_Mortalidad!$B$5:$B$75,MIN(71,Cartera_Polizas!$B$26+3-49))*(1+(Cartera_Polizas!$P$26-1)*MAX(0,1-3/Supuestos!$C$20))*(1-Supuestos!$C$18)^3)) -> 0.78350495 | G24: =F24*(1-MIN(1,INDEX(Tabla_Mortalidad!$B$5:$B$75,MIN(71,Cartera_Polizas!$B$26+4-49))*(1+(Cartera_Polizas!$P$26-1)*MAX(0,1-4/Supuestos!$C$20))*(1-Supuestos!$C$18)^4)) -> 0.73009877 | H24: =G24*(1-MIN(1,INDEX(Tabla_Mortalidad!$B$5:$B$75,MIN(71,Cartera_Polizas!$B$26+5-49))*(1+(Cartera_Polizas!$P$26-1)*MAX(0,1-5/Supuestos!$C$20))*(1-Supuestos!$C$18)^5)) -> 0.67764242 | I24: =H24*(1-MIN(1,INDEX(Tabla_Mortalidad!$B$5:$B$75,MIN(71,Cartera_Polizas!$B$26+6-49))*(1+(Cartera_Polizas!$P$26-1)*MAX(0,1-6/Supuestos!$C$20))*(1-Supuestos!$C$18)^6)) -> 0.62647185 | J24: =I24*(1-MIN(1,INDEX(Tabla_Mortalidad!$B$5:$B$75,MIN(71,Cartera_Polizas!$B$26+7-49))*(1+(Cartera_Polizas!$P$26-1)*MAX(0,1-7/Supuestos!$C$20))*(1-Supuestos!$C$18)^7)) -> 0.57691358 | K24: =J24*(1-MIN(1,INDEX(Tabla_Mortalidad!$B$5:$B$75,MIN(71,Cartera_Polizas!$B$26+8-49))*(1+(Cartera_Polizas!$P$26-1)*MAX(0,1-8/Supuestos!$C$20))*(1-Supuestos!$C$18)^8)) -> 0.52927488 | L24: =K24*(1-MIN(1,INDEX(Tabla_Mortalidad!$B$5:$B$75,MIN(71,Cartera_Polizas!$B$26+9-49))*(1+(Cartera_Polizas!$P$26-1)*MAX(0,1-9/Supuestos!$C$20))*(1-Supuestos!$C$18)^9)) -> 0.48383825 | M24: =L24*(1-MIN(1,INDEX(Tabla_Mortalidad!$B$5:$B$75,MIN(71,Cartera_Polizas!$B$26+10-49))*(1+(Cartera_Polizas!$P$26-1)*MAX(0,1-10/Supuestos!$C$20))*(1-Supuestos!$C$18)^10)) -> 0.44085564 | N24: =M24*(1-MIN(1,INDEX(Tabla_Mortalidad!$B$5:$B$75,MIN(71,Cartera_Polizas!$B$26+11-49))*(1+(Cartera_Polizas!$P$26-1)*MAX(0,1-11/Supuestos!$C$20))*(1-Supuestos!$C$18)^11)) -> 0.40054042 | O24: =N24*(1-MIN(1,INDEX(Tabla_Mortalidad!$B$5:$B$75,MIN(71,Cartera_Polizas!$B$26+12-49))*(1+(Cartera_Polizas!$P$26-1)*MAX(0,1-12/Supuestos!$C$20))*(1-Supuestos!$C$18)^12)) -> 0.36306293 | P24: =O24*(1-MIN(1,INDEX(Tabla_Mortalidad!$B$5:$B$75,MIN(71,Cartera_Polizas!$B$26+13-49))*(1+(Cartera_Polizas!$P$26-1)*MAX(0,1-13/Supuestos!$C$20))*(1-Supuestos!$C$18)^13)) -> 0.32855044 | Q24: =P24*(1-MIN(1,INDEX(Tabla_Mortalidad!$B$5:$B$75,MIN(71,Cartera_Polizas!$B$26+14-49))*(1+(Cartera_Polizas!$P$26-1)*MAX(0,1-14/Supuestos!$C$20))*(1-Supuestos!$C$18)^14)) -> 0.29708393 | R24: =Q24*(1-MIN(1,INDEX(Tabla_Mortalidad!$B$5:$B$75,MIN(71,Cartera_Polizas!$B$26+15-49))*(1+(Cartera_Polizas!$P$26-1)*MAX(0,1-15/Supuestos!$C$20))*(1-Supuestos!$C$18)^15)) -> 0.26870313 | S24: =R24*(1-MIN(1,INDEX(Tabla_Mortalidad!$B$5:$B$75,MIN(71,Cartera_Polizas!$B$26+16-49))*(1+(Cartera_Polizas!$P$26-1)*MAX(0,1-16/Supuestos!$C$20))*(1-Supuestos!$C$18)^16)) -> 0.24036827 | T24: =S24*(1-MIN(1,INDEX(Tabla_Mortalidad!$B$5:$B$75,MIN(71,Cartera_Polizas!$B$26+17-49))*(1+(Cartera_Polizas!$P$26-1)*MAX(0,1-17/Supuestos!$C$20))*(1-Supuestos!$C$18)^17)) -> 0.2124092 | U24: =T24*(1-MIN(1,INDEX(Tabla_Mortalidad!$B$5:$B$75,MIN(71,Cartera_Polizas!$B$26+18-49))*(1+(Cartera_Polizas!$P$26-1)*MAX(0,1-18/Supuestos!$C$20))*(1-Supuestos!$C$18)^18)) -> 0.18517733 | V24: =U24*(1-MIN(1,INDEX(Tabla_Mortalidad!$B$5:$B$75,MIN(71,Cartera_Polizas!$B$26+19-49))*(1+(Cartera_Polizas!$P$26-1)*MAX(0,1-19/Supuestos!$C$20))*(1-Supuestos!$C$18)^19)) -> 0.1590333 | W24: =V24*(1-MIN(1,INDEX(Tabla_Mortalidad!$B$5:$B$75,MIN(71,Cartera_Polizas!$B$26+20-49))*(1+(Cartera_Polizas!$P$26-1)*MAX(0,1-20/Supuestos!$C$20))*(1-Supuestos!$C$18)^20)) -> 0.13433127 | X24: =W24*(1-MIN(1,INDEX(Tabla_Mortalidad!$B$5:$B$75,MIN(71,Cartera_Polizas!$B$26+21-49))*(1+(Cartera_Polizas!$P$26-1)*MAX(0,1-21/Supuestos!$C$20))*(1-Supuestos!$C$18)^21)) -> 0.11140047 | Y24: =X24*(1-MIN(1,INDEX(Tabla_Mortalidad!$B$5:$B$75,MIN(71,Cartera_Polizas!$B$26+22-49))*(1+(Cartera_Polizas!$P$26-1)*MAX(0,1-22/Supuestos!$C$20))*(1-Supuestos!$C$18)^22)) -> 0.090526139 | Z24: =Y24*(1-MIN(1,INDEX(Tabla_Mortalidad!$B$5:$B$75,MIN(71,Cartera_Polizas!$B$26+23-49))*(1+(Cartera_Polizas!$P$26-1)*MAX(0,1-23/Supuestos!$C$20))*(1-Supuestos!$C$18)^23)) -> 0.071930479 | AA24: =Z24*(1-MIN(1,INDEX(Tabla_Mortalidad!$B$5:$B$75,MIN(71,Cartera_Polizas!$B$26+24-49))*(1+(Cartera_Polizas!$P$26-1)*MAX(0,1-24/Supuestos!$C$20))*(1-Supuestos!$C$18)^24)) -> 0.055755826 | AB24: =AA24*(1-MIN(1,INDEX(Tabla_Mortalidad!$B$5:$B$75,MIN(71,Cartera_Polizas!$B$26+25-49))*(1+(Cartera_Polizas!$P$26-1)*MAX(0,1-25/Supuestos!$C$20))*(1-Supuestos!$C$18)^25)) -> 0.04205322 | AC24: =AB24*(1-MIN(1,INDEX(Tabla_Mortalidad!$B$5:$B$75,MIN(71,Cartera_Polizas!$B$26+26-49))*(1+(Cartera_Polizas!$P$26-1)*MAX(0,1-26/Supuestos!$C$20))*(1-Supuestos!$C$18)^26)) -> 0.030777698 | AD24: =AC24*(1-MIN(1,INDEX(Tabla_Mortalidad!$B$5:$B$75,MIN(71,Cartera_Polizas!$B$26+27-49))*(1+(Cartera_Polizas!$P$26-1)*MAX(0,1-27/Supuestos!$C$20))*(1-Supuestos!$C$18)^27)) -> 0.021791899 | AE24: =AD24*(1-MIN(1,INDEX(Tabla_Mortalidad!$B$5:$B$75,MIN(71,Cartera_Polizas!$B$26+28-49))*(1+(Cartera_Polizas!$P$26-1)*MAX(0,1-28/Supuestos!$C$20))*(1-Supuestos!$C$18)^28)) -> 0.014878808 | AF24: =AE24*(1-MIN(1,INDEX(Tabla_Mortalidad!$B$5:$B$75,MIN(71,Cartera_Polizas!$B$26+29-49))*(1+(Cartera_Polizas!$P$26-1)*MAX(0,1-29/Supuestos!$C$20))*(1-Supuestos!$C$18)^29)) -> 0.0097621355 | AG24: =AF24*(1-MIN(1,INDEX(Tabla_Mortalidad!$B$5:$B$75,MIN(71,Cartera_Polizas!$B$26+30-49))*(1+(Cartera_Polizas!$P$26-1)*MAX(0,1-30/Supuestos!$C$20))*(1-Supuestos!$C$18)^30)) -> 0.0061322085 | AH24: =AG24*(1-MIN(1,INDEX(Tabla_Mortalidad!$B$5:$B$75,MIN(71,Cartera_Polizas!$B$26+31-49))*(1+(Cartera_Polizas!$P$26-1)*MAX(0,1-31/Supuestos!$C$20))*(1-Supuestos!$C$18)^31)) -> 0.0036735757 | AI24: =AH24*(1-MIN(1,INDEX(Tabla_Mortalidad!$B$5:$B$75,MIN(71,Cartera_Polizas!$B$26+32-49))*(1+(Cartera_Polizas!$P$26-1)*MAX(0,1-32/Supuestos!$C$20))*(1-Supuestos!$C$18)^32)) -> 0.0020902371 | AJ24: =AI24*(1-MIN(1,INDEX(Tabla_Mortalidad!$B$5:$B$75,MIN(71,Cartera_Polizas!$B$26+33-49))*(1+(Cartera_Polizas!$P$26-1)*MAX(0,1-33/Supuestos!$C$20))*(1-Supuestos!$C$18)^33)) -> 0.0011249341 | AK24: =AJ24*(1-MIN(1,INDEX(Tabla_Mortalidad!$B$5:$B$75,MIN(71,Cartera_Polizas!$B$26+34-49))*(1+(Cartera_Polizas!$P$26-1)*MAX(0,1-34/Supuestos!$C$20))*(1-Supuestos!$C$18)^34)) -> 0.0005702548 | AL24: =AK24*(1-MIN(1,INDEX(Tabla_Mortalidad!$B$5:$B$75,MIN(71,Cartera_Polizas!$B$26+35-49))*(1+(Cartera_Polizas!$P$26-1)*MAX(0,1-35/Supuestos!$C$20))*(1-Supuestos!$C$18)^35)) -> 0.00027117863 | AM24: =AL24*(1-MIN(1,INDEX(Tabla_Mortalidad!$B$5:$B$75,MIN(71,Cartera_Polizas!$B$26+36-49))*(1+(Cartera_Polizas!$P$26-1)*MAX(0,1-36/Supuestos!$C$20))*(1-Supuestos!$C$18)^36)) -> 0.00012051617 | AN24: =AM24*(1-MIN(1,INDEX(Tabla_Mortalidad!$B$5:$B$75,MIN(71,Cartera_Polizas!$B$26+37-49))*(1+(Cartera_Polizas!$P$26-1)*MAX(0,1-37/Supuestos!$C$20))*(1-Supuestos!$C$18)^37)) -> 4.9890017e-05 | AO24: =AN24*(1-MIN(1,INDEX(Tabla_Mortalidad!$B$5:$B$75,MIN(71,Cartera_Polizas!$B$26+38-49))*(1+(Cartera_Polizas!$P$26-1)*MAX(0,1-38/Supuestos!$C$20))*(1-Supuestos!$C$18)^38)) -> 1.9189843e-05 | AP24: =AO24*(1-MIN(1,INDEX(Tabla_Mortalidad!$B$5:$B$75,MIN(71,Cartera_Polizas!$B$26+39-49))*(1+(Cartera_Polizas!$P$26-1)*MAX(0,1-39/Supuestos!$C$20))*(1-Supuestos!$C$18)^39)) -> 6.8486478e-06 | AQ24: =AP24*(1-MIN(1,INDEX(Tabla_Mortalidad!$B$5:$B$75,MIN(71,Cartera_Polizas!$B$26+40-49))*(1+(Cartera_Polizas!$P$26-1)*MAX(0,1-40/Supuestos!$C$20))*(1-Supuestos!$C$18)^40)) -> 2.2678971e-06 | AR24: =AQ24*(1-MIN(1,INDEX(Tabla_Mortalidad!$B$5:$B$75,MIN(71,Cartera_Polizas!$B$26+41-49))*(1+(Cartera_Polizas!$P$26-1)*MAX(0,1-41/Supuestos!$C$20))*(1-Supuestos!$C$18)^41)) -> 6.980862e-07 | AS24: =AR24*(1-MIN(1,INDEX(Tabla_Mortalidad!$B$5:$B$75,MIN(71,Cartera_Polizas!$B$26+42-49))*(1+(Cartera_Polizas!$P$26-1)*MAX(0,1-42/Supuestos!$C$20))*(1-Supuestos!$C$18)^42)) -> 2.0050905e-07 | AT24: =AS24*(1-MIN(1,INDEX(Tabla_Mortalidad!$B$5:$B$75,MIN(71,Cartera_Polizas!$B$26+43-49))*(1+(Cartera_Polizas!$P$26-1)*MAX(0,1-43/Supuestos!$C$20))*(1-Supuestos!$C$18)^43)) -> 5.4063972e-08 | AU24: =AT24*(1-MIN(1,INDEX(Tabla_Mortalidad!$B$5:$B$75,MIN(71,Cartera_Polizas!$B$26+44-49))*(1+(Cartera_Polizas!$P$26-1)*MAX(0,1-44/Supuestos!$C$20))*(1-Supuestos!$C$18)^44)) -> 1.3795358e-08
