Workbook

Sheet LEAME
A1: Modelo ilustrativo de calificación – Titulización de Life Settlements (SPV USD 100 mm)
A2: Reconstrucción del enfoque de AM Best ('Life Settlement Securitization' + BILSM). NO es el modelo propietario de AM Best.
A4: Qué hace el modelo
A5: 1. Proyecta 25 años de flujos de una cartera de 300 vidas por cohortes (beneficios por muerte, primas, gastos, venta de remanente).
A6: 2. Aplica estrés determinístico por nivel de calificación (aaa, aa, a, bbb, bb, base): multiplicador de mortalidad (extensión de LE),
A7: penalidad por pool < 300 vidas, pérdida por default de aseguradoras, aumentos de primas (COI) y haircut del valor remanente.
A8: 3. Corre una cascada (waterfall) secuencial: interés Senior → interés Mezz → reserva de liquidez objetivo → principal Senior → principal Mezz → equity.
A9: 4. Calificación indicada: nivel de estrés más alto en el que el tramo se repaga completo al vencimiento legal (Senior además sin interés impago: pago oportuno).
A10: 5. La hoja 'Ponderacion' ajusta por factores cualitativos (notches) y aplica los chequeos de elegibilidad publicados por AM Best.
A12: Leyenda de colores
A13: Texto azul = input editable · Texto negro = fórmula · Texto verde = vínculo a otra hoja · Relleno amarillo = supuesto clave a validar.
A15: Qué está confirmado por fuentes vs. qué es supuesto
... A23: d) Lea el resultado en 'Resumen'. Detalle de flujos en las hojas CF_aaa … CF_base.

Sheet Resumen
A1: Resumen de calificación indicada
A2: Resultado del modelo ilustrativo. No es una calificación de AM Best ni una opinión de crédito.
A4: Escenario | B4: Mult. efectivo | C4: LE estresada (años) | D4: Pérdida Senior | E4: Pérdida Mezz | F4: Caja mínima c/ notas (USD mm) | G4: Años déficit | H4: WAL Senior | I4: WAL Mezz | J4: Senior pasa | K4: Mezz pasa
A5: aaa | B5: =CF_aaa!C10 -> 0.7 | C5: =CF_aaa!C93 -> 9.3305259 | D5: =CF_aaa!C86 -> 0.85693542 | E5: =CF_aaa!C87 -> 1 | F5: =CF_aaa!C89 -> 0.94001214 | G5: =CF_aaa!C90 -> 0 | H5: =CF_aaa!C91 -> 15.348002 | I5: =CF_aaa!C92 -> 0 | J5: =CF_aaa!C94 -> 0 | K5: =CF_aaa!C95 -> 0
A6: aa | B6: =CF_aa!C10 -> 0.76 | C6: =CF_aa!C93 -> 8.8779547 | D6: =CF_aa!C86 -> 0 | E6: =CF_aa!C87 -> 0.57813148 | F6: =CF_aa!C89 -> 0.64385162 | G6: =CF_aa!C90 -> 0 | H6: =CF_aa!C91 -> 13.243274 | I6: =CF_aa!C92 -> 20.359354 | J6: =CF_aa!C94 -> 1 | K6: =CF_aa!C95 -> 0
A7: a | B7: =CF_a!C10 -> 0.82 | C7: =CF_a!C93 -> 8.4709425 | D7: =CF_a!C86 -> 0 | E7: =CF_a!C87 -> 0 | F7: =CF_a!C89 -> 16.255565 | G7: =CF_a!C90 -> 0 | H7: =CF_a!C91 -> 9.270188 | I7: =CF_a!C92 -> 14.000211 | J7: =CF_a!C94 -> 1 | K7: =CF_a!C95 -> 1
A8: bbb | B8: =CF_bbb!C10 -> 0.88 | C8: =CF_bbb!C93 -> 8.1025877 | D8: =CF_bbb!C86 -> 0 | E8: =CF_bbb!C87 -> 0 | F8: =CF_bbb!C89 -> 21.926041 | G8: =CF_bbb!C90 -> 0 | H8: =CF_bbb!C91 -> 7.0561142 | I8: =CF_bbb!C92 -> 11.15277 | J8: =CF_bbb!C94 -> 1 | K8: =CF_bbb!C95 -> 1
A9: bb | B9: =CF_bb!C10 -> 0.94 | C9: =CF_bb!C93 -> 7.7673238 | D9: =CF_bb!C86 -> 0 | E9: =CF_bb!C87 -> 0 | F9: =CF_bb!C89 -> 25.809697 | G9: =CF_bb!C90 -> 0 | H9: =CF_bb!C91 -> 5.6497336 | I9: =CF_bb!C92 -> 9.407068 | J9: =CF_bb!C94 -> 1 | K9: =CF_bb!C95 -> 1
A10: base | B10: =CF_base!C10 -> 1 | C10: =CF_base!C93 -> 7.4606184 | D10: =CF_base!C86 -> 0 | E10: =CF_base!C87 -> 0 | F10: =CF_base!C89 -> 27.855196 | G10: =CF_base!C90 -> 0 | H10: =CF_base!C91 -> 4.7440768 | I10: =CF_base!C92 -> 8.1423083 | J10: =CF_base!C94 -> 1 | K10: =CF_base!C95 -> 1
A12: Escala | D12: Resultado
A13: 1 | B13: aaa | D13: Senior – índice cuantitativo | F13: =IF(J5=1,1,IF(J6=1,3,IF(J7=1,6,IF(J8=1,9,IF(J9=1,12,14))))) -> 3
A14: 2 | B14: aa+ | D14: Senior – calificación cuantitativa | F14: =INDEX($B$13:$B$26,F13) -> aa
A15: 3 | B15: aa | D15: Mezz – índice cuantitativo | F15: =IF(K5=1,1,IF(K6=1,3,IF(K7=1,6,IF(K8=1,9,IF(K9=1,12,14))))) -> 6
A16: 4 | B16: aa- | D16: Mezz – calificación cuantitativa | F16: =INDEX($B$13:$B$26,F15) -> a
A17: 5 | B17: a+ | D17: Ajuste cualitativo (notches) | F17: =Ponderacion!C31 -> -1
A18: 6 | B18: a
A19: 7 | B19: a- | D19: Senior – calificación indicada final | F19: =INDEX($B$13:$B$26,MIN(14,F13-F17)) -> aa-
A20: 8 | B20: bbb+ | D20: Mezz – calificación indicada final | F20: =INDEX($B$13:$B$26,MIN(14,F15-F17)) -> a-
A21: 9 | B21: bbb
A22: 10 | B22: bbb- | D22: Precio de compra como % del face | F22: =Cartera!C17 -> 0.22222222
A23: 11 | B23: bb+ | D23: Distribuciones a equity – caso base (USD mm) | F23: =CF_base!C96 -> 134.01544
A24: 12 | B24: bb | D24: Equity aportado (reserva inicial, USD mm) | F24: =Supuestos!C9 -> 20
A25: 13 | B25: bb- | D25: Múltiplo de equity – caso base | F25: =IFERROR(F23/F24,0) -> 6.7007721
A26: 14 | B26: b o menor

Sheet Supuestos
A1: Supuestos de estructura y estrés
B3: Parámetro | C3: Valor | D3: Unidad | E3: Fuente / nota
B5: Notas Senior | C5: 75 | D5: USD mm | E5: Supuesto (estructura ilustrativa)
B6: Cupón Senior | C6: 0.065 | D6: % anual | E6: Supuesto
B7: Notas Mezzanine | C7: 25 | D7: USD mm | E7: Supuesto
B8: Cupón Mezzanine | C8: 0.095 | D8: % anual | E8: Supuesto
B9: Reserva de liquidez inicial (fondeada por equity) | C9: 20 | D9: USD mm | E9: Supuesto
B10: Reserva objetivo (meses de primas) | C10: 12 | D10: meses | E10: Supuesto; práctica común de mercado 12–24 meses
B11: Tasa de reinversión de caja | C11: 0.03 | D11: % anual | E11: Supuesto
B12: Gastos fijos (servicer, trustee, tracking) | C12: 0.75 | D12: USD mm/año | E12: Supuesto
B13: Gasto variable sobre face en vigor | C13: 0.0005 | D13: % anual | E13: Supuesto
B14: Valor de venta de cartera remanente al vencimiento legal | C14: 0.2 | D14: % del face | E14: Supuesto
B15: Vencimiento legal (años) – fijo en 25 columnas | C15: 25 | D15: años | E15: Estructura del modelo (no editar)
B16: Umbral de vidas sin estrés adicional | C16: 300 | D16: vidas | E16: AM Best, Life Settlement Securitization (~300 vidas)
... B20: Pérdida tolerada en notas para 'pasar' el escenario | C20: 0 | D20: % del saldo | E20: Supuesto (equivale a pago completo y oportuno)
B22: Matriz de estrés por nivel de calificación (determinística)
B23: Escenario | C23: Multiplicador de mortalidad (q) | D23: Penalidad pool < umbral (resta al mult.) | E23: Pérdida por default de aseguradoras (% beneficio) | F23: Aumento anual de primas (COI) | G23: Haircut valor remanente | H23: Fuente / nota
B24: aaa | C24: 0.7 | D24: 0.05 | E24: 0.06 | F24: 0.02 | G24: 0.5 | H24: Estimación de Claude – calibrar con criterio vigente de AM Best
B25: aa | C25: 0.76 | D25: 0.04 | E25: 0.045 | F25: 0.015 | G25: 0.4 | H25: Estimación de Claude – calibrar con criterio vigente de AM Best
B26: a | C26: 0.82 | D26: 0.03 | E26: 0.03 | F26: 0.01 | G26: 0.3 | H26: Estimación de Claude – calibrar con criterio vigente de AM Best
B27: bbb | C27: 0.88 | D27: 0.02 | E27: 0.02 | F27: 0.005 | G27: 0.2 | H27: Estimación de Claude – calibrar con criterio vigente de AM Best
B28: bb | C28: 0.94 | D28: 0.01 | E28: 0.01 | F28: 0.0025 | G28: 0.1 | H28: Estimación de Claude – calibrar con criterio vigente de AM Best
B29: base | C29: 1 | D29: 0 | E29: 0.005 | F29: 0 | G29: 0 | H29: Caso esperado (LE de los proveedores sin ajuste)
B31: Nota: multiplicador < 1 reduce la probabilidad anual de muerte = extiende la LE (el riesgo central del inversionista). AM Best publica que usa la tabla 2015 VBT (revisión 2026) como base de mortalidad; aquí se aproxima con una curva por cohorte.

Sheet Cartera
A1: Cinta de datos agregada por cohortes (input)
A4: Cohorte | B4: Descripción | C4: Vidas | D4: Face (USD mm) | E4: Edad prom. | F4: q0 (prob. muerte año 1) | G4: Crec. anual de mortalidad | H4: Prima anual (% face) | I4: FSR prom. aseguradoras | J4: Mayor póliza individual (USD mm) | K4: LE implícita base (años) | L4: % del face
A5: C1 | B5: Edad 75–79, salud estándar | C5: 70 | D5: 90 | E5: 77 | F5: 0.045 | G5: 0.11 | H5: 0.04 | I5: A+ | J5: 2.5 | K5: =LE!C4 -> 9.6046412 | L5: =D5/$D$10 -> 0.2
A6: C2 | B6: Edad 80–84, deterioro moderado | C6: 80 | D6: 120 | E6: 82 | F6: 0.065 | G6: 0.1 | H6: 0.05 | I6: A | J6: 3 | K6: =LE!C5 -> 7.9397814 | L6: =D6/$D$10 -> 0.26666667
A7: C3 | B7: Edad 85–89, deterioro significativo | C7: 60 | D7: 100 | E7: 86 | F7: 0.095 | G7: 0.09 | H7: 0.06 | I7: A | J7: 3 | K7: =LE!C6 -> 6.3151825 | L7: =D7/$D$10 -> 0.22222222
A8: C4 | B8: Edad 90+, deterioro severo | C8: 50 | D8: 80 | E8: 91 | F8: 0.14 | G8: 0.08 | H8: 0.07 | I8: A- | J8: 2.5 | K8: =LE!C7 -> 4.814024 | L8: =D8/$D$10 -> 0.17777778
A9: C5 | B9: Edad 70–74, enfermedad crónica | C9: 40 | D9: 60 | E9: 72 | F9: 0.05 | G9: 0.12 | H9: 0.035 | I9: A+ | J9: 2 | K9: =LE!C8 -> 8.725913 | L9: =D9/$D$10 -> 0.13333333
A10: Total / Prom. | C10: =SUM(C5:C9) -> 300 | D10: =SUM(D5:D9) -> 450 | E10: =SUMPRODUCT(E5:E9,D5:D9)/D10 -> 82.155556 | J10: =MAX(J5:J9) -> 3 | K10: =SUMPRODUCT(K5:K9,D5:D9)/D10 -> 7.4608587 | L10: =SUM(L5:L9) -> 1
A13: Datos de underwriting
B14: Antigüedad de reportes LE (meses) | C14: 8
B15: # proveedores de LE independientes por vida | C15: 2
B16: Precio de compra de la cartera (USD mm) | C16: =Supuestos!C5+Supuestos!C7 -> 100
B17: Precio como % del face | C17: =C16/D10 -> 0.22222222
B18: Mayor póliza como % del face | C18: =J10/D10 -> 0.0066666667
A20: Nota: reemplace las cohortes con su cinta real. Para precisión de rating, AM Best trabaja póliza por póliza con las LE de ambos proveedores; las cohortes son una simplificación.

Sheet LE
A1: Supervivencia base por cohorte (sin estrés) – cálculo de LE implícita
A2: Curva: q(t) = MIN(1, q0 × (1+g)^(t−1)). LE ≈ Σ supervivencia fin de año + 0.5. Horizonte 40 años.
A3: Cohorte | C3: LE (años) | D3: 1 | E3: 2 | F3: 3 | G3: 4 | H3: 5 | I3: 6 | J3: 7 | K3: 8 | L3: 9 | M3: 10 | N3: 11 | O3: 12 | P3: 13 | Q3: 14 | R3: 15 | S3: 16 | T3: 17 | U3: 18 | V3: 19 | W3: 20 | X3: 21 | Y3: 22 | Z3: 23 | AA3: 24 | AB3: 25 | AC3: 26 | AD3: 27 | AE3: 28 | AF3: 29 | AG3: 30 | AH3: 31 | AI3: 32 | AJ3: 33 | AK3: 34 | AL3: 35 | AM3: 36 | AN3: 37 | AO3: 38 | AP3: 39 | AQ3: 40
A4: =Cartera!A5 -> C1 | C4: =SUM(D4:AQ4)+0.5 -> 9.6046412 | D4: =1-MIN(1,Cartera!$F$5*(1+Cartera!$G$5)^(1-1)) -> 0.955 | E4: =D4*(1-MIN(1,Cartera!$F$5*(1+Cartera!$G$5)^(2-1))) -> 0.90729775 | F4: =E4*(1-MIN(1,Cartera!$F$5*(1+Cartera!$G$5)^(3-1))) -> 0.85699308 | G4: =F4*(1-MIN(1,Cartera!$F$5*(1+Cartera!$G$5)^(4-1))) -> 0.80425082 | H4: =G4*(1-MIN(1,Cartera!$F$5*(1+Cartera!$G$5)^(5-1))) -> 0.74930989 | I4: =H4*(1-MIN(1,Cartera!$F$5*(1+Cartera!$G$5)^(6-1))) -> 0.69249151 | J4: =I4*(1-MIN(1,Cartera!$F$5*(1+Cartera!$G$5)^(7-1))) -> 0.63420543 | K4: =J4*(1-MIN(1,Cartera!$F$5*(1+Cartera!$G$5)^(8-1))) -> 0.57495339 | L4: =K4*(1-MIN(1,Cartera!$F$5*(1+Cartera!$G$5)^(9-1))) -> 0.51532831 | M4: =L4*(1-MIN(1,Cartera!$F$5*(1+Cartera!$G$5)^(10-1))) -> 0.45600801 | N4: =M4*(1-MIN(1,Cartera!$F$5*(1+Cartera!$G$5)^(11-1))) -> 0.39774207 | O4: =N4*(1-MIN(1,Cartera!$F$5*(1+Cartera!$G$5)^(12-1))) -> 0.34133068 | P4: =O4*(1-MIN(1,Cartera!$F$5*(1+Cartera!$G$5)^(13-1))) -> 0.28759489 | Q4: =P4*(1-MIN(1,Cartera!$F$5*(1+Cartera!$G$5)^(14-1))) -> 0.23733837 | R4: =Q4*(1-MIN(1,Cartera!$F$5*(1+Cartera!$G$5)^(15-1))) -> 0.19130189 | S4: =R4*(1-MIN(1,Cartera!$F$5*(1+Cartera!$G$5)^(16-1))) -> 0.15011334 | T4: =S4*(1-MIN(1,Cartera!$F$5*(1+Cartera!$G$5)^(17-1))) -> 0.11423772 | U4: =T4*(1-MIN(1,Cartera!$F$5*(1+Cartera!$G$5)^(18-1))) -> 0.083932831 | V4: =U4*(1-MIN(1,Cartera!$F$5*(1+Cartera!$G$5)^(19-1))) -> 0.059217979 | W4: =V4*(1-MIN(1,Cartera!$F$5*(1+Cartera!$G$5)^(20-1))) -> 0.039862555 | X4: =W4*(1-MIN(1,Cartera!$F$5*(1+Cartera!$G$5)^(21-1))) -> 0.02540026 | Y4: =X4*(1-MIN(1,Cartera!$F$5*(1+Cartera!$G$5)^(22-1))) -> 0.015171259 | Z4: =Y4*(1-MIN(1,Cartera!$F$5*(1+Cartera!$G$5)^(23-1))) -> 0.0083895417 | AA4: =Z4*(1-MIN(1,Cartera!$F$5*(1+Cartera!$G$5)^(24-1))) -> 0.0042268019 | AB4: =AA4*(1-MIN(1,Cartera!$F$5*(1+Cartera!$G$5)^(25-1))) -> 0.0018988399 | AC4: =AB4*(1-MIN(1,Cartera!$F$5*(1+Cartera!$G$5)^(26-1))) -> 0.00073799195 | AD4: =AC4*(1-MIN(1,Cartera!$F$5*(1+Cartera!$G$5)^(27-1))) -> 0.0002371951 | AE4: =AD4*(1-MIN(1,Cartera!$F$5*(1+Cartera!$G$5)^(28-1))) -> 5.8530442e-05 | AF4: =AE4*(1-MIN(1,Cartera!$F$5*(1+Cartera!$G$5)^(29-1))) -> 9.593399e-06 | AG4: =AF4*(1-MIN(1,Cartera!$F$5*(1+Cartera!$G$5)^(30-1))) -> 6.9009082e-07 | AH4: =AG4*(1-MIN(1,Cartera!$F$5*(1+Cartera!$G$5)^(31-1))) -> 0 | AI4: =AH4*(1-MIN(1,Cartera!$F$5*(1+Cartera!$G$5)^(32-1))) -> 0 | AJ4: =AI4*(1-MIN(1,Cartera!$F$5*(1+Cartera!$G$5)^(33-1))) -> 0 | AK4: =AJ4*(1-MIN(1,Cartera!$F$5*(1+Cartera!$G$5)^(34-1))) -> 0 | AL4: =AK4*(1-MIN(1,Cartera!$F$5*(1+Cartera!$G$5)^(35-1))) -> 0 | AM4: =AL4*(1-MIN(1,Cartera!$F$5*(1+Cartera!$G$5)^(36-1))) -> 0 | AN4: =AM4*(1-MIN(1,Cartera!$F$5*(1+Cartera!$G$5)^(37-1))) -> 0 | AO4: =AN4*(1-MIN(1,Cartera!$F$5*(1+Cartera!$G$5)^(38-1))) -> 0 | AP4: =AO4*(1-MIN(1,Cartera!$F$5*(1+Cartera!$G$5)^(39-1))) -> 0 | AQ4: =AP4*(1-MIN(1,Cartera!$F$5*(1+Cartera!$G$5)^(40-1))) -> 0
A5: =Cartera!A6 -> C2 | C5: =SUM(D5:AQ5)+0.5 -> 7.9397814 | D5: =1-MIN(1,Cartera!$F$6*(1+Cartera!$G$6)^(1-1)) -> 0.935 | E5: =D5*(1-MIN(1,Cartera!$F$6*(1+Cartera!$G$6)^(2-1))) -> 0.8681475 | F5: =E5*(1-MIN(1,Cartera!$F$6*(1+Cartera!$G$6)^(3-1))) -> 0.7998677 | G5: =F5*(1-MIN(1,Cartera!$F$6*(1+Cartera!$G$6)^(4-1))) -> 0.73066715 | H5: =G5*(1-MIN(1,Cartera!$F$6*(1+Cartera!$G$6)^(5-1))) -> 0.66113211 | I5: =H5*(1-MIN(1,Cartera!$F$6*(1+Cartera!$G$6)^(6-1))) -> 0.59192272 | J5: =I5*(1-MIN(1,Cartera!$F$6*(1+Cartera!$G$6)^(7-1))) -> 0.52376195 | K5: =J5*(1-MIN(1,Cartera!$F$6*(1+Cartera!$G$6)^(8-1))) -> 0.4574188 | L5: =K5*(1-MIN(1,Cartera!$F$6*(1+Cartera!$G$6)^(9-1))) -> 0.39368514 | M5: =L5*(1-MIN(1,Cartera!$F$6*(1+Cartera!$G$6)^(10-1))) -> 0.33334636 | N5: =M5*(1-MIN(1,Cartera!$F$6*(1+Cartera!$G$6)^(11-1))) -> 0.27714641 | O5: =N5*(1-MIN(1,Cartera!$F$6*(1+Cartera!$G$6)^(12-1))) -> 0.22574889 | P5: =O5*(1-MIN(1,Cartera!$F$6*(1+Cartera!$G$6)^(13-1))) -> 0.1796966 | Q5: =P5*(1-MIN(1,Cartera!$F$6*(1+Cartera!$G$6)^(14-1))) -> 0.13937311 | R5: =Q5*(1-MIN(1,Cartera!$F$6*(1+Cartera!$G$6)^(15-1))) -> 0.10497062 | S5: =R5*(1-MIN(1,Cartera!$F$6*(1+Cartera!$G$6)^(16-1))) -> 0.076468876 | T5: =S5*(1-MIN(1,Cartera!$F$6*(1+Cartera!$G$6)^(17-1))) -> 0.053629669 | U5: =T5*(1-MIN(1,Cartera!$F$6*(1+Cartera!$G$6)^(18-1))) -> 0.036010147 | V5: =U5*(1-MIN(1,Cartera!$F$6*(1+Cartera!$G$6)^(19-1))) -> 0.022996273 | W5: =V5*(1-MIN(1,Cartera!$F$6*(1+Cartera!$G$6)^(20-1))) -> 0.013854471 | X5: =W5*(1-MIN(1,Cartera!$F$6*(1+Cartera!$G$6)^(21-1))) -> 0.0077960839 | Y5: =X5*(1-MIN(1,Cartera!$F$6*(1+Cartera!$G$6)^(22-1))) -> 0.0040460409 | Z5: =Y5*(1-MIN(1,Cartera!$F$6*(1+Cartera!$G$6)^(23-1))) -> 0.0019052084 | AA5: =Z5*(1-MIN(1,Cartera!$F$6*(1+Cartera!$G$6)^(24-1))) -> 0.00079632059 | AB5: =AA5*(1-MIN(1,Cartera!$F$6*(1+Cartera!$G$6)^(25-1))) -> 0.00028649017 | AC5: =AB5*(1-MIN(1,Cartera!$F$6*(1+Cartera!$G$6)^(26-1))) -> 8.4727781e-05 | AD5: =AC5*(1-MIN(1,Cartera!$F$6*(1+Cartera!$G$6)^(27-1))) -> 1.9090739e-05 | AE5: =AD5*(1-MIN(1,Cartera!$F$6*(1+Cartera!$G$6)^(28-1))) -> 2.8225729e-06 | AF5: =AE5*(1-MIN(1,Cartera!$F$6*(1+Cartera!$G$6)^(29-1))) -> 1.7679303e-07 | AG5: =AF5*(1-MIN(1,Cartera!$F$6*(1+Cartera!$G$6)^(30-1))) -> 0 | AH5: =AG5*(1-MIN(1,Cartera!$F$6*(1+Cartera!$G$6)^(31-1))) -> 0 | AI5: =AH5*(1-MIN(1,Cartera!$F$6*(1+Cartera!$G$6)^(32-1))) -> 0 | AJ5: =AI5*(1-MIN(1,Cartera!$F$6*(1+Cartera!$G$6)^(33-1))) -> 0 | AK5: =AJ5*(1-MIN(1,Cartera!$F$6*(1+Cartera!$G$6)^(34-1))) -> 0 | AL5: =AK5*(1-MIN(1,Cartera!$F$6*(1+Cartera!$G$6)^(35-1))) -> 0 | AM5: =AL5*(1-MIN(1,Cartera!$F$6*(1+Cartera!$G$6)^(36-1))) -> 0 | AN5: =AM5*(1-MIN(1,Cartera!$F$6*(1+Cartera!$G$6)^(37-1))) -> 0 | AO5: =AN5*(1-MIN(1,Cartera!$F$6*(1+Cartera!$G$6)^(38-1))) -> 0 | AP5: =AO5*(1-MIN(1,Cartera!$F$6*(1+Cartera!$G$6)^(39-1))) -> 0 | AQ5: =AP5*(1-MIN(1,Cartera!$F$6*(1+Cartera!$G$6)^(40-1))) -> 0
A6: =Cartera!A7 -> C3 | C6: =SUM(D6:AQ6)+0.5 -> 6.3151825 | D6: =1-MIN(1,Cartera!$F$7*(1+Cartera!$G$7)^(1-1)) -> 0.905 | E6: =D6*(1-MIN(1,Cartera!$F$7*(1+Cartera!$G$7)^(2-1))) -> 0.81128725 | F6: =E6*(1-MIN(1,Cartera!$F$7*(1+Cartera!$G$7)^(3-1))) -> 0.71971766 | G6: =F6*(1-MIN(1,Cartera!$F$7*(1+Cartera!$G$7)^(4-1))) -> 0.63117242 | H6: =G6*(1-MIN(1,Cartera!$F$7*(1+Cartera!$G$7)^(5-1))) -> 0.54653203 | I6: =H6*(1-MIN(1,Cartera!$F$7*(1+Cartera!$G$7)^(6-1))) -> 0.46664584 | J6: =I6*(1-MIN(1,Cartera!$F$7*(1+Cartera!$G$7)^(7-1))) -> 0.39229772 | K6: =J6*(1-MIN(1,Cartera!$F$7*(1+Cartera!$G$7)^(8-1))) -> 0.32416984 | L6: =K6*(1-MIN(1,Cartera!$F$7*(1+Cartera!$G$7)^(9-1))) -> 0.26280661 | M6: =L6*(1-MIN(1,Cartera!$F$7*(1+Cartera!$G$7)^(10-1))) -> 0.20858176 | N6: =M6*(1-MIN(1,Cartera!$F$7*(1+Cartera!$G$7)^(11-1))) -> 0.16167182 | O6: =N6*(1-MIN(1,Cartera!$F$7*(1+Cartera!$G$7)^(12-1))) -> 0.12203951 | P6: =O6*(1-MIN(1,Cartera!$F$7*(1+Cartera!$G$7)^(13-1))) -> 0.089430165 | Q6: =P6*(1-MIN(1,Cartera!$F$7*(1+Cartera!$G$7)^(14-1))) -> 0.063383501 | R6: =Q6*(1-MIN(1,Cartera!$F$7*(1+Cartera!$G$7)^(15-1))) -> 0.043261517 | S6: =R6*(1-MIN(1,Cartera!$F$7*(1+Cartera!$G$7)^(16-1))) -> 0.028291482 | T6: =S6*(1-MIN(1,Cartera!$F$7*(1+Cartera!$G$7)^(17-1))) -> 0.017620527 | U6: =T6*(1-MIN(1,Cartera!$F$7*(1+Cartera!$G$7)^(18-1))) -> 0.010376285 | V6: =U6*(1-MIN(1,Cartera!$F$7*(1+Cartera!$G$7)^(19-1))) -> 0.0057263973 | W6: =V6*(1-MIN(1,Cartera!$F$7*(1+Cartera!$G$7)^(20-1))) -> 0.0029292938 | X6: =W6*(1-MIN(1,Cartera!$F$7*(1+Cartera!$G$7)^(21-1))) -> 0.001369682 | Y6: =X6*(1-MIN(1,Cartera!$F$7*(1+Cartera!$G$7)^(22-1))) -> 0.00057480524 | Z6: =Y6*(1-MIN(1,Cartera!$F$7*(1+Cartera!$G$7)^(23-1))) -> 0.00021120239 | AA6: =Z6*(1-MIN(1,Cartera!$F$7*(1+Cartera!$G$7)^(24-1))) -> 6.5578749e-05 | AB6: =AA6*(1-MIN(1,Cartera!$F$7*(1+Cartera!$G$7)^(25-1))) -> 1.629285e-05 | AC6: =AB6*(1-MIN(1,Cartera!$F$7*(1+Cartera!$G$7)^(26-1))) -> 2.9458668e-06 | AD6: =AC6*(1-MIN(1,Cartera!$F$7*(1+Cartera!$G$7)^(27-1))) -> 3.1544341e-07 | AE6: =AD6*(1-MIN(1,Cartera!$F$7*(1+Cartera!$G$7)^(28-1))) -> 8.4277638e-09 | AF6: =AE6*(1-MIN(1,Cartera!$F$7*(1+Cartera!$G$7)^(29-1))) -> 0 | AG6: =AF6*(1-MIN(1,Cartera!$F$7*(1+Cartera!$G$7)^(30-1))) -> 0 | AH6: =AG6*(1-MIN(1,Cartera!$F$7*(1+Cartera!$G$7)^(31-1))) -> 0 | AI6: =AH6*(1-MIN(1,Cartera!$F$7*(1+Cartera!$G$7)^(32-1))) -> 0 | AJ6: =AI6*(1-MIN(1,Cartera!$F$7*(1+Cartera!$G$7)^(33-1))) -> 0 | AK6: =AJ6*(1-MIN(1,Cartera!$F$7*(1+Cartera!$G$7)^(34-1))) -> 0 | AL6: =AK6*(1-MIN(1,Cartera!$F$7*(1+Cartera!$G$7)^(35-1))) -> 0 | AM6: =AL6*(1-MIN(1,Cartera!$F$7*(1+Cartera!$G$7)^(36-1))) -> 0 | AN6: =AM6*(1-MIN(1,Cartera!$F$7*(1+Cartera!$G$7)^(37-1))) -> 0 | AO6: =AN6*(1-MIN(1,Cartera!$F$7*(1+Cartera!$G$7)^(38-1))) -> 0 | AP6: =AO6*(1-MIN(1,Cartera!$F$7*(1+Cartera!$G$7)^(39-1))) -> 0 | AQ6: =AP6*(1-MIN(1,Cartera!$F$7*(1+Cartera!$G$7)^(40-1))) -> 0
A7: =Cartera!A8 -> C4 | C7: =SUM(D7:AQ7)+0.5 -> 4.814024 | D7: =1-MIN(1,Cartera!$F$8*(1+Cartera!$G$8)^(1-1)) -> 0.86 | E7: =D7*(1-MIN(1,Cartera!$F$8*(1+Cartera!$G$8)^(2-1))) -> 0.729968 | F7: =E7*(1-MIN(1,Cartera!$F$8*(1+Cartera!$G$8)^(3-1))) -> 0.61076715 | G7: =F7*(1-MIN(1,Cartera!$F$8*(1+Cartera!$G$8)^(4-1))) -> 0.50305245 | H7: =G7*(1-MIN(1,Cartera!$F$8*(1+Cartera!$G$8)^(5-1))) -> 0.40723683 | I7: =H7*(1-MIN(1,Cartera!$F$8*(1+Cartera!$G$8)^(6-1))) -> 0.32346579 | J7: =I7*(1-MIN(1,Cartera!$F$8*(1+Cartera!$G$8)^(7-1))) -> 0.25160386 | K7: =J7*(1-MIN(1,Cartera!$F$8*(1+Cartera!$G$8)^(8-1))) -> 0.19123518 | L7: =K7*(1-MIN(1,Cartera!$F$8*(1+Cartera!$G$8)^(9-1))) -> 0.14168037 | M7: =L7*(1-MIN(1,Cartera!$F$8*(1+Cartera!$G$8)^(10-1))) -> 0.10202961 | N7: =M7*(1-MIN(1,Cartera!$F$8*(1+Cartera!$G$8)^(11-1))) -> 0.07119121 | O7: =N7*(1-MIN(1,Cartera!$F$8*(1+Cartera!$G$8)^(12-1))) -> 0.047952302 | P7: =O7*(1-MIN(1,Cartera!$F$8*(1+Cartera!$G$8)^(13-1))) -> 0.031047014 | Q7: =P7*(1-MIN(1,Cartera!$F$8*(1+Cartera!$G$8)^(14-1))) -> 0.019225947 | R7: =Q7*(1-MIN(1,Cartera!$F$8*(1+Cartera!$G$8)^(15-1))) -> 0.011320101 | S7: =R7*(1-MIN(1,Cartera!$F$8*(1+Cartera!$G$8)^(16-1))) -> 0.0062928024 | T7: =S7*(1-MIN(1,Cartera!$F$8*(1+Cartera!$G$8)^(17-1))) -> 0.0032745732 | U7: =T7*(1-MIN(1,Cartera!$F$8*(1+Cartera!$G$8)^(18-1))) -> 0.001578336 | V7: =U7*(1-MIN(1,Cartera!$F$8*(1+Cartera!$G$8)^(19-1))) -> 0.0006953474 | W7: =V7*(1-MIN(1,Cartera!$F$8*(1+Cartera!$G$8)^(20-1))) -> 0.00027521979 | X7: =W7*(1-MIN(1,Cartera!$F$8*(1+Cartera!$G$8)^(21-1))) -> 9.5629519e-05 | Y7: =X7*(1-MIN(1,Cartera!$F$8*(1+Cartera!$G$8)^(22-1))) -> 2.8235886e-05 | Z7: =Y7*(1-MIN(1,Cartera!$F$8*(1+Cartera!$G$8)^(23-1))) -> 6.7451109e-06 | AA7: =Z7*(1-MIN(1,Cartera!$F$8*(1+Cartera!$G$8)^(24-1))) -> 1.2005966e-06 | AB7: =AA7*(1-MIN(1,Cartera!$F$8*(1+Cartera!$G$8)^(25-1))) -> 1.347486e-07 | AC7: =AB7*(1-MIN(1,Cartera!$F$8*(1+Cartera!$G$8)^(26-1))) -> 5.5534577e-09 | AD7: =AC7*(1-MIN(1,Cartera!$F$8*(1+Cartera!$G$8)^(27-1))) -> 0 | AE7: =AD7*(1-MIN(1,Cartera!$F$8*(1+Cartera!$G$8)^(28-1))) -> 0 | AF7: =AE7*(1-MIN(1,Cartera!$F$8*(1+Cartera!$G$8)^(29-1))) -> 0 | AG7: =AF7*(1-MIN(1,Cartera!$F$8*(1+Cartera!$G$8)^(30-1))) -> 0 | AH7: =AG7*(1-MIN(1,Cartera!$F$8*(1+Cartera!$G$8)^(31-1))) -> 0 | AI7: =AH7*(1-MIN(1,Cartera!$F$8*(1+Cartera!$G$8)^(32-1))) -> 0 | AJ7: =AI7*(1-MIN(1,Cartera!$F$8*(1+Cartera!$G$8)^(33-1))) -> 0 | AK7: =AJ7*(1-MIN(1,Cartera!$F$8*(1+Cartera!$G$8)^(34-1))) -> 0 | AL7: =AK7*(1-MIN(1,Cartera!$F$8*(1+Cartera!$G$8)^(35-1))) -> 0 | AM7: =AL7*(1-MIN(1,Cartera!$F$8*(1+Cartera!$G$8)^(36-1))) -> 0 | AN7: =AM7*(1-MIN(1,Cartera!$F$8*(1+Cartera!$G$8)^(37-1))) -> 0 | AO7: =AN7*(1-MIN(1,Cartera!$F$8*(1+Cartera!$G$8)^(38-1))) -> 0 | AP7: =AO7*(1-MIN(1,Cartera!$F$8*(1+Cartera!$G$8)^(39-1))) -> 0 | AQ7: =AP7*(1-MIN(1,Cartera!$F$8*(1+Cartera!$G$8)^(40-1))) -> 0
A8: =Cartera!A9 -> C5 | C8: =SUM(D8:AQ8)+0.5 -> 8.725913 | D8: =1-MIN(1,Cartera!$F$9*(1+Cartera!$G$9)^(1-1)) -> 0.95 | E8: =D8*(1-MIN(1,Cartera!$F$9*(1+Cartera!$G$9)^(2-1))) -> 0.8968 | F8: =E8*(1-MIN(1,Cartera!$F$9*(1+Cartera!$G$9)^(3-1))) -> 0.8405527 | G8: =F8*(1-MIN(1,Cartera!$F$9*(1+Cartera!$G$9)^(4-1))) -> 0.7815069 | H8: =G8*(1-MIN(1,Cartera!$F$9*(1+Cartera!$G$9)^(5-1))) -> 0.72002109 | I8: =H8*(1-MIN(1,Cartera!$F$9*(1+Cartera!$G$9)^(6-1))) -> 0.65657493 | J8: =I8*(1-MIN(1,Cartera!$F$9*(1+Cartera!$G$9)^(7-1))) -> 0.59177681 | K8: =J8*(1-MIN(1,Cartera!$F$9*(1+Cartera!$G$9)^(8-1))) -> 0.52636531 | L8: =K8*(1-MIN(1,Cartera!$F$9*(1+Cartera!$G$9)^(9-1))) -> 0.46120225 | M8: =L8*(1-MIN(1,Cartera!$F$9*(1+Cartera!$G$9)^(10-1))) -> 0.39725474 | N8: =M8*(1-MIN(1,Cartera!$F$9*(1+Cartera!$G$9)^(11-1))) -> 0.3355641 | O8: =N8*(1-MIN(1,Cartera!$F$9*(1+Cartera!$G$9)^(12-1))) -> 0.27720027 | P8: =O8*(1-MIN(1,Cartera!$F$9*(1+Cartera!$G$9)^(13-1))) -> 0.22320199 | Q8: =P8*(1-MIN(1,Cartera!$F$9*(1+Cartera!$G$9)^(14-1))) -> 0.17450497 | R8: =Q8*(1-MIN(1,Cartera!$F$9*(1+Cartera!$G$9)^(15-1))) -> 0.1318637 | S8: =R8*(1-MIN(1,Cartera!$F$9*(1+Cartera!$G$9)^(16-1))) -> 0.095775471 | T8: =S8*(1-MIN(1,Cartera!$F$9*(1+Cartera!$G$9)^(17-1))) -> 0.066418404 | U8: =T8*(1-MIN(1,Cartera!$F$9*(1+Cartera!$G$9)^(18-1))) -> 0.04361683 | V8: =U8*(1-MIN(1,Cartera!$F$9*(1+Cartera!$G$9)^(19-1))) -> 0.026846234 | W8: =V8*(1-MIN(1,Cartera!$F$9*(1+Cartera!$G$9)^(20-1))) -> 0.015285223 | X8: =W8*(1-MIN(1,Cartera!$F$9*(1+Cartera!$G$9)^(21-1))) -> 0.007912936 | Y8: =X8*(1-MIN(1,Cartera!$F$9*(1+Cartera!$G$9)^(22-1))) -> 0.003638428 | Z8: =Y8*(1-MIN(1,Cartera!$F$9*(1+Cartera!$G$9)^(23-1))) -> 0.0014371226 | AA8: =Z8*(1-MIN(1,Cartera!$F$9*(1+Cartera!$G$9)^(24-1))) -> 0.00046330339 | AB8: =AA8*(1-MIN(1,Cartera!$F$9*(1+Cartera!$G$9)^(25-1))) -> 0.00011168788 | AC8: =AB8*(1-MIN(1,Cartera!$F$9*(1+Cartera!$G$9)^(26-1))) -> 1.6752822e-05 | AD8: =AC8*(1-MIN(1,Cartera!$F$9*(1+Cartera!$G$9)^(27-1))) -> 8.0407503e-07 | AE8: =AD8*(1-MIN(1,Cartera!$F$9*(1+Cartera!$G$9)^(28-1))) -> 0 | AF8: =AE8*(1-MIN(1,Cartera!$F$9*(1+Cartera!$G$9)^(29-1))) -> 0 | AG8: =AF8*(1-MIN(1,Cartera!$F$9*(1+Cartera!$G$9)^(30-1))) -> 0 | AH8: =AG8*(1-MIN(1,Cartera!$F$9*(1+Cartera!$G$9)^(31-1))) -> 0 | AI8: =AH8*(1-MIN(1,Cartera!$F$9*(1+Cartera!$G$9)^(32-1))) -> 0 | AJ8: =AI8*(1-MIN(1,Cartera!$F$9*(1+Cartera!$G$9)^(33-1))) -> 0 | AK8: =AJ8*(1-MIN(1,Cartera!$F$9*(1+Cartera!$G$9)^(34-1))) -> 0 | AL8: =AK8*(1-MIN(1,Cartera!$F$9*(1+Cartera!$G$9)^(35-1))) -> 0 | AM8: =AL8*(1-MIN(1,Cartera!$F$9*(1+Cartera!$G$9)^(36-1))) -> 0 | AN8: =AM8*(1-MIN(1,Cartera!$F$9*(1+Cartera!$G$9)^(37-1))) -> 0 | AO8: =AN8*(1-MIN(1,Cartera!$F$9*(1+Cartera!$G$9)^(38-1))) -> 0 | AP8: =AO8*(1-MIN(1,Cartera!$F$9*(1+Cartera!$G$9)^(39-1))) -> 0 | AQ8: =AP8*(1-MIN(1,Cartera!$F$9*(1+Cartera!$G$9)^(40-1))) -> 0

Sheet CF_aaa
A1: Flujo de caja y cascada – escenario aaa
A2: Escenario | C2: aaa
A3: Año | D3: 1 | E3: 2 | F3: 3 | G3: 4 | H3: 5 | I3: 6 | J3: 7 | K3: 8 | L3: 9 | M3: 10 | N3: 11 | O3: 12 | P3: 13 | Q3: 14 | R3: 15 | S3: 16 | T3: 17 | U3: 18 | V3: 19 | W3: 20 | X3: 21 | Y3: 22 | Z3: 23 | AA3: 24 | AB3: 25
A5: Multiplicador de mortalidad | C5: =Supuestos!C24 -> 0.7
A6: Penalidad pool pequeño | C6: =Supuestos!D24 -> 0.05
A7: Pérdida default aseguradoras | C7: =Supuestos!E24 -> 0.06
A8: Aumento anual de primas | C8: =Supuestos!F24 -> 0.02
A9: Haircut valor remanente | C9: =Supuestos!G24 -> 0.5
A10: Multiplicador efectivo | C10: =MAX(0,C5-IF(Cartera!C10<Supuestos!C16,C6,0)) -> 0.7
A12: =Cartera!A5&" – "&Cartera!B5 -> C1 – Edad 75–79, salud estándar
B13: q estresada | D13: =MIN(1,Cartera!$F$5*(1+Cartera!$G$5)^(D$3-1)*$C$10) -> 0.0315 | E13: =MIN(1,Cartera!$F$5*(1+Cartera!$G$5)^(E$3-1)*$C$10) -> 0.034965 | F13: =MIN(1,Cartera!$F$5*(1+Cartera!$G$5)^(F$3-1)*$C$10) -> 0.03881115 | G13: =MIN(1,Cartera!$F$5*(1+Cartera!$G$5)^(G$3-1)*$C$10) -> 0.043080377 | H13: =MIN(1,Cartera!$F$5*(1+Cartera!$G$5)^(H$3-1)*$C$10) -> 0.047819218 | I13: =MIN(1,Cartera!$F$5*(1+Cartera!$G$5)^(I$3-1)*$C$10) -> 0.053079332 | J13: =MIN(1,Cartera!$F$5*(1+Cartera!$G$5)^(J$3-1)*$C$10) -> 0.058918058 | K13: =MIN(1,Cartera!$F$5*(1+Cartera!$G$5)^(K$3-1)*$C$10) -> 0.065399045 | ... AB13: =MIN(1,Cartera!$F$5*(1+Cartera!$G$5)^(AB$3-1)*$C$10) -> 0.38553343
B14: Supervivencia inicio | C14: LE estresada → | D14: =1 -> 1 | E14: =D18 -> 0.9685 | F14: =E18 -> 0.9346364 | G14: =F18 -> 0.89836208 | H14: =G18 -> 0.85966031 | I14: =H18 -> 0.81855202 | J14: =I18 -> 0.77510383 | K14: =J18 -> 0.72943622 | L14: =K18 -> 0.68173178 | ... AB14: =AA18 -> 0.02725588
B15: Muertes (fracción) | D15: =D14*D13 -> 0.0315 | E15: =E14*E13 -> 0.033863602 | F15: =F14*F13 -> 0.036274313 | G15: =G14*G13 -> 0.038701777 | H15: =H14*H13 -> 0.041108284 | I15: =I14*I13 -> 0.043448195 | J15: =J14*J13 -> 0.045667613 | K15: =K14*K13 -> 0.047704432 | ... AB15: =AB14*AB13 -> 0.010508053
B16: Beneficio por muerte bruto (USD mm) | D16: =D15*Cartera!$D$5 -> 2.835 | E16: =E15*Cartera!$D$5 -> 3.0477242 | F16: =F15*Cartera!$D$5 -> 3.2646882 | G16: =G15*Cartera!$D$5 -> 3.4831599 | H16: =H15*Cartera!$D$5 -> 3.6997455 | I16: =I15*Cartera!$D$5 -> 3.9103375 | J16: =J15*Cartera!$D$5 -> 4.1100851 | K16: =K15*Cartera!$D$5 -> 4.2933989 | ... AB16: =AB15*Cartera!$D$5 -> 0.94572476
B17: Primas pagadas (USD mm) | D17: =D14*Cartera!$D$5*Cartera!$H$5*(1+$C$8)^(D$3-1) -> 3.6 | E17: =E14*Cartera!$D$5*Cartera!$H$5*(1+$C$8)^(E$3-1) -> 3.556332 | F17: =F14*Cartera!$D$5*Cartera!$H$5*(1+$C$8)^(F$3-1) -> 3.5006245 | G17: =G14*Cartera!$D$5*Cartera!$H$5*(1+$C$8)^(G$3-1) -> 3.4320565 | H17: =H14*Cartera!$D$5*Cartera!$H$5*(1+$C$8)^(H$3-1) -> 3.3498863 | I17: =I14*Cartera!$D$5*Cartera!$H$5*(1+$C$8)^(I$3-1) -> 3.2534913 | J17: =J14*Cartera!$D$5*Cartera!$H$5*(1+$C$8)^(J$3-1) -> 3.1424141 | K17: =K14*Cartera!$D$5*Cartera!$H$5*(1+$C$8)^(K$3-1) -> 3.0164145 | ... AB17: =AB14*Cartera!$D$5*Cartera!$H$5*(1+$C$8)^(AB$3-1) -> 0.15782174
B18: Supervivencia fin | C18: =SUM(D18:AB18)+0.5 -> 11.681772 | D18: =D14-D15 -> 0.9685 | E18: =E14-E15 -> 0.9346364 | F18: =F14-F15 -> 0.89836208 | G18: =G14-G15 -> 0.85966031 | H18: =H14-H15 -> 0.81855202 | I18: =I14-I15 -> 0.77510383 | J18: =J14-J15 -> 0.72943622 | K18: =K14-K15 -> 0.68173178 | ... AB18: =AB14-AB15 -> 0.016747827
A20: =Cartera!A6&" – "&Cartera!B6 -> C2 – Edad 80–84, deterioro moderado
B21: q estresada | D21: =MIN(1,Cartera!$F$6*(1+Cartera!$G$6)^(D$3-1)*$C$10) -> 0.0455 | E21: =MIN(1,Cartera!$F$6*(1+Cartera!$G$6)^(E$3-1)*$C$10) -> 0.05005 | F21: =MIN(1,Cartera!$F$6*(1+Cartera!$G$6)^(F$3-1)*$C$10) -> 0.055055 | G21: =MIN(1,Cartera!$F$6*(1+Cartera!$G$6)^(G$3-1)*$C$10) -> 0.0605605 | H21: =MIN(1,Cartera!$F$6*(1+Cartera!$G$6)^(H$3-1)*$C$10) -> 0.06661655 | I21: =MIN(1,Cartera!$F$6*(1+Cartera!$G$6)^(I$3-1)*$C$10) -> 0.073278205 | J21: =MIN(1,Cartera!$F$6*(1+Cartera!$G$6)^(J$3-1)*$C$10) -> 0.080606025 | K21: =MIN(1,Cartera!$F$6*(1+Cartera!$G$6)^(K$3-1)*$C$10) -> 0.088666628 | ... AB21: =MIN(1,Cartera!$F$6*(1+Cartera!$G$6)^(AB$3-1)*$C$10) -> 0.44816284
B22: Supervivencia inicio | C22: LE estresada → | D22: =1 -> 1 | E22: =D26 -> 0.9545 | F22: =E26 -> 0.90672728 | G22: =F26 -> 0.8568074 | H22: =G26 -> 0.80491872 | I22: =H26 -> 0.75129781 | J22: =I26 -> 0.69624406 | K22: =J26 -> 0.64012259 | L22: =K26 -> 0.58336508 | ... AB22: =AA26 -> 0.0098460628
B23: Muertes (fracción) | D23: =D22*D21 -> 0.0455 | E23: =E22*E21 -> 0.047772725 | F23: =F22*F21 -> 0.04991987 | G23: =G22*G21 -> 0.051888685 | H23: =H22*H21 -> 0.053620908 | I23: =I22*I21 -> 0.055053755 | J23: =J22*J21 -> 0.056121466 | K23: =K22*K21 -> 0.056757512 | ... AB23: =AB22*AB21 -> 0.0044126394
B24: Beneficio por muerte bruto (USD mm) | D24: =D23*Cartera!$D$6 -> 5.46 | E24: =E23*Cartera!$D$6 -> 5.732727 | F24: =F23*Cartera!$D$6 -> 5.9903844 | G24: =G23*Cartera!$D$6 -> 6.2266422 | H24: =H23*Cartera!$D$6 -> 6.434509 | I24: =I23*Cartera!$D$6 -> 6.6064506 | J24: =J23*Cartera!$D$6 -> 6.7345759 | K24: =K23*Cartera!$D$6 -> 6.8109014 | ... AB24: =AB23*Cartera!$D$6 -> 0.52951673
B25: Primas pagadas (USD mm) | D25: =D22*Cartera!$D$6*Cartera!$H$6*(1+$C$8)^(D$3-1) -> 6 | E25: =E22*Cartera!$D$6*Cartera!$H$6*(1+$C$8)^(E$3-1) -> 5.84154 | F25: =F22*Cartera!$D$6*Cartera!$H$6*(1+$C$8)^(F$3-1) -> 5.6601543 | G25: =G22*Cartera!$D$6*Cartera!$H$6*(1+$C$8)^(G$3-1) -> 5.4555052 | H25: =H22*Cartera!$D$6*Cartera!$H$6*(1+$C$8)^(H$3-1) -> 5.2276195 | I25: =I22*Cartera!$D$6*Cartera!$H$6*(1+$C$8)^(I$3-1) -> 4.9769609 | J25: =J22*Cartera!$D$6*Cartera!$H$6*(1+$C$8)^(J$3-1) -> 4.7045033 | K25: =K22*Cartera!$D$6*Cartera!$H$6*(1+$C$8)^(K$3-1) -> 4.4117979 | ... AB25: =AB22*Cartera!$D$6*Cartera!$H$6*(1+$C$8)^(AB$3-1) -> 0.095020645
B26: Supervivencia fin | C26: =SUM(D26:AB26)+0.5 -> 9.9050249 | D26: =D22-D23 -> 0.9545 | E26: =E22-E23 -> 0.90672728 | F26: =F22-F23 -> 0.8568074 | G26: =G22-G23 -> 0.80491872 | H26: =H22-H23 -> 0.75129781 | I26: =I22-I23 -> 0.69624406 | J26: =J22-J23 -> 0.64012259 | K26: =K22-K23 -> 0.58336508 | ... AB26: =AB22-AB23 -> 0.0054334233
A28: =Cartera!A7&" – "&Cartera!B7 -> C3 – Edad 85–89, deterioro significativo
B29: q estresada | D29: =MIN(1,Cartera!$F$7*(1+Cartera!$G$7)^(D$3-1)*$C$10) -> 0.0665 | E29: =MIN(1,Cartera!$F$7*(1+Cartera!$G$7)^(E$3-1)*$C$10) -> 0.072485 | F29: =MIN(1,Cartera!$F$7*(1+Cartera!$G$7)^(F$3-1)*$C$10) -> 0.07900865 | G29: =MIN(1,Cartera!$F$7*(1+Cartera!$G$7)^(G$3-1)*$C$10) -> 0.086119428 | H29: =MIN(1,Cartera!$F$7*(1+Cartera!$G$7)^(H$3-1)*$C$10) -> 0.093870177 | I29: =MIN(1,Cartera!$F$7*(1+Cartera!$G$7)^(I$3-1)*$C$10) -> 0.10231849 | J29: =MIN(1,Cartera!$F$7*(1+Cartera!$G$7)^(J$3-1)*$C$10) -> 0.11152716 | K29: =MIN(1,Cartera!$F$7*(1+Cartera!$G$7)^(K$3-1)*$C$10) -> 0.1215646 | ... AB29: =MIN(1,Cartera!$F$7*(1+Cartera!$G$7)^(AB$3-1)*$C$10) -> 0.52608703
B30: Supervivencia inicio | C30: LE estresada → | D30: =1 -> 1 | E30: =D34 -> 0.9335 | F30: =E34 -> 0.86583525 | G30: =F34 -> 0.79742678 | H30: =G34 -> 0.72875284 | I30: =H34 -> 0.66034468 | J30: =I34 -> 0.59277921 | K30: =J34 -> 0.52666823 | L30: =K34 -> 0.46264402 | ... AB30: =AA34 -> 0.0023239352
B31: Muertes (fracción) | D31: =D30*D29 -> 0.0665 | E31: =E30*E29 -> 0.067664747 | F31: =F30*F29 -> 0.068408474 | G31: =G30*G29 -> 0.068673938 | H31: =H30*H29 -> 0.068408158 | I31: =I30*I29 -> 0.067565473 | J31: =J30*J29 -> 0.06611098 | K31: =K30*K29 -> 0.064024213 | ... AB31: =AB30*AB29 -> 0.0012225922
B32: Beneficio por muerte bruto (USD mm) | D32: =D31*Cartera!$D$7 -> 6.65 | E32: =E31*Cartera!$D$7 -> 6.7664748 | F32: =F31*Cartera!$D$7 -> 6.8408474 | G32: =G31*Cartera!$D$7 -> 6.8673938 | H32: =H31*Cartera!$D$7 -> 6.8408158 | I32: =I31*Cartera!$D$7 -> 6.7565473 | J32: =J31*Cartera!$D$7 -> 6.611098 | K32: =K31*Cartera!$D$7 -> 6.4024213 | ... AB32: =AB31*Cartera!$D$7 -> 0.12225922
B33: Primas pagadas (USD mm) | D33: =D30*Cartera!$D$7*Cartera!$H$7*(1+$C$8)^(D$3-1) -> 6 | E33: =E30*Cartera!$D$7*Cartera!$H$7*(1+$C$8)^(E$3-1) -> 5.71302 | F33: =F30*Cartera!$D$7*Cartera!$H$7*(1+$C$8)^(F$3-1) -> 5.40489 | G33: =G30*Cartera!$D$7*Cartera!$H$7*(1+$C$8)^(G$3-1) -> 5.0774141 | H33: =H30*Cartera!$D$7*Cartera!$H$7*(1+$C$8)^(H$3-1) -> 4.7329531 | I33: =I30*Cartera!$D$7*Cartera!$H$7*(1+$C$8)^(I$3-1) -> 4.3744433 | J33: =J30*Cartera!$D$7*Cartera!$H$7*(1+$C$8)^(J$3-1) -> 4.005394 | K33: =K30*Cartera!$D$7*Cartera!$H$7*(1+$C$8)^(K$3-1) -> 3.6298575 | ... AB33: =AB30*Cartera!$D$7*Cartera!$H$7*(1+$C$8)^(AB$3-1) -> 0.022427424
B34: Supervivencia fin | C34: =SUM(D34:AB34)+0.5 -> 8.1029851 | D34: =D30-D31 -> 0.9335 | E34: =E30-E31 -> 0.86583525 | F34: =F30-F31 -> 0.79742678 | G34: =G30-G31 -> 0.72875284 | H34: =H30-H31 -> 0.66034468 | I34: =I30-I31 -> 0.59277921 | J34: =J30-J31 -> 0.52666823 | K34: =K30-K31 -> 0.46264402 | ... AB34: =AB30-AB31 -> 0.001101343
A36: =Cartera!A8&" – "&Cartera!B8 -> C4 – Edad 90+, deterioro severo
B37: q estresada | D37: =MIN(1,Cartera!$F$8*(1+Cartera!$G$8)^(D$3-1)*$C$10) -> 0.098 | E37: =MIN(1,Cartera!$F$8*(1+Cartera!$G$8)^(E$3-1)*$C$10) -> 0.10584 | F37: =MIN(1,Cartera!$F$8*(1+Cartera!$G$8)^(F$3-1)*$C$10) -> 0.1143072 | G37: =MIN(1,Cartera!$F$8*(1+Cartera!$G$8)^(G$3-1)*$C$10) -> 0.12345178 | H37: =MIN(1,Cartera!$F$8*(1+Cartera!$G$8)^(H$3-1)*$C$10) -> 0.13332792 | I37: =MIN(1,Cartera!$F$8*(1+Cartera!$G$8)^(I$3-1)*$C$10) -> 0.14399415 | J37: =MIN(1,Cartera!$F$8*(1+Cartera!$G$8)^(J$3-1)*$C$10) -> 0.15551368 | K37: =MIN(1,Cartera!$F$8*(1+Cartera!$G$8)^(K$3-1)*$C$10) -> 0.16795478 | ... AB37: =MIN(1,Cartera!$F$8*(1+Cartera!$G$8)^(AB$3-1)*$C$10) -> 0.62143571
B38: Supervivencia inicio | C38: LE estresada → | D38: =1 -> 1 | E38: =D42 -> 0.902 | F38: =E42 -> 0.80653232 | G38: =F42 -> 0.71433987 | H38: =G42 -> 0.62615334 | I38: =H42 -> 0.54266962 | J38: =I42 -> 0.46452837 | K38: =J42 -> 0.39228785 | L38: =K42 -> 0.32640123 | ... AB38: =AA42 -> 0.00028759525
B39: Muertes (fracción) | D39: =D38*D37 -> 0.098 | E39: =E38*E37 -> 0.09546768 | F39: =F38*F37 -> 0.092192451 | G39: =G38*G37 -> 0.088186525 | H39: =H38*H37 -> 0.083483722 | I39: =I38*I37 -> 0.078141252 | J39: =J38*J37 -> 0.072240518 | K39: =K38*K37 -> 0.065886619 | ... AB39: =AB38*AB37 -> 0.00017872196
B40: Beneficio por muerte bruto (USD mm) | D40: =D39*Cartera!$D$8 -> 7.84 | E40: =E39*Cartera!$D$8 -> 7.6374144 | F40: =F39*Cartera!$D$8 -> 7.3753961 | G40: =G39*Cartera!$D$8 -> 7.054922 | H40: =H39*Cartera!$D$8 -> 6.6786977 | I40: =I39*Cartera!$D$8 -> 6.2513001 | J40: =J39*Cartera!$D$8 -> 5.7792414 | K40: =K39*Cartera!$D$8 -> 5.2709295 | ... AB40: =AB39*Cartera!$D$8 -> 0.014297757
B41: Primas pagadas (USD mm) | D41: =D38*Cartera!$D$8*Cartera!$H$8*(1+$C$8)^(D$3-1) -> 5.6 | E41: =E38*Cartera!$D$8*Cartera!$H$8*(1+$C$8)^(E$3-1) -> 5.152224 | F41: =F38*Cartera!$D$8*Cartera!$H$8*(1+$C$8)^(F$3-1) -> 4.6990509 | G41: =G38*Cartera!$D$8*Cartera!$H$8*(1+$C$8)^(G$3-1) -> 4.2451538 | H41: =H38*Cartera!$D$8*Cartera!$H$8*(1+$C$8)^(H$3-1) -> 3.7955037 | I41: =I38*Cartera!$D$8*Cartera!$H$8*(1+$C$8)^(I$3-1) -> 3.3552462 | J41: =J38*Cartera!$D$8*Cartera!$H$8*(1+$C$8)^(J$3-1) -> 2.9295526 | K41: =K38*Cartera!$D$8*Cartera!$H$8*(1+$C$8)^(K$3-1) -> 2.5234464 | ... AB41: =AB38*Cartera!$D$8*Cartera!$H$8*(1+$C$8)^(AB$3-1) -> 0.0025904419
B42: Supervivencia fin | C42: =SUM(D42:AB42)+0.5 -> 6.3728464 | D42: =D38-D39 -> 0.902 | E42: =E38-E39 -> 0.80653232 | F42: =F38-F39 -> 0.71433987 | G42: =G38-G39 -> 0.62615334 | H42: =H38-H39 -> 0.54266962 | I42: =I38-I39 -> 0.46452837 | J42: =J38-J39 -> 0.39228785 | K42: =K38-K39 -> 0.32640123 | ... AB42: =AB38-AB39 -> 0.00010887329
A44: =Cartera!A9&" – "&Cartera!B9 -> C5 – Edad 70–74, enfermedad crónica
B45: q estresada | D45: =MIN(1,Cartera!$F$9*(1+Cartera!$G$9)^(D$3-1)*$C$10) -> 0.035 | E45: =MIN(1,Cartera!$F$9*(1+Cartera!$G$9)^(E$3-1)*$C$10) -> 0.0392 | F45: =MIN(1,Cartera!$F$9*(1+Cartera!$G$9)^(F$3-1)*$C$10) -> 0.043904 | G45: =MIN(1,Cartera!$F$9*(1+Cartera!$G$9)^(G$3-1)*$C$10) -> 0.04917248 | H45: =MIN(1,Cartera!$F$9*(1+Cartera!$G$9)^(H$3-1)*$C$10) -> 0.055073178 | I45: =MIN(1,Cartera!$F$9*(1+Cartera!$G$9)^(I$3-1)*$C$10) -> 0.061681959 | J45: =MIN(1,Cartera!$F$9*(1+Cartera!$G$9)^(J$3-1)*$C$10) -> 0.069083794 | K45: =MIN(1,Cartera!$F$9*(1+Cartera!$G$9)^(K$3-1)*$C$10) -> 0.077373849 | ... AB45: =MIN(1,Cartera!$F$9*(1+Cartera!$G$9)^(AB$3-1)*$C$10) -> 0.53125201
B46: Supervivencia inicio | C46: LE estresada → | D46: =1 -> 1 | E46: =D50 -> 0.965 | F46: =E50 -> 0.927172 | G46: =F50 -> 0.88646544 | H46: =G50 -> 0.84287574 | I46: =H50 -> 0.79645589 | J46: =I50 -> 0.74732893 | K46: =J50 -> 0.69570061 | L46: =K50 -> 0.64187158 | ... AB46: =AA50 -> 0.0077266287
B47: Muertes (fracción) | D47: =D46*D45 -> 0.035 | E47: =E46*E45 -> 0.037828 | F47: =F46*F45 -> 0.040706559 | G47: =G46*G45 -> 0.043589704 | H47: =H46*H45 -> 0.046419845 | I47: =I46*I45 -> 0.04912696 | J47: =J46*J45 -> 0.051628318 | K47: =K46*K45 -> 0.053829034 | ... AB47: =AB46*AB45 -> 0.0041047871
B48: Beneficio por muerte bruto (USD mm) | D48: =D47*Cartera!$D$9 -> 2.1 | E48: =E47*Cartera!$D$9 -> 2.26968 | F48: =F47*Cartera!$D$9 -> 2.4423936 | G48: =G47*Cartera!$D$9 -> 2.6153822 | H48: =H47*Cartera!$D$9 -> 2.7851907 | I48: =I47*Cartera!$D$9 -> 2.9476176 | J48: =J47*Cartera!$D$9 -> 3.0976991 | K48: =K47*Cartera!$D$9 -> 3.2297421 | ... AB48: =AB47*Cartera!$D$9 -> 0.24628722
B49: Primas pagadas (USD mm) | D49: =D46*Cartera!$D$9*Cartera!$H$9*(1+$C$8)^(D$3-1) -> 2.1 | E49: =E46*Cartera!$D$9*Cartera!$H$9*(1+$C$8)^(E$3-1) -> 2.06703 | F49: =F46*Cartera!$D$9*Cartera!$H$9*(1+$C$8)^(F$3-1) -> 2.0257225 | G49: =G46*Cartera!$D$9*Cartera!$H$9*(1+$C$8)^(G$3-1) -> 1.9755209 | H49: =H46*Cartera!$D$9*Cartera!$H$9*(1+$C$8)^(H$3-1) -> 1.9159472 | I49: =I46*Cartera!$D$9*Cartera!$H$9*(1+$C$8)^(I$3-1) -> 1.8466385 | J49: =J46*Cartera!$D$9*Cartera!$H$9*(1+$C$8)^(J$3-1) -> 1.7673889 | K49: =K46*Cartera!$D$9*Cartera!$H$9*(1+$C$8)^(K$3-1) -> 1.6781968 | ... AB49: =AB46*Cartera!$D$9*Cartera!$H$9*(1+$C$8)^(AB$3-1) -> 0.026098375
B50: Supervivencia fin | C50: =SUM(D50:AB50)+0.5 -> 10.644133 | D50: =D46-D47 -> 0.965 | E50: =E46-E47 -> 0.927172 | F50: =F46-F47 -> 0.88646544 | G50: =G46-G47 -> 0.84287574 | H50: =H46-H47 -> 0.79645589 | I50: =I46-I47 -> 0.74732893 | J50: =J46-J47 -> 0.69570061 | K50: =K46-K47 -> 0.64187158 | ... AB50: =AB46-AB47 -> 0.0036218417
A52: CARTERA TOTAL
B53: Face en vigor inicio (USD mm) | D53: =D14*Cartera!$D$5+D22*Cartera!$D$6+D30*Cartera!$D$7+D38*Cartera!$D$8+D46*Cartera!$D$9 -> 450 | E53: =E14*Cartera!$D$5+E22*Cartera!$D$6+E30*Cartera!$D$7+E38*Cartera!$D$8+E46*Cartera!$D$9 -> 425.115 | F53: =F14*Cartera!$D$5+F22*Cartera!$D$6+F30*Cartera!$D$7+F38*Cartera!$D$8+F46*Cartera!$D$9 -> 399.66098 | G53: =G14*Cartera!$D$5+G22*Cartera!$D$6+G30*Cartera!$D$7+G38*Cartera!$D$8+G46*Cartera!$D$9 -> 373.74727 | H53: =H14*Cartera!$D$5+H22*Cartera!$D$6+H30*Cartera!$D$7+H38*Cartera!$D$8+H46*Cartera!$D$9 -> 347.49977 | I53: =I14*Cartera!$D$5+I22*Cartera!$D$6+I30*Cartera!$D$7+I38*Cartera!$D$8+I46*Cartera!$D$9 -> 321.06081 | J53: =J14*Cartera!$D$5+J22*Cartera!$D$6+J30*Cartera!$D$7+J38*Cartera!$D$8+J46*Cartera!$D$9 -> 294.58856 | K53: =K14*Cartera!$D$5+K22*Cartera!$D$6+K30*Cartera!$D$7+K38*Cartera!$D$8+K46*Cartera!$D$9 -> 268.25586 | ... AB53: =AB14*Cartera!$D$5+AB22*Cartera!$D$6+AB30*Cartera!$D$7+AB38*Cartera!$D$8+AB46*Cartera!$D$9 -> 4.3535556
B54: Beneficios por muerte brutos | D54: =D16+D24+D32+D40+D48 -> 24.885 | E54: =E16+E24+E32+E40+E48 -> 25.45402 | F54: =F16+F24+F32+F40+F48 -> 25.91371 | G54: =G16+G24+G32+G40+G48 -> 26.2475 | H54: =H16+H24+H32+H40+H48 -> 26.438959 | I54: =I16+I24+I32+I40+I48 -> 26.472253 | J54: =J16+J24+J32+J40+J48 -> 26.3327 | K54: =K16+K24+K32+K40+K48 -> 26.007393 | ... AB54: =AB16+AB24+AB32+AB40+AB48 -> 1.8580857
B55: (−) Pérdida por default de aseguradoras | D55: =-D54*$C$7 -> -1.4931 | E55: =-E54*$C$7 -> -1.5272412 | F55: =-F54*$C$7 -> -1.5548226 | G55: =-G54*$C$7 -> -1.57485 | H55: =-H54*$C$7 -> -1.5863375 | I55: =-I54*$C$7 -> -1.5883352 | J55: =-J54*$C$7 -> -1.579962 | K55: =-K54*$C$7 -> -1.5604436 | ... AB55: =-AB54*$C$7 -> -0.11148514
B56: Beneficios netos cobrados | D56: =D54+D55 -> 23.3919 | E56: =E54+E55 -> 23.926779 | F56: =F54+F55 -> 24.358887 | G56: =G54+G55 -> 24.67265 | H56: =H54+H55 -> 24.852621 | I56: =I54+I55 -> 24.883918 | J56: =J54+J55 -> 24.752738 | K56: =K54+K55 -> 24.44695 | ... AB56: =AB54+AB55 -> 1.7466006
B57: (−) Primas | D57: =-(D17+D25+D33+D41+D49) -> -23.3 | E57: =-(E17+E25+E33+E41+E49) -> -22.330146 | F57: =-(F17+F25+F33+F41+F49) -> -21.290442 | G57: =-(G17+G25+G33+G41+G49) -> -20.18565 | H57: =-(H17+H25+H33+H41+H49) -> -19.02191 | I57: =-(I17+I25+I33+I41+I49) -> -17.80678 | J57: =-(J17+J25+J33+J41+J49) -> -16.549253 | K57: =-(K17+K25+K33+K41+K49) -> -15.259713 | ... AB57: =-(AB17+AB25+AB33+AB41+AB49) -> -0.30395863
B58: (−) Gastos | D58: =-(Supuestos!$C$12+Supuestos!$C$13*D53) -> -0.975 | E58: =-(Supuestos!$C$12+Supuestos!$C$13*E53) -> -0.9625575 | F58: =-(Supuestos!$C$12+Supuestos!$C$13*F53) -> -0.94983049 | G58: =-(Supuestos!$C$12+Supuestos!$C$13*G53) -> -0.93687363 | H58: =-(Supuestos!$C$12+Supuestos!$C$13*H53) -> -0.92374988 | I58: =-(Supuestos!$C$12+Supuestos!$C$13*I53) -> -0.91053041 | J58: =-(Supuestos!$C$12+Supuestos!$C$13*J53) -> -0.89729428 | K58: =-(Supuestos!$C$12+Supuestos!$C$13*K53) -> -0.88412793 | ... AB58: =-(Supuestos!$C$12+Supuestos!$C$13*AB53) -> -0.75217678
B59: (+) Venta de cartera remanente (año final) | D59: =IF(D$3=Supuestos!$C$15,(D18*Cartera!$D$5+D26*Cartera!$D$6+D34*Cartera!$D$7+D42*Cartera!$D$8+D50*Cartera!$D$9)*Supuestos!$C$14*(1-$C$9),0) -> 0 | E59: =IF(E$3=Supuestos!$C$15,(E18*Cartera!$D$5+E26*Cartera!$D$6+E34*Cartera!$D$7+E42*Cartera!$D$8+E50*Cartera!$D$9)*Supuestos!$C$14*(1-$C$9),0) -> 0 | F59: =IF(F$3=Supuestos!$C$15,(F18*Cartera!$D$5+F26*Cartera!$D$6+F34*Cartera!$D$7+F42*Cartera!$D$8+F50*Cartera!$D$9)*Supuestos!$C$14*(1-$C$9),0) -> 0 | G59: =IF(G$3=Supuestos!$C$15,(G18*Cartera!$D$5+G26*Cartera!$D$6+G34*Cartera!$D$7+G42*Cartera!$D$8+G50*Cartera!$D$9)*Supuestos!$C$14*(1-$C$9),0) -> 0 | H59: =IF(H$3=Supuestos!$C$15,(H18*Cartera!$D$5+H26*Cartera!$D$6+H34*Cartera!$D$7+H42*Cartera!$D$8+H50*Cartera!$D$9)*Supuestos!$C$14*(1-$C$9),0) -> 0 | I59: =IF(I$3=Supuestos!$C$15,(I18*Cartera!$D$5+I26*Cartera!$D$6+I34*Cartera!$D$7+I42*Cartera!$D$8+I50*Cartera!$D$9)*Supuestos!$C$14*(1-$C$9),0) -> 0 | J59: =IF(J$3=Supuestos!$C$15,(J18*Cartera!$D$5+J26*Cartera!$D$6+J34*Cartera!$D$7+J42*Cartera!$D$8+J50*Cartera!$D$9)*Supuestos!$C$14*(1-$C$9),0) -> 0 | K59: =IF(K$3=Supuestos!$C$15,(K18*Cartera!$D$5+K26*Cartera!$D$6+K34*Cartera!$D$7+K42*Cartera!$D$8+K50*Cartera!$D$9)*Supuestos!$C$14*(1-$C$9),0) -> 0 | ... AB59: =IF(AB$3=Supuestos!$C$15,(AB18*Cartera!$D$5+AB26*Cartera!$D$6+AB34*Cartera!$D$7+AB42*Cartera!$D$8+AB50*Cartera!$D$9)*Supuestos!$C$14*(1-$C$9),0) -> 0.24954699
B60: Flujo neto de activos | D60: =D56+D57+D58+D59 -> -0.8831 | E60: =E56+E57+E58+E59 -> 0.63407565 | F60: =F56+F57+F58+F59 -> 2.1186145 | G60: =G56+G57+G58+G59 -> 3.5501261 | H60: =H56+H57+H58+H59 -> 4.9069617 | I60: =I56+I57+I58+I59 -> 6.1666073 | J60: =J56+J57+J58+J59 -> 7.3061904 | K60: =K56+K57+K58+K59 -> 8.3031086 | ... AB60: =AB56+AB57+AB58+AB59 -> 0.94001214
B62: CASCADA
B63: Caja inicio | D63: =Supuestos!$C$9 -> 20 | E63: =D82 -> 12.4669 | F63: =E82 -> 6.2249827 | G63: =F82 -> 1.2803466 | H63: =G82 -> 0 | I63: =H82 -> 0 | J63: =I82 -> 0 | K63: =J82 -> 0 | L63: =K82 -> 0.38210501 | ... AB63: =AA82 -> 0
B64: (+) Intereses de reinversión | D64: =MAX(0,D63)*Supuestos!$C$11 -> 0.6 | E64: =MAX(0,E63)*Supuestos!$C$11 -> 0.374007 | F64: =MAX(0,F63)*Supuestos!$C$11 -> 0.18674948 | G64: =MAX(0,G63)*Supuestos!$C$11 -> 0.038410397 | H64: =MAX(0,H63)*Supuestos!$C$11 -> 0 | I64: =MAX(0,I63)*Supuestos!$C$11 -> 0 | J64: =MAX(0,J63)*Supuestos!$C$11 -> 0 | K64: =MAX(0,K63)*Supuestos!$C$11 -> 0 | ... AB64: =MAX(0,AB63)*Supuestos!$C$11 -> 0
B65: Caja disponible | D65: =D63+D64+D60 -> 19.7169 | E65: =E63+E64+E60 -> 13.474983 | F65: =F63+F64+F60 -> 8.5303466 | G65: =G63+G64+G60 -> 4.8688831 | H65: =H63+H64+H60 -> 4.9069617 | I65: =I63+I64+I60 -> 6.1666073 | J65: =J63+J64+J60 -> 7.3061904 | K65: =K63+K64+K60 -> 8.3031086 | ... AB65: =AB63+AB64+AB60 -> 0.94001214
B66: Saldo Senior inicio | D66: =Supuestos!$C$5 -> 75 | E66: =D79 -> 75 | F66: =E79 -> 75 | G66: =F79 -> 75 | H66: =G79 -> 75.006117 | I66: =H79 -> 75.006117 | J66: =I79 -> 75.006117 | K66: =J79 -> 75.006117 | L66: =K79 -> 75.006117 | ... AB66: =AA79 -> 61.230205
B67: Interés Senior debido | D67: =D66*Supuestos!$C$6 -> 4.875 | E67: =E66*Supuestos!$C$6 -> 4.875 | F67: =F66*Supuestos!$C$6 -> 4.875 | G67: =G66*Supuestos!$C$6 -> 4.875 | H67: =H66*Supuestos!$C$6 -> 4.8753976 | I67: =I66*Supuestos!$C$6 -> 4.8753976 | J67: =J66*Supuestos!$C$6 -> 4.8753976 | K67: =K66*Supuestos!$C$6 -> 4.8753976 | ... AB67: =AB66*Supuestos!$C$6 -> 3.9799633
B68: Interés Senior pagado | D68: =MAX(0,MIN(D65,D67)) -> 4.875 | E68: =MAX(0,MIN(E65,E67)) -> 4.875 | F68: =MAX(0,MIN(F65,F67)) -> 4.875 | G68: =MAX(0,MIN(G65,G67)) -> 4.8688831 | H68: =MAX(0,MIN(H65,H67)) -> 4.8753976 | I68: =MAX(0,MIN(I65,I67)) -> 4.8753976 | J68: =MAX(0,MIN(J65,J67)) -> 4.8753976 | K68: =MAX(0,MIN(K65,K67)) -> 4.8753976 | ... AB68: =MAX(0,MIN(AB65,AB67)) -> 0.94001214
B69: Disponible tras int. Senior | D69: =D65-D68 -> 14.8419 | E69: =E65-E68 -> 8.5999827 | F69: =F65-F68 -> 3.6553466 | G69: =G65-G68 -> 0 | H69: =H65-H68 -> 0.03156408 | I69: =I65-I68 -> 1.2912097 | J69: =J65-J68 -> 2.4307928 | K69: =K65-K68 -> 3.427711 | ... AB69: =AB65-AB68 -> 0
B70: Saldo Mezz inicio | D70: =Supuestos!$C$7 -> 25 | E70: =D80 -> 25 | F70: =E80 -> 25 | G70: =F80 -> 25 | H70: =G80 -> 27.375 | I70: =H80 -> 29.944061 | J70: =I80 -> 31.497537 | K70: =J80 -> 32.05901 | L70: =K80 -> 32.05901 | ... AB70: =AA80 -> 43.36463
B71: Interés Mezz debido | D71: =D70*Supuestos!$C$8 -> 2.375 | E71: =E70*Supuestos!$C$8 -> 2.375 | F71: =F70*Supuestos!$C$8 -> 2.375 | G71: =G70*Supuestos!$C$8 -> 2.375 | H71: =H70*Supuestos!$C$8 -> 2.600625 | I71: =I70*Supuestos!$C$8 -> 2.8446858 | J71: =J70*Supuestos!$C$8 -> 2.992266 | K71: =K70*Supuestos!$C$8 -> 3.045606 | ... AB71: =AB70*Supuestos!$C$8 -> 4.1196398
B72: Interés Mezz pagado | D72: =MAX(0,MIN(D69,D71)) -> 2.375 | E72: =MAX(0,MIN(E69,E71)) -> 2.375 | F72: =MAX(0,MIN(F69,F71)) -> 2.375 | G72: =MAX(0,MIN(G69,G71)) -> 0 | H72: =MAX(0,MIN(H69,H71)) -> 0.03156408 | I72: =MAX(0,MIN(I69,I71)) -> 1.2912097 | J72: =MAX(0,MIN(J69,J71)) -> 2.4307928 | K72: =MAX(0,MIN(K69,K71)) -> 3.045606 | ... AB72: =MAX(0,MIN(AB69,AB71)) -> 0
B73: Disponible tras int. Mezz | D73: =D69-D72 -> 12.4669 | E73: =E69-E72 -> 6.2249827 | F73: =F69-F72 -> 1.2803466 | G73: =G69-G72 -> 0 | H73: =H69-H72 -> 0 | I73: =I69-I72 -> 0 | J73: =J69-J72 -> 0 | K73: =K69-K72 -> 0.38210501 | ... AB73: =AB69-AB72 -> 0
B74: Reserva objetivo | D74: =IF(D$3=Supuestos!$C$15,0,-D57*(1+$C$8)*Supuestos!$C$10/12) -> 23.766 | E74: =IF(E$3=Supuestos!$C$15,0,-E57*(1+$C$8)*Supuestos!$C$10/12) -> 22.776749 | F74: =IF(F$3=Supuestos!$C$15,0,-F57*(1+$C$8)*Supuestos!$C$10/12) -> 21.716251 | G74: =IF(G$3=Supuestos!$C$15,0,-G57*(1+$C$8)*Supuestos!$C$10/12) -> 20.589363 | H74: =IF(H$3=Supuestos!$C$15,0,-H57*(1+$C$8)*Supuestos!$C$10/12) -> 19.402348 | I74: =IF(I$3=Supuestos!$C$15,0,-I57*(1+$C$8)*Supuestos!$C$10/12) -> 18.162916 | J74: =IF(J$3=Supuestos!$C$15,0,-J57*(1+$C$8)*Supuestos!$C$10/12) -> 16.880238 | K74: =IF(K$3=Supuestos!$C$15,0,-K57*(1+$C$8)*Supuestos!$C$10/12) -> 15.564907 | ... AB74: =IF(AB$3=Supuestos!$C$15,0,-AB57*(1+$C$8)*Supuestos!$C$10/12) -> 0
B75: Principal Senior pagado | D75: =MAX(0,MIN(D66+D67-D68,D73-D74)) -> 0 | E75: =MAX(0,MIN(E66+E67-E68,E73-E74)) -> 0 | F75: =MAX(0,MIN(F66+F67-F68,F73-F74)) -> 0 | G75: =MAX(0,MIN(G66+G67-G68,G73-G74)) -> 0 | H75: =MAX(0,MIN(H66+H67-H68,H73-H74)) -> 0 | I75: =MAX(0,MIN(I66+I67-I68,I73-I74)) -> 0 | J75: =MAX(0,MIN(J66+J67-J68,J73-J74)) -> 0 | K75: =MAX(0,MIN(K66+K67-K68,K73-K74)) -> 0 | ... AB75: =MAX(0,MIN(AB66+AB67-AB68,AB73-AB74)) -> 0
B76: Disponible tras Senior | D76: =D73-D75 -> 12.4669 | E76: =E73-E75 -> 6.2249827 | F76: =F73-F75 -> 1.2803466 | G76: =G73-G75 -> 0 | H76: =H73-H75 -> 0 | I76: =I73-I75 -> 0 | J76: =J73-J75 -> 0 | K76: =K73-K75 -> 0.38210501 | ... AB76: =AB73-AB75 -> 0
B77: Principal Mezz pagado | D77: =MAX(0,MIN(D70+D71-D72,D76-D74)) -> 0 | E77: =MAX(0,MIN(E70+E71-E72,E76-E74)) -> 0 | F77: =MAX(0,MIN(F70+F71-F72,F76-F74)) -> 0 | G77: =MAX(0,MIN(G70+G71-G72,G76-G74)) -> 0 | H77: =MAX(0,MIN(H70+H71-H72,H76-H74)) -> 0 | I77: =MAX(0,MIN(I70+I71-I72,I76-I74)) -> 0 | J77: =MAX(0,MIN(J70+J71-J72,J76-J74)) -> 0 | K77: =MAX(0,MIN(K70+K71-K72,K76-K74)) -> 0 | ... AB77: =MAX(0,MIN(AB70+AB71-AB72,AB76-AB74)) -> 0
B78: Disponible tras Mezz | D78: =D76-D77 -> 12.4669 | E78: =E76-E77 -> 6.2249827 | F78: =F76-F77 -> 1.2803466 | G78: =G76-G77 -> 0 | H78: =H76-H77 -> 0 | I78: =I76-I77 -> 0 | J78: =J76-J77 -> 0 | K78: =K76-K77 -> 0.38210501 | ... AB78: =AB76-AB77 -> 0
B79: Saldo Senior fin | D79: =D66+D67-D68-D75 -> 75 | E79: =E66+E67-E68-E75 -> 75 | F79: =F66+F67-F68-F75 -> 75 | G79: =G66+G67-G68-G75 -> 75.006117 | H79: =H66+H67-H68-H75 -> 75.006117 | I79: =I66+I67-I68-I75 -> 75.006117 | J79: =J66+J67-J68-J75 -> 75.006117 | K79: =K66+K67-K68-K75 -> 75.006117 | ... AB79: =AB66+AB67-AB68-AB75 -> 64.270156
B80: Saldo Mezz fin | D80: =D70+D71-D72-D77 -> 25 | E80: =E70+E71-E72-E77 -> 25 | F80: =F70+F71-F72-F77 -> 25 | G80: =G70+G71-G72-G77 -> 27.375 | H80: =H70+H71-H72-H77 -> 29.944061 | I80: =I70+I71-I72-I77 -> 31.497537 | J80: =J70+J71-J72-J77 -> 32.05901 | K80: =K70+K71-K72-K77 -> 32.05901 | ... AB80: =AB70+AB71-AB72-AB77 -> 47.484269
B81: Distribución a equity | D81: =IF(D79+D80<0.000001,MAX(0,D78-D74),0) -> 0 | E81: =IF(E79+E80<0.000001,MAX(0,E78-E74),0) -> 0 | F81: =IF(F79+F80<0.000001,MAX(0,F78-F74),0) -> 0 | G81: =IF(G79+G80<0.000001,MAX(0,G78-G74),0) -> 0 | H81: =IF(H79+H80<0.000001,MAX(0,H78-H74),0) -> 0 | I81: =IF(I79+I80<0.000001,MAX(0,I78-I74),0) -> 0 | J81: =IF(J79+J80<0.000001,MAX(0,J78-J74),0) -> 0 | K81: =IF(K79+K80<0.000001,MAX(0,K78-K74),0) -> 0 | ... AB81: =IF(AB79+AB80<0.000001,MAX(0,AB78-AB74),0) -> 0
B82: Caja fin | D82: =D78-D81 -> 12.4669 | E82: =E78-E81 -> 6.2249827 | F82: =F78-F81 -> 1.2803466 | G82: =G78-G81 -> 0 | H82: =H78-H81 -> 0 | I82: =I78-I81 -> 0 | J82: =J78-J81 -> 0 | K82: =K78-K81 -> 0.38210501 | ... AB82: =AB78-AB81 -> 0
B83: Déficit de liquidez con notas vigentes (1 = sí) | D83: =IF(AND(D65<0,D66+D70>0.000001),1,0) -> 0 | E83: =IF(AND(E65<0,E66+E70>0.000001),1,0) -> 0 | F83: =IF(AND(F65<0,F66+F70>0.000001),1,0) -> 0 | G83: =IF(AND(G65<0,G66+G70>0.000001),1,0) -> 0 | H83: =IF(AND(H65<0,H66+H70>0.000001),1,0) -> 0 | I83: =IF(AND(I65<0,I66+I70>0.000001),1,0) -> 0 | J83: =IF(AND(J65<0,J66+J70>0.000001),1,0) -> 0 | K83: =IF(AND(K65<0,K66+K70>0.000001),1,0) -> 0 | ... AB83: =IF(AND(AB65<0,AB66+AB70>0.000001),1,0) -> 0
A85: MÉTRICAS DEL ESCENARIO
B86: Pérdida Senior (% del original) | C86: =MIN(1,AB79/Supuestos!C5) -> 0.85693542
B87: Pérdida Mezz (% del original) | C87: =MIN(1,AB80/Supuestos!C7) -> 1
B88: Interés Senior impagado acumulado (USD mm) | C88: =SUM(D67:AB67)-SUM(D68:AB68) -> 7.5314952
B89: Caja mínima con notas vigentes (USD mm) | C89: =MIN(IF(D66+D70>0.000001,D65,1000000000),IF(E66+E70>0.000001,E65,1000000000),IF(F66+F70>0.000001,F65,1000000000),IF(G66+G70>0.000001,G65,1000000000),IF(H66+H70>0.000001,H65,1000000000),IF(I66+I70>0.000001,I65,1000000000),IF(J66+J70>0.000001,J65,1000000000),IF(K66+K70>0.000001,K65,1000000000),IF(L66+L70>0.000001,L65,1000000000),IF(M66+M70>0.000001,M65,1000000000),IF(N66+N70>0.000001,N65,1000000000),IF(O66+O70>0.000001,O65,1000000000),IF(P66+P70>0.000001,P65,1000000000),IF(Q66+Q70>0.000001,Q65,1000000000),IF(R66+R70>0.000001,R65,1000000000),IF(S66+S70>0.000001,S65,1000000000),IF(T66+T70>0.000001,T65,1000000000),IF(U66+U70>0.000001,U65,1000000000),IF(V66+V70>0.000001,V65,1000000000),IF(W66+W70>0.000001,W65,1000000000),IF(X66+X70>0.000001,X65,1000000000),IF(Y66+Y70>0.000001,Y65,1000000000),IF(Z66+Z70>0.000001,Z65,1000000000),IF(AA66+AA70>0.000001,AA65,1000000000),IF(AB66+AB70>0.000001,AB65,1000000000)) -> 0.94001214
B90: Años con déficit de liquidez | C90: =SUM(D83:AB83) -> 0
B91: Vida promedio Senior (años) | C91: =IFERROR(SUMPRODUCT(D75:AB75,D3:AB3)/SUM(D75:AB75),0) -> 15.348002
B92: Vida promedio Mezz (años) | C92: =IFERROR(SUMPRODUCT(D77:AB77,D3:AB3)/SUM(D77:AB77),0) -> 0
B93: LE estresada ponderada por face (años) | C93: =(C18*Cartera!D5+C26*Cartera!D6+C34*Cartera!D7+C42*Cartera!D8+C50*Cartera!D9)/Cartera!D10 -> 9.3305259
B94: Senior PASA (1 = sí) | C94: =IF(AND(C86<=Supuestos!C20+0.000001,C88<0.000001),1,0) -> 0
B95: Mezz PASA (1 = sí) | C95: =IF(C87<=Supuestos!C20+0.000001,1,0) -> 0
B96: Distribuciones a equity (USD mm, sin descontar) | C96: =SUM(D81:AB81)+MAX(0,AB82) -> 0

Sheet CF_aa
A1: Flujo de caja y cascada – escenario aa
A2: Escenario | C2: aa
A3: Año | D3: 1 | E3: 2 | F3: 3 | G3: 4 | H3: 5 | I3: 6 | J3: 7 | K3: 8 | L3: 9 | M3: 10 | N3: 11 | O3: 12 | P3: 13 | Q3: 14 | R3: 15 | S3: 16 | T3: 17 | U3: 18 | V3: 19 | W3: 20 | X3: 21 | Y3: 22 | Z3: 23 | AA3: 24 | AB3: 25
A5: Multiplicador de mortalidad | C5: =Supuestos!C25 -> 0.76
A6: Penalidad pool pequeño | C6: =Supuestos!D25 -> 0.04
A7: Pérdida default aseguradoras | C7: =Supuestos!E25 -> 0.045
A8: Aumento anual de primas | C8: =Supuestos!F25 -> 0.015
A9: Haircut valor remanente | C9: =Supuestos!G25 -> 0.4
A10: Multiplicador efectivo | C10: =MAX(0,C5-IF(Cartera!C10<Supuestos!C16,C6,0)) -> 0.76
A12: =Cartera!A5&" – "&Cartera!B5 -> C1 – Edad 75–79, salud estándar
B13: q estresada | D13: =MIN(1,Cartera!$F$5*(1+Cartera!$G$5)^(D$3-1)*$C$10) -> 0.0342 | E13: =MIN(1,Cartera!$F$5*(1+Cartera!$G$5)^(E$3-1)*$C$10) -> 0.037962 | F13: =MIN(1,Cartera!$F$5*(1+Cartera!$G$5)^(F$3-1)*$C$10) -> 0.04213782 | G13: =MIN(1,Cartera!$F$5*(1+Cartera!$G$5)^(G$3-1)*$C$10) -> 0.04677298 | H13: =MIN(1,Cartera!$F$5*(1+Cartera!$G$5)^(H$3-1)*$C$10) -> 0.051918008 | I13: =MIN(1,Cartera!$F$5*(1+Cartera!$G$5)^(I$3-1)*$C$10) -> 0.057628989 | J13: =MIN(1,Cartera!$F$5*(1+Cartera!$G$5)^(J$3-1)*$C$10) -> 0.063968178 | K13: =MIN(1,Cartera!$F$5*(1+Cartera!$G$5)^(K$3-1)*$C$10) -> 0.071004677 | ... AB13: =MIN(1,Cartera!$F$5*(1+Cartera!$G$5)^(AB$3-1)*$C$10) -> 0.41857916
B14: Supervivencia inicio | C14: LE estresada → | D14: =1 -> 1 | E14: =D18 -> 0.9658 | F14: =E18 -> 0.9291363 | G14: =F18 -> 0.88998452 | H14: =G18 -> 0.84835729 | I14: =H18 -> 0.80431227 | J14: =I18 -> 0.75796057 | K14: =J18 -> 0.70947521 | L14: =K18 -> 0.65909915 | ... AB14: =AA18 -> 0.01914405
B15: Muertes (fracción) | D15: =D14*D13 -> 0.0342 | E15: =E14*E13 -> 0.0366637 | F15: =F14*F13 -> 0.039151778 | G15: =G14*G13 -> 0.041627228 | H15: =H14*H13 -> 0.044045021 | I15: =I14*I13 -> 0.046351703 | J15: =J14*J13 -> 0.048485356 | K15: =K14*K13 -> 0.050376059 | ... AB15: =AB14*AB13 -> 0.0080133004
B16: Beneficio por muerte bruto (USD mm) | D16: =D15*Cartera!$D$5 -> 3.078 | E16: =E15*Cartera!$D$5 -> 3.299733 | F16: =F15*Cartera!$D$5 -> 3.52366 | G16: =G15*Cartera!$D$5 -> 3.7464506 | H16: =H15*Cartera!$D$5 -> 3.9640519 | I16: =I15*Cartera!$D$5 -> 4.1716533 | J16: =J15*Cartera!$D$5 -> 4.3636821 | K16: =K15*Cartera!$D$5 -> 4.5338453 | ... AB16: =AB15*Cartera!$D$5 -> 0.72119703
B17: Primas pagadas (USD mm) | D17: =D14*Cartera!$D$5*Cartera!$H$5*(1+$C$8)^(D$3-1) -> 3.6 | E17: =E14*Cartera!$D$5*Cartera!$H$5*(1+$C$8)^(E$3-1) -> 3.5290332 | F17: =F14*Cartera!$D$5*Cartera!$H$5*(1+$C$8)^(F$3-1) -> 3.44599 | G17: =G14*Cartera!$D$5*Cartera!$H$5*(1+$C$8)^(G$3-1) -> 3.3502952 | H17: =H14*Cartera!$D$5*Cartera!$H$5*(1+$C$8)^(H$3-1) -> 3.2414958 | I17: =I14*Cartera!$D$5*Cartera!$H$5*(1+$C$8)^(I$3-1) -> 3.1193019 | J17: =J14*Cartera!$D$5*Cartera!$H$5*(1+$C$8)^(J$3-1) -> 2.9836328 | K17: =K14*Cartera!$D$5*Cartera!$H$5*(1+$C$8)^(K$3-1) -> 2.8346668 | ... AB17: =AB14*Cartera!$D$5*Cartera!$H$5*(1+$C$8)^(AB$3-1) -> 0.098519305
B18: Supervivencia fin | C18: =SUM(D18:AB18)+0.5 -> 11.187024 | D18: =D14-D15 -> 0.9658 | E18: =E14-E15 -> 0.9291363 | F18: =F14-F15 -> 0.88998452 | G18: =G14-G15 -> 0.84835729 | H18: =H14-H15 -> 0.80431227 | I18: =I14-I15 -> 0.75796057 | J18: =J14-J15 -> 0.70947521 | K18: =K14-K15 -> 0.65909915 | ... AB18: =AB14-AB15 -> 0.01113075
A20: =Cartera!A6&" – "&Cartera!B6 -> C2 – Edad 80–84, deterioro moderado
B21: q estresada | D21: =MIN(1,Cartera!$F$6*(1+Cartera!$G$6)^(D$3-1)*$C$10) -> 0.0494 | E21: =MIN(1,Cartera!$F$6*(1+Cartera!$G$6)^(E$3-1)*$C$10) -> 0.05434 | F21: =MIN(1,Cartera!$F$6*(1+Cartera!$G$6)^(F$3-1)*$C$10) -> 0.059774 | G21: =MIN(1,Cartera!$F$6*(1+Cartera!$G$6)^(G$3-1)*$C$10) -> 0.0657514 | H21: =MIN(1,Cartera!$F$6*(1+Cartera!$G$6)^(H$3-1)*$C$10) -> 0.07232654 | I21: =MIN(1,Cartera!$F$6*(1+Cartera!$G$6)^(I$3-1)*$C$10) -> 0.079559194 | J21: =MIN(1,Cartera!$F$6*(1+Cartera!$G$6)^(J$3-1)*$C$10) -> 0.087515113 | K21: =MIN(1,Cartera!$F$6*(1+Cartera!$G$6)^(K$3-1)*$C$10) -> 0.096266625 | ... AB21: =MIN(1,Cartera!$F$6*(1+Cartera!$G$6)^(AB$3-1)*$C$10) -> 0.48657679
B22: Supervivencia inicio | C22: LE estresada → | D22: =1 -> 1 | E22: =D26 -> 0.9506 | F22: =E26 -> 0.8989444 | G22: =F26 -> 0.84521089 | H22: =G26 -> 0.78963709 | I22: =H26 -> 0.73252538 | J22: =I26 -> 0.67424625 | K22: =J26 -> 0.61523951 | L22: =K26 -> 0.55601248 | ... AB22: =AA26 -> 0.0061637755
B23: Muertes (fracción) | D23: =D22*D21 -> 0.0494 | E23: =E22*E21 -> 0.051655604 | F23: =F22*F21 -> 0.053733502 | G23: =G22*G21 -> 0.0555738 | H23: =H22*H21 -> 0.057111719 | I23: =I22*I21 -> 0.058279128 | J23: =J22*J21 -> 0.059006737 | K23: =K22*K21 -> 0.059227031 | ... AB23: =AB22*AB21 -> 0.0029991501
B24: Beneficio por muerte bruto (USD mm) | D24: =D23*Cartera!$D$6 -> 5.928 | E24: =E23*Cartera!$D$6 -> 6.1986725 | F24: =F23*Cartera!$D$6 -> 6.4480203 | G24: =G23*Cartera!$D$6 -> 6.6688559 | H24: =H23*Cartera!$D$6 -> 6.8534063 | I24: =I23*Cartera!$D$6 -> 6.9934954 | J24: =J23*Cartera!$D$6 -> 7.0808084 | K24: =K23*Cartera!$D$6 -> 7.1072437 | ... AB24: =AB23*Cartera!$D$6 -> 0.35989802
B25: Primas pagadas (USD mm) | D25: =D22*Cartera!$D$6*Cartera!$H$6*(1+$C$8)^(D$3-1) -> 6 | E25: =E22*Cartera!$D$6*Cartera!$H$6*(1+$C$8)^(E$3-1) -> 5.789154 | F25: =F22*Cartera!$D$6*Cartera!$H$6*(1+$C$8)^(F$3-1) -> 5.5566899 | G25: =G22*Cartera!$D$6*Cartera!$H$6*(1+$C$8)^(G$3-1) -> 5.3029125 | H25: =H22*Cartera!$D$6*Cartera!$H$6*(1+$C$8)^(H$3-1) -> 5.0285522 | I25: =I22*Cartera!$D$6*Cartera!$H$6*(1+$C$8)^(I$3-1) -> 4.7348272 | J25: =J22*Cartera!$D$6*Cartera!$H$6*(1+$C$8)^(J$3-1) -> 4.4235001 | K25: =K22*Cartera!$D$6*Cartera!$H$6*(1+$C$8)^(K$3-1) -> 4.0969226 | ... AB25: =AB22*Cartera!$D$6*Cartera!$H$6*(1+$C$8)^(AB$3-1) -> 0.052866807
B26: Supervivencia fin | C26: =SUM(D26:AB26)+0.5 -> 9.4305352 | D26: =D22-D23 -> 0.9506 | E26: =E22-E23 -> 0.8989444 | F26: =F22-F23 -> 0.84521089 | G26: =G22-G23 -> 0.78963709 | H26: =H22-H23 -> 0.73252538 | I26: =I22-I23 -> 0.67424625 | J26: =J22-J23 -> 0.61523951 | K26: =K22-K23 -> 0.55601248 | ... AB26: =AB22-AB23 -> 0.0031646254
A28: =Cartera!A7&" – "&Cartera!B7 -> C3 – Edad 85–89, deterioro significativo
B29: q estresada | D29: =MIN(1,Cartera!$F$7*(1+Cartera!$G$7)^(D$3-1)*$C$10) -> 0.0722 | E29: =MIN(1,Cartera!$F$7*(1+Cartera!$G$7)^(E$3-1)*$C$10) -> 0.078698 | F29: =MIN(1,Cartera!$F$7*(1+Cartera!$G$7)^(F$3-1)*$C$10) -> 0.08578082 | G29: =MIN(1,Cartera!$F$7*(1+Cartera!$G$7)^(G$3-1)*$C$10) -> 0.093501094 | H29: =MIN(1,Cartera!$F$7*(1+Cartera!$G$7)^(H$3-1)*$C$10) -> 0.10191619 | I29: =MIN(1,Cartera!$F$7*(1+Cartera!$G$7)^(I$3-1)*$C$10) -> 0.11108865 | J29: =MIN(1,Cartera!$F$7*(1+Cartera!$G$7)^(J$3-1)*$C$10) -> 0.12108663 | K29: =MIN(1,Cartera!$F$7*(1+Cartera!$G$7)^(K$3-1)*$C$10) -> 0.13198442 | ... AB29: =MIN(1,Cartera!$F$7*(1+Cartera!$G$7)^(AB$3-1)*$C$10) -> 0.57118021
B30: Supervivencia inicio | C30: LE estresada → | D30: =1 -> 1 | E30: =D34 -> 0.9278 | F30: =E34 -> 0.854784 | G30: =F34 -> 0.78145992 | H30: =G34 -> 0.70839257 | I30: =H34 -> 0.63619589 | J30: =I34 -> 0.56552175 | K30: =J34 -> 0.49704463 | L30: =K34 -> 0.43144248 | ... AB30: =AA34 -> 0.0012193811
B31: Muertes (fracción) | D31: =D30*D29 -> 0.0722 | E31: =E30*E29 -> 0.073016004 | F31: =F30*F29 -> 0.073324072 | G31: =G30*G29 -> 0.073067358 | H31: =H30*H29 -> 0.072196673 | I31: =I30*I29 -> 0.070674143 | J31: =J30*J29 -> 0.068477122 | K31: =K30*K29 -> 0.065602149 | ... AB31: =AB30*AB29 -> 0.00069648635
B32: Beneficio por muerte bruto (USD mm) | D32: =D31*Cartera!$D$7 -> 7.22 | E32: =E31*Cartera!$D$7 -> 7.3016004 | F32: =F31*Cartera!$D$7 -> 7.3324072 | G32: =G31*Cartera!$D$7 -> 7.3067358 | H32: =H31*Cartera!$D$7 -> 7.2196673 | I32: =I31*Cartera!$D$7 -> 7.0674143 | J32: =J31*Cartera!$D$7 -> 6.8477122 | K32: =K31*Cartera!$D$7 -> 6.5602149 | ... AB32: =AB31*Cartera!$D$7 -> 0.069648635
B33: Primas pagadas (USD mm) | D33: =D30*Cartera!$D$7*Cartera!$H$7*(1+$C$8)^(D$3-1) -> 6 | E33: =E30*Cartera!$D$7*Cartera!$H$7*(1+$C$8)^(E$3-1) -> 5.650302 | F33: =F30*Cartera!$D$7*Cartera!$H$7*(1+$C$8)^(F$3-1) -> 5.2837191 | G33: =G30*Cartera!$D$7*Cartera!$H$7*(1+$C$8)^(G$3-1) -> 4.9029345 | H33: =H30*Cartera!$D$7*Cartera!$H$7*(1+$C$8)^(H$3-1) -> 4.5111723 | I33: =I30*Cartera!$D$7*Cartera!$H$7*(1+$C$8)^(I$3-1) -> 4.112182 | J33: =J30*Cartera!$D$7*Cartera!$H$7*(1+$C$8)^(J$3-1) -> 3.7101957 | K33: =K30*Cartera!$D$7*Cartera!$H$7*(1+$C$8)^(K$3-1) -> 3.3098547 | ... AB33: =AB30*Cartera!$D$7*Cartera!$H$7*(1+$C$8)^(AB$3-1) -> 0.010458652
B34: Supervivencia fin | C34: =SUM(D34:AB34)+0.5 -> 7.6656782 | D34: =D30-D31 -> 0.9278 | E34: =E30-E31 -> 0.854784 | F34: =F30-F31 -> 0.78145992 | G34: =G30-G31 -> 0.70839257 | H34: =H30-H31 -> 0.63619589 | I34: =I30-I31 -> 0.56552175 | J34: =J30-J31 -> 0.49704463 | K34: =K30-K31 -> 0.43144248 | ... AB34: =AB30-AB31 -> 0.00052289476
A36: =Cartera!A8&" – "&Cartera!B8 -> C4 – Edad 90+, deterioro severo
B37: q estresada | D37: =MIN(1,Cartera!$F$8*(1+Cartera!$G$8)^(D$3-1)*$C$10) -> 0.1064 | E37: =MIN(1,Cartera!$F$8*(1+Cartera!$G$8)^(E$3-1)*$C$10) -> 0.114912 | F37: =MIN(1,Cartera!$F$8*(1+Cartera!$G$8)^(F$3-1)*$C$10) -> 0.12410496 | G37: =MIN(1,Cartera!$F$8*(1+Cartera!$G$8)^(G$3-1)*$C$10) -> 0.13403336 | H37: =MIN(1,Cartera!$F$8*(1+Cartera!$G$8)^(H$3-1)*$C$10) -> 0.14475603 | I37: =MIN(1,Cartera!$F$8*(1+Cartera!$G$8)^(I$3-1)*$C$10) -> 0.15633651 | J37: =MIN(1,Cartera!$F$8*(1+Cartera!$G$8)^(J$3-1)*$C$10) -> 0.16884343 | K37: =MIN(1,Cartera!$F$8*(1+Cartera!$G$8)^(K$3-1)*$C$10) -> 0.1823509 | ... AB37: =MIN(1,Cartera!$F$8*(1+Cartera!$G$8)^(AB$3-1)*$C$10) -> 0.67470163
B38: Supervivencia inicio | C38: LE estresada → | D38: =1 -> 1 | E38: =D42 -> 0.8936 | F38: =E42 -> 0.79091464 | G38: =F42 -> 0.69275821 | H38: =G42 -> 0.5999055 | I38: =H42 -> 0.51306556 | J38: =I42 -> 0.43285469 | K38: =J42 -> 0.35977002 | L38: =K42 -> 0.29416563 | ... AB38: =AA42 -> 0.00011321584
B39: Muertes (fracción) | D39: =D38*D37 -> 0.1064 | E39: =E38*E37 -> 0.10268536 | F39: =F38*F37 -> 0.098156429 | G39: =G38*G37 -> 0.092852708 | H39: =H38*H37 -> 0.086839936 | I39: =I38*I37 -> 0.080210878 | J39: =J38*J37 -> 0.073084669 | K39: =K38*K37 -> 0.065604387 | ... AB39: =AB38*AB37 -> 7.6386909e-05
B40: Beneficio por muerte bruto (USD mm) | D40: =D39*Cartera!$D$8 -> 8.512 | E40: =E39*Cartera!$D$8 -> 8.2148291 | F40: =F39*Cartera!$D$8 -> 7.8525143 | G40: =G39*Cartera!$D$8 -> 7.4282166 | H40: =H39*Cartera!$D$8 -> 6.9471949 | I40: =I39*Cartera!$D$8 -> 6.4168703 | J40: =J39*Cartera!$D$8 -> 5.8467735 | K40: =K39*Cartera!$D$8 -> 5.248351 | ... AB40: =AB39*Cartera!$D$8 -> 0.0061109527
B41: Primas pagadas (USD mm) | D41: =D38*Cartera!$D$8*Cartera!$H$8*(1+$C$8)^(D$3-1) -> 5.6 | E41: =E38*Cartera!$D$8*Cartera!$H$8*(1+$C$8)^(E$3-1) -> 5.0792224 | F41: =F38*Cartera!$D$8*Cartera!$H$8*(1+$C$8)^(F$3-1) -> 4.5629922 | G41: =G38*Cartera!$D$8*Cartera!$H$8*(1+$C$8)^(G$3-1) -> 4.0566527 | H41: =H38*Cartera!$D$8*Cartera!$H$8*(1+$C$8)^(H$3-1) -> 3.5656199 | I41: =I38*Cartera!$D$8*Cartera!$H$8*(1+$C$8)^(I$3-1) -> 3.095217 | J41: =J38*Cartera!$D$8*Cartera!$H$8*(1+$C$8)^(J$3-1) -> 2.6504914 | K41: =K38*Cartera!$D$8*Cartera!$H$8*(1+$C$8)^(K$3-1) -> 2.236018 | ... AB41: =AB38*Cartera!$D$8*Cartera!$H$8*(1+$C$8)^(AB$3-1) -> 0.00090631719
B42: Supervivencia fin | C42: =SUM(D42:AB42)+0.5 -> 5.9866647 | D42: =D38-D39 -> 0.8936 | E42: =E38-E39 -> 0.79091464 | F42: =F38-F39 -> 0.69275821 | G42: =G38-G39 -> 0.5999055 | H42: =H38-H39 -> 0.51306556 | I42: =I38-I39 -> 0.43285469 | J42: =J38-J39 -> 0.35977002 | K42: =K38-K39 -> 0.29416563 | ... AB42: =AB38-AB39 -> 3.6828927e-05
A44: =Cartera!A9&" – "&Cartera!B9 -> C5 – Edad 70–74, enfermedad crónica
B45: q estresada | D45: =MIN(1,Cartera!$F$9*(1+Cartera!$G$9)^(D$3-1)*$C$10) -> 0.038 | E45: =MIN(1,Cartera!$F$9*(1+Cartera!$G$9)^(E$3-1)*$C$10) -> 0.04256 | F45: =MIN(1,Cartera!$F$9*(1+Cartera!$G$9)^(F$3-1)*$C$10) -> 0.0476672 | G45: =MIN(1,Cartera!$F$9*(1+Cartera!$G$9)^(G$3-1)*$C$10) -> 0.053387264 | H45: =MIN(1,Cartera!$F$9*(1+Cartera!$G$9)^(H$3-1)*$C$10) -> 0.059793736 | I45: =MIN(1,Cartera!$F$9*(1+Cartera!$G$9)^(I$3-1)*$C$10) -> 0.066968984 | J45: =MIN(1,Cartera!$F$9*(1+Cartera!$G$9)^(J$3-1)*$C$10) -> 0.075005262 | K45: =MIN(1,Cartera!$F$9*(1+Cartera!$G$9)^(K$3-1)*$C$10) -> 0.084005893 | ... AB45: =MIN(1,Cartera!$F$9*(1+Cartera!$G$9)^(AB$3-1)*$C$10) -> 0.5767879
B46: Supervivencia inicio | C46: LE estresada → | D46: =1 -> 1 | E46: =D50 -> 0.962 | F46: =E50 -> 0.92105728 | G46: =F50 -> 0.87715306 | H46: =G50 -> 0.83032426 | I46: =H50 -> 0.78067607 | J46: =I50 -> 0.72839498 | K46: =J50 -> 0.67376153 | L46: =K50 -> 0.61716159 | ... AB46: =AA50 -> 0.004633373
B47: Muertes (fracción) | D47: =D46*D45 -> 0.038 | E47: =E46*E45 -> 0.04094272 | F47: =F46*F45 -> 0.043904222 | G47: =G46*G45 -> 0.046828802 | H47: =H46*H45 -> 0.049648189 | I47: =I46*I45 -> 0.052281083 | J47: =J46*J45 -> 0.054633457 | K47: =K46*K45 -> 0.056599939 | ... AB47: =AB46*AB45 -> 0.0026724735
B48: Beneficio por muerte bruto (USD mm) | D48: =D47*Cartera!$D$9 -> 2.28 | E48: =E47*Cartera!$D$9 -> 2.4565632 | F48: =F47*Cartera!$D$9 -> 2.6342533 | G48: =G47*Cartera!$D$9 -> 2.8097281 | H48: =H47*Cartera!$D$9 -> 2.9788913 | I48: =I47*Cartera!$D$9 -> 3.136865 | J48: =J47*Cartera!$D$9 -> 3.2780074 | K48: =K47*Cartera!$D$9 -> 3.3959963 | ... AB48: =AB47*Cartera!$D$9 -> 0.16034841
B49: Primas pagadas (USD mm) | D49: =D46*Cartera!$D$9*Cartera!$H$9*(1+$C$8)^(D$3-1) -> 2.1 | E49: =E46*Cartera!$D$9*Cartera!$H$9*(1+$C$8)^(E$3-1) -> 2.050503 | F49: =F46*Cartera!$D$9*Cartera!$H$9*(1+$C$8)^(F$3-1) -> 1.9926821 | G49: =G46*Cartera!$D$9*Cartera!$H$9*(1+$C$8)^(G$3-1) -> 1.926162 | H49: =H46*Cartera!$D$9*Cartera!$H$9*(1+$C$8)^(H$3-1) -> 1.8506794 | I49: =I46*Cartera!$D$9*Cartera!$H$9*(1+$C$8)^(I$3-1) -> 1.7661207 | J49: =J46*Cartera!$D$9*Cartera!$H$9*(1+$C$8)^(J$3-1) -> 1.672563 | K49: =K46*Cartera!$D$9*Cartera!$H$9*(1+$C$8)^(K$3-1) -> 1.5703187 | ... AB49: =AB46*Cartera!$D$9*Cartera!$H$9*(1+$C$8)^(AB$3-1) -> 0.013909181
B50: Supervivencia fin | C50: =SUM(D50:AB50)+0.5 -> 10.184703 | D50: =D46-D47 -> 0.962 | E50: =E46-E47 -> 0.92105728 | F50: =F46-F47 -> 0.87715306 | G50: =G46-G47 -> 0.83032426 | H50: =H46-H47 -> 0.78067607 | I50: =I46-I47 -> 0.72839498 | J50: =J46-J47 -> 0.67376153 | K50: =K46-K47 -> 0.61716159 | ... AB50: =AB46-AB47 -> 0.0019608995
A52: CARTERA TOTAL
B53: Face en vigor inicio (USD mm) | D53: =D14*Cartera!$D$5+D22*Cartera!$D$6+D30*Cartera!$D$7+D38*Cartera!$D$8+D46*Cartera!$D$9 -> 450 | E53: =E14*Cartera!$D$5+E22*Cartera!$D$6+E30*Cartera!$D$7+E38*Cartera!$D$8+E46*Cartera!$D$9 -> 422.982 | F53: =F14*Cartera!$D$5+F22*Cartera!$D$6+F30*Cartera!$D$7+F38*Cartera!$D$8+F46*Cartera!$D$9 -> 395.5106 | G53: =G14*Cartera!$D$5+G22*Cartera!$D$6+G30*Cartera!$D$7+G38*Cartera!$D$8+G46*Cartera!$D$9 -> 367.71975 | H53: =H14*Cartera!$D$5+H22*Cartera!$D$6+H30*Cartera!$D$7+H38*Cartera!$D$8+H46*Cartera!$D$9 -> 339.75976 | I53: =I14*Cartera!$D$5+I22*Cartera!$D$6+I30*Cartera!$D$7+I38*Cartera!$D$8+I46*Cartera!$D$9 -> 311.79655 | J53: =J14*Cartera!$D$5+J22*Cartera!$D$6+J30*Cartera!$D$7+J38*Cartera!$D$8+J46*Cartera!$D$9 -> 284.01025 | K53: =K14*Cartera!$D$5+K22*Cartera!$D$6+K30*Cartera!$D$7+K38*Cartera!$D$8+K46*Cartera!$D$9 -> 256.59327 | ... AB53: =AB14*Cartera!$D$5+AB22*Cartera!$D$6+AB30*Cartera!$D$7+AB38*Cartera!$D$8+AB46*Cartera!$D$9 -> 2.8716153
B54: Beneficios por muerte brutos | D54: =D16+D24+D32+D40+D48 -> 27.018 | E54: =E16+E24+E32+E40+E48 -> 27.471398 | F54: =F16+F24+F32+F40+F48 -> 27.790855 | G54: =G16+G24+G32+G40+G48 -> 27.959987 | H54: =H16+H24+H32+H40+H48 -> 27.963212 | I54: =I16+I24+I32+I40+I48 -> 27.786298 | J54: =J16+J24+J32+J40+J48 -> 27.416984 | K54: =K16+K24+K32+K40+K48 -> 26.845651 | ... AB54: =AB16+AB24+AB32+AB40+AB48 -> 1.317203
B55: (−) Pérdida por default de aseguradoras | D55: =-D54*$C$7 -> -1.21581 | E55: =-E54*$C$7 -> -1.2362129 | F55: =-F54*$C$7 -> -1.2505885 | G55: =-G54*$C$7 -> -1.2581994 | H55: =-H54*$C$7 -> -1.2583445 | I55: =-I54*$C$7 -> -1.2503834 | J55: =-J54*$C$7 -> -1.2337643 | K55: =-K54*$C$7 -> -1.2080543 | ... AB55: =-AB54*$C$7 -> -0.059274137
B56: Beneficios netos cobrados | D56: =D54+D55 -> 25.80219 | E56: =E54+E55 -> 26.235185 | F56: =F54+F55 -> 26.540267 | G56: =G54+G55 -> 26.701788 | H56: =H54+H55 -> 26.704867 | I56: =I54+I55 -> 26.535915 | J56: =J54+J55 -> 26.183219 | K56: =K54+K55 -> 25.637597 | ... AB56: =AB54+AB55 -> 1.2579289
B57: (−) Primas | D57: =-(D17+D25+D33+D41+D49) -> -23.3 | E57: =-(E17+E25+E33+E41+E49) -> -22.098215 | F57: =-(F17+F25+F33+F41+F49) -> -20.842073 | G57: =-(G17+G25+G33+G41+G49) -> -19.538957 | H57: =-(H17+H25+H33+H41+H49) -> -18.19752 | I57: =-(I17+I25+I33+I41+I49) -> -16.827649 | J57: =-(J17+J25+J33+J41+J49) -> -15.440383 | K57: =-(K17+K25+K33+K41+K49) -> -14.047781 | ... AB57: =-(AB17+AB25+AB33+AB41+AB49) -> -0.17666026
B58: (−) Gastos | D58: =-(Supuestos!$C$12+Supuestos!$C$13*D53) -> -0.975 | E58: =-(Supuestos!$C$12+Supuestos!$C$13*E53) -> -0.961491 | F58: =-(Supuestos!$C$12+Supuestos!$C$13*F53) -> -0.9477553 | G58: =-(Supuestos!$C$12+Supuestos!$C$13*G53) -> -0.93385987 | H58: =-(Supuestos!$C$12+Supuestos!$C$13*H53) -> -0.91987988 | I58: =-(Supuestos!$C$12+Supuestos!$C$13*I53) -> -0.90589827 | J58: =-(Supuestos!$C$12+Supuestos!$C$13*J53) -> -0.89200512 | K58: =-(Supuestos!$C$12+Supuestos!$C$13*K53) -> -0.87829663 | ... AB58: =-(Supuestos!$C$12+Supuestos!$C$13*AB53) -> -0.75143581
B59: (+) Venta de cartera remanente (año final) | D59: =IF(D$3=Supuestos!$C$15,(D18*Cartera!$D$5+D26*Cartera!$D$6+D34*Cartera!$D$7+D42*Cartera!$D$8+D50*Cartera!$D$9)*Supuestos!$C$14*(1-$C$9),0) -> 0 | E59: =IF(E$3=Supuestos!$C$15,(E18*Cartera!$D$5+E26*Cartera!$D$6+E34*Cartera!$D$7+E42*Cartera!$D$8+E50*Cartera!$D$9)*Supuestos!$C$14*(1-$C$9),0) -> 0 | F59: =IF(F$3=Supuestos!$C$15,(F18*Cartera!$D$5+F26*Cartera!$D$6+F34*Cartera!$D$7+F42*Cartera!$D$8+F50*Cartera!$D$9)*Supuestos!$C$14*(1-$C$9),0) -> 0 | G59: =IF(G$3=Supuestos!$C$15,(G18*Cartera!$D$5+G26*Cartera!$D$6+G34*Cartera!$D$7+G42*Cartera!$D$8+G50*Cartera!$D$9)*Supuestos!$C$14*(1-$C$9),0) -> 0 | H59: =IF(H$3=Supuestos!$C$15,(H18*Cartera!$D$5+H26*Cartera!$D$6+H34*Cartera!$D$7+H42*Cartera!$D$8+H50*Cartera!$D$9)*Supuestos!$C$14*(1-$C$9),0) -> 0 | I59: =IF(I$3=Supuestos!$C$15,(I18*Cartera!$D$5+I26*Cartera!$D$6+I34*Cartera!$D$7+I42*Cartera!$D$8+I50*Cartera!$D$9)*Supuestos!$C$14*(1-$C$9),0) -> 0 | J59: =IF(J$3=Supuestos!$C$15,(J18*Cartera!$D$5+J26*Cartera!$D$6+J34*Cartera!$D$7+J42*Cartera!$D$8+J50*Cartera!$D$9)*Supuestos!$C$14*(1-$C$9),0) -> 0 | K59: =IF(K$3=Supuestos!$C$15,(K18*Cartera!$D$5+K26*Cartera!$D$6+K34*Cartera!$D$7+K42*Cartera!$D$8+K50*Cartera!$D$9)*Supuestos!$C$14*(1-$C$9),0) -> 0 | ... AB59: =IF(AB$3=Supuestos!$C$15,(AB18*Cartera!$D$5+AB26*Cartera!$D$6+AB34*Cartera!$D$7+AB42*Cartera!$D$8+AB50*Cartera!$D$9)*Supuestos!$C$14*(1-$C$9),0) -> 0.18652948
B60: Flujo neto de activos | D60: =D56+D57+D58+D59 -> 1.52719 | E60: =E56+E57+E58+E59 -> 3.1754796 | F60: =F56+F57+F58+F59 -> 4.7504381 | G60: =G56+G57+G58+G59 -> 6.2289708 | H60: =H56+H57+H58+H59 -> 7.5874677 | I60: =I56+I57+I58+I59 -> 8.8023678 | J60: =J56+J57+J58+J59 -> 9.8508312 | K60: =K56+K57+K58+K59 -> 10.711519 | ... AB60: =AB56+AB57+AB58+AB59 -> 0.51636231
B62: CASCADA
B63: Caja inicio | D63: =Supuestos!$C$9 -> 20 | E63: =D82 -> 14.87719 | F63: =E82 -> 11.248985 | G63: =F82 -> 9.086893 | H63: =G82 -> 8.3384706 | I63: =H82 -> 8.9260924 | J63: =I82 -> 10.746243 | K63: =J82 -> 13.669461 | L63: =K82 -> 14.258498 | ... AB63: =AA82 -> 0.12377602
B64: (+) Intereses de reinversión | D64: =MAX(0,D63)*Supuestos!$C$11 -> 0.6 | E64: =MAX(0,E63)*Supuestos!$C$11 -> 0.4463157 | F64: =MAX(0,F63)*Supuestos!$C$11 -> 0.33746956 | G64: =MAX(0,G63)*Supuestos!$C$11 -> 0.27260679 | H64: =MAX(0,H63)*Supuestos!$C$11 -> 0.25015412 | I64: =MAX(0,I63)*Supuestos!$C$11 -> 0.26778277 | J64: =MAX(0,J63)*Supuestos!$C$11 -> 0.32238729 | K64: =MAX(0,K63)*Supuestos!$C$11 -> 0.41008384 | ... AB64: =MAX(0,AB63)*Supuestos!$C$11 -> 0.0037132807
B65: Caja disponible | D65: =D63+D64+D60 -> 22.12719 | E65: =E63+E64+E60 -> 18.498985 | F65: =F63+F64+F60 -> 16.336893 | G65: =G63+G64+G60 -> 15.588471 | H65: =H63+H64+H60 -> 16.176092 | I65: =I63+I64+I60 -> 17.996243 | J65: =J63+J64+J60 -> 20.919461 | K65: =K63+K64+K60 -> 24.791065 | ... AB65: =AB63+AB64+AB60 -> 0.64385162
B66: Saldo Senior inicio | D66: =Supuestos!$C$5 -> 75 | E66: =D79 -> 75 | F66: =E79 -> 75 | G66: =F79 -> 75 | H66: =G79 -> 75 | I66: =H79 -> 75 | J66: =I79 -> 75 | K66: =J79 -> 75 | L66: =K79 -> 71.717433 | ... AB66: =AA79 -> 0
B67: Interés Senior debido | D67: =D66*Supuestos!$C$6 -> 4.875 | E67: =E66*Supuestos!$C$6 -> 4.875 | F67: =F66*Supuestos!$C$6 -> 4.875 | G67: =G66*Supuestos!$C$6 -> 4.875 | H67: =H66*Supuestos!$C$6 -> 4.875 | I67: =I66*Supuestos!$C$6 -> 4.875 | J67: =J66*Supuestos!$C$6 -> 4.875 | K67: =K66*Supuestos!$C$6 -> 4.875 | ... AB67: =AB66*Supuestos!$C$6 -> 0
B68: Interés Senior pagado | D68: =MAX(0,MIN(D65,D67)) -> 4.875 | E68: =MAX(0,MIN(E65,E67)) -> 4.875 | F68: =MAX(0,MIN(F65,F67)) -> 4.875 | G68: =MAX(0,MIN(G65,G67)) -> 4.875 | H68: =MAX(0,MIN(H65,H67)) -> 4.875 | I68: =MAX(0,MIN(I65,I67)) -> 4.875 | J68: =MAX(0,MIN(J65,J67)) -> 4.875 | K68: =MAX(0,MIN(K65,K67)) -> 4.875 | ... AB68: =MAX(0,MIN(AB65,AB67)) -> 0
B69: Disponible tras int. Senior | D69: =D65-D68 -> 17.25219 | E69: =E65-E68 -> 13.623985 | F69: =F65-F68 -> 11.461893 | G69: =G65-G68 -> 10.713471 | H69: =H65-H68 -> 11.301092 | I69: =I65-I68 -> 13.121243 | J69: =J65-J68 -> 16.044461 | K69: =K65-K68 -> 19.916065 | ... AB69: =AB65-AB68 -> 0.64385162
B70: Saldo Mezz inicio | D70: =Supuestos!$C$7 -> 25 | E70: =D80 -> 25 | F70: =E80 -> 25 | G70: =F80 -> 25 | H70: =G80 -> 25 | I70: =H80 -> 25 | J70: =I80 -> 25 | K70: =J80 -> 25 | L70: =K80 -> 25 | ... AB70: =AA80 -> 13.787341
B71: Interés Mezz debido | D71: =D70*Supuestos!$C$8 -> 2.375 | E71: =E70*Supuestos!$C$8 -> 2.375 | F71: =F70*Supuestos!$C$8 -> 2.375 | G71: =G70*Supuestos!$C$8 -> 2.375 | H71: =H70*Supuestos!$C$8 -> 2.375 | I71: =I70*Supuestos!$C$8 -> 2.375 | J71: =J70*Supuestos!$C$8 -> 2.375 | K71: =K70*Supuestos!$C$8 -> 2.375 | ... AB71: =AB70*Supuestos!$C$8 -> 1.3097974
B72: Interés Mezz pagado | D72: =MAX(0,MIN(D69,D71)) -> 2.375 | E72: =MAX(0,MIN(E69,E71)) -> 2.375 | F72: =MAX(0,MIN(F69,F71)) -> 2.375 | G72: =MAX(0,MIN(G69,G71)) -> 2.375 | H72: =MAX(0,MIN(H69,H71)) -> 2.375 | I72: =MAX(0,MIN(I69,I71)) -> 2.375 | J72: =MAX(0,MIN(J69,J71)) -> 2.375 | K72: =MAX(0,MIN(K69,K71)) -> 2.375 | ... AB72: =MAX(0,MIN(AB69,AB71)) -> 0.64385162
B73: Disponible tras int. Mezz | D73: =D69-D72 -> 14.87719 | E73: =E69-E72 -> 11.248985 | F73: =F69-F72 -> 9.086893 | G73: =G69-G72 -> 8.3384706 | H73: =H69-H72 -> 8.9260924 | I73: =I69-I72 -> 10.746243 | J73: =J69-J72 -> 13.669461 | K73: =K69-K72 -> 17.541065 | ... AB73: =AB69-AB72 -> 0
B74: Reserva objetivo | D74: =IF(D$3=Supuestos!$C$15,0,-D57*(1+$C$8)*Supuestos!$C$10/12) -> 23.6495 | E74: =IF(E$3=Supuestos!$C$15,0,-E57*(1+$C$8)*Supuestos!$C$10/12) -> 22.429688 | F74: =IF(F$3=Supuestos!$C$15,0,-F57*(1+$C$8)*Supuestos!$C$10/12) -> 21.154704 | G74: =IF(G$3=Supuestos!$C$15,0,-G57*(1+$C$8)*Supuestos!$C$10/12) -> 19.832041 | H74: =IF(H$3=Supuestos!$C$15,0,-H57*(1+$C$8)*Supuestos!$C$10/12) -> 18.470482 | I74: =IF(I$3=Supuestos!$C$15,0,-I57*(1+$C$8)*Supuestos!$C$10/12) -> 17.080063 | J74: =IF(J$3=Supuestos!$C$15,0,-J57*(1+$C$8)*Supuestos!$C$10/12) -> 15.671989 | K74: =IF(K$3=Supuestos!$C$15,0,-K57*(1+$C$8)*Supuestos!$C$10/12) -> 14.258498 | ... AB74: =IF(AB$3=Supuestos!$C$15,0,-AB57*(1+$C$8)*Supuestos!$C$10/12) -> 0
B75: Principal Senior pagado | D75: =MAX(0,MIN(D66+D67-D68,D73-D74)) -> 0 | E75: =MAX(0,MIN(E66+E67-E68,E73-E74)) -> 0 | F75: =MAX(0,MIN(F66+F67-F68,F73-F74)) -> 0 | G75: =MAX(0,MIN(G66+G67-G68,G73-G74)) -> 0 | H75: =MAX(0,MIN(H66+H67-H68,H73-H74)) -> 0 | I75: =MAX(0,MIN(I66+I67-I68,I73-I74)) -> 0 | J75: =MAX(0,MIN(J66+J67-J68,J73-J74)) -> 0 | K75: =MAX(0,MIN(K66+K67-K68,K73-K74)) -> 3.2825671 | ... AB75: =MAX(0,MIN(AB66+AB67-AB68,AB73-AB74)) -> 0
B76: Disponible tras Senior | D76: =D73-D75 -> 14.87719 | E76: =E73-E75 -> 11.248985 | F76: =F73-F75 -> 9.086893 | G76: =G73-G75 -> 8.3384706 | H76: =H73-H75 -> 8.9260924 | I76: =I73-I75 -> 10.746243 | J76: =J73-J75 -> 13.669461 | K76: =K73-K75 -> 14.258498 | ... AB76: =AB73-AB75 -> 0
B77: Principal Mezz pagado | D77: =MAX(0,MIN(D70+D71-D72,D76-D74)) -> 0 | E77: =MAX(0,MIN(E70+E71-E72,E76-E74)) -> 0 | F77: =MAX(0,MIN(F70+F71-F72,F76-F74)) -> 0 | G77: =MAX(0,MIN(G70+G71-G72,G76-G74)) -> 0 | H77: =MAX(0,MIN(H70+H71-H72,H76-H74)) -> 0 | I77: =MAX(0,MIN(I70+I71-I72,I76-I74)) -> 0 | J77: =MAX(0,MIN(J70+J71-J72,J76-J74)) -> 0 | K77: =MAX(0,MIN(K70+K71-K72,K76-K74)) -> 0 | ... AB77: =MAX(0,MIN(AB70+AB71-AB72,AB76-AB74)) -> 0
B78: Disponible tras Mezz | D78: =D76-D77 -> 14.87719 | E78: =E76-E77 -> 11.248985 | F78: =F76-F77 -> 9.086893 | G78: =G76-G77 -> 8.3384706 | H78: =H76-H77 -> 8.9260924 | I78: =I76-I77 -> 10.746243 | J78: =J76-J77 -> 13.669461 | K78: =K76-K77 -> 14.258498 | ... AB78: =AB76-AB77 -> 0
B79: Saldo Senior fin | D79: =D66+D67-D68-D75 -> 75 | E79: =E66+E67-E68-E75 -> 75 | F79: =F66+F67-F68-F75 -> 75 | G79: =G66+G67-G68-G75 -> 75 | H79: =H66+H67-H68-H75 -> 75 | I79: =I66+I67-I68-I75 -> 75 | J79: =J66+J67-J68-J75 -> 75 | K79: =K66+K67-K68-K75 -> 71.717433 | ... AB79: =AB66+AB67-AB68-AB75 -> 0
B80: Saldo Mezz fin | D80: =D70+D71-D72-D77 -> 25 | E80: =E70+E71-E72-E77 -> 25 | F80: =F70+F71-F72-F77 -> 25 | G80: =G70+G71-G72-G77 -> 25 | H80: =H70+H71-H72-H77 -> 25 | I80: =I70+I71-I72-I77 -> 25 | J80: =J70+J71-J72-J77 -> 25 | K80: =K70+K71-K72-K77 -> 25 | ... AB80: =AB70+AB71-AB72-AB77 -> 14.453287
B81: Distribución a equity | D81: =IF(D79+D80<0.000001,MAX(0,D78-D74),0) -> 0 | E81: =IF(E79+E80<0.000001,MAX(0,E78-E74),0) -> 0 | F81: =IF(F79+F80<0.000001,MAX(0,F78-F74),0) -> 0 | G81: =IF(G79+G80<0.000001,MAX(0,G78-G74),0) -> 0 | H81: =IF(H79+H80<0.000001,MAX(0,H78-H74),0) -> 0 | I81: =IF(I79+I80<0.000001,MAX(0,I78-I74),0) -> 0 | J81: =IF(J79+J80<0.000001,MAX(0,J78-J74),0) -> 0 | K81: =IF(K79+K80<0.000001,MAX(0,K78-K74),0) -> 0 | ... AB81: =IF(AB79+AB80<0.000001,MAX(0,AB78-AB74),0) -> 0
B82: Caja fin | D82: =D78-D81 -> 14.87719 | E82: =E78-E81 -> 11.248985 | F82: =F78-F81 -> 9.086893 | G82: =G78-G81 -> 8.3384706 | H82: =H78-H81 -> 8.9260924 | I82: =I78-I81 -> 10.746243 | J82: =J78-J81 -> 13.669461 | K82: =K78-K81 -> 14.258498 | ... AB82: =AB78-AB81 -> 0
B83: Déficit de liquidez con notas vigentes (1 = sí) | D83: =IF(AND(D65<0,D66+D70>0.000001),1,0) -> 0 | E83: =IF(AND(E65<0,E66+E70>0.000001),1,0) -> 0 | F83: =IF(AND(F65<0,F66+F70>0.000001),1,0) -> 0 | G83: =IF(AND(G65<0,G66+G70>0.000001),1,0) -> 0 | H83: =IF(AND(H65<0,H66+H70>0.000001),1,0) -> 0 | I83: =IF(AND(I65<0,I66+I70>0.000001),1,0) -> 0 | J83: =IF(AND(J65<0,J66+J70>0.000001),1,0) -> 0 | K83: =IF(AND(K65<0,K66+K70>0.000001),1,0) -> 0 | ... AB83: =IF(AND(AB65<0,AB66+AB70>0.000001),1,0) -> 0
A85: MÉTRICAS DEL ESCENARIO
B86: Pérdida Senior (% del original) | C86: =MIN(1,AB79/Supuestos!C5) -> 0
B87: Pérdida Mezz (% del original) | C87: =MIN(1,AB80/Supuestos!C7) -> 0.57813148
B88: Interés Senior impagado acumulado (USD mm) | C88: =SUM(D67:AB67)-SUM(D68:AB68) -> 0
B89: Caja mínima con notas vigentes (USD mm) | C89: =MIN(IF(D66+D70>0.000001,D65,1000000000),IF(E66+E70>0.000001,E65,1000000000),IF(F66+F70>0.000001,F65,1000000000),IF(G66+G70>0.000001,G65,1000000000),IF(H66+H70>0.000001,H65,1000000000),IF(I66+I70>0.000001,I65,1000000000),IF(J66+J70>0.000001,J65,1000000000),IF(K66+K70>0.000001,K65,1000000000),IF(L66+L70>0.000001,L65,1000000000),IF(M66+M70>0.000001,M65,1000000000),IF(N66+N70>0.000001,N65,1000000000),IF(O66+O70>0.000001,O65,1000000000),IF(P66+P70>0.000001,P65,1000000000),IF(Q66+Q70>0.000001,Q65,1000000000),IF(R66+R70>0.000001,R65,1000000000),IF(S66+S70>0.000001,S65,1000000000),IF(T66+T70>0.000001,T65,1000000000),IF(U66+U70>0.000001,U65,1000000000),IF(V66+V70>0.000001,V65,1000000000),IF(W66+W70>0.000001,W65,1000000000),IF(X66+X70>0.000001,X65,1000000000),IF(Y66+Y70>0.000001,Y65,1000000000),IF(Z66+Z70>0.000001,Z65,1000000000),IF(AA66+AA70>0.000001,AA65,1000000000),IF(AB66+AB70>0.000001,AB65,1000000000)) -> 0.64385162
B90: Años con déficit de liquidez | C90: =SUM(D83:AB83) -> 0
B91: Vida promedio Senior (años) | C91: =IFERROR(SUMPRODUCT(D75:AB75,D3:AB3)/SUM(D75:AB75),0) -> 13.243274
B92: Vida promedio Mezz (años) | C92: =IFERROR(SUMPRODUCT(D77:AB77,D3:AB3)/SUM(D77:AB77),0) -> 20.359354
B93: LE estresada ponderada por face (años) | C93: =(C18*Cartera!D5+C26*Cartera!D6+C34*Cartera!D7+C42*Cartera!D8+C50*Cartera!D9)/Cartera!D10 -> 8.8779547
B94: Senior PASA (1 = sí) | C94: =IF(AND(C86<=Supuestos!C20+0.000001,C88<0.000001),1,0) -> 1
B95: Mezz PASA (1 = sí) | C95: =IF(C87<=Supuestos!C20+0.000001,1,0) -> 0
B96: Distribuciones a equity (USD mm, sin descontar) | C96: =SUM(D81:AB81)+MAX(0,AB82) -> 0

Sheet CF_a
A1: Flujo de caja y cascada – escenario a
A2: Escenario | C2: a
A3: Año | D3: 1 | E3: 2 | F3: 3 | G3: 4 | H3: 5 | I3: 6 | J3: 7 | K3: 8 | L3: 9 | M3: 10 | N3: 11 | O3: 12 | P3: 13 | Q3: 14 | R3: 15 | S3: 16 | T3: 17 | U3: 18 | V3: 19 | W3: 20 | X3: 21 | Y3: 22 | Z3: 23 | AA3: 24 | AB3: 25
A5: Multiplicador de mortalidad | C5: =Supuestos!C26 -> 0.82
A6: Penalidad pool pequeño | C6: =Supuestos!D26 -> 0.03
A7: Pérdida default aseguradoras | C7: =Supuestos!E26 -> 0.03
A8: Aumento anual de primas | C8: =Supuestos!F26 -> 0.01
A9: Haircut valor remanente | C9: =Supuestos!G26 -> 0.3
A10: Multiplicador efectivo | C10: =MAX(0,C5-IF(Cartera!C10<Supuestos!C16,C6,0)) -> 0.82
A12: =Cartera!A5&" – "&Cartera!B5 -> C1 – Edad 75–79, salud estándar
B13: q estresada | D13: =MIN(1,Cartera!$F$5*(1+Cartera!$G$5)^(D$3-1)*$C$10) -> 0.0369 | E13: =MIN(1,Cartera!$F$5*(1+Cartera!$G$5)^(E$3-1)*$C$10) -> 0.040959 | F13: =MIN(1,Cartera!$F$5*(1+Cartera!$G$5)^(F$3-1)*$C$10) -> 0.04546449 | G13: =MIN(1,Cartera!$F$5*(1+Cartera!$G$5)^(G$3-1)*$C$10) -> 0.050465584 | H13: =MIN(1,Cartera!$F$5*(1+Cartera!$G$5)^(H$3-1)*$C$10) -> 0.056016798 | I13: =MIN(1,Cartera!$F$5*(1+Cartera!$G$5)^(I$3-1)*$C$10) -> 0.062178646 | J13: =MIN(1,Cartera!$F$5*(1+Cartera!$G$5)^(J$3-1)*$C$10) -> 0.069018297 | K13: =MIN(1,Cartera!$F$5*(1+Cartera!$G$5)^(K$3-1)*$C$10) -> 0.07661031 | ... AB13: =MIN(1,Cartera!$F$5*(1+Cartera!$G$5)^(AB$3-1)*$C$10) -> 0.45162488
B14: Supervivencia inicio | C14: LE estresada → | D14: =1 -> 1 | E14: =D18 -> 0.9631 | F14: =E18 -> 0.92365239 | G14: =F18 -> 0.881659 | H14: =G18 -> 0.83716557 | I14: =H18 -> 0.79027023 | J14: =I18 -> 0.7411323 | K14: =J18 -> 0.68998061 | L14: =K18 -> 0.63712098 | ... AB14: =AA18 -> 0.013325124
B15: Muertes (fracción) | D15: =D14*D13 -> 0.0369 | E15: =E14*E13 -> 0.039447613 | F15: =F14*F13 -> 0.041993385 | G15: =G14*G13 -> 0.044493436 | H15: =H14*H13 -> 0.046895335 | I15: =I14*I13 -> 0.049137933 | J15: =J14*J13 -> 0.051151689 | K15: =K14*K13 -> 0.052859628 | ... AB15: =AB14*AB13 -> 0.0060179575
B16: Beneficio por muerte bruto (USD mm) | D16: =D15*Cartera!$D$5 -> 3.321 | E16: =E15*Cartera!$D$5 -> 3.5502852 | F16: =F15*Cartera!$D$5 -> 3.7794046 | G16: =G15*Cartera!$D$5 -> 4.0044093 | H16: =H15*Cartera!$D$5 -> 4.2205801 | I16: =I15*Cartera!$D$5 -> 4.422414 | J16: =J15*Cartera!$D$5 -> 4.603652 | K16: =K15*Cartera!$D$5 -> 4.7573665 | ... AB16: =AB15*Cartera!$D$5 -> 0.54161618
B17: Primas pagadas (USD mm) | D17: =D14*Cartera!$D$5*Cartera!$H$5*(1+$C$8)^(D$3-1) -> 3.6 | E17: =E14*Cartera!$D$5*Cartera!$H$5*(1+$C$8)^(E$3-1) -> 3.5018316 | F17: =F14*Cartera!$D$5*Cartera!$H$5*(1+$C$8)^(F$3-1) -> 3.3919841 | G17: =G14*Cartera!$D$5*Cartera!$H$5*(1+$C$8)^(G$3-1) -> 3.2701469 | H17: =H14*Cartera!$D$5*Cartera!$H$5*(1+$C$8)^(H$3-1) -> 3.1361682 | I17: =I14*Cartera!$D$5*Cartera!$H$5*(1+$C$8)^(I$3-1) -> 2.990095 | J17: =J14*Cartera!$D$5*Cartera!$H$5*(1+$C$8)^(J$3-1) -> 2.8322167 | K17: =K14*Cartera!$D$5*Cartera!$H$5*(1+$C$8)^(K$3-1) -> 2.6631094 | ... AB17: =AB14*Cartera!$D$5*Cartera!$H$5*(1+$C$8)^(AB$3-1) -> 0.060909738
B18: Supervivencia fin | C18: =SUM(D18:AB18)+0.5 -> 10.737455 | D18: =D14-D15 -> 0.9631 | E18: =E14-E15 -> 0.92365239 | F18: =F14-F15 -> 0.881659 | G18: =G14-G15 -> 0.83716557 | H18: =H14-H15 -> 0.79027023 | I18: =I14-I15 -> 0.7411323 | J18: =J14-J15 -> 0.68998061 | K18: =K14-K15 -> 0.63712098 | ... AB18: =AB14-AB15 -> 0.0073071665
A20: =Cartera!A6&" – "&Cartera!B6 -> C2 – Edad 80–84, deterioro moderado
B21: q estresada | D21: =MIN(1,Cartera!$F$6*(1+Cartera!$G$6)^(D$3-1)*$C$10) -> 0.0533 | E21: =MIN(1,Cartera!$F$6*(1+Cartera!$G$6)^(E$3-1)*$C$10) -> 0.05863 | F21: =MIN(1,Cartera!$F$6*(1+Cartera!$G$6)^(F$3-1)*$C$10) -> 0.064493 | G21: =MIN(1,Cartera!$F$6*(1+Cartera!$G$6)^(G$3-1)*$C$10) -> 0.0709423 | H21: =MIN(1,Cartera!$F$6*(1+Cartera!$G$6)^(H$3-1)*$C$10) -> 0.07803653 | I21: =MIN(1,Cartera!$F$6*(1+Cartera!$G$6)^(I$3-1)*$C$10) -> 0.085840183 | J21: =MIN(1,Cartera!$F$6*(1+Cartera!$G$6)^(J$3-1)*$C$10) -> 0.094424201 | K21: =MIN(1,Cartera!$F$6*(1+Cartera!$G$6)^(K$3-1)*$C$10) -> 0.10386662 | ... AB21: =MIN(1,Cartera!$F$6*(1+Cartera!$G$6)^(AB$3-1)*$C$10) -> 0.52499075
B22: Supervivencia inicio | C22: LE estresada → | D22: =1 -> 1 | E22: =D26 -> 0.9467 | F22: =E26 -> 0.89119498 | G22: =F26 -> 0.83371914 | H22: =G26 -> 0.77457319 | I22: =H26 -> 0.71412818 | J22: =I26 -> 0.65282729 | K22: =J26 -> 0.59118459 | L22: =K26 -> 0.52978025 | ... AB22: =AA26 -> 0.0037985334
B23: Muertes (fracción) | D23: =D22*D21 -> 0.0533 | E23: =E22*E21 -> 0.055505021 | F23: =F22*F21 -> 0.057475838 | G23: =G22*G21 -> 0.059145953 | H23: =H22*H21 -> 0.060445004 | I23: =I22*I21 -> 0.061300894 | J23: =J22*J21 -> 0.061642695 | K23: =K22*K21 -> 0.061404346 | ... AB23: =AB22*AB21 -> 0.0019941949
B24: Beneficio por muerte bruto (USD mm) | D24: =D23*Cartera!$D$6 -> 6.396 | E24: =E23*Cartera!$D$6 -> 6.6606025 | F24: =F23*Cartera!$D$6 -> 6.8971005 | G24: =G23*Cartera!$D$6 -> 7.0975144 | H24: =H23*Cartera!$D$6 -> 7.2534005 | I24: =I23*Cartera!$D$6 -> 7.3561073 | J24: =J23*Cartera!$D$6 -> 7.3971235 | K24: =K23*Cartera!$D$6 -> 7.3685216 | ... AB24: =AB23*Cartera!$D$6 -> 0.23930339
B25: Primas pagadas (USD mm) | D25: =D22*Cartera!$D$6*Cartera!$H$6*(1+$C$8)^(D$3-1) -> 6 | E25: =E22*Cartera!$D$6*Cartera!$H$6*(1+$C$8)^(E$3-1) -> 5.737002 | F25: =F22*Cartera!$D$6*Cartera!$H$6*(1+$C$8)^(F$3-1) -> 5.454648 | G25: =G22*Cartera!$D$6*Cartera!$H$6*(1+$C$8)^(G$3-1) -> 5.15389 | H25: =H22*Cartera!$D$6*Cartera!$H$6*(1+$C$8)^(H$3-1) -> 4.8361438 | I25: =I22*Cartera!$D$6*Cartera!$H$6*(1+$C$8)^(I$3-1) -> 4.5033354 | J25: =J22*Cartera!$D$6*Cartera!$H$6*(1+$C$8)^(J$3-1) -> 4.1579359 | K25: =K22*Cartera!$D$6*Cartera!$H$6*(1+$C$8)^(K$3-1) -> 3.8029794 | ... AB25: =AB22*Cartera!$D$6*Cartera!$H$6*(1+$C$8)^(AB$3-1) -> 0.028938777
B26: Supervivencia fin | C26: =SUM(D26:AB26)+0.5 -> 9.0031274 | D26: =D22-D23 -> 0.9467 | E26: =E22-E23 -> 0.89119498 | F26: =F22-F23 -> 0.83371914 | G26: =G22-G23 -> 0.77457319 | H26: =H22-H23 -> 0.71412818 | I26: =I22-I23 -> 0.65282729 | J26: =J22-J23 -> 0.59118459 | K26: =K22-K23 -> 0.52978025 | ... AB26: =AB22-AB23 -> 0.0018043385
A28: =Cartera!A7&" – "&Cartera!B7 -> C3 – Edad 85–89, deterioro significativo
B29: q estresada | D29: =MIN(1,Cartera!$F$7*(1+Cartera!$G$7)^(D$3-1)*$C$10) -> 0.0779 | E29: =MIN(1,Cartera!$F$7*(1+Cartera!$G$7)^(E$3-1)*$C$10) -> 0.084911 | F29: =MIN(1,Cartera!$F$7*(1+Cartera!$G$7)^(F$3-1)*$C$10) -> 0.09255299 | G29: =MIN(1,Cartera!$F$7*(1+Cartera!$G$7)^(G$3-1)*$C$10) -> 0.10088276 | H29: =MIN(1,Cartera!$F$7*(1+Cartera!$G$7)^(H$3-1)*$C$10) -> 0.10996221 | I29: =MIN(1,Cartera!$F$7*(1+Cartera!$G$7)^(I$3-1)*$C$10) -> 0.11985881 | J29: =MIN(1,Cartera!$F$7*(1+Cartera!$G$7)^(J$3-1)*$C$10) -> 0.1306461 | K29: =MIN(1,Cartera!$F$7*(1+Cartera!$G$7)^(K$3-1)*$C$10) -> 0.14240425 | ... AB29: =MIN(1,Cartera!$F$7*(1+Cartera!$G$7)^(AB$3-1)*$C$10) -> 0.61627338
B30: Supervivencia inicio | C30: LE estresada → | D30: =1 -> 1 | E30: =D34 -> 0.9221 | F30: =E34 -> 0.84380357 | G30: =F34 -> 0.76570702 | H30: =G34 -> 0.68846039 | I30: =H34 -> 0.61275576 | J30: =I34 -> 0.53931159 | K30: =J34 -> 0.46885263 | L30: =K34 -> 0.40208603 | ... AB30: =AA34 -> 0.0006210267
B31: Muertes (fracción) | D31: =D30*D29 -> 0.0779 | E31: =E30*E29 -> 0.078296433 | F31: =F30*F29 -> 0.078096543 | G31: =G30*G29 -> 0.077246637 | H31: =H30*H29 -> 0.075704624 | I31: =I30*I29 -> 0.073444174 | J31: =J30*J29 -> 0.070458955 | K31: =K30*K29 -> 0.066766606 | ... AB31: =AB30*AB29 -> 0.00038272222
B32: Beneficio por muerte bruto (USD mm) | D32: =D31*Cartera!$D$7 -> 7.79 | E32: =E31*Cartera!$D$7 -> 7.8296433 | F32: =F31*Cartera!$D$7 -> 7.8096543 | G32: =G31*Cartera!$D$7 -> 7.7246637 | H32: =H31*Cartera!$D$7 -> 7.5704624 | I32: =I31*Cartera!$D$7 -> 7.3444174 | J32: =J31*Cartera!$D$7 -> 7.0458955 | K32: =K31*Cartera!$D$7 -> 6.6766606 | ... AB32: =AB31*Cartera!$D$7 -> 0.038272222
B33: Primas pagadas (USD mm) | D33: =D30*Cartera!$D$7*Cartera!$H$7*(1+$C$8)^(D$3-1) -> 6 | E33: =E30*Cartera!$D$7*Cartera!$H$7*(1+$C$8)^(E$3-1) -> 5.587926 | F33: =F30*Cartera!$D$7*Cartera!$H$7*(1+$C$8)^(F$3-1) -> 5.1645841 | G33: =G30*Cartera!$D$7*Cartera!$H$7*(1+$C$8)^(G$3-1) -> 4.7334523 | H33: =H30*Cartera!$D$7*Cartera!$H$7*(1+$C$8)^(H$3-1) -> 4.2984878 | I33: =I30*Cartera!$D$7*Cartera!$H$7*(1+$C$8)^(I$3-1) -> 3.8640748 | J33: =J30*Cartera!$D$7*Cartera!$H$7*(1+$C$8)^(J$3-1) -> 3.4349407 | K33: =K30*Cartera!$D$7*Cartera!$H$7*(1+$C$8)^(K$3-1) -> 3.0160409 | ... AB33: =AB30*Cartera!$D$7*Cartera!$H$7*(1+$C$8)^(AB$3-1) -> 0.0047312347
B34: Supervivencia fin | C34: =SUM(D34:AB34)+0.5 -> 7.2749429 | D34: =D30-D31 -> 0.9221 | E34: =E30-E31 -> 0.84380357 | F34: =F30-F31 -> 0.76570702 | G34: =G30-G31 -> 0.68846039 | H34: =H30-H31 -> 0.61275576 | I34: =I30-I31 -> 0.53931159 | J34: =J30-J31 -> 0.46885263 | K34: =K30-K31 -> 0.40208603 | ... AB34: =AB30-AB31 -> 0.00023830448
A36: =Cartera!A8&" – "&Cartera!B8 -> C4 – Edad 90+, deterioro severo
B37: q estresada | D37: =MIN(1,Cartera!$F$8*(1+Cartera!$G$8)^(D$3-1)*$C$10) -> 0.1148 | E37: =MIN(1,Cartera!$F$8*(1+Cartera!$G$8)^(E$3-1)*$C$10) -> 0.123984 | F37: =MIN(1,Cartera!$F$8*(1+Cartera!$G$8)^(F$3-1)*$C$10) -> 0.13390272 | G37: =MIN(1,Cartera!$F$8*(1+Cartera!$G$8)^(G$3-1)*$C$10) -> 0.14461494 | H37: =MIN(1,Cartera!$F$8*(1+Cartera!$G$8)^(H$3-1)*$C$10) -> 0.15618413 | I37: =MIN(1,Cartera!$F$8*(1+Cartera!$G$8)^(I$3-1)*$C$10) -> 0.16867886 | J37: =MIN(1,Cartera!$F$8*(1+Cartera!$G$8)^(J$3-1)*$C$10) -> 0.18217317 | K37: =MIN(1,Cartera!$F$8*(1+Cartera!$G$8)^(K$3-1)*$C$10) -> 0.19674703 | ... AB37: =MIN(1,Cartera!$F$8*(1+Cartera!$G$8)^(AB$3-1)*$C$10) -> 0.72796755
B38: Supervivencia inicio | C38: LE estresada → | D38: =1 -> 1 | E38: =D42 -> 0.8852 | F38: =E42 -> 0.77544936 | G38: =F42 -> 0.67161458 | H38: =G42 -> 0.57448908 | I38: =H42 -> 0.484763 | J38: =I42 -> 0.40299373 | K38: =J42 -> 0.32957909 | L38: =K42 -> 0.26473538 | ... AB38: =AA42 -> 4.1786061e-05
B39: Muertes (fracción) | D39: =D38*D37 -> 0.1148 | E39: =E38*E37 -> 0.10975064 | F39: =F38*F37 -> 0.10383478 | G39: =G38*G37 -> 0.097125501 | H39: =H38*H37 -> 0.089726079 | I39: =I38*I37 -> 0.081769272 | J39: =J38*J37 -> 0.073414646 | K39: =K38*K37 -> 0.064843705 | ... AB39: =AB38*AB37 -> 3.0418896e-05
B40: Beneficio por muerte bruto (USD mm) | D40: =D39*Cartera!$D$8 -> 9.184 | E40: =E39*Cartera!$D$8 -> 8.7800509 | F40: =F39*Cartera!$D$8 -> 8.3067823 | G40: =G39*Cartera!$D$8 -> 7.7700401 | H40: =H39*Cartera!$D$8 -> 7.1780863 | I40: =I39*Cartera!$D$8 -> 6.5415418 | J40: =J39*Cartera!$D$8 -> 5.8731717 | K40: =K39*Cartera!$D$8 -> 5.1874964 | ... AB40: =AB39*Cartera!$D$8 -> 0.0024335117
B41: Primas pagadas (USD mm) | D41: =D38*Cartera!$D$8*Cartera!$H$8*(1+$C$8)^(D$3-1) -> 5.6 | E41: =E38*Cartera!$D$8*Cartera!$H$8*(1+$C$8)^(E$3-1) -> 5.0066912 | F41: =F38*Cartera!$D$8*Cartera!$H$8*(1+$C$8)^(F$3-1) -> 4.429801 | G41: =G38*Cartera!$D$8*Cartera!$H$8*(1+$C$8)^(G$3-1) -> 3.875005 | H41: =H38*Cartera!$D$8*Cartera!$H$8*(1+$C$8)^(H$3-1) -> 3.3477676 | I41: =I38*Cartera!$D$8*Cartera!$H$8*(1+$C$8)^(I$3-1) -> 2.8531484 | J41: =J38*Cartera!$D$8*Cartera!$H$8*(1+$C$8)^(J$3-1) -> 2.3956014 | K41: =K38*Cartera!$D$8*Cartera!$H$8*(1+$C$8)^(K$3-1) -> 1.978779 | ... AB41: =AB38*Cartera!$D$8*Cartera!$H$8*(1+$C$8)^(AB$3-1) -> 0.00029712037
B42: Supervivencia fin | C42: =SUM(D42:AB42)+0.5 -> 5.6442719 | D42: =D38-D39 -> 0.8852 | E42: =E38-E39 -> 0.77544936 | F42: =F38-F39 -> 0.67161458 | G42: =G38-G39 -> 0.57448908 | H42: =H38-H39 -> 0.484763 | I42: =I38-I39 -> 0.40299373 | J42: =J38-J39 -> 0.32957909 | K42: =K38-K39 -> 0.26473538 | ... AB42: =AB38-AB39 -> 1.1367164e-05
A44: =Cartera!A9&" – "&Cartera!B9 -> C5 – Edad 70–74, enfermedad crónica
B45: q estresada | D45: =MIN(1,Cartera!$F$9*(1+Cartera!$G$9)^(D$3-1)*$C$10) -> 0.041 | E45: =MIN(1,Cartera!$F$9*(1+Cartera!$G$9)^(E$3-1)*$C$10) -> 0.04592 | F45: =MIN(1,Cartera!$F$9*(1+Cartera!$G$9)^(F$3-1)*$C$10) -> 0.0514304 | G45: =MIN(1,Cartera!$F$9*(1+Cartera!$G$9)^(G$3-1)*$C$10) -> 0.057602048 | H45: =MIN(1,Cartera!$F$9*(1+Cartera!$G$9)^(H$3-1)*$C$10) -> 0.064514294 | I45: =MIN(1,Cartera!$F$9*(1+Cartera!$G$9)^(I$3-1)*$C$10) -> 0.072256009 | J45: =MIN(1,Cartera!$F$9*(1+Cartera!$G$9)^(J$3-1)*$C$10) -> 0.08092673 | K45: =MIN(1,Cartera!$F$9*(1+Cartera!$G$9)^(K$3-1)*$C$10) -> 0.090637938 | ... AB45: =MIN(1,Cartera!$F$9*(1+Cartera!$G$9)^(AB$3-1)*$C$10) -> 0.62232379
B46: Supervivencia inicio | C46: LE estresada → | D46: =1 -> 1 | E46: =D50 -> 0.959 | F46: =E50 -> 0.91496272 | G46: =F50 -> 0.86790582 | H46: =G50 -> 0.81791267 | I46: =H50 -> 0.76514561 | J46: =I50 -> 0.70985924 | K46: =J50 -> 0.65241265 | L46: =K50 -> 0.59327932 | ... AB46: =AA50 -> 0.0027169342
B47: Muertes (fracción) | D47: =D46*D45 -> 0.041 | E47: =E46*E45 -> 0.04403728 | F47: =F46*F45 -> 0.047056899 | G47: =G46*G45 -> 0.049993153 | H47: =H46*H45 -> 0.052767058 | I47: =I46*I45 -> 0.055286368 | J47: =J46*J45 -> 0.057446587 | K47: =K46*K45 -> 0.059133338 | ... AB47: =AB46*AB45 -> 0.0016908128
B48: Beneficio por muerte bruto (USD mm) | D48: =D47*Cartera!$D$9 -> 2.46 | E48: =E47*Cartera!$D$9 -> 2.6422368 | F48: =F47*Cartera!$D$9 -> 2.8234139 | G48: =G47*Cartera!$D$9 -> 2.9995892 | H48: =H47*Cartera!$D$9 -> 3.1660235 | I48: =I47*Cartera!$D$9 -> 3.3171821 | J48: =J47*Cartera!$D$9 -> 3.4467952 | K48: =K47*Cartera!$D$9 -> 3.5480003 | ... AB48: =AB47*Cartera!$D$9 -> 0.10144877
B49: Primas pagadas (USD mm) | D49: =D46*Cartera!$D$9*Cartera!$H$9*(1+$C$8)^(D$3-1) -> 2.1 | E49: =E46*Cartera!$D$9*Cartera!$H$9*(1+$C$8)^(E$3-1) -> 2.034039 | F49: =F46*Cartera!$D$9*Cartera!$H$9*(1+$C$8)^(F$3-1) -> 1.9600423 | G49: =G46*Cartera!$D$9*Cartera!$H$9*(1+$C$8)^(G$3-1) -> 1.8778289 | H49: =H46*Cartera!$D$9*Cartera!$H$9*(1+$C$8)^(H$3-1) -> 1.7873587 | I49: =I46*Cartera!$D$9*Cartera!$H$9*(1+$C$8)^(I$3-1) -> 1.688769 | J49: =J46*Cartera!$D$9*Cartera!$H$9*(1+$C$8)^(J$3-1) -> 1.5824128 | K49: =K46*Cartera!$D$9*Cartera!$H$9*(1+$C$8)^(K$3-1) -> 1.4688968 | ... AB49: =AB46*Cartera!$D$9*Cartera!$H$9*(1+$C$8)^(AB$3-1) -> 0.0072445494
B50: Supervivencia fin | C50: =SUM(D50:AB50)+0.5 -> 9.7690305 | D50: =D46-D47 -> 0.959 | E50: =E46-E47 -> 0.91496272 | F50: =F46-F47 -> 0.86790582 | G50: =G46-G47 -> 0.81791267 | H50: =H46-H47 -> 0.76514561 | I50: =I46-I47 -> 0.70985924 | J50: =J46-J47 -> 0.65241265 | K50: =K46-K47 -> 0.59327932 | ... AB50: =AB46-AB47 -> 0.0010261214
A52: CARTERA TOTAL
B53: Face en vigor inicio (USD mm) | D53: =D14*Cartera!$D$5+D22*Cartera!$D$6+D30*Cartera!$D$7+D38*Cartera!$D$8+D46*Cartera!$D$9 -> 450 | E53: =E14*Cartera!$D$5+E22*Cartera!$D$6+E30*Cartera!$D$7+E38*Cartera!$D$8+E46*Cartera!$D$9 -> 420.849 | F53: =F14*Cartera!$D$5+F22*Cartera!$D$6+F30*Cartera!$D$7+F38*Cartera!$D$8+F46*Cartera!$D$9 -> 391.38618 | G53: =G14*Cartera!$D$5+G22*Cartera!$D$6+G30*Cartera!$D$7+G38*Cartera!$D$8+G46*Cartera!$D$9 -> 361.76983 | H53: =H14*Cartera!$D$5+H22*Cartera!$D$6+H30*Cartera!$D$7+H38*Cartera!$D$8+H46*Cartera!$D$9 -> 332.17361 | I53: =I14*Cartera!$D$5+I22*Cartera!$D$6+I30*Cartera!$D$7+I38*Cartera!$D$8+I46*Cartera!$D$9 -> 302.78506 | J53: =J14*Cartera!$D$5+J22*Cartera!$D$6+J30*Cartera!$D$7+J38*Cartera!$D$8+J46*Cartera!$D$9 -> 273.80339 | K53: =K14*Cartera!$D$5+K22*Cartera!$D$6+K30*Cartera!$D$7+K38*Cartera!$D$8+K46*Cartera!$D$9 -> 245.43676 | ... AB53: =AB14*Cartera!$D$5+AB22*Cartera!$D$6+AB30*Cartera!$D$7+AB38*Cartera!$D$8+AB46*Cartera!$D$9 -> 1.8835468
B54: Beneficios por muerte brutos | D54: =D16+D24+D32+D40+D48 -> 29.151 | E54: =E16+E24+E32+E40+E48 -> 29.462819 | F54: =F16+F24+F32+F40+F48 -> 29.616356 | G54: =G16+G24+G32+G40+G48 -> 29.596217 | H54: =H16+H24+H32+H40+H48 -> 29.388553 | I54: =I16+I24+I32+I40+I48 -> 28.981663 | J54: =J16+J24+J32+J40+J48 -> 28.366638 | K54: =K16+K24+K32+K40+K48 -> 27.538045 | ... AB54: =AB16+AB24+AB32+AB40+AB48 -> 0.92307406
B55: (−) Pérdida por default de aseguradoras | D55: =-D54*$C$7 -> -0.87453 | E55: =-E54*$C$7 -> -0.88388456 | F55: =-F54*$C$7 -> -0.88849067 | G55: =-G54*$C$7 -> -0.8878865 | H55: =-H54*$C$7 -> -0.88165658 | I55: =-I54*$C$7 -> -0.86944988 | J55: =-J54*$C$7 -> -0.85099914 | K55: =-K54*$C$7 -> -0.82614136 | ... AB55: =-AB54*$C$7 -> -0.027692222
B56: Beneficios netos cobrados | D56: =D54+D55 -> 28.27647 | E56: =E54+E55 -> 28.578934 | F56: =F54+F55 -> 28.727865 | G56: =G54+G55 -> 28.70833 | H56: =H54+H55 -> 28.506896 | I56: =I54+I55 -> 28.112213 | J56: =J54+J55 -> 27.515639 | K56: =K54+K55 -> 26.711904 | ... AB56: =AB54+AB55 -> 0.89538184
B57: (−) Primas | D57: =-(D17+D25+D33+D41+D49) -> -23.3 | E57: =-(E17+E25+E33+E41+E49) -> -21.86749 | F57: =-(F17+F25+F33+F41+F49) -> -20.401059 | G57: =-(G17+G25+G33+G41+G49) -> -18.910323 | H57: =-(H17+H25+H33+H41+H49) -> -17.405926 | I57: =-(I17+I25+I33+I41+I49) -> -15.899423 | J57: =-(J17+J25+J33+J41+J49) -> -14.403108 | K57: =-(K17+K25+K33+K41+K49) -> -12.929805 | ... AB57: =-(AB17+AB25+AB33+AB41+AB49) -> -0.10212142
B58: (−) Gastos | D58: =-(Supuestos!$C$12+Supuestos!$C$13*D53) -> -0.975 | E58: =-(Supuestos!$C$12+Supuestos!$C$13*E53) -> -0.9604245 | F58: =-(Supuestos!$C$12+Supuestos!$C$13*F53) -> -0.94569309 | G58: =-(Supuestos!$C$12+Supuestos!$C$13*G53) -> -0.93088491 | H58: =-(Supuestos!$C$12+Supuestos!$C$13*H53) -> -0.9160868 | I58: =-(Supuestos!$C$12+Supuestos!$C$13*I53) -> -0.90139253 | J58: =-(Supuestos!$C$12+Supuestos!$C$13*J53) -> -0.8869017 | K58: =-(Supuestos!$C$12+Supuestos!$C$13*K53) -> -0.87271838 | ... AB58: =-(Supuestos!$C$12+Supuestos!$C$13*AB53) -> -0.75094177
B59: (+) Venta de cartera remanente (año final) | D59: =IF(D$3=Supuestos!$C$15,(D18*Cartera!$D$5+D26*Cartera!$D$6+D34*Cartera!$D$7+D42*Cartera!$D$8+D50*Cartera!$D$9)*Supuestos!$C$14*(1-$C$9),0) -> 0 | E59: =IF(E$3=Supuestos!$C$15,(E18*Cartera!$D$5+E26*Cartera!$D$6+E34*Cartera!$D$7+E42*Cartera!$D$8+E50*Cartera!$D$9)*Supuestos!$C$14*(1-$C$9),0) -> 0 | F59: =IF(F$3=Supuestos!$C$15,(F18*Cartera!$D$5+F26*Cartera!$D$6+F34*Cartera!$D$7+F42*Cartera!$D$8+F50*Cartera!$D$9)*Supuestos!$C$14*(1-$C$9),0) -> 0 | G59: =IF(G$3=Supuestos!$C$15,(G18*Cartera!$D$5+G26*Cartera!$D$6+G34*Cartera!$D$7+G42*Cartera!$D$8+G50*Cartera!$D$9)*Supuestos!$C$14*(1-$C$9),0) -> 0 | H59: =IF(H$3=Supuestos!$C$15,(H18*Cartera!$D$5+H26*Cartera!$D$6+H34*Cartera!$D$7+H42*Cartera!$D$8+H50*Cartera!$D$9)*Supuestos!$C$14*(1-$C$9),0) -> 0 | I59: =IF(I$3=Supuestos!$C$15,(I18*Cartera!$D$5+I26*Cartera!$D$6+I34*Cartera!$D$7+I42*Cartera!$D$8+I50*Cartera!$D$9)*Supuestos!$C$14*(1-$C$9),0) -> 0 | J59: =IF(J$3=Supuestos!$C$15,(J18*Cartera!$D$5+J26*Cartera!$D$6+J34*Cartera!$D$7+J42*Cartera!$D$8+J50*Cartera!$D$9)*Supuestos!$C$14*(1-$C$9),0) -> 0 | K59: =IF(K$3=Supuestos!$C$15,(K18*Cartera!$D$5+K26*Cartera!$D$6+K34*Cartera!$D$7+K42*Cartera!$D$8+K50*Cartera!$D$9)*Supuestos!$C$14*(1-$C$9),0) -> 0 | ... AB59: =IF(AB$3=Supuestos!$C$15,(AB18*Cartera!$D$5+AB26*Cartera!$D$6+AB34*Cartera!$D$7+AB42*Cartera!$D$8+AB50*Cartera!$D$9)*Supuestos!$C$14*(1-$C$9),0) -> 0.13446618
B60: Flujo neto de activos | D60: =D56+D57+D58+D59 -> 4.00147 | E60: =E56+E57+E58+E59 -> 5.7510199 | F60: =F56+F57+F58+F59 -> 7.3811125 | G60: =G56+G57+G58+G59 -> 8.8671222 | H60: =H56+H57+H58+H59 -> 10.184883 | I60: =I56+I57+I58+I59 -> 11.311397 | J60: =J56+J57+J58+J59 -> 12.22563 | K60: =K56+K57+K58+K59 -> 12.90938 | ... AB60: =AB56+AB57+AB58+AB59 -> 0.17678483
B62: CASCADA
B63: Caja inicio | D63: =Supuestos!$C$9 -> 20 | E63: =D82 -> 17.35147 | F63: =E82 -> 16.373034 | G63: =F82 -> 16.995337 | H63: =G82 -> 19.099426 | I63: =H82 -> 17.579985 | J63: =I82 -> 16.058417 | K63: =J82 -> 14.547139 | L63: =K82 -> 13.059104 | ... AB63: =AA82 -> 0.18615339
B64: (+) Intereses de reinversión | D64: =MAX(0,D63)*Supuestos!$C$11 -> 0.6 | E64: =MAX(0,E63)*Supuestos!$C$11 -> 0.5205441 | F64: =MAX(0,F63)*Supuestos!$C$11 -> 0.49119102 | G64: =MAX(0,G63)*Supuestos!$C$11 -> 0.50986012 | H64: =MAX(0,H63)*Supuestos!$C$11 -> 0.57298279 | I64: =MAX(0,I63)*Supuestos!$C$11 -> 0.52739956 | J64: =MAX(0,J63)*Supuestos!$C$11 -> 0.48175251 | K64: =MAX(0,K63)*Supuestos!$C$11 -> 0.43641416 | ... AB64: =MAX(0,AB63)*Supuestos!$C$11 -> 0.0055846018
B65: Caja disponible | D65: =D63+D64+D60 -> 24.60147 | E65: =E63+E64+E60 -> 23.623034 | F65: =F63+F64+F60 -> 24.245337 | G65: =G63+G64+G60 -> 26.37232 | H65: =H63+H64+H60 -> 29.857292 | I65: =I63+I64+I60 -> 29.418782 | J65: =J63+J64+J60 -> 28.765799 | K65: =K63+K64+K60 -> 27.892933 | ... AB65: =AB63+AB64+AB60 -> 0.36852282
B66: Saldo Senior inicio | D66: =Supuestos!$C$5 -> 75 | E66: =D79 -> 75 | F66: =E79 -> 75 | G66: =F79 -> 75 | H66: =G79 -> 74.977107 | I66: =H79 -> 69.948312 | J66: =I79 -> 63.509586 | K66: =J79 -> 55.794049 | L66: =K79 -> 46.961833 | ... AB66: =AA79 -> 0
B67: Interés Senior debido | D67: =D66*Supuestos!$C$6 -> 4.875 | E67: =E66*Supuestos!$C$6 -> 4.875 | F67: =F66*Supuestos!$C$6 -> 4.875 | G67: =G66*Supuestos!$C$6 -> 4.875 | H67: =H66*Supuestos!$C$6 -> 4.8735119 | I67: =I66*Supuestos!$C$6 -> 4.5466403 | J67: =J66*Supuestos!$C$6 -> 4.1281231 | K67: =K66*Supuestos!$C$6 -> 3.6266132 | ... AB67: =AB66*Supuestos!$C$6 -> 0
B68: Interés Senior pagado | D68: =MAX(0,MIN(D65,D67)) -> 4.875 | E68: =MAX(0,MIN(E65,E67)) -> 4.875 | F68: =MAX(0,MIN(F65,F67)) -> 4.875 | G68: =MAX(0,MIN(G65,G67)) -> 4.875 | H68: =MAX(0,MIN(H65,H67)) -> 4.8735119 | I68: =MAX(0,MIN(I65,I67)) -> 4.5466403 | J68: =MAX(0,MIN(J65,J67)) -> 4.1281231 | K68: =MAX(0,MIN(K65,K67)) -> 3.6266132 | ... AB68: =MAX(0,MIN(AB65,AB67)) -> 0
B69: Disponible tras int. Senior | D69: =D65-D68 -> 19.72647 | E69: =E65-E68 -> 18.748034 | F69: =F65-F68 -> 19.370337 | G69: =G65-G68 -> 21.49732 | H69: =H65-H68 -> 24.98378 | I69: =I65-I68 -> 24.872142 | J69: =J65-J68 -> 24.637676 | K69: =K65-K68 -> 24.26632 | ... AB69: =AB65-AB68 -> 0.36852282
B70: Saldo Mezz inicio | D70: =Supuestos!$C$7 -> 25 | E70: =D80 -> 25 | F70: =E80 -> 25 | G70: =F80 -> 25 | H70: =G80 -> 25 | I70: =H80 -> 25 | J70: =I80 -> 25 | K70: =J80 -> 25 | L70: =K80 -> 25 | ... AB70: =AA80 -> 0
B71: Interés Mezz debido | D71: =D70*Supuestos!$C$8 -> 2.375 | E71: =E70*Supuestos!$C$8 -> 2.375 | F71: =F70*Supuestos!$C$8 -> 2.375 | G71: =G70*Supuestos!$C$8 -> 2.375 | H71: =H70*Supuestos!$C$8 -> 2.375 | I71: =I70*Supuestos!$C$8 -> 2.375 | J71: =J70*Supuestos!$C$8 -> 2.375 | K71: =K70*Supuestos!$C$8 -> 2.375 | ... AB71: =AB70*Supuestos!$C$8 -> 0
B72: Interés Mezz pagado | D72: =MAX(0,MIN(D69,D71)) -> 2.375 | E72: =MAX(0,MIN(E69,E71)) -> 2.375 | F72: =MAX(0,MIN(F69,F71)) -> 2.375 | G72: =MAX(0,MIN(G69,G71)) -> 2.375 | H72: =MAX(0,MIN(H69,H71)) -> 2.375 | I72: =MAX(0,MIN(I69,I71)) -> 2.375 | J72: =MAX(0,MIN(J69,J71)) -> 2.375 | K72: =MAX(0,MIN(K69,K71)) -> 2.375 | ... AB72: =MAX(0,MIN(AB69,AB71)) -> 0
B73: Disponible tras int. Mezz | D73: =D69-D72 -> 17.35147 | E73: =E69-E72 -> 16.373034 | F73: =F69-F72 -> 16.995337 | G73: =G69-G72 -> 19.12232 | H73: =H69-H72 -> 22.60878 | I73: =I69-I72 -> 22.497142 | J73: =J69-J72 -> 22.262676 | K73: =K69-K72 -> 21.89132 | ... AB73: =AB69-AB72 -> 0.36852282
B74: Reserva objetivo | D74: =IF(D$3=Supuestos!$C$15,0,-D57*(1+$C$8)*Supuestos!$C$10/12) -> 23.533 | E74: =IF(E$3=Supuestos!$C$15,0,-E57*(1+$C$8)*Supuestos!$C$10/12) -> 22.086165 | F74: =IF(F$3=Supuestos!$C$15,0,-F57*(1+$C$8)*Supuestos!$C$10/12) -> 20.60507 | G74: =IF(G$3=Supuestos!$C$15,0,-G57*(1+$C$8)*Supuestos!$C$10/12) -> 19.099426 | H74: =IF(H$3=Supuestos!$C$15,0,-H57*(1+$C$8)*Supuestos!$C$10/12) -> 17.579985 | I74: =IF(I$3=Supuestos!$C$15,0,-I57*(1+$C$8)*Supuestos!$C$10/12) -> 16.058417 | J74: =IF(J$3=Supuestos!$C$15,0,-J57*(1+$C$8)*Supuestos!$C$10/12) -> 14.547139 | K74: =IF(K$3=Supuestos!$C$15,0,-K57*(1+$C$8)*Supuestos!$C$10/12) -> 13.059104 | ... AB74: =IF(AB$3=Supuestos!$C$15,0,-AB57*(1+$C$8)*Supuestos!$C$10/12) -> 0
B75: Principal Senior pagado | D75: =MAX(0,MIN(D66+D67-D68,D73-D74)) -> 0 | E75: =MAX(0,MIN(E66+E67-E68,E73-E74)) -> 0 | F75: =MAX(0,MIN(F66+F67-F68,F73-F74)) -> 0 | G75: =MAX(0,MIN(G66+G67-G68,G73-G74)) -> 0.022893399 | H75: =MAX(0,MIN(H66+H67-H68,H73-H74)) -> 5.0287949 | I75: =MAX(0,MIN(I66+I67-I68,I73-I74)) -> 6.4387253 | J75: =MAX(0,MIN(J66+J67-J68,J73-J74)) -> 7.7155372 | K75: =MAX(0,MIN(K66+K67-K68,K73-K74)) -> 8.8322162 | ... AB75: =MAX(0,MIN(AB66+AB67-AB68,AB73-AB74)) -> 0
B76: Disponible tras Senior | D76: =D73-D75 -> 17.35147 | E76: =E73-E75 -> 16.373034 | F76: =F73-F75 -> 16.995337 | G76: =G73-G75 -> 19.099426 | H76: =H73-H75 -> 17.579985 | I76: =I73-I75 -> 16.058417 | J76: =J73-J75 -> 14.547139 | K76: =K73-K75 -> 13.059104 | ... AB76: =AB73-AB75 -> 0.36852282
B77: Principal Mezz pagado | D77: =MAX(0,MIN(D70+D71-D72,D76-D74)) -> 0 | E77: =MAX(0,MIN(E70+E71-E72,E76-E74)) -> 0 | F77: =MAX(0,MIN(F70+F71-F72,F76-F74)) -> 0 | G77: =MAX(0,MIN(G70+G71-G72,G76-G74)) -> 0 | H77: =MAX(0,MIN(H70+H71-H72,H76-H74)) -> 0 | I77: =MAX(0,MIN(I70+I71-I72,I76-I74)) -> 0 | J77: =MAX(0,MIN(J70+J71-J72,J76-J74)) -> 0 | K77: =MAX(0,MIN(K70+K71-K72,K76-K74)) -> 0 | ... AB77: =MAX(0,MIN(AB70+AB71-AB72,AB76-AB74)) -> 0
B78: Disponible tras Mezz | D78: =D76-D77 -> 17.35147 | E78: =E76-E77 -> 16.373034 | F78: =F76-F77 -> 16.995337 | G78: =G76-G77 -> 19.099426 | H78: =H76-H77 -> 17.579985 | I78: =I76-I77 -> 16.058417 | J78: =J76-J77 -> 14.547139 | K78: =K76-K77 -> 13.059104 | ... AB78: =AB76-AB77 -> 0.36852282
B79: Saldo Senior fin | D79: =D66+D67-D68-D75 -> 75 | E79: =E66+E67-E68-E75 -> 75 | F79: =F66+F67-F68-F75 -> 75 | G79: =G66+G67-G68-G75 -> 74.977107 | H79: =H66+H67-H68-H75 -> 69.948312 | I79: =I66+I67-I68-I75 -> 63.509586 | J79: =J66+J67-J68-J75 -> 55.794049 | K79: =K66+K67-K68-K75 -> 46.961833 | ... AB79: =AB66+AB67-AB68-AB75 -> 0
B80: Saldo Mezz fin | D80: =D70+D71-D72-D77 -> 25 | E80: =E70+E71-E72-E77 -> 25 | F80: =F70+F71-F72-F77 -> 25 | G80: =G70+G71-G72-G77 -> 25 | H80: =H70+H71-H72-H77 -> 25 | I80: =I70+I71-I72-I77 -> 25 | J80: =J70+J71-J72-J77 -> 25 | K80: =K70+K71-K72-K77 -> 25 | ... AB80: =AB70+AB71-AB72-AB77 -> 0
B81: Distribución a equity | D81: =IF(D79+D80<0.000001,MAX(0,D78-D74),0) -> 0 | E81: =IF(E79+E80<0.000001,MAX(0,E78-E74),0) -> 0 | F81: =IF(F79+F80<0.000001,MAX(0,F78-F74),0) -> 0 | G81: =IF(G79+G80<0.000001,MAX(0,G78-G74),0) -> 0 | H81: =IF(H79+H80<0.000001,MAX(0,H78-H74),0) -> 0 | I81: =IF(I79+I80<0.000001,MAX(0,I78-I74),0) -> 0 | J81: =IF(J79+J80<0.000001,MAX(0,J78-J74),0) -> 0 | K81: =IF(K79+K80<0.000001,MAX(0,K78-K74),0) -> 0 | ... AB81: =IF(AB79+AB80<0.000001,MAX(0,AB78-AB74),0) -> 0.36852282
B82: Caja fin | D82: =D78-D81 -> 17.35147 | E82: =E78-E81 -> 16.373034 | F82: =F78-F81 -> 16.995337 | G82: =G78-G81 -> 19.099426 | H82: =H78-H81 -> 17.579985 | I82: =I78-I81 -> 16.058417 | J82: =J78-J81 -> 14.547139 | K82: =K78-K81 -> 13.059104 | ... AB82: =AB78-AB81 -> 0
B83: Déficit de liquidez con notas vigentes (1 = sí) | D83: =IF(AND(D65<0,D66+D70>0.000001),1,0) -> 0 | E83: =IF(AND(E65<0,E66+E70>0.000001),1,0) -> 0 | F83: =IF(AND(F65<0,F66+F70>0.000001),1,0) -> 0 | G83: =IF(AND(G65<0,G66+G70>0.000001),1,0) -> 0 | H83: =IF(AND(H65<0,H66+H70>0.000001),1,0) -> 0 | I83: =IF(AND(I65<0,I66+I70>0.000001),1,0) -> 0 | J83: =IF(AND(J65<0,J66+J70>0.000001),1,0) -> 0 | K83: =IF(AND(K65<0,K66+K70>0.000001),1,0) -> 0 | ... AB83: =IF(AND(AB65<0,AB66+AB70>0.000001),1,0) -> 0
A85: MÉTRICAS DEL ESCENARIO
B86: Pérdida Senior (% del original) | C86: =MIN(1,AB79/Supuestos!C5) -> 0
B87: Pérdida Mezz (% del original) | C87: =MIN(1,AB80/Supuestos!C7) -> 0
B88: Interés Senior impagado acumulado (USD mm) | C88: =SUM(D67:AB67)-SUM(D68:AB68) -> 0
B89: Caja mínima con notas vigentes (USD mm) | C89: =MIN(IF(D66+D70>0.000001,D65,1000000000),IF(E66+E70>0.000001,E65,1000000000),IF(F66+F70>0.000001,F65,1000000000),IF(G66+G70>0.000001,G65,1000000000),IF(H66+H70>0.000001,H65,1000000000),IF(I66+I70>0.000001,I65,1000000000),IF(J66+J70>0.000001,J65,1000000000),IF(K66+K70>0.000001,K65,1000000000),IF(L66+L70>0.000001,L65,1000000000),IF(M66+M70>0.000001,M65,1000000000),IF(N66+N70>0.000001,N65,1000000000),IF(O66+O70>0.000001,O65,1000000000),IF(P66+P70>0.000001,P65,1000000000),IF(Q66+Q70>0.000001,Q65,1000000000),IF(R66+R70>0.000001,R65,1000000000),IF(S66+S70>0.000001,S65,1000000000),IF(T66+T70>0.000001,T65,1000000000),IF(U66+U70>0.000001,U65,1000000000),IF(V66+V70>0.000001,V65,1000000000),IF(W66+W70>0.000001,W65,1000000000),IF(X66+X70>0.000001,X65,1000000000),IF(Y66+Y70>0.000001,Y65,1000000000),IF(Z66+Z70>0.000001,Z65,1000000000),IF(AA66+AA70>0.000001,AA65,1000000000),IF(AB66+AB70>0.000001,AB65,1000000000)) -> 16.255565
B90: Años con déficit de liquidez | C90: =SUM(D83:AB83) -> 0
B91: Vida promedio Senior (años) | C91: =IFERROR(SUMPRODUCT(D75:AB75,D3:AB3)/SUM(D75:AB75),0) -> 9.270188
B92: Vida promedio Mezz (años) | C92: =IFERROR(SUMPRODUCT(D77:AB77,D3:AB3)/SUM(D77:AB77),0) -> 14.000211
B93: LE estresada ponderada por face (años) | C93: =(C18*Cartera!D5+C26*Cartera!D6+C34*Cartera!D7+C42*Cartera!D8+C50*Cartera!D9)/Cartera!D10 -> 8.4709425
B94: Senior PASA (1 = sí) | C94: =IF(AND(C86<=Supuestos!C20+0.000001,C88<0.000001),1,0) -> 1
B95: Mezz PASA (1 = sí) | C95: =IF(C87<=Supuestos!C20+0.000001,1,0) -> 1
B96: Distribuciones a equity (USD mm, sin descontar) | C96: =SUM(D81:AB81)+MAX(0,AB82) -> 51.393535

Sheet CF_bbb
A1: Flujo de caja y cascada – escenario bbb
A2: Escenario | C2: bbb
A3: Año | D3: 1 | E3: 2 | F3: 3 | G3: 4 | H3: 5 | I3: 6 | J3: 7 | K3: 8 | L3: 9 | M3: 10 | N3: 11 | O3: 12 | P3: 13 | Q3: 14 | R3: 15 | S3: 16 | T3: 17 | U3: 18 | V3: 19 | W3: 20 | X3: 21 | Y3: 22 | Z3: 23 | AA3: 24 | AB3: 25
A5: Multiplicador de mortalidad | C5: =Supuestos!C27 -> 0.88
A6: Penalidad pool pequeño | C6: =Supuestos!D27 -> 0.02
A7: Pérdida default aseguradoras | C7: =Supuestos!E27 -> 0.02
A8: Aumento anual de primas | C8: =Supuestos!F27 -> 0.005
A9: Haircut valor remanente | C9: =Supuestos!G27 -> 0.2
A10: Multiplicador efectivo | C10: =MAX(0,C5-IF(Cartera!C10<Supuestos!C16,C6,0)) -> 0.88
A12: =Cartera!A5&" – "&Cartera!B5 -> C1 – Edad 75–79, salud estándar
B13: q estresada | D13: =MIN(1,Cartera!$F$5*(1+Cartera!$G$5)^(D$3-1)*$C$10) -> 0.0396 | E13: =MIN(1,Cartera!$F$5*(1+Cartera!$G$5)^(E$3-1)*$C$10) -> 0.043956 | F13: =MIN(1,Cartera!$F$5*(1+Cartera!$G$5)^(F$3-1)*$C$10) -> 0.04879116 | G13: =MIN(1,Cartera!$F$5*(1+Cartera!$G$5)^(G$3-1)*$C$10) -> 0.054158188 | H13: =MIN(1,Cartera!$F$5*(1+Cartera!$G$5)^(H$3-1)*$C$10) -> 0.060115588 | I13: =MIN(1,Cartera!$F$5*(1+Cartera!$G$5)^(I$3-1)*$C$10) -> 0.066728303 | J13: =MIN(1,Cartera!$F$5*(1+Cartera!$G$5)^(J$3-1)*$C$10) -> 0.074068416 | K13: =MIN(1,Cartera!$F$5*(1+Cartera!$G$5)^(K$3-1)*$C$10) -> 0.082215942 | ... AB13: =MIN(1,Cartera!$F$5*(1+Cartera!$G$5)^(AB$3-1)*$C$10) -> 0.4846706
B14: Supervivencia inicio | C14: LE estresada → | D14: =1 -> 1 | E14: =D18 -> 0.9604 | F14: =E18 -> 0.91818466 | G14: =F18 -> 0.87338536 | H14: =G18 -> 0.82608439 | I14: =H18 -> 0.77642385 | J14: =I18 -> 0.7246144 | K14: =J18 -> 0.67094336 | L14: =K18 -> 0.61578112 | ... AB14: =AA18 -> 0.0091853418
B15: Muertes (fracción) | D15: =D14*D13 -> 0.0396 | E15: =E14*E13 -> 0.042215342 | F15: =F14*F13 -> 0.044799295 | G15: =G14*G13 -> 0.047300968 | H15: =H14*H13 -> 0.049660549 | I15: =I14*I13 -> 0.051809446 | J15: =J14*J13 -> 0.053671041 | K15: =K14*K13 -> 0.05516224 | ... AB15: =AB14*AB13 -> 0.0044518651
B16: Beneficio por muerte bruto (USD mm) | D16: =D15*Cartera!$D$5 -> 3.564 | E16: =E15*Cartera!$D$5 -> 3.7993808 | F16: =F15*Cartera!$D$5 -> 4.0319365 | G16: =G15*Cartera!$D$5 -> 4.2570872 | H16: =H15*Cartera!$D$5 -> 4.4694494 | I16: =I15*Cartera!$D$5 -> 4.6628501 | J16: =J15*Cartera!$D$5 -> 4.8303937 | K16: =K15*Cartera!$D$5 -> 4.9646016 | ... AB16: =AB15*Cartera!$D$5 -> 0.40066786
B17: Primas pagadas (USD mm) | D17: =D14*Cartera!$D$5*Cartera!$H$5*(1+$C$8)^(D$3-1) -> 3.6 | E17: =E14*Cartera!$D$5*Cartera!$H$5*(1+$C$8)^(E$3-1) -> 3.4747272 | F17: =F14*Cartera!$D$5*Cartera!$H$5*(1+$C$8)^(F$3-1) -> 3.3386021 | G17: =G14*Cartera!$D$5*Cartera!$H$5*(1+$C$8)^(G$3-1) -> 3.1915863 | H17: =H14*Cartera!$D$5*Cartera!$H$5*(1+$C$8)^(H$3-1) -> 3.0338295 | I17: =I14*Cartera!$D$5*Cartera!$H$5*(1+$C$8)^(I$3-1) -> 2.8657063 | J17: =J14*Cartera!$D$5*Cartera!$H$5*(1+$C$8)^(J$3-1) -> 2.687855 | K17: =K14*Cartera!$D$5*Cartera!$H$5*(1+$C$8)^(K$3-1) -> 2.5012137 | ... AB17: =AB14*Cartera!$D$5*Cartera!$H$5*(1+$C$8)^(AB$3-1) -> 0.037272052
B18: Supervivencia fin | C18: =SUM(D18:AB18)+0.5 -> 10.326955 | D18: =D14-D15 -> 0.9604 | E18: =E14-E15 -> 0.91818466 | F18: =F14-F15 -> 0.87338536 | G18: =G14-G15 -> 0.82608439 | H18: =H14-H15 -> 0.77642385 | I18: =I14-I15 -> 0.7246144 | J18: =J14-J15 -> 0.67094336 | K18: =K14-K15 -> 0.61578112 | ... AB18: =AB14-AB15 -> 0.0047334767
A20: =Cartera!A6&" – "&Cartera!B6 -> C2 – Edad 80–84, deterioro moderado
B21: q estresada | D21: =MIN(1,Cartera!$F$6*(1+Cartera!$G$6)^(D$3-1)*$C$10) -> 0.0572 | E21: =MIN(1,Cartera!$F$6*(1+Cartera!$G$6)^(E$3-1)*$C$10) -> 0.06292 | F21: =MIN(1,Cartera!$F$6*(1+Cartera!$G$6)^(F$3-1)*$C$10) -> 0.069212 | G21: =MIN(1,Cartera!$F$6*(1+Cartera!$G$6)^(G$3-1)*$C$10) -> 0.0761332 | H21: =MIN(1,Cartera!$F$6*(1+Cartera!$G$6)^(H$3-1)*$C$10) -> 0.08374652 | I21: =MIN(1,Cartera!$F$6*(1+Cartera!$G$6)^(I$3-1)*$C$10) -> 0.092121172 | J21: =MIN(1,Cartera!$F$6*(1+Cartera!$G$6)^(J$3-1)*$C$10) -> 0.10133329 | K21: =MIN(1,Cartera!$F$6*(1+Cartera!$G$6)^(K$3-1)*$C$10) -> 0.11146662 | ... AB21: =MIN(1,Cartera!$F$6*(1+Cartera!$G$6)^(AB$3-1)*$C$10) -> 0.56340471
B22: Supervivencia inicio | C22: LE estresada → | D22: =1 -> 1 | E22: =D26 -> 0.9428 | F22: =E26 -> 0.88347902 | G22: =F26 -> 0.82233167 | H22: =G26 -> 0.75972493 | I22: =H26 -> 0.69610061 | J22: =I26 -> 0.63197501 | K22: =J26 -> 0.5679349 | L22: =K26 -> 0.50462912 | ... AB22: =AA26 -> 0.0023010881
B23: Muertes (fracción) | D23: =D22*D21 -> 0.0572 | E23: =E22*E21 -> 0.059320976 | F23: =F22*F21 -> 0.06114735 | G23: =G22*G21 -> 0.062606742 | H23: =H22*H21 -> 0.063624319 | I23: =I22*I21 -> 0.064125604 | J23: =J22*J21 -> 0.064040106 | K23: =K22*K21 -> 0.063305783 | ... AB23: =AB22*AB21 -> 0.0012964439
B24: Beneficio por muerte bruto (USD mm) | D24: =D23*Cartera!$D$6 -> 6.864 | E24: =E23*Cartera!$D$6 -> 7.1185171 | F24: =F23*Cartera!$D$6 -> 7.337682 | G24: =G23*Cartera!$D$6 -> 7.512809 | H24: =H23*Cartera!$D$6 -> 7.6349183 | I24: =I23*Cartera!$D$6 -> 7.6950725 | J24: =J23*Cartera!$D$6 -> 7.6848128 | K24: =K23*Cartera!$D$6 -> 7.5966939 | ... AB24: =AB23*Cartera!$D$6 -> 0.15557327
B25: Primas pagadas (USD mm) | D25: =D22*Cartera!$D$6*Cartera!$H$6*(1+$C$8)^(D$3-1) -> 6 | E25: =E22*Cartera!$D$6*Cartera!$H$6*(1+$C$8)^(E$3-1) -> 5.685084 | F25: =F22*Cartera!$D$6*Cartera!$H$6*(1+$C$8)^(F$3-1) -> 5.3540154 | G25: =G22*Cartera!$D$6*Cartera!$H$6*(1+$C$8)^(G$3-1) -> 5.0083706 | H25: =H22*Cartera!$D$6*Cartera!$H$6*(1+$C$8)^(H$3-1) -> 4.6502026 | I25: =I22*Cartera!$D$6*Cartera!$H$6*(1+$C$8)^(I$3-1) -> 4.2820682 | J25: =J22*Cartera!$D$6*Cartera!$H$6*(1+$C$8)^(J$3-1) -> 3.907037 | K25: =K22*Cartera!$D$6*Cartera!$H$6*(1+$C$8)^(K$3-1) -> 3.5286797 | ... AB25: =AB22*Cartera!$D$6*Cartera!$H$6*(1+$C$8)^(AB$3-1) -> 0.015562164
B26: Supervivencia fin | C26: =SUM(D26:AB26)+0.5 -> 8.6158016 | D26: =D22-D23 -> 0.9428 | E26: =E22-E23 -> 0.88347902 | F26: =F22-F23 -> 0.82233167 | G26: =G22-G23 -> 0.75972493 | H26: =H22-H23 -> 0.69610061 | I26: =I22-I23 -> 0.63197501 | J26: =J22-J23 -> 0.5679349 | K26: =K22-K23 -> 0.50462912 | ... AB26: =AB22-AB23 -> 0.0010046442
A28: =Cartera!A7&" – "&Cartera!B7 -> C3 – Edad 85–89, deterioro significativo
B29: q estresada | D29: =MIN(1,Cartera!$F$7*(1+Cartera!$G$7)^(D$3-1)*$C$10) -> 0.0836 | E29: =MIN(1,Cartera!$F$7*(1+Cartera!$G$7)^(E$3-1)*$C$10) -> 0.091124 | F29: =MIN(1,Cartera!$F$7*(1+Cartera!$G$7)^(F$3-1)*$C$10) -> 0.09932516 | G29: =MIN(1,Cartera!$F$7*(1+Cartera!$G$7)^(G$3-1)*$C$10) -> 0.10826442 | H29: =MIN(1,Cartera!$F$7*(1+Cartera!$G$7)^(H$3-1)*$C$10) -> 0.11800822 | I29: =MIN(1,Cartera!$F$7*(1+Cartera!$G$7)^(I$3-1)*$C$10) -> 0.12862896 | J29: =MIN(1,Cartera!$F$7*(1+Cartera!$G$7)^(J$3-1)*$C$10) -> 0.14020557 | K29: =MIN(1,Cartera!$F$7*(1+Cartera!$G$7)^(K$3-1)*$C$10) -> 0.15282407 | ... AB29: =MIN(1,Cartera!$F$7*(1+Cartera!$G$7)^(AB$3-1)*$C$10) -> 0.66136655
B30: Supervivencia inicio | C30: LE estresada → | D30: =1 -> 1 | E30: =D34 -> 0.9164 | F30: =E34 -> 0.83289397 | G30: =F34 -> 0.75016664 | H30: =G34 -> 0.66895028 | I30: =H34 -> 0.59000865 | J30: =I34 -> 0.51411645 | K30: =J34 -> 0.44203446 | L30: =K34 -> 0.37448095 | ... AB30: =AA34 -> 0.00030578409
B31: Muertes (fracción) | D31: =D30*D29 -> 0.0836 | E31: =E30*E29 -> 0.083506034 | F31: =F30*F29 -> 0.082727326 | G31: =G30*G29 -> 0.081216359 | H31: =H30*H29 -> 0.078941634 | I31: =I30*I29 -> 0.0758922 | J31: =J30*J29 -> 0.072081989 | K31: =K30*K29 -> 0.067553505 | ... AB31: =AB30*AB29 -> 0.00020223537
B32: Beneficio por muerte bruto (USD mm) | D32: =D31*Cartera!$D$7 -> 8.36 | E32: =E31*Cartera!$D$7 -> 8.3506034 | F32: =F31*Cartera!$D$7 -> 8.2727326 | G32: =G31*Cartera!$D$7 -> 8.1216359 | H32: =H31*Cartera!$D$7 -> 7.8941634 | I32: =I31*Cartera!$D$7 -> 7.58922 | J32: =J31*Cartera!$D$7 -> 7.2081989 | K32: =K31*Cartera!$D$7 -> 6.7553505 | ... AB32: =AB31*Cartera!$D$7 -> 0.020223537
B33: Primas pagadas (USD mm) | D33: =D30*Cartera!$D$7*Cartera!$H$7*(1+$C$8)^(D$3-1) -> 6 | E33: =E30*Cartera!$D$7*Cartera!$H$7*(1+$C$8)^(E$3-1) -> 5.525892 | F33: =F30*Cartera!$D$7*Cartera!$H$7*(1+$C$8)^(F$3-1) -> 5.0474624 | G33: =G30*Cartera!$D$7*Cartera!$H$7*(1+$C$8)^(G$3-1) -> 4.568853 | H33: =H30*Cartera!$D$7*Cartera!$H$7*(1+$C$8)^(H$3-1) -> 4.0945798 | I33: =I30*Cartera!$D$7*Cartera!$H$7*(1+$C$8)^(I$3-1) -> 3.6294426 | J33: =J30*Cartera!$D$7*Cartera!$H$7*(1+$C$8)^(J$3-1) -> 3.1784041 | K33: =K30*Cartera!$D$7*Cartera!$H$7*(1+$C$8)^(K$3-1) -> 2.7464381 | ... AB33: =AB30*Cartera!$D$7*Cartera!$H$7*(1+$C$8)^(AB$3-1) -> 0.0020680052
B34: Supervivencia fin | C34: =SUM(D34:AB34)+0.5 -> 6.9233557 | D34: =D30-D31 -> 0.9164 | E34: =E30-E31 -> 0.83289397 | F34: =F30-F31 -> 0.75016664 | G34: =G30-G31 -> 0.66895028 | H34: =H30-H31 -> 0.59000865 | I34: =I30-I31 -> 0.51411645 | J34: =J30-J31 -> 0.44203446 | K34: =K30-K31 -> 0.37448095 | ... AB34: =AB30-AB31 -> 0.00010354872
A36: =Cartera!A8&" – "&Cartera!B8 -> C4 – Edad 90+, deterioro severo
B37: q estresada | D37: =MIN(1,Cartera!$F$8*(1+Cartera!$G$8)^(D$3-1)*$C$10) -> 0.1232 | E37: =MIN(1,Cartera!$F$8*(1+Cartera!$G$8)^(E$3-1)*$C$10) -> 0.133056 | F37: =MIN(1,Cartera!$F$8*(1+Cartera!$G$8)^(F$3-1)*$C$10) -> 0.14370048 | G37: =MIN(1,Cartera!$F$8*(1+Cartera!$G$8)^(G$3-1)*$C$10) -> 0.15519652 | H37: =MIN(1,Cartera!$F$8*(1+Cartera!$G$8)^(H$3-1)*$C$10) -> 0.16761224 | I37: =MIN(1,Cartera!$F$8*(1+Cartera!$G$8)^(I$3-1)*$C$10) -> 0.18102122 | J37: =MIN(1,Cartera!$F$8*(1+Cartera!$G$8)^(J$3-1)*$C$10) -> 0.19550292 | K37: =MIN(1,Cartera!$F$8*(1+Cartera!$G$8)^(K$3-1)*$C$10) -> 0.21114315 | ... AB37: =MIN(1,Cartera!$F$8*(1+Cartera!$G$8)^(AB$3-1)*$C$10) -> 0.78123347
B38: Supervivencia inicio | C38: LE estresada → | D38: =1 -> 1 | E38: =D42 -> 0.8768 | F38: =E42 -> 0.7601365 | G38: =F42 -> 0.65090452 | H38: =G42 -> 0.5498864 | I38: =H42 -> 0.45771871 | J38: =I42 -> 0.37486191 | K38: =J42 -> 0.30157532 | L38: =K42 -> 0.23789975 | ... AB38: =AA42 -> 1.4262397e-05
B39: Muertes (fracción) | D39: =D38*D37 -> 0.1232 | E39: =E38*E37 -> 0.1166635 | F39: =F38*F37 -> 0.10923198 | G39: =G38*G37 -> 0.10101812 | H39: =H38*H37 -> 0.092167692 | I39: =I38*I37 -> 0.082856799 | J39: =J38*J37 -> 0.073286597 | K39: =K38*K37 -> 0.063675562 | ... AB39: =AB38*AB37 -> 1.1142262e-05
B40: Beneficio por muerte bruto (USD mm) | D40: =D39*Cartera!$D$8 -> 9.856 | E40: =E39*Cartera!$D$8 -> 9.3330801 | F40: =F39*Cartera!$D$8 -> 8.7385584 | G40: =G39*Cartera!$D$8 -> 8.0814492 | H40: =H39*Cartera!$D$8 -> 7.3734154 | I40: =I39*Cartera!$D$8 -> 6.6285439 | J40: =J39*Cartera!$D$8 -> 5.8629278 | K40: =K39*Cartera!$D$8 -> 5.094045 | ... AB40: =AB39*Cartera!$D$8 -> 0.00089138094
B41: Primas pagadas (USD mm) | D41: =D38*Cartera!$D$8*Cartera!$H$8*(1+$C$8)^(D$3-1) -> 5.6 | E41: =E38*Cartera!$D$8*Cartera!$H$8*(1+$C$8)^(E$3-1) -> 4.9346304 | F41: =F38*Cartera!$D$8*Cartera!$H$8*(1+$C$8)^(F$3-1) -> 4.2994385 | G41: =G38*Cartera!$D$8*Cartera!$H$8*(1+$C$8)^(G$3-1) -> 3.7000151 | H41: =H38*Cartera!$D$8*Cartera!$H$8*(1+$C$8)^(H$3-1) -> 3.1414146 | I41: =I38*Cartera!$D$8*Cartera!$H$8*(1+$C$8)^(I$3-1) -> 2.6279494 | J41: =J38*Cartera!$D$8*Cartera!$H$8*(1+$C$8)^(J$3-1) -> 2.162996 | K41: =K38*Cartera!$D$8*Cartera!$H$8*(1+$C$8)^(K$3-1) -> 1.7488246 | ... AB41: =AB38*Cartera!$D$8*Cartera!$H$8*(1+$C$8)^(AB$3-1) -> 9.00256e-05
B42: Supervivencia fin | C42: =SUM(D42:AB42)+0.5 -> 5.3383351 | D42: =D38-D39 -> 0.8768 | E42: =E38-E39 -> 0.7601365 | F42: =F38-F39 -> 0.65090452 | G42: =G38-G39 -> 0.5498864 | H42: =H38-H39 -> 0.45771871 | I42: =I38-I39 -> 0.37486191 | J42: =J38-J39 -> 0.30157532 | K42: =K38-K39 -> 0.23789975 | ... AB42: =AB38-AB39 -> 3.1201351e-06
A44: =Cartera!A9&" – "&Cartera!B9 -> C5 – Edad 70–74, enfermedad crónica
B45: q estresada | D45: =MIN(1,Cartera!$F$9*(1+Cartera!$G$9)^(D$3-1)*$C$10) -> 0.044 | E45: =MIN(1,Cartera!$F$9*(1+Cartera!$G$9)^(E$3-1)*$C$10) -> 0.04928 | F45: =MIN(1,Cartera!$F$9*(1+Cartera!$G$9)^(F$3-1)*$C$10) -> 0.0551936 | G45: =MIN(1,Cartera!$F$9*(1+Cartera!$G$9)^(G$3-1)*$C$10) -> 0.061816832 | H45: =MIN(1,Cartera!$F$9*(1+Cartera!$G$9)^(H$3-1)*$C$10) -> 0.069234852 | I45: =MIN(1,Cartera!$F$9*(1+Cartera!$G$9)^(I$3-1)*$C$10) -> 0.077543034 | J45: =MIN(1,Cartera!$F$9*(1+Cartera!$G$9)^(J$3-1)*$C$10) -> 0.086848198 | K45: =MIN(1,Cartera!$F$9*(1+Cartera!$G$9)^(K$3-1)*$C$10) -> 0.097269982 | ... AB45: =MIN(1,Cartera!$F$9*(1+Cartera!$G$9)^(AB$3-1)*$C$10) -> 0.66785967
B46: Supervivencia inicio | C46: LE estresada → | D46: =1 -> 1 | E46: =D50 -> 0.956 | F46: =E50 -> 0.90888832 | G46: =F50 -> 0.8587235 | H46: =G50 -> 0.80563994 | I46: =H50 -> 0.74986157 | J46: =I50 -> 0.69171503 | K46: =J50 -> 0.63164083 | L46: =K50 -> 0.57020114 | ... AB46: =AA50 -> 0.0015533394
B47: Muertes (fracción) | D47: =D46*D45 -> 0.044 | E47: =E46*E45 -> 0.04711168 | F47: =F46*F45 -> 0.050164818 | G47: =G46*G45 -> 0.053083566 | H47: =H46*H45 -> 0.055778362 | I47: =I46*I45 -> 0.058146542 | J47: =J46*J45 -> 0.060074204 | K47: =K46*K45 -> 0.061439692 | ... AB47: =AB46*AB45 -> 0.0010374127
B48: Beneficio por muerte bruto (USD mm) | D48: =D47*Cartera!$D$9 -> 2.64 | E48: =E47*Cartera!$D$9 -> 2.8267008 | F48: =F47*Cartera!$D$9 -> 3.0098891 | G48: =G47*Cartera!$D$9 -> 3.185014 | H48: =H47*Cartera!$D$9 -> 3.3467017 | I48: =I47*Cartera!$D$9 -> 3.4887925 | J48: =J47*Cartera!$D$9 -> 3.6044523 | K48: =K47*Cartera!$D$9 -> 3.6863815 | ... AB48: =AB47*Cartera!$D$9 -> 0.062244763
B49: Primas pagadas (USD mm) | D49: =D46*Cartera!$D$9*Cartera!$H$9*(1+$C$8)^(D$3-1) -> 2.1 | E49: =E46*Cartera!$D$9*Cartera!$H$9*(1+$C$8)^(E$3-1) -> 2.017638 | F49: =F46*Cartera!$D$9*Cartera!$H$9*(1+$C$8)^(F$3-1) -> 1.9277998 | G49: =G46*Cartera!$D$9*Cartera!$H$9*(1+$C$8)^(G$3-1) -> 1.8305046 | H49: =H46*Cartera!$D$9*Cartera!$H$9*(1+$C$8)^(H$3-1) -> 1.7259354 | I49: =I46*Cartera!$D$9*Cartera!$H$9*(1+$C$8)^(I$3-1) -> 1.6144727 | J49: =J46*Cartera!$D$9*Cartera!$H$9*(1+$C$8)^(J$3-1) -> 1.496728 | K49: =K46*Cartera!$D$9*Cartera!$H$9*(1+$C$8)^(K$3-1) -> 1.3735736 | ... AB49: =AB46*Cartera!$D$9*Cartera!$H$9*(1+$C$8)^(AB$3-1) -> 0.0036768094
B50: Supervivencia fin | C50: =SUM(D50:AB50)+0.5 -> 9.3906647 | D50: =D46-D47 -> 0.956 | E50: =E46-E47 -> 0.90888832 | F50: =F46-F47 -> 0.8587235 | G50: =G46-G47 -> 0.80563994 | H50: =H46-H47 -> 0.74986157 | I50: =I46-I47 -> 0.69171503 | J50: =J46-J47 -> 0.63164083 | K50: =K46-K47 -> 0.57020114 | ... AB50: =AB46-AB47 -> 0.00051592664
A52: CARTERA TOTAL
B53: Face en vigor inicio (USD mm) | D53: =D14*Cartera!$D$5+D22*Cartera!$D$6+D30*Cartera!$D$7+D38*Cartera!$D$8+D46*Cartera!$D$9 -> 450 | E53: =E14*Cartera!$D$5+E22*Cartera!$D$6+E30*Cartera!$D$7+E38*Cartera!$D$8+E46*Cartera!$D$9 -> 418.716 | F53: =F14*Cartera!$D$5+F22*Cartera!$D$6+F30*Cartera!$D$7+F38*Cartera!$D$8+F46*Cartera!$D$9 -> 387.28772 | G53: =G14*Cartera!$D$5+G22*Cartera!$D$6+G30*Cartera!$D$7+G38*Cartera!$D$8+G46*Cartera!$D$9 -> 355.89692 | H53: =H14*Cartera!$D$5+H22*Cartera!$D$6+H30*Cartera!$D$7+H38*Cartera!$D$8+H46*Cartera!$D$9 -> 324.73892 | I53: =I14*Cartera!$D$5+I22*Cartera!$D$6+I30*Cartera!$D$7+I38*Cartera!$D$8+I46*Cartera!$D$9 -> 294.02028 | J53: =J14*Cartera!$D$5+J22*Cartera!$D$6+J30*Cartera!$D$7+J38*Cartera!$D$8+J46*Cartera!$D$9 -> 263.9558 | K53: =K14*Cartera!$D$5+K22*Cartera!$D$6+K30*Cartera!$D$7+K38*Cartera!$D$8+K46*Cartera!$D$9 -> 234.76501 | ... AB53: =AB14*Cartera!$D$5+AB22*Cartera!$D$6+AB30*Cartera!$D$7+AB38*Cartera!$D$8+AB46*Cartera!$D$9 -> 1.2277311
B54: Beneficios por muerte brutos | D54: =D16+D24+D32+D40+D48 -> 31.284 | E54: =E16+E24+E32+E40+E48 -> 31.428282 | F54: =F16+F24+F32+F40+F48 -> 31.390799 | G54: =G16+G24+G32+G40+G48 -> 31.157995 | H54: =H16+H24+H32+H40+H48 -> 30.718648 | I54: =I16+I24+I32+I40+I48 -> 30.064479 | J54: =J16+J24+J32+J40+J48 -> 29.190785 | K54: =K16+K24+K32+K40+K48 -> 28.097073 | ... AB54: =AB16+AB24+AB32+AB40+AB48 -> 0.63960081
B55: (−) Pérdida por default de aseguradoras | D55: =-D54*$C$7 -> -0.62568 | E55: =-E54*$C$7 -> -0.62856564 | F55: =-F54*$C$7 -> -0.62781597 | G55: =-G54*$C$7 -> -0.62315991 | H55: =-H54*$C$7 -> -0.61437296 | I55: =-I54*$C$7 -> -0.60128958 | J55: =-J54*$C$7 -> -0.58381571 | K55: =-K54*$C$7 -> -0.56194145 | ... AB55: =-AB54*$C$7 -> -0.012792016
B56: Beneficios netos cobrados | D56: =D54+D55 -> 30.65832 | E56: =E54+E55 -> 30.799717 | F56: =F54+F55 -> 30.762983 | G56: =G54+G55 -> 30.534835 | H56: =H54+H55 -> 30.104275 | I56: =I54+I55 -> 29.463189 | J56: =J54+J55 -> 28.60697 | K56: =K54+K55 -> 27.535131 | ... AB56: =AB54+AB55 -> 0.62680879
B57: (−) Primas | D57: =-(D17+D25+D33+D41+D49) -> -23.3 | E57: =-(E17+E25+E33+E41+E49) -> -21.637972 | F57: =-(F17+F25+F33+F41+F49) -> -19.967318 | G57: =-(G17+G25+G33+G41+G49) -> -18.29933 | H57: =-(H17+H25+H33+H41+H49) -> -16.645962 | I57: =-(I17+I25+I33+I41+I49) -> -15.019639 | J57: =-(J17+J25+J33+J41+J49) -> -13.43302 | K57: =-(K17+K25+K33+K41+K49) -> -11.89873 | ... AB57: =-(AB17+AB25+AB33+AB41+AB49) -> -0.058669056
B58: (−) Gastos | D58: =-(Supuestos!$C$12+Supuestos!$C$13*D53) -> -0.975 | E58: =-(Supuestos!$C$12+Supuestos!$C$13*E53) -> -0.959358 | F58: =-(Supuestos!$C$12+Supuestos!$C$13*F53) -> -0.94364386 | G58: =-(Supuestos!$C$12+Supuestos!$C$13*G53) -> -0.92794846 | H58: =-(Supuestos!$C$12+Supuestos!$C$13*H53) -> -0.91236946 | I58: =-(Supuestos!$C$12+Supuestos!$C$13*I53) -> -0.89701014 | J58: =-(Supuestos!$C$12+Supuestos!$C$13*J53) -> -0.8819779 | K58: =-(Supuestos!$C$12+Supuestos!$C$13*K53) -> -0.86738251 | ... AB58: =-(Supuestos!$C$12+Supuestos!$C$13*AB53) -> -0.75061387
B59: (+) Venta de cartera remanente (año final) | D59: =IF(D$3=Supuestos!$C$15,(D18*Cartera!$D$5+D26*Cartera!$D$6+D34*Cartera!$D$7+D42*Cartera!$D$8+D50*Cartera!$D$9)*Supuestos!$C$14*(1-$C$9),0) -> 0 | E59: =IF(E$3=Supuestos!$C$15,(E18*Cartera!$D$5+E26*Cartera!$D$6+E34*Cartera!$D$7+E42*Cartera!$D$8+E50*Cartera!$D$9)*Supuestos!$C$14*(1-$C$9),0) -> 0 | F59: =IF(F$3=Supuestos!$C$15,(F18*Cartera!$D$5+F26*Cartera!$D$6+F34*Cartera!$D$7+F42*Cartera!$D$8+F50*Cartera!$D$9)*Supuestos!$C$14*(1-$C$9),0) -> 0 | G59: =IF(G$3=Supuestos!$C$15,(G18*Cartera!$D$5+G26*Cartera!$D$6+G34*Cartera!$D$7+G42*Cartera!$D$8+G50*Cartera!$D$9)*Supuestos!$C$14*(1-$C$9),0) -> 0 | H59: =IF(H$3=Supuestos!$C$15,(H18*Cartera!$D$5+H26*Cartera!$D$6+H34*Cartera!$D$7+H42*Cartera!$D$8+H50*Cartera!$D$9)*Supuestos!$C$14*(1-$C$9),0) -> 0 | I59: =IF(I$3=Supuestos!$C$15,(I18*Cartera!$D$5+I26*Cartera!$D$6+I34*Cartera!$D$7+I42*Cartera!$D$8+I50*Cartera!$D$9)*Supuestos!$C$14*(1-$C$9),0) -> 0 | J59: =IF(J$3=Supuestos!$C$15,(J18*Cartera!$D$5+J26*Cartera!$D$6+J34*Cartera!$D$7+J42*Cartera!$D$8+J50*Cartera!$D$9)*Supuestos!$C$14*(1-$C$9),0) -> 0 | K59: =IF(K$3=Supuestos!$C$15,(K18*Cartera!$D$5+K26*Cartera!$D$6+K34*Cartera!$D$7+K42*Cartera!$D$8+K50*Cartera!$D$9)*Supuestos!$C$14*(1-$C$9),0) -> 0 | ... AB59: =IF(AB$3=Supuestos!$C$15,(AB18*Cartera!$D$5+AB26*Cartera!$D$6+AB34*Cartera!$D$7+AB42*Cartera!$D$8+AB50*Cartera!$D$9)*Supuestos!$C$14*(1-$C$9),0) -> 0.094100847
B60: Flujo neto de activos | D60: =D56+D57+D58+D59 -> 6.38332 | E60: =E56+E57+E58+E59 -> 8.2023869 | F60: =F56+F57+F58+F59 -> 9.8520207 | G60: =G56+G57+G58+G59 -> 11.307557 | H60: =H56+H57+H58+H59 -> 12.545944 | I60: =I56+I57+I58+I59 -> 13.54654 | J60: =J56+J57+J58+J59 -> 14.291972 | K60: =K56+K57+K58+K59 -> 14.769019 | ... AB60: =AB56+AB57+AB58+AB59 -> -0.088373281
B62: CASCADA
B63: Caja inicio | D63: =Supuestos!$C$9 -> 20 | E63: =D82 -> 19.73332 | F63: =E82 -> 21.277707 | G63: =F82 -> 20.067155 | H63: =G82 -> 18.390826 | I63: =H82 -> 16.729192 | J63: =I82 -> 15.094737 | K63: =J82 -> 13.500185 | L63: =K82 -> 11.958223 | ... AB63: =AA82 -> 0.11275429
B64: (+) Intereses de reinversión | D64: =MAX(0,D63)*Supuestos!$C$11 -> 0.6 | E64: =MAX(0,E63)*Supuestos!$C$11 -> 0.5919996 | F64: =MAX(0,F63)*Supuestos!$C$11 -> 0.6383312 | G64: =MAX(0,G63)*Supuestos!$C$11 -> 0.60201464 | H64: =MAX(0,H63)*Supuestos!$C$11 -> 0.55172479 | I64: =MAX(0,I63)*Supuestos!$C$11 -> 0.50187575 | J64: =MAX(0,J63)*Supuestos!$C$11 -> 0.45284212 | K64: =MAX(0,K63)*Supuestos!$C$11 -> 0.40500556 | ... AB64: =MAX(0,AB63)*Supuestos!$C$11 -> 0.0033826286
B65: Caja disponible | D65: =D63+D64+D60 -> 26.98332 | E65: =E63+E64+E60 -> 28.527707 | F65: =F63+F64+F60 -> 31.768058 | G65: =G63+G64+G60 -> 31.976727 | H65: =H63+H64+H60 -> 31.488495 | I65: =I63+I64+I60 -> 30.777608 | J65: =J63+J64+J60 -> 29.839551 | K65: =K63+K64+K60 -> 28.67421 | ... AB65: =AB63+AB64+AB60 -> 0.027763635
B66: Saldo Senior inicio | D66: =Supuestos!$C$5 -> 75 | E66: =D79 -> 75 | F66: =E79 -> 75 | G66: =F79 -> 70.549096 | H66: =G79 -> 63.923887 | I66: =H79 -> 55.694636 | J66: =I79 -> 46.006918 | K66: =J79 -> 35.033001 | L66: =K79 -> 22.96916 | ... AB66: =AA79 -> 0
B67: Interés Senior debido | D67: =D66*Supuestos!$C$6 -> 4.875 | E67: =E66*Supuestos!$C$6 -> 4.875 | F67: =F66*Supuestos!$C$6 -> 4.875 | G67: =G66*Supuestos!$C$6 -> 4.5856913 | H67: =H66*Supuestos!$C$6 -> 4.1550527 | I67: =I66*Supuestos!$C$6 -> 3.6201514 | J67: =J66*Supuestos!$C$6 -> 2.9904496 | K67: =K66*Supuestos!$C$6 -> 2.2771451 | ... AB67: =AB66*Supuestos!$C$6 -> 0
B68: Interés Senior pagado | D68: =MAX(0,MIN(D65,D67)) -> 4.875 | E68: =MAX(0,MIN(E65,E67)) -> 4.875 | F68: =MAX(0,MIN(F65,F67)) -> 4.875 | G68: =MAX(0,MIN(G65,G67)) -> 4.5856913 | H68: =MAX(0,MIN(H65,H67)) -> 4.1550527 | I68: =MAX(0,MIN(I65,I67)) -> 3.6201514 | J68: =MAX(0,MIN(J65,J67)) -> 2.9904496 | K68: =MAX(0,MIN(K65,K67)) -> 2.2771451 | ... AB68: =MAX(0,MIN(AB65,AB67)) -> 0
B69: Disponible tras int. Senior | D69: =D65-D68 -> 22.10832 | E69: =E65-E68 -> 23.652707 | F69: =F65-F68 -> 26.893058 | G69: =G65-G68 -> 27.391035 | H69: =H65-H68 -> 27.333442 | I69: =I65-I68 -> 27.157456 | J69: =J65-J68 -> 26.849102 | K69: =K65-K68 -> 26.397065 | ... AB69: =AB65-AB68 -> 0.027763635
B70: Saldo Mezz inicio | D70: =Supuestos!$C$7 -> 25 | E70: =D80 -> 25 | F70: =E80 -> 25 | G70: =F80 -> 25 | H70: =G80 -> 25 | I70: =H80 -> 25 | J70: =I80 -> 25 | K70: =J80 -> 25 | L70: =K80 -> 25 | ... AB70: =AA80 -> 0
B71: Interés Mezz debido | D71: =D70*Supuestos!$C$8 -> 2.375 | E71: =E70*Supuestos!$C$8 -> 2.375 | F71: =F70*Supuestos!$C$8 -> 2.375 | G71: =G70*Supuestos!$C$8 -> 2.375 | H71: =H70*Supuestos!$C$8 -> 2.375 | I71: =I70*Supuestos!$C$8 -> 2.375 | J71: =J70*Supuestos!$C$8 -> 2.375 | K71: =K70*Supuestos!$C$8 -> 2.375 | ... AB71: =AB70*Supuestos!$C$8 -> 0
B72: Interés Mezz pagado | D72: =MAX(0,MIN(D69,D71)) -> 2.375 | E72: =MAX(0,MIN(E69,E71)) -> 2.375 | F72: =MAX(0,MIN(F69,F71)) -> 2.375 | G72: =MAX(0,MIN(G69,G71)) -> 2.375 | H72: =MAX(0,MIN(H69,H71)) -> 2.375 | I72: =MAX(0,MIN(I69,I71)) -> 2.375 | J72: =MAX(0,MIN(J69,J71)) -> 2.375 | K72: =MAX(0,MIN(K69,K71)) -> 2.375 | ... AB72: =MAX(0,MIN(AB69,AB71)) -> 0
B73: Disponible tras int. Mezz | D73: =D69-D72 -> 19.73332 | E73: =E69-E72 -> 21.277707 | F73: =F69-F72 -> 24.518058 | G73: =G69-G72 -> 25.016035 | H73: =H69-H72 -> 24.958442 | I73: =I69-I72 -> 24.782456 | J73: =J69-J72 -> 24.474102 | K73: =K69-K72 -> 24.022065 | ... AB73: =AB69-AB72 -> 0.027763635
B74: Reserva objetivo | D74: =IF(D$3=Supuestos!$C$15,0,-D57*(1+$C$8)*Supuestos!$C$10/12) -> 23.4165 | E74: =IF(E$3=Supuestos!$C$15,0,-E57*(1+$C$8)*Supuestos!$C$10/12) -> 21.746161 | F74: =IF(F$3=Supuestos!$C$15,0,-F57*(1+$C$8)*Supuestos!$C$10/12) -> 20.067155 | G74: =IF(G$3=Supuestos!$C$15,0,-G57*(1+$C$8)*Supuestos!$C$10/12) -> 18.390826 | H74: =IF(H$3=Supuestos!$C$15,0,-H57*(1+$C$8)*Supuestos!$C$10/12) -> 16.729192 | I74: =IF(I$3=Supuestos!$C$15,0,-I57*(1+$C$8)*Supuestos!$C$10/12) -> 15.094737 | J74: =IF(J$3=Supuestos!$C$15,0,-J57*(1+$C$8)*Supuestos!$C$10/12) -> 13.500185 | K74: =IF(K$3=Supuestos!$C$15,0,-K57*(1+$C$8)*Supuestos!$C$10/12) -> 11.958223 | ... AB74: =IF(AB$3=Supuestos!$C$15,0,-AB57*(1+$C$8)*Supuestos!$C$10/12) -> 0
B75: Principal Senior pagado | D75: =MAX(0,MIN(D66+D67-D68,D73-D74)) -> 0 | E75: =MAX(0,MIN(E66+E67-E68,E73-E74)) -> 0 | F75: =MAX(0,MIN(F66+F67-F68,F73-F74)) -> 4.4509037 | G75: =MAX(0,MIN(G66+G67-G68,G73-G74)) -> 6.6252092 | H75: =MAX(0,MIN(H66+H67-H68,H73-H74)) -> 8.2292506 | I75: =MAX(0,MIN(I66+I67-I68,I73-I74)) -> 9.6877188 | J75: =MAX(0,MIN(J66+J67-J68,J73-J74)) -> 10.973916 | K75: =MAX(0,MIN(K66+K67-K68,K73-K74)) -> 12.063841 | ... AB75: =MAX(0,MIN(AB66+AB67-AB68,AB73-AB74)) -> 0
B76: Disponible tras Senior | D76: =D73-D75 -> 19.73332 | E76: =E73-E75 -> 21.277707 | F76: =F73-F75 -> 20.067155 | G76: =G73-G75 -> 18.390826 | H76: =H73-H75 -> 16.729192 | I76: =I73-I75 -> 15.094737 | J76: =J73-J75 -> 13.500185 | K76: =K73-K75 -> 11.958223 | ... AB76: =AB73-AB75 -> 0.027763635
B77: Principal Mezz pagado | D77: =MAX(0,MIN(D70+D71-D72,D76-D74)) -> 0 | E77: =MAX(0,MIN(E70+E71-E72,E76-E74)) -> 0 | F77: =MAX(0,MIN(F70+F71-F72,F76-F74)) -> 0 | G77: =MAX(0,MIN(G70+G71-G72,G76-G74)) -> 0 | H77: =MAX(0,MIN(H70+H71-H72,H76-H74)) -> 0 | I77: =MAX(0,MIN(I70+I71-I72,I76-I74)) -> 0 | J77: =MAX(0,MIN(J70+J71-J72,J76-J74)) -> 0 | K77: =MAX(0,MIN(K70+K71-K72,K76-K74)) -> 0 | ... AB77: =MAX(0,MIN(AB70+AB71-AB72,AB76-AB74)) -> 0
B78: Disponible tras Mezz | D78: =D76-D77 -> 19.73332 | E78: =E76-E77 -> 21.277707 | F78: =F76-F77 -> 20.067155 | G78: =G76-G77 -> 18.390826 | H78: =H76-H77 -> 16.729192 | I78: =I76-I77 -> 15.094737 | J78: =J76-J77 -> 13.500185 | K78: =K76-K77 -> 11.958223 | ... AB78: =AB76-AB77 -> 0.027763635
B79: Saldo Senior fin | D79: =D66+D67-D68-D75 -> 75 | E79: =E66+E67-E68-E75 -> 75 | F79: =F66+F67-F68-F75 -> 70.549096 | G79: =G66+G67-G68-G75 -> 63.923887 | H79: =H66+H67-H68-H75 -> 55.694636 | I79: =I66+I67-I68-I75 -> 46.006918 | J79: =J66+J67-J68-J75 -> 35.033001 | K79: =K66+K67-K68-K75 -> 22.96916 | ... AB79: =AB66+AB67-AB68-AB75 -> 0
B80: Saldo Mezz fin | D80: =D70+D71-D72-D77 -> 25 | E80: =E70+E71-E72-E77 -> 25 | F80: =F70+F71-F72-F77 -> 25 | G80: =G70+G71-G72-G77 -> 25 | H80: =H70+H71-H72-H77 -> 25 | I80: =I70+I71-I72-I77 -> 25 | J80: =J70+J71-J72-J77 -> 25 | K80: =K70+K71-K72-K77 -> 25 | ... AB80: =AB70+AB71-AB72-AB77 -> 0
B81: Distribución a equity | D81: =IF(D79+D80<0.000001,MAX(0,D78-D74),0) -> 0 | E81: =IF(E79+E80<0.000001,MAX(0,E78-E74),0) -> 0 | F81: =IF(F79+F80<0.000001,MAX(0,F78-F74),0) -> 0 | G81: =IF(G79+G80<0.000001,MAX(0,G78-G74),0) -> 0 | H81: =IF(H79+H80<0.000001,MAX(0,H78-H74),0) -> 0 | I81: =IF(I79+I80<0.000001,MAX(0,I78-I74),0) -> 0 | J81: =IF(J79+J80<0.000001,MAX(0,J78-J74),0) -> 0 | K81: =IF(K79+K80<0.000001,MAX(0,K78-K74),0) -> 0 | ... AB81: =IF(AB79+AB80<0.000001,MAX(0,AB78-AB74),0) -> 0.027763635
B82: Caja fin | D82: =D78-D81 -> 19.73332 | E82: =E78-E81 -> 21.277707 | F82: =F78-F81 -> 20.067155 | G82: =G78-G81 -> 18.390826 | H82: =H78-H81 -> 16.729192 | I82: =I78-I81 -> 15.094737 | J82: =J78-J81 -> 13.500185 | K82: =K78-K81 -> 11.958223 | ... AB82: =AB78-AB81 -> 0
B83: Déficit de liquidez con notas vigentes (1 = sí) | D83: =IF(AND(D65<0,D66+D70>0.000001),1,0) -> 0 | E83: =IF(AND(E65<0,E66+E70>0.000001),1,0) -> 0 | F83: =IF(AND(F65<0,F66+F70>0.000001),1,0) -> 0 | G83: =IF(AND(G65<0,G66+G70>0.000001),1,0) -> 0 | H83: =IF(AND(H65<0,H66+H70>0.000001),1,0) -> 0 | I83: =IF(AND(I65<0,I66+I70>0.000001),1,0) -> 0 | J83: =IF(AND(J65<0,J66+J70>0.000001),1,0) -> 0 | K83: =IF(AND(K65<0,K66+K70>0.000001),1,0) -> 0 | ... AB83: =IF(AND(AB65<0,AB66+AB70>0.000001),1,0) -> 0
A85: MÉTRICAS DEL ESCENARIO
B86: Pérdida Senior (% del original) | C86: =MIN(1,AB79/Supuestos!C5) -> 0
B87: Pérdida Mezz (% del original) | C87: =MIN(1,AB80/Supuestos!C7) -> 0
B88: Interés Senior impagado acumulado (USD mm) | C88: =SUM(D67:AB67)-SUM(D68:AB68) -> 0
B89: Caja mínima con notas vigentes (USD mm) | C89: =MIN(IF(D66+D70>0.000001,D65,1000000000),IF(E66+E70>0.000001,E65,1000000000),IF(F66+F70>0.000001,F65,1000000000),IF(G66+G70>0.000001,G65,1000000000),IF(H66+H70>0.000001,H65,1000000000),IF(I66+I70>0.000001,I65,1000000000),IF(J66+J70>0.000001,J65,1000000000),IF(K66+K70>0.000001,K65,1000000000),IF(L66+L70>0.000001,L65,1000000000),IF(M66+M70>0.000001,M65,1000000000),IF(N66+N70>0.000001,N65,1000000000),IF(O66+O70>0.000001,O65,1000000000),IF(P66+P70>0.000001,P65,1000000000),IF(Q66+Q70>0.000001,Q65,1000000000),IF(R66+R70>0.000001,R65,1000000000),IF(S66+S70>0.000001,S65,1000000000),IF(T66+T70>0.000001,T65,1000000000),IF(U66+U70>0.000001,U65,1000000000),IF(V66+V70>0.000001,V65,1000000000),IF(W66+W70>0.000001,W65,1000000000),IF(X66+X70>0.000001,X65,1000000000),IF(Y66+Y70>0.000001,Y65,1000000000),IF(Z66+Z70>0.000001,Z65,1000000000),IF(AA66+AA70>0.000001,AA65,1000000000),IF(AB66+AB70>0.000001,AB65,1000000000)) -> 21.926041
B90: Años con déficit de liquidez | C90: =SUM(D83:AB83) -> 0
B91: Vida promedio Senior (años) | C91: =IFERROR(SUMPRODUCT(D75:AB75,D3:AB3)/SUM(D75:AB75),0) -> 7.0561142
B92: Vida promedio Mezz (años) | C92: =IFERROR(SUMPRODUCT(D77:AB77,D3:AB3)/SUM(D77:AB77),0) -> 11.15277
B93: LE estresada ponderada por face (años) | C93: =(C18*Cartera!D5+C26*Cartera!D6+C34*Cartera!D7+C42*Cartera!D8+C50*Cartera!D9)/Cartera!D10 -> 8.1025877
B94: Senior PASA (1 = sí) | C94: =IF(AND(C86<=Supuestos!C20+0.000001,C88<0.000001),1,0) -> 1
B95: Mezz PASA (1 = sí) | C95: =IF(C87<=Supuestos!C20+0.000001,1,0) -> 1
B96: Distribuciones a equity (USD mm, sin descontar) | C96: =SUM(D81:AB81)+MAX(0,AB82) -> 88.484419

Sheet CF_bb
A1: Flujo de caja y cascada – escenario bb
A2: Escenario | C2: bb
A3: Año | D3: 1 | E3: 2 | F3: 3 | G3: 4 | H3: 5 | I3: 6 | J3: 7 | K3: 8 | L3: 9 | M3: 10 | N3: 11 | O3: 12 | P3: 13 | Q3: 14 | R3: 15 | S3: 16 | T3: 17 | U3: 18 | V3: 19 | W3: 20 | X3: 21 | Y3: 22 | Z3: 23 | AA3: 24 | AB3: 25
A5: Multiplicador de mortalidad | C5: =Supuestos!C28 -> 0.94
A6: Penalidad pool pequeño | C6: =Supuestos!D28 -> 0.01
A7: Pérdida default aseguradoras | C7: =Supuestos!E28 -> 0.01
A8: Aumento anual de primas | C8: =Supuestos!F28 -> 0.0025
A9: Haircut valor remanente | C9: =Supuestos!G28 -> 0.1
A10: Multiplicador efectivo | C10: =MAX(0,C5-IF(Cartera!C10<Supuestos!C16,C6,0)) -> 0.94
A12: =Cartera!A5&" – "&Cartera!B5 -> C1 – Edad 75–79, salud estándar
B13: q estresada | D13: =MIN(1,Cartera!$F$5*(1+Cartera!$G$5)^(D$3-1)*$C$10) -> 0.0423 | E13: =MIN(1,Cartera!$F$5*(1+Cartera!$G$5)^(E$3-1)*$C$10) -> 0.046953 | F13: =MIN(1,Cartera!$F$5*(1+Cartera!$G$5)^(F$3-1)*$C$10) -> 0.05211783 | G13: =MIN(1,Cartera!$F$5*(1+Cartera!$G$5)^(G$3-1)*$C$10) -> 0.057850791 | H13: =MIN(1,Cartera!$F$5*(1+Cartera!$G$5)^(H$3-1)*$C$10) -> 0.064214378 | I13: =MIN(1,Cartera!$F$5*(1+Cartera!$G$5)^(I$3-1)*$C$10) -> 0.07127796 | J13: =MIN(1,Cartera!$F$5*(1+Cartera!$G$5)^(J$3-1)*$C$10) -> 0.079118536 | K13: =MIN(1,Cartera!$F$5*(1+Cartera!$G$5)^(K$3-1)*$C$10) -> 0.087821574 | ... AB13: =MIN(1,Cartera!$F$5*(1+Cartera!$G$5)^(AB$3-1)*$C$10) -> 0.51771632
B14: Supervivencia inicio | C14: LE estresada → | D14: =1 -> 1 | E14: =D18 -> 0.9577 | F14: =E18 -> 0.91273311 | G14: =F18 -> 0.86516344 | H14: =G18 -> 0.81511305 | I14: =H18 -> 0.76277107 | J14: =I18 -> 0.70840231 | K14: =J18 -> 0.65235456 | L14: =K18 -> 0.59506375 | ... AB14: =AA18 -> 0.0062660469
B15: Muertes (fracción) | D15: =D14*D13 -> 0.0423 | E15: =E14*E13 -> 0.044966888 | F15: =F14*F13 -> 0.047569669 | G15: =G14*G13 -> 0.05005039 | H15: =H14*H13 -> 0.052341978 | I15: =I14*I13 -> 0.054368766 | J15: =J14*J13 -> 0.056047753 | K15: =K14*K13 -> 0.057290804 | ... AB15: =AB14*AB13 -> 0.0032440348
B16: Beneficio por muerte bruto (USD mm) | D16: =D15*Cartera!$D$5 -> 3.807 | E16: =E15*Cartera!$D$5 -> 4.0470199 | F16: =F15*Cartera!$D$5 -> 4.2812702 | G16: =G15*Cartera!$D$5 -> 4.5045351 | H16: =H15*Cartera!$D$5 -> 4.710778 | I16: =I15*Cartera!$D$5 -> 4.893189 | J16: =J15*Cartera!$D$5 -> 5.0442978 | K16: =K15*Cartera!$D$5 -> 5.1561724 | ... AB16: =AB15*Cartera!$D$5 -> 0.29196313
B17: Primas pagadas (USD mm) | D17: =D14*Cartera!$D$5*Cartera!$H$5*(1+$C$8)^(D$3-1) -> 3.6 | E17: =E14*Cartera!$D$5*Cartera!$H$5*(1+$C$8)^(E$3-1) -> 3.4563393 | F17: =F14*Cartera!$D$5*Cartera!$H$5*(1+$C$8)^(F$3-1) -> 3.3022889 | G17: =G14*Cartera!$D$5*Cartera!$H$5*(1+$C$8)^(G$3-1) -> 3.1380063 | H17: =H14*Cartera!$D$5*Cartera!$H$5*(1+$C$8)^(H$3-1) -> 2.9638613 | I17: =I14*Cartera!$D$5*Cartera!$H$5*(1+$C$8)^(I$3-1) -> 2.7804726 | J17: =J14*Cartera!$D$5*Cartera!$H$5*(1+$C$8)^(J$3-1) -> 2.5887419 | K17: =K14*Cartera!$D$5*Cartera!$H$5*(1+$C$8)^(K$3-1) -> 2.3898843 | ... AB17: =AB14*Cartera!$D$5*Cartera!$H$5*(1+$C$8)^(AB$3-1) -> 0.02395087
B18: Supervivencia fin | C18: =SUM(D18:AB18)+0.5 -> 9.9504265 | D18: =D14-D15 -> 0.9577 | E18: =E14-E15 -> 0.91273311 | F18: =F14-F15 -> 0.86516344 | G18: =G14-G15 -> 0.81511305 | H18: =H14-H15 -> 0.76277107 | I18: =I14-I15 -> 0.70840231 | J18: =J14-J15 -> 0.65235456 | K18: =K14-K15 -> 0.59506375 | ... AB18: =AB14-AB15 -> 0.0030220121
A20: =Cartera!A6&" – "&Cartera!B6 -> C2 – Edad 80–84, deterioro moderado
B21: q estresada | D21: =MIN(1,Cartera!$F$6*(1+Cartera!$G$6)^(D$3-1)*$C$10) -> 0.0611 | E21: =MIN(1,Cartera!$F$6*(1+Cartera!$G$6)^(E$3-1)*$C$10) -> 0.06721 | F21: =MIN(1,Cartera!$F$6*(1+Cartera!$G$6)^(F$3-1)*$C$10) -> 0.073931 | G21: =MIN(1,Cartera!$F$6*(1+Cartera!$G$6)^(G$3-1)*$C$10) -> 0.0813241 | H21: =MIN(1,Cartera!$F$6*(1+Cartera!$G$6)^(H$3-1)*$C$10) -> 0.08945651 | I21: =MIN(1,Cartera!$F$6*(1+Cartera!$G$6)^(I$3-1)*$C$10) -> 0.098402161 | J21: =MIN(1,Cartera!$F$6*(1+Cartera!$G$6)^(J$3-1)*$C$10) -> 0.10824238 | K21: =MIN(1,Cartera!$F$6*(1+Cartera!$G$6)^(K$3-1)*$C$10) -> 0.11906661 | ... AB21: =MIN(1,Cartera!$F$6*(1+Cartera!$G$6)^(AB$3-1)*$C$10) -> 0.60181867
B22: Supervivencia inicio | C22: LE estresada → | D22: =1 -> 1 | E22: =D26 -> 0.9389 | F22: =E26 -> 0.87579653 | G22: =F26 -> 0.81104802 | H22: =G26 -> 0.74509027 | I22: =H26 -> 0.67843709 | J22: =I26 -> 0.61167742 | K22: =J26 -> 0.545468 | L22: =K26 -> 0.48052097 | ... AB22: =AA26 -> 0.0013678937
B23: Muertes (fracción) | D23: =D22*D21 -> 0.0611 | E23: =E22*E21 -> 0.063103469 | F23: =F22*F21 -> 0.064748513 | G23: =G22*G21 -> 0.06595775 | H23: =H22*H21 -> 0.066653175 | I23: =I22*I21 -> 0.066759676 | J23: =J22*J21 -> 0.066209418 | K23: =K22*K21 -> 0.064947028 | ... AB23: =AB22*AB21 -> 0.00082322398
B24: Beneficio por muerte bruto (USD mm) | D24: =D23*Cartera!$D$6 -> 7.332 | E24: =E23*Cartera!$D$6 -> 7.5724163 | F24: =F23*Cartera!$D$6 -> 7.7698216 | G24: =G23*Cartera!$D$6 -> 7.91493 | H24: =H23*Cartera!$D$6 -> 7.998381 | I24: =I23*Cartera!$D$6 -> 8.0111611 | J24: =J23*Cartera!$D$6 -> 7.9451301 | K24: =K23*Cartera!$D$6 -> 7.7936434 | ... AB24: =AB23*Cartera!$D$6 -> 0.098786877
B25: Primas pagadas (USD mm) | D25: =D22*Cartera!$D$6*Cartera!$H$6*(1+$C$8)^(D$3-1) -> 6 | E25: =E22*Cartera!$D$6*Cartera!$H$6*(1+$C$8)^(E$3-1) -> 5.6474835 | F25: =F22*Cartera!$D$6*Cartera!$H$6*(1+$C$8)^(F$3-1) -> 5.2810859 | G25: =G22*Cartera!$D$6*Cartera!$H$6*(1+$C$8)^(G$3-1) -> 4.9028766 | H25: =H22*Cartera!$D$6*Cartera!$H$6*(1+$C$8)^(H$3-1) -> 4.5154149 | I25: =I22*Cartera!$D$6*Cartera!$H$6*(1+$C$8)^(I$3-1) -> 4.1217604 | J25: =J22*Cartera!$D$6*Cartera!$H$6*(1+$C$8)^(J$3-1) -> 3.7254607 | K25: =K22*Cartera!$D$6*Cartera!$H$6*(1+$C$8)^(K$3-1) -> 3.3305135 | ... AB25: =AB22*Cartera!$D$6*Cartera!$H$6*(1+$C$8)^(AB$3-1) -> 0.0087142248
B26: Supervivencia fin | C26: =SUM(D26:AB26)+0.5 -> 8.2628696 | D26: =D22-D23 -> 0.9389 | E26: =E22-E23 -> 0.87579653 | F26: =F22-F23 -> 0.81104802 | G26: =G22-G23 -> 0.74509027 | H26: =H22-H23 -> 0.67843709 | I26: =I22-I23 -> 0.61167742 | J26: =J22-J23 -> 0.545468 | K26: =K22-K23 -> 0.48052097 | ... AB26: =AB22-AB23 -> 0.00054466975
A28: =Cartera!A7&" – "&Cartera!B7 -> C3 – Edad 85–89, deterioro significativo
B29: q estresada | D29: =MIN(1,Cartera!$F$7*(1+Cartera!$G$7)^(D$3-1)*$C$10) -> 0.0893 | E29: =MIN(1,Cartera!$F$7*(1+Cartera!$G$7)^(E$3-1)*$C$10) -> 0.097337 | F29: =MIN(1,Cartera!$F$7*(1+Cartera!$G$7)^(F$3-1)*$C$10) -> 0.10609733 | G29: =MIN(1,Cartera!$F$7*(1+Cartera!$G$7)^(G$3-1)*$C$10) -> 0.11564609 | H29: =MIN(1,Cartera!$F$7*(1+Cartera!$G$7)^(H$3-1)*$C$10) -> 0.12605424 | I29: =MIN(1,Cartera!$F$7*(1+Cartera!$G$7)^(I$3-1)*$C$10) -> 0.13739912 | J29: =MIN(1,Cartera!$F$7*(1+Cartera!$G$7)^(J$3-1)*$C$10) -> 0.14976504 | K29: =MIN(1,Cartera!$F$7*(1+Cartera!$G$7)^(K$3-1)*$C$10) -> 0.16324389 | ... AB29: =MIN(1,Cartera!$F$7*(1+Cartera!$G$7)^(AB$3-1)*$C$10) -> 0.70645973
B30: Supervivencia inicio | C30: LE estresada → | D30: =1 -> 1 | E30: =D34 -> 0.9107 | F30: =E34 -> 0.82205519 | G30: =F34 -> 0.73483733 | H30: =G34 -> 0.64985627 | I30: =H34 -> 0.56793913 | J30: =I34 -> 0.4899048 | K30: =J34 -> 0.41653418 | L30: =K34 -> 0.34853752 | ... AB30: =AA34 -> 0.00014484145
B31: Muertes (fracción) | D31: =D30*D29 -> 0.0893 | E31: =E30*E29 -> 0.088644806 | F31: =F30*F29 -> 0.087217861 | G31: =G30*G29 -> 0.084981064 | H31: =H30*H29 -> 0.081917137 | I31: =I30*I29 -> 0.078034337 | J31: =J30*J29 -> 0.073370611 | K31: =K30*K29 -> 0.067996662 | ... AB31: =AB30*AB29 -> 0.00010232465
B32: Beneficio por muerte bruto (USD mm) | D32: =D31*Cartera!$D$7 -> 8.93 | E32: =E31*Cartera!$D$7 -> 8.8644806 | F32: =F31*Cartera!$D$7 -> 8.7217861 | G32: =G31*Cartera!$D$7 -> 8.4981064 | H32: =H31*Cartera!$D$7 -> 8.1917137 | I32: =I31*Cartera!$D$7 -> 7.8034337 | J32: =J31*Cartera!$D$7 -> 7.3370611 | K32: =K31*Cartera!$D$7 -> 6.7996662 | ... AB32: =AB31*Cartera!$D$7 -> 0.010232465
B33: Primas pagadas (USD mm) | D33: =D30*Cartera!$D$7*Cartera!$H$7*(1+$C$8)^(D$3-1) -> 6 | E33: =E30*Cartera!$D$7*Cartera!$H$7*(1+$C$8)^(E$3-1) -> 5.4778605 | F33: =F30*Cartera!$D$7*Cartera!$H$7*(1+$C$8)^(F$3-1) -> 4.9570236 | G33: =G30*Cartera!$D$7*Cartera!$H$7*(1+$C$8)^(G$3-1) -> 4.4421744 | H33: =H30*Cartera!$D$7*Cartera!$H$7*(1+$C$8)^(H$3-1) -> 3.9382755 | I33: =I30*Cartera!$D$7*Cartera!$H$7*(1+$C$8)^(I$3-1) -> 3.4504437 | J33: =J30*Cartera!$D$7*Cartera!$H$7*(1+$C$8)^(J$3-1) -> 2.9837967 | K33: =K30*Cartera!$D$7*Cartera!$H$7*(1+$C$8)^(K$3-1) -> 2.5432706 | ... AB33: =AB30*Cartera!$D$7*Cartera!$H$7*(1+$C$8)^(AB$3-1) -> 0.00092271858
B34: Supervivencia fin | C34: =SUM(D34:AB34)+0.5 -> 6.6050163 | D34: =D30-D31 -> 0.9107 | E34: =E30-E31 -> 0.82205519 | F34: =F30-F31 -> 0.73483733 | G34: =G30-G31 -> 0.64985627 | H34: =H30-H31 -> 0.56793913 | I34: =I30-I31 -> 0.4899048 | J34: =J30-J31 -> 0.41653418 | K34: =K30-K31 -> 0.34853752 | ... AB34: =AB30-AB31 -> 4.2516799e-05
A36: =Cartera!A8&" – "&Cartera!B8 -> C4 – Edad 90+, deterioro severo
B37: q estresada | D37: =MIN(1,Cartera!$F$8*(1+Cartera!$G$8)^(D$3-1)*$C$10) -> 0.1316 | E37: =MIN(1,Cartera!$F$8*(1+Cartera!$G$8)^(E$3-1)*$C$10) -> 0.142128 | F37: =MIN(1,Cartera!$F$8*(1+Cartera!$G$8)^(F$3-1)*$C$10) -> 0.15349824 | G37: =MIN(1,Cartera!$F$8*(1+Cartera!$G$8)^(G$3-1)*$C$10) -> 0.1657781 | H37: =MIN(1,Cartera!$F$8*(1+Cartera!$G$8)^(H$3-1)*$C$10) -> 0.17904035 | I37: =MIN(1,Cartera!$F$8*(1+Cartera!$G$8)^(I$3-1)*$C$10) -> 0.19336357 | J37: =MIN(1,Cartera!$F$8*(1+Cartera!$G$8)^(J$3-1)*$C$10) -> 0.20883266 | K37: =MIN(1,Cartera!$F$8*(1+Cartera!$G$8)^(K$3-1)*$C$10) -> 0.22553927 | ... AB37: =MIN(1,Cartera!$F$8*(1+Cartera!$G$8)^(AB$3-1)*$C$10) -> 0.83449939
B38: Supervivencia inicio | C38: LE estresada → | D38: =1 -> 1 | E38: =D42 -> 0.8684 | F38: =E42 -> 0.74497604 | G38: =F42 -> 0.63062353 | H38: =G42 -> 0.52607996 | I38: =H42 -> 0.43189042 | J38: =I42 -> 0.34837855 | K38: =J42 -> 0.27562573 | L38: =K42 -> 0.2134613 | ... AB38: =AA42 -> 4.4134666e-06
B39: Muertes (fracción) | D39: =D38*D37 -> 0.1316 | E39: =E38*E37 -> 0.12342396 | F39: =F38*F37 -> 0.11435251 | G39: =G38*G37 -> 0.10454357 | H39: =H38*H37 -> 0.094189539 | I39: =I38*I37 -> 0.083511876 | J39: =J38*J37 -> 0.072752819 | K39: =K38*K37 -> 0.062164427 | ... AB39: =AB38*AB37 -> 3.6830352e-06
B40: Beneficio por muerte bruto (USD mm) | D40: =D39*Cartera!$D$8 -> 10.528 | E40: =E39*Cartera!$D$8 -> 9.8739164 | F40: =F39*Cartera!$D$8 -> 9.1482009 | G40: =G39*Cartera!$D$8 -> 8.3634856 | H40: =H39*Cartera!$D$8 -> 7.5351631 | I40: =I39*Cartera!$D$8 -> 6.6809501 | J40: =J39*Cartera!$D$8 -> 5.8202255 | K40: =K39*Cartera!$D$8 -> 4.9731541 | ... AB40: =AB39*Cartera!$D$8 -> 0.00029464282
B41: Primas pagadas (USD mm) | D41: =D38*Cartera!$D$8*Cartera!$H$8*(1+$C$8)^(D$3-1) -> 5.6 | E41: =E38*Cartera!$D$8*Cartera!$H$8*(1+$C$8)^(E$3-1) -> 4.8751976 | F41: =F38*Cartera!$D$8*Cartera!$H$8*(1+$C$8)^(F$3-1) -> 4.1927513 | G41: =G38*Cartera!$D$8*Cartera!$H$8*(1+$C$8)^(G$3-1) -> 3.5580442 | H41: =H38*Cartera!$D$8*Cartera!$H$8*(1+$C$8)^(H$3-1) -> 2.9756189 | I41: =I38*Cartera!$D$8*Cartera!$H$8*(1+$C$8)^(I$3-1) -> 2.4489702 | J41: =J38*Cartera!$D$8*Cartera!$H$8*(1+$C$8)^(J$3-1) -> 1.9803672 | K41: =K38*Cartera!$D$8*Cartera!$H$8*(1+$C$8)^(K$3-1) -> 1.5707188 | ... AB41: =AB38*Cartera!$D$8*Cartera!$H$8*(1+$C$8)^(AB$3-1) -> 2.6241764e-05
B42: Supervivencia fin | C42: =SUM(D42:AB42)+0.5 -> 5.0631091 | D42: =D38-D39 -> 0.8684 | E42: =E38-E39 -> 0.74497604 | F42: =F38-F39 -> 0.63062353 | G42: =G38-G39 -> 0.52607996 | H42: =H38-H39 -> 0.43189042 | I42: =I38-I39 -> 0.34837855 | J42: =J38-J39 -> 0.27562573 | K42: =K38-K39 -> 0.2134613 | ... AB42: =AB38-AB39 -> 7.3043144e-07
A44: =Cartera!A9&" – "&Cartera!B9 -> C5 – Edad 70–74, enfermedad crónica
B45: q estresada | D45: =MIN(1,Cartera!$F$9*(1+Cartera!$G$9)^(D$3-1)*$C$10) -> 0.047 | E45: =MIN(1,Cartera!$F$9*(1+Cartera!$G$9)^(E$3-1)*$C$10) -> 0.05264 | F45: =MIN(1,Cartera!$F$9*(1+Cartera!$G$9)^(F$3-1)*$C$10) -> 0.0589568 | G45: =MIN(1,Cartera!$F$9*(1+Cartera!$G$9)^(G$3-1)*$C$10) -> 0.066031616 | H45: =MIN(1,Cartera!$F$9*(1+Cartera!$G$9)^(H$3-1)*$C$10) -> 0.07395541 | I45: =MIN(1,Cartera!$F$9*(1+Cartera!$G$9)^(I$3-1)*$C$10) -> 0.082830059 | J45: =MIN(1,Cartera!$F$9*(1+Cartera!$G$9)^(J$3-1)*$C$10) -> 0.092769666 | K45: =MIN(1,Cartera!$F$9*(1+Cartera!$G$9)^(K$3-1)*$C$10) -> 0.10390203 | ... AB45: =MIN(1,Cartera!$F$9*(1+Cartera!$G$9)^(AB$3-1)*$C$10) -> 0.71339556
B46: Supervivencia inicio | C46: LE estresada → | D46: =1 -> 1 | E46: =D50 -> 0.953 | F46: =E50 -> 0.90283408 | G46: =F50 -> 0.84960587 | H46: =G50 -> 0.79350502 | I46: =H50 -> 0.73482103 | J46: =I50 -> 0.67395576 | K46: =J50 -> 0.61143311 | L46: =K50 -> 0.54790397 | ... AB46: =AA50 -> 0.00086272509
B47: Muertes (fracción) | D47: =D46*D45 -> 0.047 | E47: =E46*E45 -> 0.05016592 | F47: =F46*F45 -> 0.053228208 | G47: =G46*G45 -> 0.056100849 | H47: =H46*H45 -> 0.058683989 | I47: =I46*I45 -> 0.06086527 | J47: =J46*J45 -> 0.062522651 | K47: =K46*K45 -> 0.063529139 | ... AB47: =AB46*AB45 -> 0.00061546425
B48: Beneficio por muerte bruto (USD mm) | D48: =D47*Cartera!$D$9 -> 2.82 | E48: =E47*Cartera!$D$9 -> 3.0099552 | F48: =F47*Cartera!$D$9 -> 3.1936925 | G48: =G47*Cartera!$D$9 -> 3.3660509 | H48: =H47*Cartera!$D$9 -> 3.5210394 | I48: =I47*Cartera!$D$9 -> 3.6519162 | J48: =J47*Cartera!$D$9 -> 3.7513591 | K48: =K47*Cartera!$D$9 -> 3.8117484 | ... AB48: =AB47*Cartera!$D$9 -> 0.036927855
B49: Primas pagadas (USD mm) | D49: =D46*Cartera!$D$9*Cartera!$H$9*(1+$C$8)^(D$3-1) -> 2.1 | E49: =E46*Cartera!$D$9*Cartera!$H$9*(1+$C$8)^(E$3-1) -> 2.0063033 | F49: =F46*Cartera!$D$9*Cartera!$H$9*(1+$C$8)^(F$3-1) -> 1.9054432 | G49: =G46*Cartera!$D$9*Cartera!$H$9*(1+$C$8)^(G$3-1) -> 1.7975871 | H49: =H46*Cartera!$D$9*Cartera!$H$9*(1+$C$8)^(H$3-1) -> 1.6830867 | I49: =I46*Cartera!$D$9*Cartera!$H$9*(1+$C$8)^(I$3-1) -> 1.5625099 | J49: =J46*Cartera!$D$9*Cartera!$H$9*(1+$C$8)^(J$3-1) -> 1.4366698 | K49: =K46*Cartera!$D$9*Cartera!$H$9*(1+$C$8)^(K$3-1) -> 1.3066489 | ... AB49: =AB46*Cartera!$D$9*Cartera!$H$9*(1+$C$8)^(AB$3-1) -> 0.0019236093
B50: Supervivencia fin | C50: =SUM(D50:AB50)+0.5 -> 9.0443773 | D50: =D46-D47 -> 0.953 | E50: =E46-E47 -> 0.90283408 | F50: =F46-F47 -> 0.84960587 | G50: =G46-G47 -> 0.79350502 | H50: =H46-H47 -> 0.73482103 | I50: =I46-I47 -> 0.67395576 | J50: =J46-J47 -> 0.61143311 | K50: =K46-K47 -> 0.54790397 | ... AB50: =AB46-AB47 -> 0.00024726084
A52: CARTERA TOTAL
B53: Face en vigor inicio (USD mm) | D53: =D14*Cartera!$D$5+D22*Cartera!$D$6+D30*Cartera!$D$7+D38*Cartera!$D$8+D46*Cartera!$D$9 -> 450 | E53: =E14*Cartera!$D$5+E22*Cartera!$D$6+E30*Cartera!$D$7+E38*Cartera!$D$8+E46*Cartera!$D$9 -> 416.583 | F53: =F14*Cartera!$D$5+F22*Cartera!$D$6+F30*Cartera!$D$7+F38*Cartera!$D$8+F46*Cartera!$D$9 -> 383.21521 | G53: =G14*Cartera!$D$5+G22*Cartera!$D$6+G30*Cartera!$D$7+G38*Cartera!$D$8+G46*Cartera!$D$9 -> 350.10044 | H53: =H14*Cartera!$D$5+H22*Cartera!$D$6+H30*Cartera!$D$7+H38*Cartera!$D$8+H46*Cartera!$D$9 -> 317.45333 | I53: =I14*Cartera!$D$5+I22*Cartera!$D$6+I30*Cartera!$D$7+I38*Cartera!$D$8+I46*Cartera!$D$9 -> 285.49626 | J53: =J14*Cartera!$D$5+J22*Cartera!$D$6+J30*Cartera!$D$7+J38*Cartera!$D$8+J46*Cartera!$D$9 -> 254.45561 | K53: =K14*Cartera!$D$5+K22*Cartera!$D$6+K30*Cartera!$D$7+K38*Cartera!$D$8+K46*Cartera!$D$9 -> 224.55753 | ... AB53: =AB14*Cartera!$D$5+AB22*Cartera!$D$6+AB30*Cartera!$D$7+AB38*Cartera!$D$8+AB46*Cartera!$D$9 -> 0.7946922
B54: Beneficios por muerte brutos | D54: =D16+D24+D32+D40+D48 -> 33.417 | E54: =E16+E24+E32+E40+E48 -> 33.367788 | F54: =F16+F24+F32+F40+F48 -> 33.114771 | G54: =G16+G24+G32+G40+G48 -> 32.647108 | H54: =H16+H24+H32+H40+H48 -> 31.957075 | I54: =I16+I24+I32+I40+I48 -> 31.04065 | J54: =J16+J24+J32+J40+J48 -> 29.898074 | K54: =K16+K24+K32+K40+K48 -> 28.534384 | ... AB54: =AB16+AB24+AB32+AB40+AB48 -> 0.43820497
B55: (−) Pérdida por default de aseguradoras | D55: =-D54*$C$7 -> -0.33417 | E55: =-E54*$C$7 -> -0.33367788 | F55: =-F54*$C$7 -> -0.33114771 | G55: =-G54*$C$7 -> -0.32647108 | H55: =-H54*$C$7 -> -0.31957075 | I55: =-I54*$C$7 -> -0.3104065 | J55: =-J54*$C$7 -> -0.29898074 | K55: =-K54*$C$7 -> -0.28534384 | ... AB55: =-AB54*$C$7 -> -0.0043820497
B56: Beneficios netos cobrados | D56: =D54+D55 -> 33.08283 | E56: =E54+E55 -> 33.034111 | F56: =F54+F55 -> 32.783624 | G56: =G54+G55 -> 32.320637 | H56: =H54+H55 -> 31.637504 | I56: =I54+I55 -> 30.730244 | J56: =J54+J55 -> 29.599093 | K56: =K54+K55 -> 28.249041 | ... AB56: =AB54+AB55 -> 0.43382292
B57: (−) Primas | D57: =-(D17+D25+D33+D41+D49) -> -23.3 | E57: =-(E17+E25+E33+E41+E49) -> -21.463184 | F57: =-(F17+F25+F33+F41+F49) -> -19.638593 | G57: =-(G17+G25+G33+G41+G49) -> -17.838689 | H57: =-(H17+H25+H33+H41+H49) -> -16.076257 | I57: =-(I17+I25+I33+I41+I49) -> -14.364157 | J57: =-(J17+J25+J33+J41+J49) -> -12.715036 | K57: =-(K17+K25+K33+K41+K49) -> -11.141036 | ... AB57: =-(AB17+AB25+AB33+AB41+AB49) -> -0.035537664
B58: (−) Gastos | D58: =-(Supuestos!$C$12+Supuestos!$C$13*D53) -> -0.975 | E58: =-(Supuestos!$C$12+Supuestos!$C$13*E53) -> -0.9582915 | F58: =-(Supuestos!$C$12+Supuestos!$C$13*F53) -> -0.94160761 | G58: =-(Supuestos!$C$12+Supuestos!$C$13*G53) -> -0.92505022 | H58: =-(Supuestos!$C$12+Supuestos!$C$13*H53) -> -0.90872667 | I58: =-(Supuestos!$C$12+Supuestos!$C$13*I53) -> -0.89274813 | J58: =-(Supuestos!$C$12+Supuestos!$C$13*J53) -> -0.8772278 | K58: =-(Supuestos!$C$12+Supuestos!$C$13*K53) -> -0.86227877 | ... AB58: =-(Supuestos!$C$12+Supuestos!$C$13*AB53) -> -0.75039735
B59: (+) Venta de cartera remanente (año final) | D59: =IF(D$3=Supuestos!$C$15,(D18*Cartera!$D$5+D26*Cartera!$D$6+D34*Cartera!$D$7+D42*Cartera!$D$8+D50*Cartera!$D$9)*Supuestos!$C$14*(1-$C$9),0) -> 0 | E59: =IF(E$3=Supuestos!$C$15,(E18*Cartera!$D$5+E26*Cartera!$D$6+E34*Cartera!$D$7+E42*Cartera!$D$8+E50*Cartera!$D$9)*Supuestos!$C$14*(1-$C$9),0) -> 0 | F59: =IF(F$3=Supuestos!$C$15,(F18*Cartera!$D$5+F26*Cartera!$D$6+F34*Cartera!$D$7+F42*Cartera!$D$8+F50*Cartera!$D$9)*Supuestos!$C$14*(1-$C$9),0) -> 0 | G59: =IF(G$3=Supuestos!$C$15,(G18*Cartera!$D$5+G26*Cartera!$D$6+G34*Cartera!$D$7+G42*Cartera!$D$8+G50*Cartera!$D$9)*Supuestos!$C$14*(1-$C$9),0) -> 0 | H59: =IF(H$3=Supuestos!$C$15,(H18*Cartera!$D$5+H26*Cartera!$D$6+H34*Cartera!$D$7+H42*Cartera!$D$8+H50*Cartera!$D$9)*Supuestos!$C$14*(1-$C$9),0) -> 0 | I59: =IF(I$3=Supuestos!$C$15,(I18*Cartera!$D$5+I26*Cartera!$D$6+I34*Cartera!$D$7+I42*Cartera!$D$8+I50*Cartera!$D$9)*Supuestos!$C$14*(1-$C$9),0) -> 0 | J59: =IF(J$3=Supuestos!$C$15,(J18*Cartera!$D$5+J26*Cartera!$D$6+J34*Cartera!$D$7+J42*Cartera!$D$8+J50*Cartera!$D$9)*Supuestos!$C$14*(1-$C$9),0) -> 0 | K59: =IF(K$3=Supuestos!$C$15,(K18*Cartera!$D$5+K26*Cartera!$D$6+K34*Cartera!$D$7+K42*Cartera!$D$8+K50*Cartera!$D$9)*Supuestos!$C$14*(1-$C$9),0) -> 0 | ... AB59: =IF(AB$3=Supuestos!$C$15,(AB18*Cartera!$D$5+AB26*Cartera!$D$6+AB34*Cartera!$D$7+AB42*Cartera!$D$8+AB50*Cartera!$D$9)*Supuestos!$C$14*(1-$C$9),0) -> 0.064167701
B60: Flujo neto de activos | D60: =D56+D57+D58+D59 -> 8.80783 | E60: =E56+E57+E58+E59 -> 10.612635 | F60: =F56+F57+F58+F59 -> 12.203423 | G60: =G56+G57+G58+G59 -> 13.556898 | H60: =H56+H57+H58+H59 -> 14.65252 | I60: =I56+I57+I58+I59 -> 15.473338 | J60: =J56+J57+J58+J59 -> 16.006829 | K60: =K56+K57+K58+K59 -> 16.245726 | ... AB60: =AB56+AB57+AB58+AB59 -> -0.28794439
B62: CASCADA
B63: Caja inicio | D63: =Supuestos!$C$9 -> 20 | E63: =D82 -> 22.15783 | F63: =E82 -> 21.516842 | G63: =F82 -> 19.687689 | H63: =G82 -> 17.883285 | I63: =H82 -> 16.116448 | J63: =I82 -> 14.400067 | K63: =J82 -> 12.746824 | L63: =K82 -> 11.168889 | ... AB63: =AA82 -> 0.072164031
B64: (+) Intereses de reinversión | D64: =MAX(0,D63)*Supuestos!$C$11 -> 0.6 | E64: =MAX(0,E63)*Supuestos!$C$11 -> 0.6647349 | F64: =MAX(0,F63)*Supuestos!$C$11 -> 0.64550526 | G64: =MAX(0,G63)*Supuestos!$C$11 -> 0.59063068 | H64: =MAX(0,H63)*Supuestos!$C$11 -> 0.53649856 | I64: =MAX(0,I63)*Supuestos!$C$11 -> 0.48349344 | J64: =MAX(0,J63)*Supuestos!$C$11 -> 0.43200202 | K64: =MAX(0,K63)*Supuestos!$C$11 -> 0.38240472 | ... AB64: =MAX(0,AB63)*Supuestos!$C$11 -> 0.0021649209
B65: Caja disponible | D65: =D63+D64+D60 -> 29.40783 | E65: =E63+E64+E60 -> 33.4352 | F65: =F63+F64+F60 -> 34.36577 | G65: =G63+G64+G60 -> 33.835218 | H65: =H63+H64+H60 -> 33.072304 | I65: =I63+I64+I60 -> 32.07328 | J65: =J63+J64+J60 -> 30.838898 | K65: =K63+K64+K60 -> 29.374954 | ... AB65: =AB63+AB64+AB60 -> -0.21361544
B66: Saldo Senior inicio | D66: =Supuestos!$C$5 -> 75 | E66: =D79 -> 75 | F66: =E79 -> 70.331642 | G66: =F79 -> 62.600118 | H66: =G79 -> 53.092193 | I66: =H79 -> 41.962329 | J66: =I79 -> 29.391668 | K66: =J79 -> 15.585052 | L66: =K79 -> 0.76701468 | ... AB66: =AA79 -> 0
B67: Interés Senior debido | D67: =D66*Supuestos!$C$6 -> 4.875 | E67: =E66*Supuestos!$C$6 -> 4.875 | F67: =F66*Supuestos!$C$6 -> 4.5715568 | G67: =G66*Supuestos!$C$6 -> 4.0690077 | H67: =H66*Supuestos!$C$6 -> 3.4509925 | I67: =I66*Supuestos!$C$6 -> 2.7275514 | J67: =J66*Supuestos!$C$6 -> 1.9104584 | K67: =K66*Supuestos!$C$6 -> 1.0130284 | ... AB67: =AB66*Supuestos!$C$6 -> 0
B68: Interés Senior pagado | D68: =MAX(0,MIN(D65,D67)) -> 4.875 | E68: =MAX(0,MIN(E65,E67)) -> 4.875 | F68: =MAX(0,MIN(F65,F67)) -> 4.5715568 | G68: =MAX(0,MIN(G65,G67)) -> 4.0690077 | H68: =MAX(0,MIN(H65,H67)) -> 3.4509925 | I68: =MAX(0,MIN(I65,I67)) -> 2.7275514 | J68: =MAX(0,MIN(J65,J67)) -> 1.9104584 | K68: =MAX(0,MIN(K65,K67)) -> 1.0130284 | ... AB68: =MAX(0,MIN(AB65,AB67)) -> 0
B69: Disponible tras int. Senior | D69: =D65-D68 -> 24.53283 | E69: =E65-E68 -> 28.5602 | F69: =F65-F68 -> 29.794214 | G69: =G65-G68 -> 29.766211 | H69: =H65-H68 -> 29.621312 | I69: =I65-I68 -> 29.345729 | J69: =J65-J68 -> 28.92844 | K69: =K65-K68 -> 28.361926 | ... AB69: =AB65-AB68 -> -0.21361544
B70: Saldo Mezz inicio | D70: =Supuestos!$C$7 -> 25 | E70: =D80 -> 25 | F70: =E80 -> 25 | G70: =F80 -> 25 | H70: =G80 -> 25 | I70: =H80 -> 25 | J70: =I80 -> 25 | K70: =J80 -> 25 | L70: =K80 -> 25 | ... AB70: =AA80 -> 0
B71: Interés Mezz debido | D71: =D70*Supuestos!$C$8 -> 2.375 | E71: =E70*Supuestos!$C$8 -> 2.375 | F71: =F70*Supuestos!$C$8 -> 2.375 | G71: =G70*Supuestos!$C$8 -> 2.375 | H71: =H70*Supuestos!$C$8 -> 2.375 | I71: =I70*Supuestos!$C$8 -> 2.375 | J71: =J70*Supuestos!$C$8 -> 2.375 | K71: =K70*Supuestos!$C$8 -> 2.375 | ... AB71: =AB70*Supuestos!$C$8 -> 0
B72: Interés Mezz pagado | D72: =MAX(0,MIN(D69,D71)) -> 2.375 | E72: =MAX(0,MIN(E69,E71)) -> 2.375 | F72: =MAX(0,MIN(F69,F71)) -> 2.375 | G72: =MAX(0,MIN(G69,G71)) -> 2.375 | H72: =MAX(0,MIN(H69,H71)) -> 2.375 | I72: =MAX(0,MIN(I69,I71)) -> 2.375 | J72: =MAX(0,MIN(J69,J71)) -> 2.375 | K72: =MAX(0,MIN(K69,K71)) -> 2.375 | ... AB72: =MAX(0,MIN(AB69,AB71)) -> 0
B73: Disponible tras int. Mezz | D73: =D69-D72 -> 22.15783 | E73: =E69-E72 -> 26.1852 | F73: =F69-F72 -> 27.419214 | G73: =G69-G72 -> 27.391211 | H73: =H69-H72 -> 27.246312 | I73: =I69-I72 -> 26.970729 | J73: =J69-J72 -> 26.55344 | K73: =K69-K72 -> 25.986926 | ... AB73: =AB69-AB72 -> -0.21361544
B74: Reserva objetivo | D74: =IF(D$3=Supuestos!$C$15,0,-D57*(1+$C$8)*Supuestos!$C$10/12) -> 23.35825 | E74: =IF(E$3=Supuestos!$C$15,0,-E57*(1+$C$8)*Supuestos!$C$10/12) -> 21.516842 | F74: =IF(F$3=Supuestos!$C$15,0,-F57*(1+$C$8)*Supuestos!$C$10/12) -> 19.687689 | G74: =IF(G$3=Supuestos!$C$15,0,-G57*(1+$C$8)*Supuestos!$C$10/12) -> 17.883285 | H74: =IF(H$3=Supuestos!$C$15,0,-H57*(1+$C$8)*Supuestos!$C$10/12) -> 16.116448 | I74: =IF(I$3=Supuestos!$C$15,0,-I57*(1+$C$8)*Supuestos!$C$10/12) -> 14.400067 | J74: =IF(J$3=Supuestos!$C$15,0,-J57*(1+$C$8)*Supuestos!$C$10/12) -> 12.746824 | K74: =IF(K$3=Supuestos!$C$15,0,-K57*(1+$C$8)*Supuestos!$C$10/12) -> 11.168889 | ... AB74: =IF(AB$3=Supuestos!$C$15,0,-AB57*(1+$C$8)*Supuestos!$C$10/12) -> 0
B75: Principal Senior pagado | D75: =MAX(0,MIN(D66+D67-D68,D73-D74)) -> 0 | E75: =MAX(0,MIN(E66+E67-E68,E73-E74)) -> 4.6683577 | F75: =MAX(0,MIN(F66+F67-F68,F73-F74)) -> 7.7315243 | G75: =MAX(0,MIN(G66+G67-G68,G73-G74)) -> 9.5079253 | H75: =MAX(0,MIN(H66+H67-H68,H73-H74)) -> 11.129864 | I75: =MAX(0,MIN(I66+I67-I68,I73-I74)) -> 12.570661 | J75: =MAX(0,MIN(J66+J67-J68,J73-J74)) -> 13.806616 | K75: =MAX(0,MIN(K66+K67-K68,K73-K74)) -> 14.818037 | ... AB75: =MAX(0,MIN(AB66+AB67-AB68,AB73-AB74)) -> 0
B76: Disponible tras Senior | D76: =D73-D75 -> 22.15783 | E76: =E73-E75 -> 21.516842 | F76: =F73-F75 -> 19.687689 | G76: =G73-G75 -> 17.883285 | H76: =H73-H75 -> 16.116448 | I76: =I73-I75 -> 14.400067 | J76: =J73-J75 -> 12.746824 | K76: =K73-K75 -> 11.168889 | ... AB76: =AB73-AB75 -> -0.21361544
B77: Principal Mezz pagado | D77: =MAX(0,MIN(D70+D71-D72,D76-D74)) -> 0 | E77: =MAX(0,MIN(E70+E71-E72,E76-E74)) -> 0 | F77: =MAX(0,MIN(F70+F71-F72,F76-F74)) -> 0 | G77: =MAX(0,MIN(G70+G71-G72,G76-G74)) -> 0 | H77: =MAX(0,MIN(H70+H71-H72,H76-H74)) -> 0 | I77: =MAX(0,MIN(I70+I71-I72,I76-I74)) -> 0 | J77: =MAX(0,MIN(J70+J71-J72,J76-J74)) -> 0 | K77: =MAX(0,MIN(K70+K71-K72,K76-K74)) -> 0 | ... AB77: =MAX(0,MIN(AB70+AB71-AB72,AB76-AB74)) -> 0
B78: Disponible tras Mezz | D78: =D76-D77 -> 22.15783 | E78: =E76-E77 -> 21.516842 | F78: =F76-F77 -> 19.687689 | G78: =G76-G77 -> 17.883285 | H78: =H76-H77 -> 16.116448 | I78: =I76-I77 -> 14.400067 | J78: =J76-J77 -> 12.746824 | K78: =K76-K77 -> 11.168889 | ... AB78: =AB76-AB77 -> -0.21361544
B79: Saldo Senior fin | D79: =D66+D67-D68-D75 -> 75 | E79: =E66+E67-E68-E75 -> 70.331642 | F79: =F66+F67-F68-F75 -> 62.600118 | G79: =G66+G67-G68-G75 -> 53.092193 | H79: =H66+H67-H68-H75 -> 41.962329 | I79: =I66+I67-I68-I75 -> 29.391668 | J79: =J66+J67-J68-J75 -> 15.585052 | K79: =K66+K67-K68-K75 -> 0.76701468 | ... AB79: =AB66+AB67-AB68-AB75 -> 0
B80: Saldo Mezz fin | D80: =D70+D71-D72-D77 -> 25 | E80: =E70+E71-E72-E77 -> 25 | F80: =F70+F71-F72-F77 -> 25 | G80: =G70+G71-G72-G77 -> 25 | H80: =H70+H71-H72-H77 -> 25 | I80: =I70+I71-I72-I77 -> 25 | J80: =J70+J71-J72-J77 -> 25 | K80: =K70+K71-K72-K77 -> 25 | ... AB80: =AB70+AB71-AB72-AB77 -> 0
B81: Distribución a equity | D81: =IF(D79+D80<0.000001,MAX(0,D78-D74),0) -> 0 | E81: =IF(E79+E80<0.000001,MAX(0,E78-E74),0) -> 0 | F81: =IF(F79+F80<0.000001,MAX(0,F78-F74),0) -> 0 | G81: =IF(G79+G80<0.000001,MAX(0,G78-G74),0) -> 0 | H81: =IF(H79+H80<0.000001,MAX(0,H78-H74),0) -> 0 | I81: =IF(I79+I80<0.000001,MAX(0,I78-I74),0) -> 0 | J81: =IF(J79+J80<0.000001,MAX(0,J78-J74),0) -> 0 | K81: =IF(K79+K80<0.000001,MAX(0,K78-K74),0) -> 0 | ... AB81: =IF(AB79+AB80<0.000001,MAX(0,AB78-AB74),0) -> 0
B82: Caja fin | D82: =D78-D81 -> 22.15783 | E82: =E78-E81 -> 21.516842 | F82: =F78-F81 -> 19.687689 | G82: =G78-G81 -> 17.883285 | H82: =H78-H81 -> 16.116448 | I82: =I78-I81 -> 14.400067 | J82: =J78-J81 -> 12.746824 | K82: =K78-K81 -> 11.168889 | ... AB82: =AB78-AB81 -> -0.21361544
B83: Déficit de liquidez con notas vigentes (1 = sí) | D83: =IF(AND(D65<0,D66+D70>0.000001),1,0) -> 0 | E83: =IF(AND(E65<0,E66+E70>0.000001),1,0) -> 0 | F83: =IF(AND(F65<0,F66+F70>0.000001),1,0) -> 0 | G83: =IF(AND(G65<0,G66+G70>0.000001),1,0) -> 0 | H83: =IF(AND(H65<0,H66+H70>0.000001),1,0) -> 0 | I83: =IF(AND(I65<0,I66+I70>0.000001),1,0) -> 0 | J83: =IF(AND(J65<0,J66+J70>0.000001),1,0) -> 0 | K83: =IF(AND(K65<0,K66+K70>0.000001),1,0) -> 0 | ... AB83: =IF(AND(AB65<0,AB66+AB70>0.000001),1,0) -> 0
A85: MÉTRICAS DEL ESCENARIO
B86: Pérdida Senior (% del original) | C86: =MIN(1,AB79/Supuestos!C5) -> 0
B87: Pérdida Mezz (% del original) | C87: =MIN(1,AB80/Supuestos!C7) -> 0
B88: Interés Senior impagado acumulado (USD mm) | C88: =SUM(D67:AB67)-SUM(D68:AB68) -> 0
B89: Caja mínima con notas vigentes (USD mm) | C89: =MIN(IF(D66+D70>0.000001,D65,1000000000),IF(E66+E70>0.000001,E65,1000000000),IF(F66+F70>0.000001,F65,1000000000),IF(G66+G70>0.000001,G65,1000000000),IF(H66+H70>0.000001,H65,1000000000),IF(I66+I70>0.000001,I65,1000000000),IF(J66+J70>0.000001,J65,1000000000),IF(K66+K70>0.000001,K65,1000000000),IF(L66+L70>0.000001,L65,1000000000),IF(M66+M70>0.000001,M65,1000000000),IF(N66+N70>0.000001,N65,1000000000),IF(O66+O70>0.000001,O65,1000000000),IF(P66+P70>0.000001,P65,1000000000),IF(Q66+Q70>0.000001,Q65,1000000000),IF(R66+R70>0.000001,R65,1000000000),IF(S66+S70>0.000001,S65,1000000000),IF(T66+T70>0.000001,T65,1000000000),IF(U66+U70>0.000001,U65,1000000000),IF(V66+V70>0.000001,V65,1000000000),IF(W66+W70>0.000001,W65,1000000000),IF(X66+X70>0.000001,X65,1000000000),IF(Y66+Y70>0.000001,Y65,1000000000),IF(Z66+Z70>0.000001,Z65,1000000000),IF(AA66+AA70>0.000001,AA65,1000000000),IF(AB66+AB70>0.000001,AB65,1000000000)) -> 25.809697
B90: Años con déficit de liquidez | C90: =SUM(D83:AB83) -> 0
B91: Vida promedio Senior (años) | C91: =IFERROR(SUMPRODUCT(D75:AB75,D3:AB3)/SUM(D75:AB75),0) -> 5.6497336
B92: Vida promedio Mezz (años) | C92: =IFERROR(SUMPRODUCT(D77:AB77,D3:AB3)/SUM(D77:AB77),0) -> 9.407068
B93: LE estresada ponderada por face (años) | C93: =(C18*Cartera!D5+C26*Cartera!D6+C34*Cartera!D7+C42*Cartera!D8+C50*Cartera!D9)/Cartera!D10 -> 7.7673238
B94: Senior PASA (1 = sí) | C94: =IF(AND(C86<=Supuestos!C20+0.000001,C88<0.000001),1,0) -> 1
B95: Mezz PASA (1 = sí) | C95: =IF(C87<=Supuestos!C20+0.000001,1,0) -> 1
B96: Distribuciones a equity (USD mm, sin descontar) | C96: =SUM(D81:AB81)+MAX(0,AB82) -> 114.70175

Sheet CF_base
A1: Flujo de caja y cascada – escenario base
A2: Escenario | C2: base
A3: Año | D3: 1 | E3: 2 | F3: 3 | G3: 4 | H3: 5 | I3: 6 | J3: 7 | K3: 8 | L3: 9 | M3: 10 | N3: 11 | O3: 12 | P3: 13 | Q3: 14 | R3: 15 | S3: 16 | T3: 17 | U3: 18 | V3: 19 | W3: 20 | X3: 21 | Y3: 22 | Z3: 23 | AA3: 24 | AB3: 25
A5: Multiplicador de mortalidad | C5: =Supuestos!C29 -> 1
A6: Penalidad pool pequeño | C6: =Supuestos!D29 -> 0
A7: Pérdida default aseguradoras | C7: =Supuestos!E29 -> 0.005
A8: Aumento anual de primas | C8: =Supuestos!F29 -> 0
A9: Haircut valor remanente | C9: =Supuestos!G29 -> 0
A10: Multiplicador efectivo | C10: =MAX(0,C5-IF(Cartera!C10<Supuestos!C16,C6,0)) -> 1
A12: =Cartera!A5&" – "&Cartera!B5 -> C1 – Edad 75–79, salud estándar
B13: q estresada | D13: =MIN(1,Cartera!$F$5*(1+Cartera!$G$5)^(D$3-1)*$C$10) -> 0.045 | E13: =MIN(1,Cartera!$F$5*(1+Cartera!$G$5)^(E$3-1)*$C$10) -> 0.04995 | F13: =MIN(1,Cartera!$F$5*(1+Cartera!$G$5)^(F$3-1)*$C$10) -> 0.0554445 | G13: =MIN(1,Cartera!$F$5*(1+Cartera!$G$5)^(G$3-1)*$C$10) -> 0.061543395 | H13: =MIN(1,Cartera!$F$5*(1+Cartera!$G$5)^(H$3-1)*$C$10) -> 0.068313168 | I13: =MIN(1,Cartera!$F$5*(1+Cartera!$G$5)^(I$3-1)*$C$10) -> 0.075827617 | J13: =MIN(1,Cartera!$F$5*(1+Cartera!$G$5)^(J$3-1)*$C$10) -> 0.084168655 | K13: =MIN(1,Cartera!$F$5*(1+Cartera!$G$5)^(K$3-1)*$C$10) -> 0.093427207 | ... AB13: =MIN(1,Cartera!$F$5*(1+Cartera!$G$5)^(AB$3-1)*$C$10) -> 0.55076205
B14: Supervivencia inicio | C14: LE estresada → | D14: =1 -> 1 | E14: =D18 -> 0.955 | F14: =E18 -> 0.90729775 | G14: =F18 -> 0.85699308 | H14: =G18 -> 0.80425082 | I14: =H18 -> 0.74930989 | J14: =I18 -> 0.69249151 | K14: =J18 -> 0.63420543 | L14: =K18 -> 0.57495339 | ... AB14: =AA18 -> 0.0042268019
B15: Muertes (fracción) | D15: =D14*D13 -> 0.045 | E15: =E14*E13 -> 0.04770225 | F15: =F14*F13 -> 0.05030467 | G15: =G14*G13 -> 0.052742264 | H15: =H14*H13 -> 0.054940921 | I15: =I14*I13 -> 0.056818384 | J15: =J14*J13 -> 0.058286079 | K15: =K14*K13 -> 0.059252042 | ... AB15: =AB14*AB13 -> 0.0023279621
B16: Beneficio por muerte bruto (USD mm) | D16: =D15*Cartera!$D$5 -> 4.05 | E16: =E15*Cartera!$D$5 -> 4.2932025 | F16: =F15*Cartera!$D$5 -> 4.5274203 | G16: =G15*Cartera!$D$5 -> 4.7468037 | H16: =H15*Cartera!$D$5 -> 4.9446829 | I16: =I15*Cartera!$D$5 -> 5.1136545 | J16: =J15*Cartera!$D$5 -> 5.2457471 | K16: =K15*Cartera!$D$5 -> 5.3326838 | ... AB16: =AB15*Cartera!$D$5 -> 0.20951659
B17: Primas pagadas (USD mm) | D17: =D14*Cartera!$D$5*Cartera!$H$5*(1+$C$8)^(D$3-1) -> 3.6 | E17: =E14*Cartera!$D$5*Cartera!$H$5*(1+$C$8)^(E$3-1) -> 3.438 | F17: =F14*Cartera!$D$5*Cartera!$H$5*(1+$C$8)^(F$3-1) -> 3.2662719 | G17: =G14*Cartera!$D$5*Cartera!$H$5*(1+$C$8)^(G$3-1) -> 3.0851751 | H17: =H14*Cartera!$D$5*Cartera!$H$5*(1+$C$8)^(H$3-1) -> 2.8953029 | I17: =I14*Cartera!$D$5*Cartera!$H$5*(1+$C$8)^(I$3-1) -> 2.6975156 | J17: =J14*Cartera!$D$5*Cartera!$H$5*(1+$C$8)^(J$3-1) -> 2.4929694 | K17: =K14*Cartera!$D$5*Cartera!$H$5*(1+$C$8)^(K$3-1) -> 2.2831396 | ... AB17: =AB14*Cartera!$D$5*Cartera!$H$5*(1+$C$8)^(AB$3-1) -> 0.015216487
B18: Supervivencia fin | C18: =SUM(D18:AB18)+0.5 -> 9.6035972 | D18: =D14-D15 -> 0.955 | E18: =E14-E15 -> 0.90729775 | F18: =F14-F15 -> 0.85699308 | G18: =G14-G15 -> 0.80425082 | H18: =H14-H15 -> 0.74930989 | I18: =I14-I15 -> 0.69249151 | J18: =J14-J15 -> 0.63420543 | K18: =K14-K15 -> 0.57495339 | ... AB18: =AB14-AB15 -> 0.0018988399
A20: =Cartera!A6&" – "&Cartera!B6 -> C2 – Edad 80–84, deterioro moderado
B21: q estresada | D21: =MIN(1,Cartera!$F$6*(1+Cartera!$G$6)^(D$3-1)*$C$10) -> 0.065 | E21: =MIN(1,Cartera!$F$6*(1+Cartera!$G$6)^(E$3-1)*$C$10) -> 0.0715 | F21: =MIN(1,Cartera!$F$6*(1+Cartera!$G$6)^(F$3-1)*$C$10) -> 0.07865 | G21: =MIN(1,Cartera!$F$6*(1+Cartera!$G$6)^(G$3-1)*$C$10) -> 0.086515 | H21: =MIN(1,Cartera!$F$6*(1+Cartera!$G$6)^(H$3-1)*$C$10) -> 0.0951665 | I21: =MIN(1,Cartera!$F$6*(1+Cartera!$G$6)^(I$3-1)*$C$10) -> 0.10468315 | J21: =MIN(1,Cartera!$F$6*(1+Cartera!$G$6)^(J$3-1)*$C$10) -> 0.11515146 | K21: =MIN(1,Cartera!$F$6*(1+Cartera!$G$6)^(K$3-1)*$C$10) -> 0.12666661 | ... AB21: =MIN(1,Cartera!$F$6*(1+Cartera!$G$6)^(AB$3-1)*$C$10) -> 0.64023262
B22: Supervivencia inicio | C22: LE estresada → | D22: =1 -> 1 | E22: =D26 -> 0.935 | F22: =E26 -> 0.8681475 | G22: =F26 -> 0.7998677 | H22: =G26 -> 0.73066715 | I22: =H26 -> 0.66113211 | J22: =I26 -> 0.59192272 | K22: =J26 -> 0.52376195 | L22: =K26 -> 0.4574188 | ... AB22: =AA26 -> 0.00079632059
B23: Muertes (fracción) | D23: =D22*D21 -> 0.065 | E23: =E22*E21 -> 0.0668525 | F23: =F22*F21 -> 0.068279801 | G23: =G22*G21 -> 0.069200554 | H23: =H22*H21 -> 0.069535035 | I23: =I22*I21 -> 0.069209392 | J23: =J22*J21 -> 0.068160768 | K23: =K22*K21 -> 0.066343151 | ... AB23: =AB22*AB21 -> 0.00050983042
B24: Beneficio por muerte bruto (USD mm) | D24: =D23*Cartera!$D$6 -> 7.8 | E24: =E23*Cartera!$D$6 -> 8.0223 | F24: =F23*Cartera!$D$6 -> 8.1935761 | G24: =G23*Cartera!$D$6 -> 8.3040665 | H24: =H23*Cartera!$D$6 -> 8.3442042 | I24: =I23*Cartera!$D$6 -> 8.305127 | J24: =J23*Cartera!$D$6 -> 8.1792922 | K24: =K23*Cartera!$D$6 -> 7.9611782 | ... AB24: =AB23*Cartera!$D$6 -> 0.06117965
B25: Primas pagadas (USD mm) | D25: =D22*Cartera!$D$6*Cartera!$H$6*(1+$C$8)^(D$3-1) -> 6 | E25: =E22*Cartera!$D$6*Cartera!$H$6*(1+$C$8)^(E$3-1) -> 5.61 | F25: =F22*Cartera!$D$6*Cartera!$H$6*(1+$C$8)^(F$3-1) -> 5.208885 | G25: =G22*Cartera!$D$6*Cartera!$H$6*(1+$C$8)^(G$3-1) -> 4.7992062 | H25: =H22*Cartera!$D$6*Cartera!$H$6*(1+$C$8)^(H$3-1) -> 4.3840029 | I25: =I22*Cartera!$D$6*Cartera!$H$6*(1+$C$8)^(I$3-1) -> 3.9667927 | J25: =J22*Cartera!$D$6*Cartera!$H$6*(1+$C$8)^(J$3-1) -> 3.5515363 | K25: =K22*Cartera!$D$6*Cartera!$H$6*(1+$C$8)^(K$3-1) -> 3.1425717 | ... AB25: =AB22*Cartera!$D$6*Cartera!$H$6*(1+$C$8)^(AB$3-1) -> 0.0047779235
B26: Supervivencia fin | C26: =SUM(D26:AB26)+0.5 -> 7.9396746 | D26: =D22-D23 -> 0.935 | E26: =E22-E23 -> 0.8681475 | F26: =F22-F23 -> 0.7998677 | G26: =G22-G23 -> 0.73066715 | H26: =H22-H23 -> 0.66113211 | I26: =I22-I23 -> 0.59192272 | J26: =J22-J23 -> 0.52376195 | K26: =K22-K23 -> 0.4574188 | ... AB26: =AB22-AB23 -> 0.00028649017
A28: =Cartera!A7&" – "&Cartera!B7 -> C3 – Edad 85–89, deterioro significativo
B29: q estresada | D29: =MIN(1,Cartera!$F$7*(1+Cartera!$G$7)^(D$3-1)*$C$10) -> 0.095 | E29: =MIN(1,Cartera!$F$7*(1+Cartera!$G$7)^(E$3-1)*$C$10) -> 0.10355 | F29: =MIN(1,Cartera!$F$7*(1+Cartera!$G$7)^(F$3-1)*$C$10) -> 0.1128695 | G29: =MIN(1,Cartera!$F$7*(1+Cartera!$G$7)^(G$3-1)*$C$10) -> 0.12302776 | H29: =MIN(1,Cartera!$F$7*(1+Cartera!$G$7)^(H$3-1)*$C$10) -> 0.13410025 | I29: =MIN(1,Cartera!$F$7*(1+Cartera!$G$7)^(I$3-1)*$C$10) -> 0.14616928 | J29: =MIN(1,Cartera!$F$7*(1+Cartera!$G$7)^(J$3-1)*$C$10) -> 0.15932451 | K29: =MIN(1,Cartera!$F$7*(1+Cartera!$G$7)^(K$3-1)*$C$10) -> 0.17366372 | ... AB29: =MIN(1,Cartera!$F$7*(1+Cartera!$G$7)^(AB$3-1)*$C$10) -> 0.7515529
B30: Supervivencia inicio | C30: LE estresada → | D30: =1 -> 1 | E30: =D34 -> 0.905 | F30: =E34 -> 0.81128725 | G30: =F34 -> 0.71971766 | H30: =G34 -> 0.63117242 | I30: =H34 -> 0.54653203 | J30: =I34 -> 0.46664584 | K30: =J34 -> 0.39229772 | L30: =K34 -> 0.32416984 | ... AB30: =AA34 -> 6.5578749e-05
B31: Muertes (fracción) | D31: =D30*D29 -> 0.095 | E31: =E30*E29 -> 0.09371275 | F31: =F30*F29 -> 0.091569586 | G31: =G30*G29 -> 0.088545248 | H31: =H30*H29 -> 0.084640381 | I31: =I30*I29 -> 0.079886192 | J31: =J30*J29 -> 0.074348121 | K31: =K30*K29 -> 0.06812788 | ... AB31: =AB30*AB29 -> 4.9285899e-05
B32: Beneficio por muerte bruto (USD mm) | D32: =D31*Cartera!$D$7 -> 9.5 | E32: =E31*Cartera!$D$7 -> 9.371275 | F32: =F31*Cartera!$D$7 -> 9.1569586 | G32: =G31*Cartera!$D$7 -> 8.8545248 | H32: =H31*Cartera!$D$7 -> 8.4640381 | I32: =I31*Cartera!$D$7 -> 7.9886192 | J32: =J31*Cartera!$D$7 -> 7.4348121 | K32: =K31*Cartera!$D$7 -> 6.812788 | ... AB32: =AB31*Cartera!$D$7 -> 0.0049285899
B33: Primas pagadas (USD mm) | D33: =D30*Cartera!$D$7*Cartera!$H$7*(1+$C$8)^(D$3-1) -> 6 | E33: =E30*Cartera!$D$7*Cartera!$H$7*(1+$C$8)^(E$3-1) -> 5.43 | F33: =F30*Cartera!$D$7*Cartera!$H$7*(1+$C$8)^(F$3-1) -> 4.8677235 | G33: =G30*Cartera!$D$7*Cartera!$H$7*(1+$C$8)^(G$3-1) -> 4.318306 | H33: =H30*Cartera!$D$7*Cartera!$H$7*(1+$C$8)^(H$3-1) -> 3.7870345 | I33: =I30*Cartera!$D$7*Cartera!$H$7*(1+$C$8)^(I$3-1) -> 3.2791922 | J33: =J30*Cartera!$D$7*Cartera!$H$7*(1+$C$8)^(J$3-1) -> 2.7998751 | K33: =K30*Cartera!$D$7*Cartera!$H$7*(1+$C$8)^(K$3-1) -> 2.3537863 | ... AB33: =AB30*Cartera!$D$7*Cartera!$H$7*(1+$C$8)^(AB$3-1) -> 0.00039347249
B34: Supervivencia fin | C34: =SUM(D34:AB34)+0.5 -> 6.3151792 | D34: =D30-D31 -> 0.905 | E34: =E30-E31 -> 0.81128725 | F34: =F30-F31 -> 0.71971766 | G34: =G30-G31 -> 0.63117242 | H34: =H30-H31 -> 0.54653203 | I34: =I30-I31 -> 0.46664584 | J34: =J30-J31 -> 0.39229772 | K34: =K30-K31 -> 0.32416984 | ... AB34: =AB30-AB31 -> 1.629285e-05
A36: =Cartera!A8&" – "&Cartera!B8 -> C4 – Edad 90+, deterioro severo
B37: q estresada | D37: =MIN(1,Cartera!$F$8*(1+Cartera!$G$8)^(D$3-1)*$C$10) -> 0.14 | E37: =MIN(1,Cartera!$F$8*(1+Cartera!$G$8)^(E$3-1)*$C$10) -> 0.1512 | F37: =MIN(1,Cartera!$F$8*(1+Cartera!$G$8)^(F$3-1)*$C$10) -> 0.163296 | G37: =MIN(1,Cartera!$F$8*(1+Cartera!$G$8)^(G$3-1)*$C$10) -> 0.17635968 | H37: =MIN(1,Cartera!$F$8*(1+Cartera!$G$8)^(H$3-1)*$C$10) -> 0.19046845 | I37: =MIN(1,Cartera!$F$8*(1+Cartera!$G$8)^(I$3-1)*$C$10) -> 0.20570593 | J37: =MIN(1,Cartera!$F$8*(1+Cartera!$G$8)^(J$3-1)*$C$10) -> 0.22216241 | K37: =MIN(1,Cartera!$F$8*(1+Cartera!$G$8)^(K$3-1)*$C$10) -> 0.2399354 | ... AB37: =MIN(1,Cartera!$F$8*(1+Cartera!$G$8)^(AB$3-1)*$C$10) -> 0.8877653
B38: Supervivencia inicio | C38: LE estresada → | D38: =1 -> 1 | E38: =D42 -> 0.86 | F38: =E42 -> 0.729968 | G38: =F42 -> 0.61076715 | H38: =G42 -> 0.50305245 | I38: =H42 -> 0.40723683 | J38: =I42 -> 0.32346579 | K38: =J42 -> 0.25160386 | L38: =K42 -> 0.19123518 | ... AB38: =AA42 -> 1.2005966e-06
B39: Muertes (fracción) | D39: =D38*D37 -> 0.14 | E39: =E38*E37 -> 0.130032 | F39: =F38*F37 -> 0.11920085 | G39: =G38*G37 -> 0.1077147 | H39: =H38*H37 -> 0.095815622 | I39: =I38*I37 -> 0.08377103 | J39: =J38*J37 -> 0.071861939 | K39: =K38*K37 -> 0.060368671 | ... AB39: =AB38*AB37 -> 1.065848e-06
B40: Beneficio por muerte bruto (USD mm) | D40: =D39*Cartera!$D$8 -> 11.2 | E40: =E39*Cartera!$D$8 -> 10.40256 | F40: =F39*Cartera!$D$8 -> 9.5360684 | G40: =G39*Cartera!$D$8 -> 8.6171759 | H40: =H39*Cartera!$D$8 -> 7.6652498 | I40: =I39*Cartera!$D$8 -> 6.7016824 | J40: =J39*Cartera!$D$8 -> 5.7489551 | K40: =K39*Cartera!$D$8 -> 4.8294937 | ... AB40: =AB39*Cartera!$D$8 -> 8.5267842e-05
B41: Primas pagadas (USD mm) | D41: =D38*Cartera!$D$8*Cartera!$H$8*(1+$C$8)^(D$3-1) -> 5.6 | E41: =E38*Cartera!$D$8*Cartera!$H$8*(1+$C$8)^(E$3-1) -> 4.816 | F41: =F38*Cartera!$D$8*Cartera!$H$8*(1+$C$8)^(F$3-1) -> 4.0878208 | G41: =G38*Cartera!$D$8*Cartera!$H$8*(1+$C$8)^(G$3-1) -> 3.420296 | H41: =H38*Cartera!$D$8*Cartera!$H$8*(1+$C$8)^(H$3-1) -> 2.8170937 | I41: =I38*Cartera!$D$8*Cartera!$H$8*(1+$C$8)^(I$3-1) -> 2.2805262 | J41: =J38*Cartera!$D$8*Cartera!$H$8*(1+$C$8)^(J$3-1) -> 1.8114085 | K41: =K38*Cartera!$D$8*Cartera!$H$8*(1+$C$8)^(K$3-1) -> 1.4089816 | ... AB41: =AB38*Cartera!$D$8*Cartera!$H$8*(1+$C$8)^(AB$3-1) -> 6.7233411e-06
B42: Supervivencia fin | C42: =SUM(D42:AB42)+0.5 -> 4.814024 | D42: =D38-D39 -> 0.86 | E42: =E38-E39 -> 0.729968 | F42: =F38-F39 -> 0.61076715 | G42: =G38-G39 -> 0.50305245 | H42: =H38-H39 -> 0.40723683 | I42: =I38-I39 -> 0.32346579 | J42: =J38-J39 -> 0.25160386 | K42: =K38-K39 -> 0.19123518 | ... AB42: =AB38-AB39 -> 1.347486e-07
A44: =Cartera!A9&" – "&Cartera!B9 -> C5 – Edad 70–74, enfermedad crónica
B45: q estresada | D45: =MIN(1,Cartera!$F$9*(1+Cartera!$G$9)^(D$3-1)*$C$10) -> 0.05 | E45: =MIN(1,Cartera!$F$9*(1+Cartera!$G$9)^(E$3-1)*$C$10) -> 0.056 | F45: =MIN(1,Cartera!$F$9*(1+Cartera!$G$9)^(F$3-1)*$C$10) -> 0.06272 | G45: =MIN(1,Cartera!$F$9*(1+Cartera!$G$9)^(G$3-1)*$C$10) -> 0.0702464 | H45: =MIN(1,Cartera!$F$9*(1+Cartera!$G$9)^(H$3-1)*$C$10) -> 0.078675968 | I45: =MIN(1,Cartera!$F$9*(1+Cartera!$G$9)^(I$3-1)*$C$10) -> 0.088117084 | J45: =MIN(1,Cartera!$F$9*(1+Cartera!$G$9)^(J$3-1)*$C$10) -> 0.098691134 | K45: =MIN(1,Cartera!$F$9*(1+Cartera!$G$9)^(K$3-1)*$C$10) -> 0.11053407 | ... AB45: =MIN(1,Cartera!$F$9*(1+Cartera!$G$9)^(AB$3-1)*$C$10) -> 0.75893145
B46: Supervivencia inicio | C46: LE estresada → | D46: =1 -> 1 | E46: =D50 -> 0.95 | F46: =E50 -> 0.8968 | G46: =F50 -> 0.8405527 | H46: =G50 -> 0.7815069 | I46: =H50 -> 0.72002109 | J46: =I50 -> 0.65657493 | K46: =J50 -> 0.59177681 | L46: =K50 -> 0.52636531 | ... AB46: =AA50 -> 0.00046330339
B47: Muertes (fracción) | D47: =D46*D45 -> 0.05 | E47: =E46*E45 -> 0.0532 | F47: =F46*F45 -> 0.056247296 | G47: =G46*G45 -> 0.059045801 | H47: =H46*H45 -> 0.061485812 | I47: =I46*I45 -> 0.063446159 | J47: =J46*J45 -> 0.064798125 | K47: =K46*K45 -> 0.065411499 | ... AB47: =AB46*AB45 -> 0.00035161551
B48: Beneficio por muerte bruto (USD mm) | D48: =D47*Cartera!$D$9 -> 3 | E48: =E47*Cartera!$D$9 -> 3.192 | F48: =F47*Cartera!$D$9 -> 3.3748378 | G48: =G47*Cartera!$D$9 -> 3.5427481 | H48: =H47*Cartera!$D$9 -> 3.6891487 | I48: =I47*Cartera!$D$9 -> 3.8067695 | J48: =J47*Cartera!$D$9 -> 3.8878875 | K48: =K47*Cartera!$D$9 -> 3.92469 | ... AB48: =AB47*Cartera!$D$9 -> 0.021096931
B49: Primas pagadas (USD mm) | D49: =D46*Cartera!$D$9*Cartera!$H$9*(1+$C$8)^(D$3-1) -> 2.1 | E49: =E46*Cartera!$D$9*Cartera!$H$9*(1+$C$8)^(E$3-1) -> 1.995 | F49: =F46*Cartera!$D$9*Cartera!$H$9*(1+$C$8)^(F$3-1) -> 1.88328 | G49: =G46*Cartera!$D$9*Cartera!$H$9*(1+$C$8)^(G$3-1) -> 1.7651607 | H49: =H46*Cartera!$D$9*Cartera!$H$9*(1+$C$8)^(H$3-1) -> 1.6411645 | I49: =I46*Cartera!$D$9*Cartera!$H$9*(1+$C$8)^(I$3-1) -> 1.5120443 | J49: =J46*Cartera!$D$9*Cartera!$H$9*(1+$C$8)^(J$3-1) -> 1.3788074 | K49: =K46*Cartera!$D$9*Cartera!$H$9*(1+$C$8)^(K$3-1) -> 1.2427313 | ... AB49: =AB46*Cartera!$D$9*Cartera!$H$9*(1+$C$8)^(AB$3-1) -> 0.00097293712
B50: Supervivencia fin | C50: =SUM(D50:AB50)+0.5 -> 8.7258954 | D50: =D46-D47 -> 0.95 | E50: =E46-E47 -> 0.8968 | F50: =F46-F47 -> 0.8405527 | G50: =G46-G47 -> 0.7815069 | H50: =H46-H47 -> 0.72002109 | I50: =I46-I47 -> 0.65657493 | J50: =J46-J47 -> 0.59177681 | K50: =K46-K47 -> 0.52636531 | ... AB50: =AB46-AB47 -> 0.00011168788
A52: CARTERA TOTAL
B53: Face en vigor inicio (USD mm) | D53: =D14*Cartera!$D$5+D22*Cartera!$D$6+D30*Cartera!$D$7+D38*Cartera!$D$8+D46*Cartera!$D$9 -> 450 | E53: =E14*Cartera!$D$5+E22*Cartera!$D$6+E30*Cartera!$D$7+E38*Cartera!$D$8+E46*Cartera!$D$9 -> 414.45 | F53: =F14*Cartera!$D$5+F22*Cartera!$D$6+F30*Cartera!$D$7+F38*Cartera!$D$8+F46*Cartera!$D$9 -> 379.16866 | G53: =G14*Cartera!$D$5+G22*Cartera!$D$6+G30*Cartera!$D$7+G38*Cartera!$D$8+G46*Cartera!$D$9 -> 344.3798 | H53: =H14*Cartera!$D$5+H22*Cartera!$D$6+H30*Cartera!$D$7+H38*Cartera!$D$8+H46*Cartera!$D$9 -> 310.31448 | I53: =I14*Cartera!$D$5+I22*Cartera!$D$6+I30*Cartera!$D$7+I38*Cartera!$D$8+I46*Cartera!$D$9 -> 277.20716 | J53: =J14*Cartera!$D$5+J22*Cartera!$D$6+J30*Cartera!$D$7+J38*Cartera!$D$8+J46*Cartera!$D$9 -> 245.29131 | K53: =K14*Cartera!$D$5+K22*Cartera!$D$6+K30*Cartera!$D$7+K38*Cartera!$D$8+K46*Cartera!$D$9 -> 214.79461 | ... AB53: =AB14*Cartera!$D$5+AB22*Cartera!$D$6+AB30*Cartera!$D$7+AB38*Cartera!$D$8+AB46*Cartera!$D$9 -> 0.51042277
B54: Beneficios por muerte brutos | D54: =D16+D24+D32+D40+D48 -> 35.55 | E54: =E16+E24+E32+E40+E48 -> 35.281337 | F54: =F16+F24+F32+F40+F48 -> 34.788861 | G54: =G16+G24+G32+G40+G48 -> 34.065319 | H54: =H16+H24+H32+H40+H48 -> 33.107324 | I54: =I16+I24+I32+I40+I48 -> 31.915853 | J54: =J16+J24+J32+J40+J48 -> 30.496694 | K54: =K16+K24+K32+K40+K48 -> 28.860834 | ... AB54: =AB16+AB24+AB32+AB40+AB48 -> 0.29680703
B55: (−) Pérdida por default de aseguradoras | D55: =-D54*$C$7 -> -0.17775 | E55: =-E54*$C$7 -> -0.17640669 | F55: =-F54*$C$7 -> -0.17394431 | G55: =-G54*$C$7 -> -0.1703266 | H55: =-H54*$C$7 -> -0.16553662 | I55: =-I54*$C$7 -> -0.15957926 | J55: =-J54*$C$7 -> -0.15248347 | K55: =-K54*$C$7 -> -0.14430417 | ... AB55: =-AB54*$C$7 -> -0.0014840351
B56: Beneficios netos cobrados | D56: =D54+D55 -> 35.37225 | E56: =E54+E55 -> 35.104931 | F56: =F54+F55 -> 34.614917 | G56: =G54+G55 -> 33.894992 | H56: =H54+H55 -> 32.941787 | I56: =I54+I55 -> 31.756273 | J56: =J54+J55 -> 30.34421 | K56: =K54+K55 -> 28.716529 | ... AB56: =AB54+AB55 -> 0.29532299
B57: (−) Primas | D57: =-(D17+D25+D33+D41+D49) -> -23.3 | E57: =-(E17+E25+E33+E41+E49) -> -21.289 | F57: =-(F17+F25+F33+F41+F49) -> -19.313981 | G57: =-(G17+G25+G33+G41+G49) -> -17.388144 | H57: =-(H17+H25+H33+H41+H49) -> -15.524599 | I57: =-(I17+I25+I33+I41+I49) -> -13.736071 | J57: =-(J17+J25+J33+J41+J49) -> -12.034597 | K57: =-(K17+K25+K33+K41+K49) -> -10.43121 | ... AB57: =-(AB17+AB25+AB33+AB41+AB49) -> -0.021367543
B58: (−) Gastos | D58: =-(Supuestos!$C$12+Supuestos!$C$13*D53) -> -0.975 | E58: =-(Supuestos!$C$12+Supuestos!$C$13*E53) -> -0.957225 | F58: =-(Supuestos!$C$12+Supuestos!$C$13*F53) -> -0.93958433 | G58: =-(Supuestos!$C$12+Supuestos!$C$13*G53) -> -0.9221899 | H58: =-(Supuestos!$C$12+Supuestos!$C$13*H53) -> -0.90515724 | I58: =-(Supuestos!$C$12+Supuestos!$C$13*I53) -> -0.88860358 | J58: =-(Supuestos!$C$12+Supuestos!$C$13*J53) -> -0.87264565 | K58: =-(Supuestos!$C$12+Supuestos!$C$13*K53) -> -0.85739731 | ... AB58: =-(Supuestos!$C$12+Supuestos!$C$13*AB53) -> -0.75025521
B59: (+) Venta de cartera remanente (año final) | D59: =IF(D$3=Supuestos!$C$15,(D18*Cartera!$D$5+D26*Cartera!$D$6+D34*Cartera!$D$7+D42*Cartera!$D$8+D50*Cartera!$D$9)*Supuestos!$C$14*(1-$C$9),0) -> 0 | E59: =IF(E$3=Supuestos!$C$15,(E18*Cartera!$D$5+E26*Cartera!$D$6+E34*Cartera!$D$7+E42*Cartera!$D$8+E50*Cartera!$D$9)*Supuestos!$C$14*(1-$C$9),0) -> 0 | F59: =IF(F$3=Supuestos!$C$15,(F18*Cartera!$D$5+F26*Cartera!$D$6+F34*Cartera!$D$7+F42*Cartera!$D$8+F50*Cartera!$D$9)*Supuestos!$C$14*(1-$C$9),0) -> 0 | G59: =IF(G$3=Supuestos!$C$15,(G18*Cartera!$D$5+G26*Cartera!$D$6+G34*Cartera!$D$7+G42*Cartera!$D$8+G50*Cartera!$D$9)*Supuestos!$C$14*(1-$C$9),0) -> 0 | H59: =IF(H$3=Supuestos!$C$15,(H18*Cartera!$D$5+H26*Cartera!$D$6+H34*Cartera!$D$7+H42*Cartera!$D$8+H50*Cartera!$D$9)*Supuestos!$C$14*(1-$C$9),0) -> 0 | I59: =IF(I$3=Supuestos!$C$15,(I18*Cartera!$D$5+I26*Cartera!$D$6+I34*Cartera!$D$7+I42*Cartera!$D$8+I50*Cartera!$D$9)*Supuestos!$C$14*(1-$C$9),0) -> 0 | J59: =IF(J$3=Supuestos!$C$15,(J18*Cartera!$D$5+J26*Cartera!$D$6+J34*Cartera!$D$7+J42*Cartera!$D$8+J50*Cartera!$D$9)*Supuestos!$C$14*(1-$C$9),0) -> 0 | K59: =IF(K$3=Supuestos!$C$15,(K18*Cartera!$D$5+K26*Cartera!$D$6+K34*Cartera!$D$7+K42*Cartera!$D$8+K50*Cartera!$D$9)*Supuestos!$C$14*(1-$C$9),0) -> 0 | ... AB59: =IF(AB$3=Supuestos!$C$15,(AB18*Cartera!$D$5+AB26*Cartera!$D$6+AB34*Cartera!$D$7+AB42*Cartera!$D$8+AB50*Cartera!$D$9)*Supuestos!$C$14*(1-$C$9),0) -> 0.042723149
B60: Flujo neto de activos | D60: =D56+D57+D58+D59 -> 11.09725 | E60: =E56+E57+E58+E59 -> 12.858706 | F60: =F56+F57+F58+F59 -> 14.361351 | G60: =G56+G57+G58+G59 -> 15.584659 | H60: =H56+H57+H58+H59 -> 16.512031 | I60: =I56+I57+I58+I59 -> 17.131599 | J60: =J56+J57+J58+J59 -> 17.436968 | K60: =K56+K57+K58+K59 -> 17.427922 | ... AB60: =AB56+AB57+AB58+AB59 -> -0.43357661
B62: CASCADA
B63: Caja inicio | D63: =Supuestos!$C$9 -> 20 | E63: =D82 -> 23.3 | F63: =E82 -> 21.289 | G63: =F82 -> 19.313981 | H63: =G82 -> 17.388144 | I63: =H82 -> 15.524599 | J63: =I82 -> 13.736071 | K63: =J82 -> 12.034597 | L63: =K82 -> 10.43121 | ... AB63: =AA82 -> -0.12541524
B64: (+) Intereses de reinversión | D64: =MAX(0,D63)*Supuestos!$C$11 -> 0.6 | E64: =MAX(0,E63)*Supuestos!$C$11 -> 0.699 | F64: =MAX(0,F63)*Supuestos!$C$11 -> 0.63867 | G64: =MAX(0,G63)*Supuestos!$C$11 -> 0.57941944 | H64: =MAX(0,H63)*Supuestos!$C$11 -> 0.52164432 | I64: =MAX(0,I63)*Supuestos!$C$11 -> 0.46573796 | J64: =MAX(0,J63)*Supuestos!$C$11 -> 0.41208213 | K64: =MAX(0,K63)*Supuestos!$C$11 -> 0.3610379 | ... AB64: =MAX(0,AB63)*Supuestos!$C$11 -> 0
B65: Caja disponible | D65: =D63+D64+D60 -> 31.69725 | E65: =E63+E64+E60 -> 36.857706 | F65: =F63+F64+F60 -> 36.289021 | G65: =G63+G64+G60 -> 35.478059 | H65: =H63+H64+H60 -> 34.42182 | I65: =I63+I64+I60 -> 33.121935 | J65: =J63+J64+J60 -> 31.585121 | K65: =K63+K64+K60 -> 29.823556 | ... AB65: =AB63+AB64+AB60 -> -0.55899185
B66: Saldo Senior inicio | D66: =Supuestos!$C$5 -> 75 | E66: =D79 -> 73.85275 | F66: =E79 -> 65.459473 | G66: =F79 -> 55.114299 | H66: =G79 -> 42.981813 | I66: =H79 -> 29.253409 | J66: =I79 -> 14.144017 | K66: =J79 -> 0 | L66: =K79 -> 0 | ... AB66: =AA79 -> 0
B67: Interés Senior debido | D67: =D66*Supuestos!$C$6 -> 4.875 | E67: =E66*Supuestos!$C$6 -> 4.8004288 | F67: =F66*Supuestos!$C$6 -> 4.2548657 | G67: =G66*Supuestos!$C$6 -> 3.5824294 | H67: =H66*Supuestos!$C$6 -> 2.7938178 | I67: =I66*Supuestos!$C$6 -> 1.9014716 | J67: =J66*Supuestos!$C$6 -> 0.91936109 | K67: =K66*Supuestos!$C$6 -> 0 | ... AB67: =AB66*Supuestos!$C$6 -> 0
B68: Interés Senior pagado | D68: =MAX(0,MIN(D65,D67)) -> 4.875 | E68: =MAX(0,MIN(E65,E67)) -> 4.8004288 | F68: =MAX(0,MIN(F65,F67)) -> 4.2548657 | G68: =MAX(0,MIN(G65,G67)) -> 3.5824294 | H68: =MAX(0,MIN(H65,H67)) -> 2.7938178 | I68: =MAX(0,MIN(I65,I67)) -> 1.9014716 | J68: =MAX(0,MIN(J65,J67)) -> 0.91936109 | K68: =MAX(0,MIN(K65,K67)) -> 0 | ... AB68: =MAX(0,MIN(AB65,AB67)) -> 0
B69: Disponible tras int. Senior | D69: =D65-D68 -> 26.82225 | E69: =E65-E68 -> 32.057277 | F69: =F65-F68 -> 32.034156 | G69: =G65-G68 -> 31.89563 | H69: =H65-H68 -> 31.628002 | I69: =I65-I68 -> 31.220464 | J69: =J65-J68 -> 30.66576 | K69: =K65-K68 -> 29.823556 | ... AB69: =AB65-AB68 -> -0.55899185
B70: Saldo Mezz inicio | D70: =Supuestos!$C$7 -> 25 | E70: =D80 -> 25 | F70: =E80 -> 25 | G70: =F80 -> 25 | H70: =G80 -> 25 | I70: =H80 -> 25 | J70: =I80 -> 25 | K70: =J80 -> 22.887853 | L70: =K80 -> 5.6698535 | ... AB70: =AA80 -> 0
B71: Interés Mezz debido | D71: =D70*Supuestos!$C$8 -> 2.375 | E71: =E70*Supuestos!$C$8 -> 2.375 | F71: =F70*Supuestos!$C$8 -> 2.375 | G71: =G70*Supuestos!$C$8 -> 2.375 | H71: =H70*Supuestos!$C$8 -> 2.375 | I71: =I70*Supuestos!$C$8 -> 2.375 | J71: =J70*Supuestos!$C$8 -> 2.375 | K71: =K70*Supuestos!$C$8 -> 2.1743461 | ... AB71: =AB70*Supuestos!$C$8 -> 0
B72: Interés Mezz pagado | D72: =MAX(0,MIN(D69,D71)) -> 2.375 | E72: =MAX(0,MIN(E69,E71)) -> 2.375 | F72: =MAX(0,MIN(F69,F71)) -> 2.375 | G72: =MAX(0,MIN(G69,G71)) -> 2.375 | H72: =MAX(0,MIN(H69,H71)) -> 2.375 | I72: =MAX(0,MIN(I69,I71)) -> 2.375 | J72: =MAX(0,MIN(J69,J71)) -> 2.375 | K72: =MAX(0,MIN(K69,K71)) -> 2.1743461 | ... AB72: =MAX(0,MIN(AB69,AB71)) -> 0
B73: Disponible tras int. Mezz | D73: =D69-D72 -> 24.44725 | E73: =E69-E72 -> 29.682277 | F73: =F69-F72 -> 29.659156 | G73: =G69-G72 -> 29.52063 | H73: =H69-H72 -> 29.253002 | I73: =I69-I72 -> 28.845464 | J73: =J69-J72 -> 28.29076 | K73: =K69-K72 -> 27.64921 | ... AB73: =AB69-AB72 -> -0.55899185
B74: Reserva objetivo | D74: =IF(D$3=Supuestos!$C$15,0,-D57*(1+$C$8)*Supuestos!$C$10/12) -> 23.3 | E74: =IF(E$3=Supuestos!$C$15,0,-E57*(1+$C$8)*Supuestos!$C$10/12) -> 21.289 | F74: =IF(F$3=Supuestos!$C$15,0,-F57*(1+$C$8)*Supuestos!$C$10/12) -> 19.313981 | G74: =IF(G$3=Supuestos!$C$15,0,-G57*(1+$C$8)*Supuestos!$C$10/12) -> 17.388144 | H74: =IF(H$3=Supuestos!$C$15,0,-H57*(1+$C$8)*Supuestos!$C$10/12) -> 15.524599 | I74: =IF(I$3=Supuestos!$C$15,0,-I57*(1+$C$8)*Supuestos!$C$10/12) -> 13.736071 | J74: =IF(J$3=Supuestos!$C$15,0,-J57*(1+$C$8)*Supuestos!$C$10/12) -> 12.034597 | K74: =IF(K$3=Supuestos!$C$15,0,-K57*(1+$C$8)*Supuestos!$C$10/12) -> 10.43121 | ... AB74: =IF(AB$3=Supuestos!$C$15,0,-AB57*(1+$C$8)*Supuestos!$C$10/12) -> 0
B75: Principal Senior pagado | D75: =MAX(0,MIN(D66+D67-D68,D73-D74)) -> 1.14725 | E75: =MAX(0,MIN(E66+E67-E68,E73-E74)) -> 8.3932771 | F75: =MAX(0,MIN(F66+F67-F68,F73-F74)) -> 10.345174 | G75: =MAX(0,MIN(G66+G67-G68,G73-G74)) -> 12.132486 | H75: =MAX(0,MIN(H66+H67-H68,H73-H74)) -> 13.728403 | I75: =MAX(0,MIN(I66+I67-I68,I73-I74)) -> 15.109393 | J75: =MAX(0,MIN(J66+J67-J68,J73-J74)) -> 14.144017 | K75: =MAX(0,MIN(K66+K67-K68,K73-K74)) -> 0 | ... AB75: =MAX(0,MIN(AB66+AB67-AB68,AB73-AB74)) -> 0
B76: Disponible tras Senior | D76: =D73-D75 -> 23.3 | E76: =E73-E75 -> 21.289 | F76: =F73-F75 -> 19.313981 | G76: =G73-G75 -> 17.388144 | H76: =H73-H75 -> 15.524599 | I76: =I73-I75 -> 13.736071 | J76: =J73-J75 -> 14.146743 | K76: =K73-K75 -> 27.64921 | ... AB76: =AB73-AB75 -> -0.55899185
B77: Principal Mezz pagado | D77: =MAX(0,MIN(D70+D71-D72,D76-D74)) -> 0 | E77: =MAX(0,MIN(E70+E71-E72,E76-E74)) -> 0 | F77: =MAX(0,MIN(F70+F71-F72,F76-F74)) -> 0 | G77: =MAX(0,MIN(G70+G71-G72,G76-G74)) -> 0 | H77: =MAX(0,MIN(H70+H71-H72,H76-H74)) -> 0 | I77: =MAX(0,MIN(I70+I71-I72,I76-I74)) -> 0 | J77: =MAX(0,MIN(J70+J71-J72,J76-J74)) -> 2.1121468 | K77: =MAX(0,MIN(K70+K71-K72,K76-K74)) -> 17.218 | ... AB77: =MAX(0,MIN(AB70+AB71-AB72,AB76-AB74)) -> 0
B78: Disponible tras Mezz | D78: =D76-D77 -> 23.3 | E78: =E76-E77 -> 21.289 | F78: =F76-F77 -> 19.313981 | G78: =G76-G77 -> 17.388144 | H78: =H76-H77 -> 15.524599 | I78: =I76-I77 -> 13.736071 | J78: =J76-J77 -> 12.034597 | K78: =K76-K77 -> 10.43121 | ... AB78: =AB76-AB77 -> -0.55899185
B79: Saldo Senior fin | D79: =D66+D67-D68-D75 -> 73.85275 | E79: =E66+E67-E68-E75 -> 65.459473 | F79: =F66+F67-F68-F75 -> 55.114299 | G79: =G66+G67-G68-G75 -> 42.981813 | H79: =H66+H67-H68-H75 -> 29.253409 | I79: =I66+I67-I68-I75 -> 14.144017 | J79: =J66+J67-J68-J75 -> 0 | K79: =K66+K67-K68-K75 -> 0 | ... AB79: =AB66+AB67-AB68-AB75 -> 0
B80: Saldo Mezz fin | D80: =D70+D71-D72-D77 -> 25 | E80: =E70+E71-E72-E77 -> 25 | F80: =F70+F71-F72-F77 -> 25 | G80: =G70+G71-G72-G77 -> 25 | H80: =H70+H71-H72-H77 -> 25 | I80: =I70+I71-I72-I77 -> 25 | J80: =J70+J71-J72-J77 -> 22.887853 | K80: =K70+K71-K72-K77 -> 5.6698535 | ... AB80: =AB70+AB71-AB72-AB77 -> 0
B81: Distribución a equity | D81: =IF(D79+D80<0.000001,MAX(0,D78-D74),0) -> 0 | E81: =IF(E79+E80<0.000001,MAX(0,E78-E74),0) -> 0 | F81: =IF(F79+F80<0.000001,MAX(0,F78-F74),0) -> 0 | G81: =IF(G79+G80<0.000001,MAX(0,G78-G74),0) -> 0 | H81: =IF(H79+H80<0.000001,MAX(0,H78-H74),0) -> 0 | I81: =IF(I79+I80<0.000001,MAX(0,I78-I74),0) -> 0 | J81: =IF(J79+J80<0.000001,MAX(0,J78-J74),0) -> 0 | K81: =IF(K79+K80<0.000001,MAX(0,K78-K74),0) -> 0 | ... AB81: =IF(AB79+AB80<0.000001,MAX(0,AB78-AB74),0) -> 0
B82: Caja fin | D82: =D78-D81 -> 23.3 | E82: =E78-E81 -> 21.289 | F82: =F78-F81 -> 19.313981 | G82: =G78-G81 -> 17.388144 | H82: =H78-H81 -> 15.524599 | I82: =I78-I81 -> 13.736071 | J82: =J78-J81 -> 12.034597 | K82: =K78-K81 -> 10.43121 | ... AB82: =AB78-AB81 -> -0.55899185
B83: Déficit de liquidez con notas vigentes (1 = sí) | D83: =IF(AND(D65<0,D66+D70>0.000001),1,0) -> 0 | E83: =IF(AND(E65<0,E66+E70>0.000001),1,0) -> 0 | F83: =IF(AND(F65<0,F66+F70>0.000001),1,0) -> 0 | G83: =IF(AND(G65<0,G66+G70>0.000001),1,0) -> 0 | H83: =IF(AND(H65<0,H66+H70>0.000001),1,0) -> 0 | I83: =IF(AND(I65<0,I66+I70>0.000001),1,0) -> 0 | J83: =IF(AND(J65<0,J66+J70>0.000001),1,0) -> 0 | K83: =IF(AND(K65<0,K66+K70>0.000001),1,0) -> 0 | ... AB83: =IF(AND(AB65<0,AB66+AB70>0.000001),1,0) -> 0
A85: MÉTRICAS DEL ESCENARIO
B86: Pérdida Senior (% del original) | C86: =MIN(1,AB79/Supuestos!C5) -> 0
B87: Pérdida Mezz (% del original) | C87: =MIN(1,AB80/Supuestos!C7) -> 0
B88: Interés Senior impagado acumulado (USD mm) | C88: =SUM(D67:AB67)-SUM(D68:AB68) -> 0
B89: Caja mínima con notas vigentes (USD mm) | C89: =MIN(IF(D66+D70>0.000001,D65,1000000000),IF(E66+E70>0.000001,E65,1000000000),IF(F66+F70>0.000001,F65,1000000000),IF(G66+G70>0.000001,G65,1000000000),IF(H66+H70>0.000001,H65,1000000000),IF(I66+I70>0.000001,I65,1000000000),IF(J66+J70>0.000001,J65,1000000000),IF(K66+K70>0.000001,K65,1000000000),IF(L66+L70>0.000001,L65,1000000000),IF(M66+M70>0.000001,M65,1000000000),IF(N66+N70>0.000001,N65,1000000000),IF(O66+O70>0.000001,O65,1000000000),IF(P66+P70>0.000001,P65,1000000000),IF(Q66+Q70>0.000001,Q65,1000000000),IF(R66+R70>0.000001,R65,1000000000),IF(S66+S70>0.000001,S65,1000000000),IF(T66+T70>0.000001,T65,1000000000),IF(U66+U70>0.000001,U65,1000000000),IF(V66+V70>0.000001,V65,1000000000),IF(W66+W70>0.000001,W65,1000000000),IF(X66+X70>0.000001,X65,1000000000),IF(Y66+Y70>0.000001,Y65,1000000000),IF(Z66+Z70>0.000001,Z65,1000000000),IF(AA66+AA70>0.000001,AA65,1000000000),IF(AB66+AB70>0.000001,AB65,1000000000)) -> 27.855196
B90: Años con déficit de liquidez | C90: =SUM(D83:AB83) -> 0
B91: Vida promedio Senior (años) | C91: =IFERROR(SUMPRODUCT(D75:AB75,D3:AB3)/SUM(D75:AB75),0) -> 4.7440768
B92: Vida promedio Mezz (años) | C92: =IFERROR(SUMPRODUCT(D77:AB77,D3:AB3)/SUM(D77:AB77),0) -> 8.1423083
B93: LE estresada ponderada por face (años) | C93: =(C18*Cartera!D5+C26*Cartera!D6+C34*Cartera!D7+C42*Cartera!D8+C50*Cartera!D9)/Cartera!D10 -> 7.4606184
B94: Senior PASA (1 = sí) | C94: =IF(AND(C86<=Supuestos!C20+0.000001,C88<0.000001),1,0) -> 1
B95: Mezz PASA (1 = sí) | C95: =IF(C87<=Supuestos!C20+0.000001,1,0) -> 1
B96: Distribuciones a equity (USD mm, sin descontar) | C96: =SUM(D81:AB81)+MAX(0,AB82) -> 134.01544

Sheet Ponderacion
A1: Factores cualitativos, pesos y chequeos de elegibilidad
A2: Pesos = estimación de Claude sobre la importancia relativa en el análisis de AM Best (AM Best no publica una ponderación de este tipo; su núcleo es el estrés de flujos).
A4: # | B4: Factor | C4: Qué revisa AM Best | D4: Peso | E4: Puntaje (1–5) | F4: Puntaje ponderado | G4: Fuente del factor
A5: 1 | B5: Calidad de LE / underwriting médico | C5: ≥2 proveedores independientes, reportes ≤12 meses, historial de los proveedores, todas las LE entregadas | D5: 0.25 | E5: 4 | F5: =D5*E5 -> 1 | G5: AM Best LSS
A6: 2 | B6: Diversificación de la cartera | C6: # vidas (≥300), concentración por vida (≤3.33%), concentración por enfermedad | D6: 0.2 | E6: 4 | F6: =D6*E6 -> 0.8 | G6: AM Best LSS
A7: 3 | B7: Liquidez para primas | C7: Reserva / facilidad de liquidez frente a primas en escenarios de extensión | D7: 0.2 | E7: 3 | F7: =D7*E7 -> 0.6 | G7: AM Best LSS; práctica de mercado
A8: 4 | B8: Calidad crediticia de aseguradoras | C8: FSR de las aseguradoras emisoras y concentración por aseguradora | D8: 0.1 | E8: 4 | F8: =D8*E8 -> 0.4 | G8: AM Best LSS
A9: 5 | B9: Riesgo legal de pólizas | C9: STOLI, interés asegurable, impugnabilidad, rescisión | D9: 0.1 | E9: 3 | F9: =D9*E9 -> 0.3 | G9: Práctica de mercado / litigios
A10: 6 | B10: Estructura legal del SPV | C10: Bankruptcy-remote, true sale, opiniones legales, securities intermediary | D10: 0.1 | E10: 4 | F10: =D10*E10 -> 0.4 | G10: BILSM / práctica ABS
A11: 7 | B11: Contrapartes operativas | C11: Servicer, tracking agent, custodio, trustee | D11: 0.05 | E11: 4 | F11: =D11*E11 -> 0.2 | G11: BILSM / práctica ABS
B12: Total | D12: =SUM(D5:D11) -> 1 | F12: =SUM(F5:F11) -> 3.7
B13: Control: pesos suman 100% | D13: =IF(ABS(D12-1)<0.0001,"OK","REVISAR") -> OK
B15: Ajuste en notches (heurística de Claude)
B16: Puntaje ponderado ≥ | C16: Notches
B17: 0 | C17: -3
B18: 2.5 | C18: -2
B19: 3.5 | C19: -1
B20: 4.5 | C20: 0
B22: Notches aplicados | C22: =INDEX(C17:C20,MATCH(F12,B17:B20,1)) -> -1
B24: Chequeos de elegibilidad (parámetros publicados por AM Best)
B25: Chequeo | C25: Valor | D25: Límite | E25: Resultado
B26: # de vidas | C26: =Cartera!C10 -> 300 | D26: =Supuestos!C16 -> 300 | E26: =IF(C26>=D26,"OK","ESTRÉS ADICIONAL") -> OK
B27: Mayor póliza / face total | C27: =Cartera!C18 -> 0.0066666667 | D27: =Supuestos!C17 -> 0.0333 | E27: =IF(C27<=D27,"OK","EXCEDE") -> OK
B28: Antigüedad LE (meses) | C28: =Cartera!C14 -> 8 | D28: =Supuestos!C18 -> 12 | E28: =IF(C28<=D28,"OK","ACTUALIZAR LE") -> OK
B29: # proveedores LE | C29: =Cartera!C15 -> 2 | D29: =Supuestos!C19 -> 2 | E29: =IF(C29>=D29,"OK","INSUFICIENTE") -> OK
B30: Notch adicional por chequeos fallidos (−1 c/u, heurística) | C30: =-COUNTIF(E26:E29,"<>OK") -> 0
B31: Total notches | C31: =C22+C30 -> -1

Sheet Fuentes
A1: Fuentes y estatus de cada parámetro
A3: Parámetro | B3: Estatus | C3: Fuente
